Workbook
Name SegmentaçãodeDados_Ano: #N/A
Name SegmentaçãodeDados_Centro_de_Custo___Obra: #N/A
Name SegmentaçãodeDados_Conta_Pai: #N/A
Name SegmentaçãodeDados_Empresa: #N/A
Name SegmentaçãodeDados_Mês: #N/A

Sheet Painel

Sheet DRE
F2: =F6/$AH$6 -> 0 | J2: =J6/$AH$6 -> 0 | L2: =L6/$AH$6 -> 0 | N2: =N6/$AH$6 -> 0 | R2: =R6/$AH$6 -> 0 | T2: =T6/$AH$6 -> 0 | V2: =V6/$AH$6 -> 0 | Z2: =Z6/$AH$6 -> 0 | AB2: =AB6/$AH$6 -> 0 | AD2: =AD6/$AH$6 -> 0
A5: DEMONSTRATIVO DE RESULTADO GERENCIAL | B5: Jan | C5: %Jan | D5: Fev | E5: %Fev | F5: Mar | G5: %Mar | H5: 1ºTRI | I5: %1ºTRI | J5: Abr | K5: %Abr | L5: Mai | M5: %Mai | N5: Jun | O5: %Jun | P5: 2ºTRI | Q5: %2ºTRI | R5: Jul | S5: %Jul | T5: Ago | U5: %Ago | V5: Set | W5: %Set | X5: 3ºTRI | Y5: %3ºTRI | Z5: Out | AA5: %Out | AB5: Nov | AC5: %Nov | AD5: Dez | AE5: %Dez | AF5: 4ºTRI | AG5: %4ºTRI | AH5: ANO | AI5: %ANO
A6: (=)Receita Bruta | B6: =IFERROR(VLOOKUP($A6,APOIO!$B:$N,MATCH(B$5,APOIO!$B$5:$N$5,0),FALSE),0) -> 173156.44 | C6: =IFERROR(B6/B$6,0) -> 1 | D6: =IFERROR(VLOOKUP($A6,APOIO!$B:$N,MATCH(D$5,APOIO!$B$5:$N$5,0),FALSE),0) -> 420327.6 | E6: =IFERROR(D6/D$6,0) -> 1 | F6: =IFERROR(VLOOKUP($A6,APOIO!$B:$N,MATCH(F$5,APOIO!$B$5:$N$5,0),FALSE),0) -> 0 | G6: =IFERROR(F6/F$6,0) -> 0 | H6: =SUM(B6,D6,F6) -> 593484.04 | I6: =IFERROR(H6/H$6,0) -> 1 | J6: =IFERROR(VLOOKUP($A6,APOIO!$B:$N,MATCH(J$5,APOIO!$B$5:$N$5,0),FALSE),0) -> 0 | K6: =IFERROR(J6/J$6,0) -> 0 | L6: =IFERROR(VLOOKUP($A6,APOIO!$B:$N,MATCH(L$5,APOIO!$B$5:$N$5,0),FALSE),0) -> 0 | M6: =IFERROR(L6/L$6,0) -> 0 | N6: =IFERROR(VLOOKUP($A6,APOIO!$B:$N,MATCH(N$5,APOIO!$B$5:$N$5,0),FALSE),0) -> 0 | O6: =IFERROR(N6/N$6,0) -> 0 | P6: =SUM(J6,L6,N6) -> 0 | Q6: =IFERROR(P6/P$6,0) -> 0 | R6: =IFERROR(VLOOKUP($A6,APOIO!$B:$N,MATCH(R$5,APOIO!$B$5:$N$5,0),FALSE),0) -> 0 | S6: =IFERROR(R6/R$6,0) -> 0 | T6: =IFERROR(VLOOKUP($A6,APOIO!$B:$N,MATCH(T$5,APOIO!$B$5:$N$5,0),FALSE),0) -> 0 | U6: =IFERROR(T6/T$6,0) -> 0 | V6: =IFERROR(VLOOKUP($A6,APOIO!$B:$N,MATCH(V$5,APOIO!$B$5:$N$5,0),FALSE),0) -> 0 | W6: =IFERROR(V6/V$6,0) -> 0 | X6: =SUM(R6,T6,V6) -> 0 | Y6: =IFERROR(X6/X$6,0) -> 0 | Z6: =IFERROR(VLOOKUP($A6,APOIO!$B:$N,MATCH(Z$5,APOIO!$B$5:$N$5,0),FALSE),0) -> 0 | AA6: =IFERROR(Z6/Z$6,0) -> 0 | AB6: =IFERROR(VLOOKUP($A6,APOIO!$B:$N,MATCH(AB$5,APOIO!$B$5:$N$5,0),FALSE),0) -> 0 | AC6: =IFERROR(AB6/AB$6,0) -> 0 | AD6: =IFERROR(VLOOKUP($A6,APOIO!$B:$N,MATCH(AD$5,APOIO!$B$5:$N$5,0),FALSE),0) -> 0 | AE6: =IFERROR(AD6/AD$6,0) -> 0 | AF6: =SUM(Z6,AB6,AD6) -> 0 | AG6: =IFERROR(AF6/AF$6,0) -> 0 | AH6: =SUM(B6,D6,F6,J6,L6,N6,R6,T6,V6,Z6,AB6,AD6) -> 593484.04 | AI6: =IFERROR(AH6/AH$6,0) -> 1
A7: Faturamento | B7: =IFERROR(VLOOKUP($A7,APOIO!$B:$N,MATCH(B$5,APOIO!$B$5:$N$5,0),FALSE),0) -> 173156.44 | C7: =B7/B$6 -> 1 | D7: =IFERROR(VLOOKUP($A7,APOIO!$B:$N,MATCH(D$5,APOIO!$B$5:$N$5,0),FALSE),0) -> 420327.6 | E7: =D7/D$6 -> 1 | F7: =IFERROR(VLOOKUP($A7,APOIO!$B:$N,MATCH(F$5,APOIO!$B$5:$N$5,0),FALSE),0) -> 0 | G7: =F7/F$6 -> #DIV/0! | H7: =SUM(B7,D7,F7) -> 593484.04 | I7: =H7/H$6 -> 1 | J7: =IFERROR(VLOOKUP($A7,APOIO!$B:$N,MATCH(J$5,APOIO!$B$5:$N$5,0),FALSE),0) -> 0 | K7: =J7/J$6 -> #DIV/0! | L7: =IFERROR(VLOOKUP($A7,APOIO!$B:$N,MATCH(L$5,APOIO!$B$5:$N$5,0),FALSE),0) -> 0 | M7: =L7/L$6 -> #DIV/0! | N7: =IFERROR(VLOOKUP($A7,APOIO!$B:$N,MATCH(N$5,APOIO!$B$5:$N$5,0),FALSE),0) -> 0 | O7: =N7/N$6 -> #DIV/0! | P7: =SUM(J7,L7,N7) -> 0 | Q7: =P7/P$6 -> #DIV/0! | R7: =IFERROR(VLOOKUP($A7,APOIO!$B:$N,MATCH(R$5,APOIO!$B$5:$N$5,0),FALSE),0) -> 0 | S7: =R7/R$6 -> #DIV/0! | T7: =IFERROR(VLOOKUP($A7,APOIO!$B:$N,MATCH(T$5,APOIO!$B$5:$N$5,0),FALSE),0) -> 0 | U7: =T7/T$6 -> #DIV/0! | V7: =IFERROR(VLOOKUP($A7,APOIO!$B:$N,MATCH(V$5,APOIO!$B$5:$N$5,0),FALSE),0) -> 0 | W7: =V7/V$6 -> #DIV/0! | X7: =SUM(R7,T7,V7) -> 0 | Y7: =X7/X$6 -> #DIV/0! | Z7: =IFERROR(VLOOKUP($A7,APOIO!$B:$N,MATCH(Z$5,APOIO!$B$5:$N$5,0),FALSE),0) -> 0 | AA7: =Z7/Z$6 -> #DIV/0! | AB7: =IFERROR(VLOOKUP($A7,APOIO!$B:$N,MATCH(AB$5,APOIO!$B$5:$N$5,0),FALSE),0) -> 0 | AC7: =AB7/AB$6 -> #DIV/0! | AD7: =IFERROR(VLOOKUP($A7,APOIO!$B:$N,MATCH(AD$5,APOIO!$B$5:$N$5,0),FALSE),0) -> 0 | AE7: =AD7/AD$6 -> #DIV/0! | AF7: =SUM(Z7,AB7,AD7) -> 0 | AG7: =AF7/AF$6 -> #DIV/0! | AH7: =SUM(B7,D7,F7,J7,L7,N7,R7,T7,V7,Z7,AB7,AD7) -> 593484.04 | AI7: =AH7/AH$6 -> 1
A8: (-)Deduções sobre vendas | B8: =IFERROR(VLOOKUP($A8,APOIO!$B:$N,MATCH(B$5,APOIO!$B$5:$N$5,0),FALSE),0) -> -17981.98 | C8: =IFERROR(B8/B$6,0) -> -0.10384817 | D8: =IFERROR(VLOOKUP($A8,APOIO!$B:$N,MATCH(D$5,APOIO!$B$5:$N$5,0),FALSE),0) -> -55263.83 | E8: =IFERROR(D8/D$6,0) -> -0.13147799 | F8: =IFERROR(VLOOKUP($A8,APOIO!$B:$N,MATCH(F$5,APOIO!$B$5:$N$5,0),FALSE),0) -> 0 | G8: =IFERROR(F8/F$6,0) -> 0 | H8: =SUM(B8,D8,F8) -> -73245.81 | I8: =IFERROR(H8/H$6,0) -> -0.12341665 | J8: =IFERROR(VLOOKUP($A8,APOIO!$B:$N,MATCH(J$5,APOIO!$B$5:$N$5,0),FALSE),0) -> 0 | K8: =IFERROR(J8/J$6,0) -> 0 | L8: =IFERROR(VLOOKUP($A8,APOIO!$B:$N,MATCH(L$5,APOIO!$B$5:$N$5,0),FALSE),0) -> 0 | M8: =IFERROR(L8/L$6,0) -> 0 | N8: =IFERROR(VLOOKUP($A8,APOIO!$B:$N,MATCH(N$5,APOIO!$B$5:$N$5,0),FALSE),0) -> 0 | O8: =IFERROR(N8/N$6,0) -> 0 | P8: =SUM(J8,L8,N8) -> 0 | Q8: =IFERROR(P8/P$6,0) -> 0 | R8: =IFERROR(VLOOKUP($A8,APOIO!$B:$N,MATCH(R$5,APOIO!$B$5:$N$5,0),FALSE),0) -> 0 | S8: =IFERROR(R8/R$6,0) -> 0 | T8: =IFERROR(VLOOKUP($A8,APOIO!$B:$N,MATCH(T$5,APOIO!$B$5:$N$5,0),FALSE),0) -> 0 | U8: =IFERROR(T8/T$6,0) -> 0 | V8: =IFERROR(VLOOKUP($A8,APOIO!$B:$N,MATCH(V$5,APOIO!$B$5:$N$5,0),FALSE),0) -> 0 | W8: =IFERROR(V8/V$6,0) -> 0 | X8: =SUM(R8,T8,V8) -> 0 | Y8: =IFERROR(X8/X$6,0) -> 0 | Z8: =IFERROR(VLOOKUP($A8,APOIO!$B:$N,MATCH(Z$5,APOIO!$B$5:$N$5,0),FALSE),0) -> 0 | AA8: =IFERROR(Z8/Z$6,0) -> 0 | AB8: =IFERROR(VLOOKUP($A8,APOIO!$B:$N,MATCH(AB$5,APOIO!$B$5:$N$5,0),FALSE),0) -> 0 | AC8: =IFERROR(AB8/AB$6,0) -> 0 | AD8: =IFERROR(VLOOKUP($A8,APOIO!$B:$N,MATCH(AD$5,APOIO!$B$5:$N$5,0),FALSE),0) -> 0 | AE8: =IFERROR(AD8/AD$6,0) -> 0 | AF8: =SUM(Z8,AB8,AD8) -> 0 | AG8: =IFERROR(AF8/AF$6,0) -> 0 | AH8: =SUM(B8,D8,F8,J8,L8,N8,R8,T8,V8,Z8,AB8,AD8) -> -73245.81 | AI8: =IFERROR(AH8/AH$6,0) -> -0.12341665
A9: Descontos sobre vendas | B9: =IFERROR(VLOOKUP($A9,APOIO!$B:$N,MATCH(B$5,APOIO!$B$5:$N$5,0),FALSE),0) -> 0 | C9: =IFERROR(B9/B$6,0) -> 0 | D9: =IFERROR(VLOOKUP($A9,APOIO!$B:$N,MATCH(D$5,APOIO!$B$5:$N$5,0),FALSE),0) -> 0 | E9: =IFERROR(D9/D$6,0) -> 0 | F9: =IFERROR(VLOOKUP($A9,APOIO!$B:$N,MATCH(F$5,APOIO!$B$5:$N$5,0),FALSE),0) -> 0 | G9: =IFERROR(F9/F$6,0) -> 0 | H9: =SUM(B9,D9,F9) -> 0 | I9: =IFERROR(H9/H$6,0) -> 0 | J9: =IFERROR(VLOOKUP($A9,APOIO!$B:$N,MATCH(J$5,APOIO!$B$5:$N$5,0),FALSE),0) -> 0 | K9: =IFERROR(J9/J$6,0) -> 0 | L9: =IFERROR(VLOOKUP($A9,APOIO!$B:$N,MATCH(L$5,APOIO!$B$5:$N$5,0),FALSE),0) -> 0 | M9: =IFERROR(L9/L$6,0) -> 0 | N9: =IFERROR(VLOOKUP($A9,APOIO!$B:$N,MATCH(N$5,APOIO!$B$5:$N$5,0),FALSE),0) -> 0 | O9: =IFERROR(N9/N$6,0) -> 0 | P9: =SUM(J9,L9,N9) -> 0 | Q9: =IFERROR(P9/P$6,0) -> 0 | R9: =IFERROR(VLOOKUP($A9,APOIO!$B:$N,MATCH(R$5,APOIO!$B$5:$N$5,0),FALSE),0) -> 0 | S9: =IFERROR(R9/R$6,0) -> 0 | T9: =IFERROR(VLOOKUP($A9,APOIO!$B:$N,MATCH(T$5,APOIO!$B$5:$N$5,0),FALSE),0) -> 0 | U9: =IFERROR(T9/T$6,0) -> 0 | V9: =IFERROR(VLOOKUP($A9,APOIO!$B:$N,MATCH(V$5,APOIO!$B$5:$N$5,0),FALSE),0) -> 0 | W9: =IFERROR(V9/V$6,0) -> 0 | X9: =SUM(R9,T9,V9) -> 0 | Y9: =IFERROR(X9/X$6,0) -> 0 | Z9: =IFERROR(VLOOKUP($A9,APOIO!$B:$N,MATCH(Z$5,APOIO!$B$5:$N$5,0),FALSE),0) -> 0 | AA9: =IFERROR(Z9/Z$6,0) -> 0 | AB9: =IFERROR(VLOOKUP($A9,APOIO!$B:$N,MATCH(AB$5,APOIO!$B$5:$N$5,0),FALSE),0) -> 0 | AC9: =IFERROR(AB9/AB$6,0) -> 0 | AD9: =IFERROR(VLOOKUP($A9,APOIO!$B:$N,MATCH(AD$5,APOIO!$B$5:$N$5,0),FALSE),0) -> 0 | AE9: =IFERROR(AD9/AD$6,0) -> 0 | AF9: =SUM(Z9,AB9,AD9) -> 0 | AG9: =IFERROR(AF9/AF$6,0) -> 0 | AH9: =SUM(B9,D9,F9,J9,L9,N9,R9,T9,V9,Z9,AB9,AD9) -> 0 | AI9: =IFERROR(AH9/AH$6,0) -> 0
A10: Impostos sobre vendas | B10: =IFERROR(VLOOKUP($A10,APOIO!$B:$N,MATCH(B$5,APOIO!$B$5:$N$5,0),FALSE),0) -> -17981.98 | C10: =IFERROR(B10/B$6,0) -> -0.10384817 | D10: =IFERROR(VLOOKUP($A10,APOIO!$B:$N,MATCH(D$5,APOIO!$B$5:$N$5,0),FALSE),0) -> -55263.83 | E10: =IFERROR(D10/D$6,0) -> -0.13147799 | F10: =IFERROR(VLOOKUP($A10,APOIO!$B:$N,MATCH(F$5,APOIO!$B$5:$N$5,0),FALSE),0) -> 0 | G10: =IFERROR(F10/F$6,0) -> 0 | H10: =SUM(B10,D10,F10) -> -73245.81 | I10: =IFERROR(H10/H$6,0) -> -0.12341665 | J10: =IFERROR(VLOOKUP($A10,APOIO!$B:$N,MATCH(J$5,APOIO!$B$5:$N$5,0),FALSE),0) -> 0 | K10: =IFERROR(J10/J$6,0) -> 0 | L10: =IFERROR(VLOOKUP($A10,APOIO!$B:$N,MATCH(L$5,APOIO!$B$5:$N$5,0),FALSE),0) -> 0 | M10: =IFERROR(L10/L$6,0) -> 0 | N10: =IFERROR(VLOOKUP($A10,APOIO!$B:$N,MATCH(N$5,APOIO!$B$5:$N$5,0),FALSE),0) -> 0 | O10: =IFERROR(N10/N$6,0) -> 0 | P10: =SUM(J10,L10,N10) -> 0 | Q10: =IFERROR(P10/P$6,0) -> 0 | R10: =IFERROR(VLOOKUP($A10,APOIO!$B:$N,MATCH(R$5,APOIO!$B$5:$N$5,0),FALSE),0) -> 0 | S10: =IFERROR(R10/R$6,0) -> 0 | T10: =IFERROR(VLOOKUP($A10,APOIO!$B:$N,MATCH(T$5,APOIO!$B$5:$N$5,0),FALSE),0) -> 0 | U10: =IFERROR(T10/T$6,0) -> 0 | V10: =IFERROR(VLOOKUP($A10,APOIO!$B:$N,MATCH(V$5,APOIO!$B$5:$N$5,0),FALSE),0) -> 0 | W10: =IFERROR(V10/V$6,0) -> 0 | X10: =SUM(R10,T10,V10) -> 0 | Y10: =IFERROR(X10/X$6,0) -> 0 | Z10: =IFERROR(VLOOKUP($A10,APOIO!$B:$N,MATCH(Z$5,APOIO!$B$5:$N$5,0),FALSE),0) -> 0 | AA10: =IFERROR(Z10/Z$6,0) -> 0 | AB10: =IFERROR(VLOOKUP($A10,APOIO!$B:$N,MATCH(AB$5,APOIO!$B$5:$N$5,0),FALSE),0) -> 0 | AC10: =IFERROR(AB10/AB$6,0) -> 0 | AD10: =IFERROR(VLOOKUP($A10,APOIO!$B:$N,MATCH(AD$5,APOIO!$B$5:$N$5,0),FALSE),0) -> 0 | AE10: =IFERROR(AD10/AD$6,0) -> 0 | AF10: =SUM(Z10,AB10,AD10) -> 0 | AG10: =IFERROR(AF10/AF$6,0) -> 0 | AH10: =SUM(B10,D10,F10,J10,L10,N10,R10,T10,V10,Z10,AB10,AD10) -> -73245.81 | AI10: =IFERROR(AH10/AH$6,0) -> -0.12341665
A11: Simples Nacional | B11: =IFERROR(VLOOKUP($A11,APOIO!$B:$N,MATCH(B$5,APOIO!$B$5:$N$5,0),FALSE),0) -> 0 | C11: =IFERROR(B11/B$6,0) -> 0 | D11: =IFERROR(VLOOKUP($A11,APOIO!$B:$N,MATCH(D$5,APOIO!$B$5:$N$5,0),FALSE),0) -> 0 | E11: =IFERROR(D11/D$6,0) -> 0 | F11: =IFERROR(VLOOKUP($A11,APOIO!$B:$N,MATCH(F$5,APOIO!$B$5:$N$5,0),FALSE),0) -> 0 | G11: =IFERROR(F11/F$6,0) -> 0 | H11: =SUM(B11,D11,F11) -> 0 | I11: =IFERROR(H11/H$6,0) -> 0 | J11: =IFERROR(VLOOKUP($A11,APOIO!$B:$N,MATCH(J$5,APOIO!$B$5:$N$5,0),FALSE),0) -> 0 | K11: =IFERROR(J11/J$6,0) -> 0 | L11: =IFERROR(VLOOKUP($A11,APOIO!$B:$N,MATCH(L$5,APOIO!$B$5:$N$5,0),FALSE),0) -> 0 | M11: =IFERROR(L11/L$6,0) -> 0 | N11: =IFERROR(VLOOKUP($A11,APOIO!$B:$N,MATCH(N$5,APOIO!$B$5:$N$5,0),FALSE),0) -> 0 | O11: =IFERROR(N11/N$6,0) -> 0 | P11: =SUM(J11,L11,N11) -> 0 | Q11: =IFERROR(P11/P$6,0) -> 0 | R11: =IFERROR(VLOOKUP($A11,APOIO!$B:$N,MATCH(R$5,APOIO!$B$5:$N$5,0),FALSE),0) -> 0 | S11: =IFERROR(R11/R$6,0) -> 0 | T11: =IFERROR(VLOOKUP($A11,APOIO!$B:$N,MATCH(T$5,APOIO!$B$5:$N$5,0),FALSE),0) -> 0 | U11: =IFERROR(T11/T$6,0) -> 0 | V11: =IFERROR(VLOOKUP($A11,APOIO!$B:$N,MATCH(V$5,APOIO!$B$5:$N$5,0),FALSE),0) -> 0 | W11: =IFERROR(V11/V$6,0) -> 0 | X11: =SUM(R11,T11,V11) -> 0 | Y11: =IFERROR(X11/X$6,0) -> 0 | Z11: =IFERROR(VLOOKUP($A11,APOIO!$B:$N,MATCH(Z$5,APOIO!$B$5:$N$5,0),FALSE),0) -> 0 | AA11: =IFERROR(Z11/Z$6,0) -> 0 | AB11: =IFERROR(VLOOKUP($A11,APOIO!$B:$N,MATCH(AB$5,APOIO!$B$5:$N$5,0),FALSE),0) -> 0 | AC11: =IFERROR(AB11/AB$6,0) -> 0 | AD11: =IFERROR(VLOOKUP($A11,APOIO!$B:$N,MATCH(AD$5,APOIO!$B$5:$N$5,0),FALSE),0) -> 0 | AE11: =IFERROR(AD11/AD$6,0) -> 0 | AF11: =SUM(Z11,AB11,AD11) -> 0 | AG11: =IFERROR(AF11/AF$6,0) -> 0 | AH11: =SUM(B11,D11,F11,J11,L11,N11,R11,T11,V11,Z11,AB11,AD11) -> 0 | AI11: =IFERROR(AH11/AH$6,0) -> 0
A12: IR Retido | B12: =IFERROR(VLOOKUP($A12,APOIO!$B:$N,MATCH(B$5,APOIO!$B$5:$N$5,0),FALSE),0) -> -1976.04 | C12: =IFERROR(B12/B$6,0) -> -0.011411877 | D12: =IFERROR(VLOOKUP($A12,APOIO!$B:$N,MATCH(D$5,APOIO!$B$5:$N$5,0),FALSE),0) -> -6072.95 | E12: =IFERROR(D12/D$6,0) -> -0.014448135 | F12: =IFERROR(VLOOKUP($A12,APOIO!$B:$N,MATCH(F$5,APOIO!$B$5:$N$5,0),FALSE),0) -> 0 | G12: =IFERROR(F12/F$6,0) -> 0 | H12: =SUM(B12,D12,F12) -> -8048.99 | I12: =IFERROR(H12/H$6,0) -> -0.013562269 | J12: =IFERROR(VLOOKUP($A12,APOIO!$B:$N,MATCH(J$5,APOIO!$B$5:$N$5,0),FALSE),0) -> 0 | K12: =IFERROR(J12/J$6,0) -> 0 | L12: =IFERROR(VLOOKUP($A12,APOIO!$B:$N,MATCH(L$5,APOIO!$B$5:$N$5,0),FALSE),0) -> 0 | M12: =IFERROR(L12/L$6,0) -> 0 | N12: =IFERROR(VLOOKUP($A12,APOIO!$B:$N,MATCH(N$5,APOIO!$B$5:$N$5,0),FALSE),0) -> 0 | O12: =IFERROR(N12/N$6,0) -> 0 | P12: =SUM(J12,L12,N12) -> 0 | Q12: =IFERROR(P12/P$6,0) -> 0 | R12: =IFERROR(VLOOKUP($A12,APOIO!$B:$N,MATCH(R$5,APOIO!$B$5:$N$5,0),FALSE),0) -> 0 | S12: =IFERROR(R12/R$6,0) -> 0 | T12: =IFERROR(VLOOKUP($A12,APOIO!$B:$N,MATCH(T$5,APOIO!$B$5:$N$5,0),FALSE),0) -> 0 | U12: =IFERROR(T12/T$6,0) -> 0 | V12: =IFERROR(VLOOKUP($A12,APOIO!$B:$N,MATCH(V$5,APOIO!$B$5:$N$5,0),FALSE),0) -> 0 | W12: =IFERROR(V12/V$6,0) -> 0 | X12: =SUM(R12,T12,V12) -> 0 | Y12: =IFERROR(X12/X$6,0) -> 0 | Z12: =IFERROR(VLOOKUP($A12,APOIO!$B:$N,MATCH(Z$5,APOIO!$B$5:$N$5,0),FALSE),0) -> 0 | AA12: =IFERROR(Z12/Z$6,0) -> 0 | AB12: =IFERROR(VLOOKUP($A12,APOIO!$B:$N,MATCH(AB$5,APOIO!$B$5:$N$5,0),FALSE),0) -> 0 | AC12: =IFERROR(AB12/AB$6,0) -> 0 | AD12: =IFERROR(VLOOKUP($A12,APOIO!$B:$N,MATCH(AD$5,APOIO!$B$5:$N$5,0),FALSE),0) -> 0 | AE12: =IFERROR(AD12/AD$6,0) -> 0 | AF12: =SUM(Z12,AB12,AD12) -> 0 | AG12: =IFERROR(AF12/AF$6,0) -> 0 | AH12: =SUM(B12,D12,F12,J12,L12,N12,R12,T12,V12,Z12,AB12,AD12) -> -8048.99 | AI12: =IFERROR(AH12/AH$6,0) -> -0.013562269
A13: ISS Retido | B13: =IFERROR(VLOOKUP($A13,APOIO!$B:$N,MATCH(B$5,APOIO!$B$5:$N$5,0),FALSE),0) -> -6586.81 | C13: =IFERROR(B13/B$6,0) -> -0.038039648 | D13: =IFERROR(VLOOKUP($A13,APOIO!$B:$N,MATCH(D$5,APOIO!$B$5:$N$5,0),FALSE),0) -> -20243.16 | E13: =IFERROR(D13/D$6,0) -> -0.048160435 | F13: =IFERROR(VLOOKUP($A13,APOIO!$B:$N,MATCH(F$5,APOIO!$B$5:$N$5,0),FALSE),0) -> 0 | G13: =IFERROR(F13/F$6,0) -> 0 | H13: =SUM(B13,D13,F13) -> -26829.97 | I13: =IFERROR(H13/H$6,0) -> -0.045207568 | J13: =IFERROR(VLOOKUP($A13,APOIO!$B:$N,MATCH(J$5,APOIO!$B$5:$N$5,0),FALSE),0) -> 0 | K13: =IFERROR(J13/J$6,0) -> 0 | L13: =IFERROR(VLOOKUP($A13,APOIO!$B:$N,MATCH(L$5,APOIO!$B$5:$N$5,0),FALSE),0) -> 0 | M13: =IFERROR(L13/L$6,0) -> 0 | N13: =IFERROR(VLOOKUP($A13,APOIO!$B:$N,MATCH(N$5,APOIO!$B$5:$N$5,0),FALSE),0) -> 0 | O13: =IFERROR(N13/N$6,0) -> 0 | P13: =SUM(J13,L13,N13) -> 0 | Q13: =IFERROR(P13/P$6,0) -> 0 | R13: =IFERROR(VLOOKUP($A13,APOIO!$B:$N,MATCH(R$5,APOIO!$B$5:$N$5,0),FALSE),0) -> 0 | S13: =IFERROR(R13/R$6,0) -> 0 | T13: =IFERROR(VLOOKUP($A13,APOIO!$B:$N,MATCH(T$5,APOIO!$B$5:$N$5,0),FALSE),0) -> 0 | U13: =IFERROR(T13/T$6,0) -> 0 | V13: =IFERROR(VLOOKUP($A13,APOIO!$B:$N,MATCH(V$5,APOIO!$B$5:$N$5,0),FALSE),0) -> 0 | W13: =IFERROR(V13/V$6,0) -> 0 | X13: =SUM(R13,T13,V13) -> 0 | Y13: =IFERROR(X13/X$6,0) -> 0 | Z13: =IFERROR(VLOOKUP($A13,APOIO!$B:$N,MATCH(Z$5,APOIO!$B$5:$N$5,0),FALSE),0) -> 0 | AA13: =IFERROR(Z13/Z$6,0) -> 0 | AB13: =IFERROR(VLOOKUP($A13,APOIO!$B:$N,MATCH(AB$5,APOIO!$B$5:$N$5,0),FALSE),0) -> 0 | AC13: =IFERROR(AB13/AB$6,0) -> 0 | AD13: =IFERROR(VLOOKUP($A13,APOIO!$B:$N,MATCH(AD$5,APOIO!$B$5:$N$5,0),FALSE),0) -> 0 | AE13: =IFERROR(AD13/AD$6,0) -> 0 | AF13: =SUM(Z13,AB13,AD13) -> 0 | AG13: =IFERROR(AF13/AF$6,0) -> 0 | AH13: =SUM(B13,D13,F13,J13,L13,N13,R13,T13,V13,Z13,AB13,AD13) -> -26829.97 | AI13: =IFERROR(AH13/AH$6,0) -> -0.045207568
A14: INSS Retido | B14: =IFERROR(VLOOKUP($A14,APOIO!$B:$N,MATCH(B$5,APOIO!$B$5:$N$5,0),FALSE),0) -> -4610.76 | C14: =IFERROR(B14/B$6,0) -> -0.026627713 | D14: =IFERROR(VLOOKUP($A14,APOIO!$B:$N,MATCH(D$5,APOIO!$B$5:$N$5,0),FALSE),0) -> -14170.21 | E14: =IFERROR(D14/D$6,0) -> -0.0337123 | F14: =IFERROR(VLOOKUP($A14,APOIO!$B:$N,MATCH(F$5,APOIO!$B$5:$N$5,0),FALSE),0) -> 0 | G14: =IFERROR(F14/F$6,0) -> 0 | H14: =SUM(B14,D14,F14) -> -18780.97 | I14: =IFERROR(H14/H$6,0) -> -0.031645282 | J14: =IFERROR(VLOOKUP($A14,APOIO!$B:$N,MATCH(J$5,APOIO!$B$5:$N$5,0),FALSE),0) -> 0 | K14: =IFERROR(J14/J$6,0) -> 0 | L14: =IFERROR(VLOOKUP($A14,APOIO!$B:$N,MATCH(L$5,APOIO!$B$5:$N$5,0),FALSE),0) -> 0 | M14: =IFERROR(L14/L$6,0) -> 0 | N14: =IFERROR(VLOOKUP($A14,APOIO!$B:$N,MATCH(N$5,APOIO!$B$5:$N$5,0),FALSE),0) -> 0 | O14: =IFERROR(N14/N$6,0) -> 0 | P14: =SUM(J14,L14,N14) -> 0 | Q14: =IFERROR(P14/P$6,0) -> 0 | R14: =IFERROR(VLOOKUP($A14,APOIO!$B:$N,MATCH(R$5,APOIO!$B$5:$N$5,0),FALSE),0) -> 0 | S14: =IFERROR(R14/R$6,0) -> 0 | T14: =IFERROR(VLOOKUP($A14,APOIO!$B:$N,MATCH(T$5,APOIO!$B$5:$N$5,0),FALSE),0) -> 0 | U14: =IFERROR(T14/T$6,0) -> 0 | V14: =IFERROR(VLOOKUP($A14,APOIO!$B:$N,MATCH(V$5,APOIO!$B$5:$N$5,0),FALSE),0) -> 0 | W14: =IFERROR(V14/V$6,0) -> 0 | X14: =SUM(R14,T14,V14) -> 0 | Y14: =IFERROR(X14/X$6,0) -> 0 | Z14: =IFERROR(VLOOKUP($A14,APOIO!$B:$N,MATCH(Z$5,APOIO!$B$5:$N$5,0),FALSE),0) -> 0 | AA14: =IFERROR(Z14/Z$6,0) -> 0 | AB14: =IFERROR(VLOOKUP($A14,APOIO!$B:$N,MATCH(AB$5,APOIO!$B$5:$N$5,0),FALSE),0) -> 0 | AC14: =IFERROR(AB14/AB$6,0) -> 0 | AD14: =IFERROR(VLOOKUP($A14,APOIO!$B:$N,MATCH(AD$5,APOIO!$B$5:$N$5,0),FALSE),0) -> 0 | AE14: =IFERROR(AD14/AD$6,0) -> 0 | AF14: =SUM(Z14,AB14,AD14) -> 0 | AG14: =IFERROR(AF14/AF$6,0) -> 0 | AH14: =SUM(B14,D14,F14,J14,L14,N14,R14,T14,V14,Z14,AB14,AD14) -> -18780.97 | AI14: =IFERROR(AH14/AH$6,0) -> -0.031645282
A15: Tarifa de Antecipação | B15: =IFERROR(VLOOKUP($A15,APOIO!$B:$N,MATCH(B$5,APOIO!$B$5:$N$5,0),FALSE),0) -> 0 | C15: =IFERROR(B15/B$6,0) -> 0 | D15: =IFERROR(VLOOKUP($A15,APOIO!$B:$N,MATCH(D$5,APOIO!$B$5:$N$5,0),FALSE),0) -> 0 | E15: =IFERROR(D15/D$6,0) -> 0 | F15: =IFERROR(VLOOKUP($A15,APOIO!$B:$N,MATCH(F$5,APOIO!$B$5:$N$5,0),FALSE),0) -> 0 | G15: =IFERROR(F15/F$6,0) -> 0 | H15: =SUM(B15,D15,F15) -> 0 | I15: =IFERROR(H15/H$6,0) -> 0 | J15: =IFERROR(VLOOKUP($A15,APOIO!$B:$N,MATCH(J$5,APOIO!$B$5:$N$5,0),FALSE),0) -> 0 | K15: =IFERROR(J15/J$6,0) -> 0 | L15: =IFERROR(VLOOKUP($A15,APOIO!$B:$N,MATCH(L$5,APOIO!$B$5:$N$5,0),FALSE),0) -> 0 | M15: =IFERROR(L15/L$6,0) -> 0 | N15: =IFERROR(VLOOKUP($A15,APOIO!$B:$N,MATCH(N$5,APOIO!$B$5:$N$5,0),FALSE),0) -> 0 | O15: =IFERROR(N15/N$6,0) -> 0 | P15: =SUM(J15,L15,N15) -> 0 | Q15: =IFERROR(P15/P$6,0) -> 0 | R15: =IFERROR(VLOOKUP($A15,APOIO!$B:$N,MATCH(R$5,APOIO!$B$5:$N$5,0),FALSE),0) -> 0 | S15: =IFERROR(R15/R$6,0) -> 0 | T15: =IFERROR(VLOOKUP($A15,APOIO!$B:$N,MATCH(T$5,APOIO!$B$5:$N$5,0),FALSE),0) -> 0 | U15: =IFERROR(T15/T$6,0) -> 0 | V15: =IFERROR(VLOOKUP($A15,APOIO!$B:$N,MATCH(V$5,APOIO!$B$5:$N$5,0),FALSE),0) -> 0 | W15: =IFERROR(V15/V$6,0) -> 0 | X15: =SUM(R15,T15,V15) -> 0 | Y15: =IFERROR(X15/X$6,0) -> 0 | Z15: =IFERROR(VLOOKUP($A15,APOIO!$B:$N,MATCH(Z$5,APOIO!$B$5:$N$5,0),FALSE),0) -> 0 | AA15: =IFERROR(Z15/Z$6,0) -> 0 | AB15: =IFERROR(VLOOKUP($A15,APOIO!$B:$N,MATCH(AB$5,APOIO!$B$5:$N$5,0),FALSE),0) -> 0 | AC15: =IFERROR(AB15/AB$6,0) -> 0 | AD15: =IFERROR(VLOOKUP($A15,APOIO!$B:$N,MATCH(AD$5,APOIO!$B$5:$N$5,0),FALSE),0) -> 0 | AE15: =IFERROR(AD15/AD$6,0) -> 0 | AF15: =SUM(Z15,AB15,AD15) -> 0 | AG15: =IFERROR(AF15/AF$6,0) -> 0 | AH15: =SUM(B15,D15,F15,J15,L15,N15,R15,T15,V15,Z15,AB15,AD15) -> 0 | AI15: =IFERROR(AH15/AH$6,0) -> 0
A16: ISS | B16: =IFERROR(VLOOKUP($A16,APOIO!$B:$N,MATCH(B$5,APOIO!$B$5:$N$5,0),FALSE),0) -> 0 | C16: =IFERROR(B16/B$6,0) -> 0 | D16: =IFERROR(VLOOKUP($A16,APOIO!$B:$N,MATCH(D$5,APOIO!$B$5:$N$5,0),FALSE),0) -> 0 | E16: =IFERROR(D16/D$6,0) -> 0 | F16: =IFERROR(VLOOKUP($A16,APOIO!$B:$N,MATCH(F$5,APOIO!$B$5:$N$5,0),FALSE),0) -> 0 | G16: =IFERROR(F16/F$6,0) -> 0 | H16: =SUM(B16,D16,F16) -> 0 | I16: =IFERROR(H16/H$6,0) -> 0 | J16: =IFERROR(VLOOKUP($A16,APOIO!$B:$N,MATCH(J$5,APOIO!$B$5:$N$5,0),FALSE),0) -> 0 | K16: =IFERROR(J16/J$6,0) -> 0 | L16: =IFERROR(VLOOKUP($A16,APOIO!$B:$N,MATCH(L$5,APOIO!$B$5:$N$5,0),FALSE),0) -> 0 | M16: =IFERROR(L16/L$6,0) -> 0 | N16: =IFERROR(VLOOKUP($A16,APOIO!$B:$N,MATCH(N$5,APOIO!$B$5:$N$5,0),FALSE),0) -> 0 | O16: =IFERROR(N16/N$6,0) -> 0 | P16: =SUM(J16,L16,N16) -> 0 | Q16: =IFERROR(P16/P$6,0) -> 0 | R16: =IFERROR(VLOOKUP($A16,APOIO!$B:$N,MATCH(R$5,APOIO!$B$5:$N$5,0),FALSE),0) -> 0 | S16: =IFERROR(R16/R$6,0) -> 0 | T16: =IFERROR(VLOOKUP($A16,APOIO!$B:$N,MATCH(T$5,APOIO!$B$5:$N$5,0),FALSE),0) -> 0 | U16: =IFERROR(T16/T$6,0) -> 0 | V16: =IFERROR(VLOOKUP($A16,APOIO!$B:$N,MATCH(V$5,APOIO!$B$5:$N$5,0),FALSE),0) -> 0 | W16: =IFERROR(V16/V$6,0) -> 0 | X16: =SUM(R16,T16,V16) -> 0 | Y16: =IFERROR(X16/X$6,0) -> 0 | Z16: =IFERROR(VLOOKUP($A16,APOIO!$B:$N,MATCH(Z$5,APOIO!$B$5:$N$5,0),FALSE),0) -> 0 | AA16: =IFERROR(Z16/Z$6,0) -> 0 | AB16: =IFERROR(VLOOKUP($A16,APOIO!$B:$N,MATCH(AB$5,APOIO!$B$5:$N$5,0),FALSE),0) -> 0 | AC16: =IFERROR(AB16/AB$6,0) -> 0 | AD16: =IFERROR(VLOOKUP($A16,APOIO!$B:$N,MATCH(AD$5,APOIO!$B$5:$N$5,0),FALSE),0) -> 0 | AE16: =IFERROR(AD16/AD$6,0) -> 0 | AF16: =SUM(Z16,AB16,AD16) -> 0 | AG16: =IFERROR(AF16/AF$6,0) -> 0 | AH16: =SUM(B16,D16,F16,J16,L16,N16,R16,T16,V16,Z16,AB16,AD16) -> 0 | AI16: =IFERROR(AH16/AH$6,0) -> 0
A17: PIS | B17: =IFERROR(VLOOKUP($A17,APOIO!$B:$N,MATCH(B$5,APOIO!$B$5:$N$5,0),FALSE),0) -> -856.29 | C17: =IFERROR(B17/B$6,0) -> -0.0049451814 | D17: =IFERROR(VLOOKUP($A17,APOIO!$B:$N,MATCH(D$5,APOIO!$B$5:$N$5,0),FALSE),0) -> -2631.62 | E17: =IFERROR(D17/D$6,0) -> -0.0062608784 | F17: =IFERROR(VLOOKUP($A17,APOIO!$B:$N,MATCH(F$5,APOIO!$B$5:$N$5,0),FALSE),0) -> 0 | G17: =IFERROR(F17/F$6,0) -> 0 | H17: =SUM(B17,D17,F17) -> -3487.91 | I17: =IFERROR(H17/H$6,0) -> -0.0058770072 | J17: =IFERROR(VLOOKUP($A17,APOIO!$B:$N,MATCH(J$5,APOIO!$B$5:$N$5,0),FALSE),0) -> 0 | K17: =IFERROR(J17/J$6,0) -> 0 | L17: =IFERROR(VLOOKUP($A17,APOIO!$B:$N,MATCH(L$5,APOIO!$B$5:$N$5,0),FALSE),0) -> 0 | M17: =IFERROR(L17/L$6,0) -> 0 | N17: =IFERROR(VLOOKUP($A17,APOIO!$B:$N,MATCH(N$5,APOIO!$B$5:$N$5,0),FALSE),0) -> 0 | O17: =IFERROR(N17/N$6,0) -> 0 | P17: =SUM(J17,L17,N17) -> 0 | Q17: =IFERROR(P17/P$6,0) -> 0 | R17: =IFERROR(VLOOKUP($A17,APOIO!$B:$N,MATCH(R$5,APOIO!$B$5:$N$5,0),FALSE),0) -> 0 | S17: =IFERROR(R17/R$6,0) -> 0 | T17: =IFERROR(VLOOKUP($A17,APOIO!$B:$N,MATCH(T$5,APOIO!$B$5:$N$5,0),FALSE),0) -> 0 | U17: =IFERROR(T17/T$6,0) -> 0 | V17: =IFERROR(VLOOKUP($A17,APOIO!$B:$N,MATCH(V$5,APOIO!$B$5:$N$5,0),FALSE),0) -> 0 | W17: =IFERROR(V17/V$6,0) -> 0 | X17: =SUM(R17,T17,V17) -> 0 | Y17: =IFERROR(X17/X$6,0) -> 0 | Z17: =IFERROR(VLOOKUP($A17,APOIO!$B:$N,MATCH(Z$5,APOIO!$B$5:$N$5,0),FALSE),0) -> 0 | AA17: =IFERROR(Z17/Z$6,0) -> 0 | AB17: =IFERROR(VLOOKUP($A17,APOIO!$B:$N,MATCH(AB$5,APOIO!$B$5:$N$5,0),FALSE),0) -> 0 | AC17: =IFERROR(AB17/AB$6,0) -> 0 | AD17: =IFERROR(VLOOKUP($A17,APOIO!$B:$N,MATCH(AD$5,APOIO!$B$5:$N$5,0),FALSE),0) -> 0 | AE17: =IFERROR(AD17/AD$6,0) -> 0 | AF17: =SUM(Z17,AB17,AD17) -> 0 | AG17: =IFERROR(AF17/AF$6,0) -> 0 | AH17: =SUM(B17,D17,F17,J17,L17,N17,R17,T17,V17,Z17,AB17,AD17) -> -3487.91 | AI17: =IFERROR(AH17/AH$6,0) -> -0.0058770072
A18: COFINS | B18: =IFERROR(VLOOKUP($A18,APOIO!$B:$N,MATCH(B$5,APOIO!$B$5:$N$5,0),FALSE),0) -> -3952.08 | C18: =IFERROR(B18/B$6,0) -> -0.022823754 | D18: =IFERROR(VLOOKUP($A18,APOIO!$B:$N,MATCH(D$5,APOIO!$B$5:$N$5,0),FALSE),0) -> -12145.89 | E18: =IFERROR(D18/D$6,0) -> -0.028896247 | F18: =IFERROR(VLOOKUP($A18,APOIO!$B:$N,MATCH(F$5,APOIO!$B$5:$N$5,0),FALSE),0) -> 0 | G18: =IFERROR(F18/F$6,0) -> 0 | H18: =SUM(B18,D18,F18) -> -16097.97 | I18: =IFERROR(H18/H$6,0) -> -0.02712452 | J18: =IFERROR(VLOOKUP($A18,APOIO!$B:$N,MATCH(J$5,APOIO!$B$5:$N$5,0),FALSE),0) -> 0 | K18: =IFERROR(J18/J$6,0) -> 0 | L18: =IFERROR(VLOOKUP($A18,APOIO!$B:$N,MATCH(L$5,APOIO!$B$5:$N$5,0),FALSE),0) -> 0 | M18: =IFERROR(L18/L$6,0) -> 0 | N18: =IFERROR(VLOOKUP($A18,APOIO!$B:$N,MATCH(N$5,APOIO!$B$5:$N$5,0),FALSE),0) -> 0 | O18: =IFERROR(N18/N$6,0) -> 0 | P18: =SUM(J18,L18,N18) -> 0 | Q18: =IFERROR(P18/P$6,0) -> 0 | R18: =IFERROR(VLOOKUP($A18,APOIO!$B:$N,MATCH(R$5,APOIO!$B$5:$N$5,0),FALSE),0) -> 0 | S18: =IFERROR(R18/R$6,0) -> 0 | T18: =IFERROR(VLOOKUP($A18,APOIO!$B:$N,MATCH(T$5,APOIO!$B$5:$N$5,0),FALSE),0) -> 0 | U18: =IFERROR(T18/T$6,0) -> 0 | V18: =IFERROR(VLOOKUP($A18,APOIO!$B:$N,MATCH(V$5,APOIO!$B$5:$N$5,0),FALSE),0) -> 0 | W18: =IFERROR(V18/V$6,0) -> 0 | X18: =SUM(R18,T18,V18) -> 0 | Y18: =IFERROR(X18/X$6,0) -> 0 | Z18: =IFERROR(VLOOKUP($A18,APOIO!$B:$N,MATCH(Z$5,APOIO!$B$5:$N$5,0),FALSE),0) -> 0 | AA18: =IFERROR(Z18/Z$6,0) -> 0 | AB18: =IFERROR(VLOOKUP($A18,APOIO!$B:$N,MATCH(AB$5,APOIO!$B$5:$N$5,0),FALSE),0) -> 0 | AC18: =IFERROR(AB18/AB$6,0) -> 0 | AD18: =IFERROR(VLOOKUP($A18,APOIO!$B:$N,MATCH(AD$5,APOIO!$B$5:$N$5,0),FALSE),0) -> 0 | AE18: =IFERROR(AD18/AD$6,0) -> 0 | AF18: =SUM(Z18,AB18,AD18) -> 0 | AG18: =IFERROR(AF18/AF$6,0) -> 0 | AH18: =SUM(B18,D18,F18,J18,L18,N18,R18,T18,V18,Z18,AB18,AD18) -> -16097.97 | AI18: =IFERROR(AH18/AH$6,0) -> -0.02712452
A19: (=)Receita Líquida | B19: =SUM(B8,B6) -> 155174.46 | C19: =IFERROR(B19/B$6,0) -> 0.89615183 | D19: =SUM(D8,D6) -> 365063.77 | E19: =IFERROR(D19/D$6,0) -> 0.86852201 | F19: =SUM(F8,F6) -> 0 | G19: =IFERROR(F19/F$6,0) -> 0 | H19: =SUM(B19,D19,F19) -> 520238.23 | I19: =IFERROR(H19/H$6,0) -> 0.87658335 | J19: =SUM(J8,J6) -> 0 | K19: =IFERROR(J19/J$6,0) -> 0 | L19: =SUM(L8,L6) -> 0 | M19: =IFERROR(L19/L$6,0) -> 0 | N19: =SUM(N8,N6) -> 0 | O19: =IFERROR(N19/N$6,0) -> 0 | P19: =SUM(J19,L19,N19) -> 0 | Q19: =IFERROR(P19/P$6,0) -> 0 | R19: =SUM(R8,R6) -> 0 | S19: =IFERROR(R19/R$6,0) -> 0 | T19: =SUM(T8,T6) -> 0 | U19: =IFERROR(T19/T$6,0) -> 0 | V19: =SUM(V8,V6) -> 0 | W19: =IFERROR(V19/V$6,0) -> 0 | X19: =SUM(R19,T19,V19) -> 0 | Y19: =IFERROR(X19/X$6,0) -> 0 | Z19: =SUM(Z8,Z6) -> 0 | AA19: =IFERROR(Z19/Z$6,0) -> 0 | AB19: =SUM(AB8,AB6) -> 0 | AC19: =IFERROR(AB19/AB$6,0) -> 0 | AD19: =SUM(AD8,AD6) -> 0 | AE19: =IFERROR(AD19/AD$6,0) -> 0 | AF19: =SUM(Z19,AB19,AD19) -> 0 | AG19: =IFERROR(AF19/AF$6,0) -> 0 | AH19: =SUM(B19,D19,F19,J19,L19,N19,R19,T19,V19,Z19,AB19,AD19) -> 520238.23 | AI19: =IFERROR(AH19/AH$6,0) -> 0.87658335
A20: (-)Custos Variavéis | B20: =IFERROR(VLOOKUP($A20,APOIO!$B:$N,MATCH(B$5,APOIO!$B$5:$N$5,0),FALSE),0) -> -1314.12 | C20: =IFERROR(B20/B$19,0) -> -0.0084686617 | D20: =IFERROR(VLOOKUP($A20,APOIO!$B:$N,MATCH(D$5,APOIO!$B$5:$N$5,0),FALSE),0) -> -20346.43 | E20: =IFERROR(D20/D$19,0) -> -0.055733906 | F20: =IFERROR(VLOOKUP($A20,APOIO!$B:$N,MATCH(F$5,APOIO!$B$5:$N$5,0),FALSE),0) -> -1333.2045 | G20: =IFERROR(F20/F$19,0) -> 0 | H20: =SUM(B20,D20,F20) -> -22993.755 | I20: =IFERROR(H20/H$19,0) -> -0.04419851 | J20: =IFERROR(VLOOKUP($A20,APOIO!$B:$N,MATCH(J$5,APOIO!$B$5:$N$5,0),FALSE),0) -> 0 | K20: =IFERROR(J20/J$19,0) -> 0 | L20: =IFERROR(VLOOKUP($A20,APOIO!$B:$N,MATCH(L$5,APOIO!$B$5:$N$5,0),FALSE),0) -> -312.58 | M20: =IFERROR(L20/L$19,0) -> 0 | N20: =IFERROR(VLOOKUP($A20,APOIO!$B:$N,MATCH(N$5,APOIO!$B$5:$N$5,0),FALSE),0) -> 0 | O20: =IFERROR(N20/N$19,0) -> 0 | P20: =SUM(J20,L20,N20) -> -312.58 | Q20: =IFERROR(P20/P$19,0) -> 0 | R20: =IFERROR(VLOOKUP($A20,APOIO!$B:$N,MATCH(R$5,APOIO!$B$5:$N$5,0),FALSE),0) -> 0 | S20: =IFERROR(R20/R$19,0) -> 0 | T20: =IFERROR(VLOOKUP($A20,APOIO!$B:$N,MATCH(T$5,APOIO!$B$5:$N$5,0),FALSE),0) -> 0 | U20: =IFERROR(T20/T$19,0) -> 0 | V20: =IFERROR(VLOOKUP($A20,APOIO!$B:$N,MATCH(V$5,APOIO!$B$5:$N$5,0),FALSE),0) -> 0 | W20: =IFERROR(V20/V$19,0) -> 0 | X20: =SUM(R20,T20,V20) -> 0 | Y20: =IFERROR(X20/X$19,0) -> 0 | Z20: =IFERROR(VLOOKUP($A20,APOIO!$B:$N,MATCH(Z$5,APOIO!$B$5:$N$5,0),FALSE),0) -> 0 | AA20: =IFERROR(Z20/Z$19,0) -> 0 | AB20: =IFERROR(VLOOKUP($A20,APOIO!$B:$N,MATCH(AB$5,APOIO!$B$5:$N$5,0),FALSE),0) -> 0 | AC20: =IFERROR(AB20/AB$19,0) -> 0 | AD20: =IFERROR(VLOOKUP($A20,APOIO!$B:$N,MATCH(AD$5,APOIO!$B$5:$N$5,0),FALSE),0) -> 0 | AE20: =IFERROR(AD20/AD$19,0) -> 0 | AF20: =SUM(Z20,AB20,AD20) -> 0 | AG20: =IFERROR(AF20/AF$19,0) -> 0 | AH20: =SUM(B20,D20,F20,J20,L20,N20,R20,T20,V20,Z20,AB20,AD20) -> -23306.335 | AI20: =IFERROR(AH20/AH$19,0) -> -0.04479935
A21: Fornecedores | B21: =IFERROR(VLOOKUP($A21,APOIO!$B:$N,MATCH(B$5,APOIO!$B$5:$N$5,0),FALSE),0) -> -1314.12 | C21: =IFERROR(B21/B$19,0) -> -0.0084686617 | D21: =IFERROR(VLOOKUP($A21,APOIO!$B:$N,MATCH(D$5,APOIO!$B$5:$N$5,0),FALSE),0) -> -20346.43 | E21: =IFERROR(D21/D$19,0) -> -0.055733906 | F21: =IFERROR(VLOOKUP($A21,APOIO!$B:$N,MATCH(F$5,APOIO!$B$5:$N$5,0),FALSE),0) -> -1333.2045 | G21: =IFERROR(F21/F$19,0) -> 0 | H21: =SUM(B21,D21,F21) -> -22993.755 | I21: =IFERROR(H21/H$19,0) -> -0.04419851 | J21: =IFERROR(VLOOKUP($A21,APOIO!$B:$N,MATCH(J$5,APOIO!$B$5:$N$5,0),FALSE),0) -> 0 | K21: =IFERROR(J21/J$19,0) -> 0 | L21: =IFERROR(VLOOKUP($A21,APOIO!$B:$N,MATCH(L$5,APOIO!$B$5:$N$5,0),FALSE),0) -> -312.58 | M21: =IFERROR(L21/L$19,0) -> 0 | N21: =IFERROR(VLOOKUP($A21,APOIO!$B:$N,MATCH(N$5,APOIO!$B$5:$N$5,0),FALSE),0) -> 0 | O21: =IFERROR(N21/N$19,0) -> 0 | P21: =SUM(J21,L21,N21) -> -312.58 | Q21: =IFERROR(P21/P$19,0) -> 0 | R21: =IFERROR(VLOOKUP($A21,APOIO!$B:$N,MATCH(R$5,APOIO!$B$5:$N$5,0),FALSE),0) -> 0 | S21: =IFERROR(R21/R$19,0) -> 0 | T21: =IFERROR(VLOOKUP($A21,APOIO!$B:$N,MATCH(T$5,APOIO!$B$5:$N$5,0),FALSE),0) -> 0 | U21: =IFERROR(T21/T$19,0) -> 0 | V21: =IFERROR(VLOOKUP($A21,APOIO!$B:$N,MATCH(V$5,APOIO!$B$5:$N$5,0),FALSE),0) -> 0 | W21: =IFERROR(V21/V$19,0) -> 0 | X21: =SUM(R21,T21,V21) -> 0 | Y21: =IFERROR(X21/X$19,0) -> 0 | Z21: =IFERROR(VLOOKUP($A21,APOIO!$B:$N,MATCH(Z$5,APOIO!$B$5:$N$5,0),FALSE),0) -> 0 | AA21: =IFERROR(Z21/Z$19,0) -> 0 | AB21: =IFERROR(VLOOKUP($A21,APOIO!$B:$N,MATCH(AB$5,APOIO!$B$5:$N$5,0),FALSE),0) -> 0 | AC21: =IFERROR(AB21/AB$19,0) -> 0 | AD21: =IFERROR(VLOOKUP($A21,APOIO!$B:$N,MATCH(AD$5,APOIO!$B$5:$N$5,0),FALSE),0) -> 0 | AE21: =IFERROR(AD21/AD$19,0) -> 0 | AF21: =SUM(Z21,AB21,AD21) -> 0 | AG21: =IFERROR(AF21/AF$19,0) -> 0 | AH21: =SUM(B21,D21,F21,J21,L21,N21,R21,T21,V21,Z21,AB21,AD21) -> -23306.335 | AI21: =IFERROR(AH21/AH$19,0) -> -0.04479935
A22: FRETE MATERIAIS E EQUIPAMENTOS | B22: =IFERROR(VLOOKUP($A22,APOIO!$B:$N,MATCH(B$5,APOIO!$B$5:$N$5,0),FALSE),0) -> 0 | C22: =IFERROR(B22/B$19,0) -> 0 | D22: =IFERROR(VLOOKUP($A22,APOIO!$B:$N,MATCH(D$5,APOIO!$B$5:$N$5,0),FALSE),0) -> -2345.47 | E22: =IFERROR(D22/D$19,0) -> -0.0064248227 | F22: =IFERROR(VLOOKUP($A22,APOIO!$B:$N,MATCH(F$5,APOIO!$B$5:$N$5,0),FALSE),0) -> 0 | G22: =IFERROR(F22/F$19,0) -> 0 | H22: =SUM(B22,D22,F22) -> -2345.47 | I22: =IFERROR(H22/H$19,0) -> -0.0045084538 | J22: =IFERROR(VLOOKUP($A22,APOIO!$B:$N,MATCH(J$5,APOIO!$B$5:$N$5,0),FALSE),0) -> 0 | K22: =IFERROR(J22/J$19,0) -> 0 | L22: =IFERROR(VLOOKUP($A22,APOIO!$B:$N,MATCH(L$5,APOIO!$B$5:$N$5,0),FALSE),0) -> 0 | M22: =IFERROR(L22/L$19,0) -> 0 | N22: =IFERROR(VLOOKUP($A22,APOIO!$B:$N,MATCH(N$5,APOIO!$B$5:$N$5,0),FALSE),0) -> 0 | O22: =IFERROR(N22/N$19,0) -> 0 | P22: =SUM(J22,L22,N22) -> 0 | Q22: =IFERROR(P22/P$19,0) -> 0 | R22: =IFERROR(VLOOKUP($A22,APOIO!$B:$N,MATCH(R$5,APOIO!$B$5:$N$5,0),FALSE),0) -> 0 | S22: =IFERROR(R22/R$19,0) -> 0 | T22: =IFERROR(VLOOKUP($A22,APOIO!$B:$N,MATCH(T$5,APOIO!$B$5:$N$5,0),FALSE),0) -> 0 | U22: =IFERROR(T22/T$19,0) -> 0 | V22: =IFERROR(VLOOKUP($A22,APOIO!$B:$N,MATCH(V$5,APOIO!$B$5:$N$5,0),FALSE),0) -> 0 | W22: =IFERROR(V22/V$19,0) -> 0 | X22: =SUM(R22,T22,V22) -> 0 | Y22: =IFERROR(X22/X$19,0) -> 0 | Z22: =IFERROR(VLOOKUP($A22,APOIO!$B:$N,MATCH(Z$5,APOIO!$B$5:$N$5,0),FALSE),0) -> 0 | AA22: =IFERROR(Z22/Z$19,0) -> 0 | AB22: =IFERROR(VLOOKUP($A22,APOIO!$B:$N,MATCH(AB$5,APOIO!$B$5:$N$5,0),FALSE),0) -> 0 | AC22: =IFERROR(AB22/AB$19,0) -> 0 | AD22: =IFERROR(VLOOKUP($A22,APOIO!$B:$N,MATCH(AD$5,APOIO!$B$5:$N$5,0),FALSE),0) -> 0 | AE22: =IFERROR(AD22/AD$19,0) -> 0 | AF22: =SUM(Z22,AB22,AD22) -> 0 | AG22: =IFERROR(AF22/AF$19,0) -> 0 | AH22: =SUM(B22,D22,F22,J22,L22,N22,R22,T22,V22,Z22,AB22,AD22) -> -2345.47 | AI22: =IFERROR(AH22/AH$19,0) -> -0.0045084538
A23: FRETE ABRASIVOS | B23: =IFERROR(VLOOKUP($A23,APOIO!$B:$N,MATCH(B$5,APOIO!$B$5:$N$5,0),FALSE),0) -> 0 | C23: =IFERROR(B23/B$19,0) -> 0 | D23: =IFERROR(VLOOKUP($A23,APOIO!$B:$N,MATCH(D$5,APOIO!$B$5:$N$5,0),FALSE),0) -> 0 | E23: =IFERROR(D23/D$19,0) -> 0 | F23: =IFERROR(VLOOKUP($A23,APOIO!$B:$N,MATCH(F$5,APOIO!$B$5:$N$5,0),FALSE),0) -> 0 | G23: =IFERROR(F23/F$19,0) -> 0 | H23: =SUM(B23,D23,F23) -> 0 | I23: =IFERROR(H23/H$19,0) -> 0 | J23: =IFERROR(VLOOKUP($A23,APOIO!$B:$N,MATCH(J$5,APOIO!$B$5:$N$5,0),FALSE),0) -> 0 | K23: =IFERROR(J23/J$19,0) -> 0 | L23: =IFERROR(VLOOKUP($A23,APOIO!$B:$N,MATCH(L$5,APOIO!$B$5:$N$5,0),FALSE),0) -> 0 | M23: =IFERROR(L23/L$19,0) -> 0 | N23: =IFERROR(VLOOKUP($A23,APOIO!$B:$N,MATCH(N$5,APOIO!$B$5:$N$5,0),FALSE),0) -> 0 | O23: =IFERROR(N23/N$19,0) -> 0 | P23: =SUM(J23,L23,N23) -> 0 | Q23: =IFERROR(P23/P$19,0) -> 0 | R23: =IFERROR(VLOOKUP($A23,APOIO!$B:$N,MATCH(R$5,APOIO!$B$5:$N$5,0),FALSE),0) -> 0 | S23: =IFERROR(R23/R$19,0) -> 0 | T23: =IFERROR(VLOOKUP($A23,APOIO!$B:$N,MATCH(T$5,APOIO!$B$5:$N$5,0),FALSE),0) -> 0 | U23: =IFERROR(T23/T$19,0) -> 0 | V23: =IFERROR(VLOOKUP($A23,APOIO!$B:$N,MATCH(V$5,APOIO!$B$5:$N$5,0),FALSE),0) -> 0 | W23: =IFERROR(V23/V$19,0) -> 0 | X23: =SUM(R23,T23,V23) -> 0 | Y23: =IFERROR(X23/X$19,0) -> 0 | Z23: =IFERROR(VLOOKUP($A23,APOIO!$B:$N,MATCH(Z$5,APOIO!$B$5:$N$5,0),FALSE),0) -> 0 | AA23: =IFERROR(Z23/Z$19,0) -> 0 | AB23: =IFERROR(VLOOKUP($A23,APOIO!$B:$N,MATCH(AB$5,APOIO!$B$5:$N$5,0),FALSE),0) -> 0 | AC23: =IFERROR(AB23/AB$19,0) -> 0 | AD23: =IFERROR(VLOOKUP($A23,APOIO!$B:$N,MATCH(AD$5,APOIO!$B$5:$N$5,0),FALSE),0) -> 0 | AE23: =IFERROR(AD23/AD$19,0) -> 0 | AF23: =SUM(Z23,AB23,AD23) -> 0 | AG23: =IFERROR(AF23/AF$19,0) -> 0 | AH23: =SUM(B23,D23,F23,J23,L23,N23,R23,T23,V23,Z23,AB23,AD23) -> 0 | AI23: =IFERROR(AH23/AH$19,0) -> 0
A24: FRETE TINTAS E SOLVENTE | B24: =IFERROR(VLOOKUP($A24,APOIO!$B:$N,MATCH(B$5,APOIO!$B$5:$N$5,0),FALSE),0) -> 0 | C24: =IFERROR(B24/B$19,0) -> 0 | D24: =IFERROR(VLOOKUP($A24,APOIO!$B:$N,MATCH(D$5,APOIO!$B$5:$N$5,0),FALSE),0) -> -953 | E24: =IFERROR(D24/D$19,0) -> -0.0026105028 | F24: =IFERROR(VLOOKUP($A24,APOIO!$B:$N,MATCH(F$5,APOIO!$B$5:$N$5,0),FALSE),0) -> 0 | G24: =IFERROR(F24/F$19,0) -> 0 | H24: =SUM(B24,D24,F24) -> -953 | I24: =IFERROR(H24/H$19,0) -> -0.0018318531 | J24: =IFERROR(VLOOKUP($A24,APOIO!$B:$N,MATCH(J$5,APOIO!$B$5:$N$5,0),FALSE),0) -> 0 | K24: =IFERROR(J24/J$19,0) -> 0 | L24: =IFERROR(VLOOKUP($A24,APOIO!$B:$N,MATCH(L$5,APOIO!$B$5:$N$5,0),FALSE),0) -> 0 | M24: =IFERROR(L24/L$19,0) -> 0 | N24: =IFERROR(VLOOKUP($A24,APOIO!$B:$N,MATCH(N$5,APOIO!$B$5:$N$5,0),FALSE),0) -> 0 | O24: =IFERROR(N24/N$19,0) -> 0 | P24: =SUM(J24,L24,N24) -> 0 | Q24: =IFERROR(P24/P$19,0) -> 0 | R24: =IFERROR(VLOOKUP($A24,APOIO!$B:$N,MATCH(R$5,APOIO!$B$5:$N$5,0),FALSE),0) -> 0 | S24: =IFERROR(R24/R$19,0) -> 0 | T24: =IFERROR(VLOOKUP($A24,APOIO!$B:$N,MATCH(T$5,APOIO!$B$5:$N$5,0),FALSE),0) -> 0 | U24: =IFERROR(T24/T$19,0) -> 0 | V24: =IFERROR(VLOOKUP($A24,APOIO!$B:$N,MATCH(V$5,APOIO!$B$5:$N$5,0),FALSE),0) -> 0 | W24: =IFERROR(V24/V$19,0) -> 0 | X24: =SUM(R24,T24,V24) -> 0 | Y24: =IFERROR(X24/X$19,0) -> 0 | Z24: =IFERROR(VLOOKUP($A24,APOIO!$B:$N,MATCH(Z$5,APOIO!$B$5:$N$5,0),FALSE),0) -> 0 | AA24: =IFERROR(Z24/Z$19,0) -> 0 | AB24: =IFERROR(VLOOKUP($A24,APOIO!$B:$N,MATCH(AB$5,APOIO!$B$5:$N$5,0),FALSE),0) -> 0 | AC24: =IFERROR(AB24/AB$19,0) -> 0 | AD24: =IFERROR(VLOOKUP($A24,APOIO!$B:$N,MATCH(AD$5,APOIO!$B$5:$N$5,0),FALSE),0) -> 0 | AE24: =IFERROR(AD24/AD$19,0) -> 0 | AF24: =SUM(Z24,AB24,AD24) -> 0 | AG24: =IFERROR(AF24/AF$19,0) -> 0 | AH24: =SUM(B24,D24,F24,J24,L24,N24,R24,T24,V24,Z24,AB24,AD24) -> -953 | AI24: =IFERROR(AH24/AH$19,0) -> -0.0018318531
A25: FRETE TRANSPORTADORA | B25: =IFERROR(VLOOKUP($A25,APOIO!$B:$N,MATCH(B$5,APOIO!$B$5:$N$5,0),FALSE),0) -> -1314.12 | C25: =IFERROR(B25/B$19,0) -> -0.0084686617 | D25: =IFERROR(VLOOKUP($A25,APOIO!$B:$N,MATCH(D$5,APOIO!$B$5:$N$5,0),FALSE),0) -> 0 | E25: =IFERROR(D25/D$19,0) -> 0 | F25: =IFERROR(VLOOKUP($A25,APOIO!$B:$N,MATCH(F$5,APOIO!$B$5:$N$5,0),FALSE),0) -> -1333.2045 | G25: =IFERROR(F25/F$19,0) -> 0 | H25: =SUM(B25,D25,F25) -> -2647.3245 | I25: =IFERROR(H25/H$19,0) -> -0.0050886774 | J25: =IFERROR(VLOOKUP($A25,APOIO!$B:$N,MATCH(J$5,APOIO!$B$5:$N$5,0),FALSE),0) -> 0 | K25: =IFERROR(J25/J$19,0) -> 0 | L25: =IFERROR(VLOOKUP($A25,APOIO!$B:$N,MATCH(L$5,APOIO!$B$5:$N$5,0),FALSE),0) -> -312.58 | M25: =IFERROR(L25/L$19,0) -> 0 | N25: =IFERROR(VLOOKUP($A25,APOIO!$B:$N,MATCH(N$5,APOIO!$B$5:$N$5,0),FALSE),0) -> 0 | O25: =IFERROR(N25/N$19,0) -> 0 | P25: =SUM(J25,L25,N25) -> -312.58 | Q25: =IFERROR(P25/P$19,0) -> 0 | R25: =IFERROR(VLOOKUP($A25,APOIO!$B:$N,MATCH(R$5,APOIO!$B$5:$N$5,0),FALSE),0) -> 0 | S25: =IFERROR(R25/R$19,0) -> 0 | T25: =IFERROR(VLOOKUP($A25,APOIO!$B:$N,MATCH(T$5,APOIO!$B$5:$N$5,0),FALSE),0) -> 0 | U25: =IFERROR(T25/T$19,0) -> 0 | V25: =IFERROR(VLOOKUP($A25,APOIO!$B:$N,MATCH(V$5,APOIO!$B$5:$N$5,0),FALSE),0) -> 0 | W25: =IFERROR(V25/V$19,0) -> 0 | X25: =SUM(R25,T25,V25) -> 0 | Y25: =IFERROR(X25/X$19,0) -> 0 | Z25: =IFERROR(VLOOKUP($A25,APOIO!$B:$N,MATCH(Z$5,APOIO!$B$5:$N$5,0),FALSE),0) -> 0 | AA25: =IFERROR(Z25/Z$19,0) -> 0 | AB25: =IFERROR(VLOOKUP($A25,APOIO!$B:$N,MATCH(AB$5,APOIO!$B$5:$N$5,0),FALSE),0) -> 0 | AC25: =IFERROR(AB25/AB$19,0) -> 0 | AD25: =IFERROR(VLOOKUP($A25,APOIO!$B:$N,MATCH(AD$5,APOIO!$B$5:$N$5,0),FALSE),0) -> 0 | AE25: =IFERROR(AD25/AD$19,0) -> 0 | AF25: =SUM(Z25,AB25,AD25) -> 0 | AG25: =IFERROR(AF25/AF$19,0) -> 0 | AH25: =SUM(B25,D25,F25,J25,L25,N25,R25,T25,V25,Z25,AB25,AD25) -> -2959.9045 | AI25: =IFERROR(AH25/AH$19,0) -> -0.0056895176
A26: TINTAS E SOLVENTES | B26: =IFERROR(VLOOKUP($A26,APOIO!$B:$N,MATCH(B$5,APOIO!$B$5:$N$5,0),FALSE),0) -> 0 | C26: =IFERROR(B26/B$19,0) -> 0 | D26: =IFERROR(VLOOKUP($A26,APOIO!$B:$N,MATCH(D$5,APOIO!$B$5:$N$5,0),FALSE),0) -> -17047.96 | E26: =IFERROR(D26/D$19,0) -> -0.046698581 | F26: =IFERROR(VLOOKUP($A26,APOIO!$B:$N,MATCH(F$5,APOIO!$B$5:$N$5,0),FALSE),0) -> 0 | G26: =IFERROR(F26/F$19,0) -> 0 | H26: =SUM(B26,D26,F26) -> -17047.96 | I26: =IFERROR(H26/H$19,0) -> -0.032769526 | J26: =IFERROR(VLOOKUP($A26,APOIO!$B:$N,MATCH(J$5,APOIO!$B$5:$N$5,0),FALSE),0) -> 0 | K26: =IFERROR(J26/J$19,0) -> 0 | L26: =IFERROR(VLOOKUP($A26,APOIO!$B:$N,MATCH(L$5,APOIO!$B$5:$N$5,0),FALSE),0) -> 0 | M26: =IFERROR(L26/L$19,0) -> 0 | N26: =IFERROR(VLOOKUP($A26,APOIO!$B:$N,MATCH(N$5,APOIO!$B$5:$N$5,0),FALSE),0) -> 0 | O26: =IFERROR(N26/N$19,0) -> 0 | P26: =SUM(J26,L26,N26) -> 0 | Q26: =IFERROR(P26/P$19,0) -> 0 | R26: =IFERROR(VLOOKUP($A26,APOIO!$B:$N,MATCH(R$5,APOIO!$B$5:$N$5,0),FALSE),0) -> 0 | S26: =IFERROR(R26/R$19,0) -> 0 | T26: =IFERROR(VLOOKUP($A26,APOIO!$B:$N,MATCH(T$5,APOIO!$B$5:$N$5,0),FALSE),0) -> 0 | U26: =IFERROR(T26/T$19,0) -> 0 | V26: =IFERROR(VLOOKUP($A26,APOIO!$B:$N,MATCH(V$5,APOIO!$B$5:$N$5,0),FALSE),0) -> 0 | W26: =IFERROR(V26/V$19,0) -> 0 | X26: =SUM(R26,T26,V26) -> 0 | Y26: =IFERROR(X26/X$19,0) -> 0 | Z26: =IFERROR(VLOOKUP($A26,APOIO!$B:$N,MATCH(Z$5,APOIO!$B$5:$N$5,0),FALSE),0) -> 0 | AA26: =IFERROR(Z26/Z$19,0) -> 0 | AB26: =IFERROR(VLOOKUP($A26,APOIO!$B:$N,MATCH(AB$5,APOIO!$B$5:$N$5,0),FALSE),0) -> 0 | AC26: =IFERROR(AB26/AB$19,0) -> 0 | AD26: =IFERROR(VLOOKUP($A26,APOIO!$B:$N,MATCH(AD$5,APOIO!$B$5:$N$5,0),FALSE),0) -> 0 | AE26: =IFERROR(AD26/AD$19,0) -> 0 | AF26: =SUM(Z26,AB26,AD26) -> 0 | AG26: =IFERROR(AF26/AF$19,0) -> 0 | AH26: =SUM(B26,D26,F26,J26,L26,N26,R26,T26,V26,Z26,AB26,AD26) -> -17047.96 | AI26: =IFERROR(AH26/AH$19,0) -> -0.032769526
A27: ABRASIVOS | B27: =IFERROR(VLOOKUP($A27,APOIO!$B:$N,MATCH(B$5,APOIO!$B$5:$N$5,0),FALSE),0) -> 0 | C27: =IFERROR(B27/B$19,0) -> 0 | D27: =IFERROR(VLOOKUP($A27,APOIO!$B:$N,MATCH(D$5,APOIO!$B$5:$N$5,0),FALSE),0) -> 0 | E27: =IFERROR(D27/D$19,0) -> 0 | F27: =IFERROR(VLOOKUP($A27,APOIO!$B:$N,MATCH(F$5,APOIO!$B$5:$N$5,0),FALSE),0) -> 0 | G27: =IFERROR(F27/F$19,0) -> 0 | H27: =SUM(B27,D27,F27) -> 0 | I27: =IFERROR(H27/H$19,0) -> 0 | J27: =IFERROR(VLOOKUP($A27,APOIO!$B:$N,MATCH(J$5,APOIO!$B$5:$N$5,0),FALSE),0) -> 0 | K27: =IFERROR(J27/J$19,0) -> 0 | L27: =IFERROR(VLOOKUP($A27,APOIO!$B:$N,MATCH(L$5,APOIO!$B$5:$N$5,0),FALSE),0) -> 0 | M27: =IFERROR(L27/L$19,0) -> 0 | N27: =IFERROR(VLOOKUP($A27,APOIO!$B:$N,MATCH(N$5,APOIO!$B$5:$N$5,0),FALSE),0) -> 0 | O27: =IFERROR(N27/N$19,0) -> 0 | P27: =SUM(J27,L27,N27) -> 0 | Q27: =IFERROR(P27/P$19,0) -> 0 | R27: =IFERROR(VLOOKUP($A27,APOIO!$B:$N,MATCH(R$5,APOIO!$B$5:$N$5,0),FALSE),0) -> 0 | S27: =IFERROR(R27/R$19,0) -> 0 | T27: =IFERROR(VLOOKUP($A27,APOIO!$B:$N,MATCH(T$5,APOIO!$B$5:$N$5,0),FALSE),0) -> 0 | U27: =IFERROR(T27/T$19,0) -> 0 | V27: =IFERROR(VLOOKUP($A27,APOIO!$B:$N,MATCH(V$5,APOIO!$B$5:$N$5,0),FALSE),0) -> 0 | W27: =IFERROR(V27/V$19,0) -> 0 | X27: =SUM(R27,T27,V27) -> 0 | Y27: =IFERROR(X27/X$19,0) -> 0 | Z27: =IFERROR(VLOOKUP($A27,APOIO!$B:$N,MATCH(Z$5,APOIO!$B$5:$N$5,0),FALSE),0) -> 0 | AA27: =IFERROR(Z27/Z$19,0) -> 0 | AB27: =IFERROR(VLOOKUP($A27,APOIO!$B:$N,MATCH(AB$5,APOIO!$B$5:$N$5,0),FALSE),0) -> 0 | AC27: =IFERROR(AB27/AB$19,0) -> 0 | AD27: =IFERROR(VLOOKUP($A27,APOIO!$B:$N,MATCH(AD$5,APOIO!$B$5:$N$5,0),FALSE),0) -> 0 | AE27: =IFERROR(AD27/AD$19,0) -> 0 | AF27: =SUM(Z27,AB27,AD27) -> 0 | AG27: =IFERROR(AF27/AF$19,0) -> 0 | AH27: =SUM(B27,D27,F27,J27,L27,N27,R27,T27,V27,Z27,AB27,AD27) -> 0 | AI27: =IFERROR(AH27/AH$19,0) -> 0
A28: OUTROS MATERIAIS DE APLICAÇÃO | B28: =IFERROR(VLOOKUP($A28,APOIO!$B:$N,MATCH(B$5,APOIO!$B$5:$N$5,0),FALSE),0) -> 0 | C28: =IFERROR(B28/B$19,0) -> 0 | D28: =IFERROR(VLOOKUP($A28,APOIO!$B:$N,MATCH(D$5,APOIO!$B$5:$N$5,0),FALSE),0) -> 0 | E28: =IFERROR(D28/D$19,0) -> 0 | F28: =IFERROR(VLOOKUP($A28,APOIO!$B:$N,MATCH(F$5,APOIO!$B$5:$N$5,0),FALSE),0) -> 0 | G28: =IFERROR(F28/F$19,0) -> 0 | H28: =SUM(B28,D28,F28) -> 0 | I28: =IFERROR(H28/H$19,0) -> 0 | J28: =IFERROR(VLOOKUP($A28,APOIO!$B:$N,MATCH(J$5,APOIO!$B$5:$N$5,0),FALSE),0) -> 0 | K28: =IFERROR(J28/J$19,0) -> 0 | L28: =IFERROR(VLOOKUP($A28,APOIO!$B:$N,MATCH(L$5,APOIO!$B$5:$N$5,0),FALSE),0) -> 0 | M28: =IFERROR(L28/L$19,0) -> 0 | N28: =IFERROR(VLOOKUP($A28,APOIO!$B:$N,MATCH(N$5,APOIO!$B$5:$N$5,0),FALSE),0) -> 0 | O28: =IFERROR(N28/N$19,0) -> 0 | P28: =SUM(J28,L28,N28) -> 0 | Q28: =IFERROR(P28/P$19,0) -> 0 | R28: =IFERROR(VLOOKUP($A28,APOIO!$B:$N,MATCH(R$5,APOIO!$B$5:$N$5,0),FALSE),0) -> 0 | S28: =IFERROR(R28/R$19,0) -> 0 | T28: =IFERROR(VLOOKUP($A28,APOIO!$B:$N,MATCH(T$5,APOIO!$B$5:$N$5,0),FALSE),0) -> 0 | U28: =IFERROR(T28/T$19,0) -> 0 | V28: =IFERROR(VLOOKUP($A28,APOIO!$B:$N,MATCH(V$5,APOIO!$B$5:$N$5,0),FALSE),0) -> 0 | W28: =IFERROR(V28/V$19,0) -> 0 | X28: =SUM(R28,T28,V28) -> 0 | Y28: =IFERROR(X28/X$19,0) -> 0 | Z28: =IFERROR(VLOOKUP($A28,APOIO!$B:$N,MATCH(Z$5,APOIO!$B$5:$N$5,0),FALSE),0) -> 0 | AA28: =IFERROR(Z28/Z$19,0) -> 0 | AB28: =IFERROR(VLOOKUP($A28,APOIO!$B:$N,MATCH(AB$5,APOIO!$B$5:$N$5,0),FALSE),0) -> 0 | AC28: =IFERROR(AB28/AB$19,0) -> 0 | AD28: =IFERROR(VLOOKUP($A28,APOIO!$B:$N,MATCH(AD$5,APOIO!$B$5:$N$5,0),FALSE),0) -> 0 | AE28: =IFERROR(AD28/AD$19,0) -> 0 | AF28: =SUM(Z28,AB28,AD28) -> 0 | AG28: =IFERROR(AF28/AF$19,0) -> 0 | AH28: =SUM(B28,D28,F28,J28,L28,N28,R28,T28,V28,Z28,AB28,AD28) -> 0 | AI28: =IFERROR(AH28/AH$19,0) -> 0
B29: =IFERROR(VLOOKUP($A29,APOIO!$B:$N,MATCH(B$5,APOIO!$B$5:$N$5,0),FALSE),0) -> 0 | C29: =IFERROR(B29/B$19,0) -> 0 | D29: =IFERROR(VLOOKUP($A29,APOIO!$B:$N,MATCH(D$5,APOIO!$B$5:$N$5,0),FALSE),0) -> 0 | E29: =IFERROR(D29/D$19,0) -> 0 | F29: =IFERROR(VLOOKUP($A29,APOIO!$B:$N,MATCH(F$5,APOIO!$B$5:$N$5,0),FALSE),0) -> 0 | G29: =IFERROR(F29/F$19,0) -> 0 | H29: =SUM(B29,D29,F29) -> 0 | I29: =IFERROR(H29/H$19,0) -> 0 | J29: =IFERROR(VLOOKUP($A29,APOIO!$B:$N,MATCH(J$5,APOIO!$B$5:$N$5,0),FALSE),0) -> 0 | K29: =IFERROR(J29/J$19,0) -> 0 | L29: =IFERROR(VLOOKUP($A29,APOIO!$B:$N,MATCH(L$5,APOIO!$B$5:$N$5,0),FALSE),0) -> 0 | M29: =IFERROR(L29/L$19,0) -> 0 | N29: =IFERROR(VLOOKUP($A29,APOIO!$B:$N,MATCH(N$5,APOIO!$B$5:$N$5,0),FALSE),0) -> 0 | O29: =IFERROR(N29/N$19,0) -> 0 | P29: =SUM(J29,L29,N29) -> 0 | Q29: =IFERROR(P29/P$19,0) -> 0 | R29: =IFERROR(VLOOKUP($A29,APOIO!$B:$N,MATCH(R$5,APOIO!$B$5:$N$5,0),FALSE),0) -> 0 | S29: =IFERROR(R29/R$19,0) -> 0 | T29: =IFERROR(VLOOKUP($A29,APOIO!$B:$N,MATCH(T$5,APOIO!$B$5:$N$5,0),FALSE),0) -> 0 | U29: =IFERROR(T29/T$19,0) -> 0 | V29: =IFERROR(VLOOKUP($A29,APOIO!$B:$N,MATCH(V$5,APOIO!$B$5:$N$5,0),FALSE),0) -> 0 | W29: =IFERROR(V29/V$19,0) -> 0 | X29: =SUM(R29,T29,V29) -> 0 | Y29: =IFERROR(X29/X$19,0) -> 0 | Z29: =IFERROR(VLOOKUP($A29,APOIO!$B:$N,MATCH(Z$5,APOIO!$B$5:$N$5,0),FALSE),0) -> 0 | AA29: =IFERROR(Z29/Z$19,0) -> 0 | AB29: =IFERROR(VLOOKUP($A29,APOIO!$B:$N,MATCH(AB$5,APOIO!$B$5:$N$5,0),FALSE),0) -> 0 | AC29: =IFERROR(AB29/AB$19,0) -> 0 | AD29: =IFERROR(VLOOKUP($A29,APOIO!$B:$N,MATCH(AD$5,APOIO!$B$5:$N$5,0),FALSE),0) -> 0 | AE29: =IFERROR(AD29/AD$19,0) -> 0 | AF29: =SUM(Z29,AB29,AD29) -> 0 | AG29: =IFERROR(AF29/AF$19,0) -> 0 | AH29: =SUM(B29,D29,F29,J29,L29,N29,R29,T29,V29,Z29,AB29,AD29) -> 0 | AI29: =IFERROR(AH29/AH$19,0) -> 0
A30: Gastos Comerciais | B30: =IFERROR(VLOOKUP($A30,APOIO!$B:$N,MATCH(B$5,APOIO!$B$5:$N$5,0),FALSE),0) -> 0 | C30: =IFERROR(B30/B$19,0) -> 0 | D30: =IFERROR(VLOOKUP($A30,APOIO!$B:$N,MATCH(D$5,APOIO!$B$5:$N$5,0),FALSE),0) -> 0 | E30: =IFERROR(D30/D$19,0) -> 0 | F30: =IFERROR(VLOOKUP($A30,APOIO!$B:$N,MATCH(F$5,APOIO!$B$5:$N$5,0),FALSE),0) -> 0 | G30: =IFERROR(F30/F$19,0) -> 0 | H30: =SUM(B30,D30,F30) -> 0 | I30: =IFERROR(H30/H$19,0) -> 0 | J30: =IFERROR(VLOOKUP($A30,APOIO!$B:$N,MATCH(J$5,APOIO!$B$5:$N$5,0),FALSE),0) -> 0 | K30: =IFERROR(J30/J$19,0) -> 0 | L30: =IFERROR(VLOOKUP($A30,APOIO!$B:$N,MATCH(L$5,APOIO!$B$5:$N$5,0),FALSE),0) -> 0 | M30: =IFERROR(L30/L$19,0) -> 0 | N30: =IFERROR(VLOOKUP($A30,APOIO!$B:$N,MATCH(N$5,APOIO!$B$5:$N$5,0),FALSE),0) -> 0 | O30: =IFERROR(N30/N$19,0) -> 0 | P30: =SUM(J30,L30,N30) -> 0 | Q30: =IFERROR(P30/P$19,0) -> 0 | R30: =IFERROR(VLOOKUP($A30,APOIO!$B:$N,MATCH(R$5,APOIO!$B$5:$N$5,0),FALSE),0) -> 0 | S30: =IFERROR(R30/R$19,0) -> 0 | T30: =IFERROR(VLOOKUP($A30,APOIO!$B:$N,MATCH(T$5,APOIO!$B$5:$N$5,0),FALSE),0) -> 0 | U30: =IFERROR(T30/T$19,0) -> 0 | V30: =IFERROR(VLOOKUP($A30,APOIO!$B:$N,MATCH(V$5,APOIO!$B$5:$N$5,0),FALSE),0) -> 0 | W30: =IFERROR(V30/V$19,0) -> 0 | X30: =SUM(R30,T30,V30) -> 0 | Y30: =IFERROR(X30/X$19,0) -> 0 | Z30: =IFERROR(VLOOKUP($A30,APOIO!$B:$N,MATCH(Z$5,APOIO!$B$5:$N$5,0),FALSE),0) -> 0 | AA30: =IFERROR(Z30/Z$19,0) -> 0 | AB30: =IFERROR(VLOOKUP($A30,APOIO!$B:$N,MATCH(AB$5,APOIO!$B$5:$N$5,0),FALSE),0) -> 0 | AC30: =IFERROR(AB30/AB$19,0) -> 0 | AD30: =IFERROR(VLOOKUP($A30,APOIO!$B:$N,MATCH(AD$5,APOIO!$B$5:$N$5,0),FALSE),0) -> 0 | AE30: =IFERROR(AD30/AD$19,0) -> 0 | AF30: =SUM(Z30,AB30,AD30) -> 0 | AG30: =IFERROR(AF30/AF$19,0) -> 0 | AH30: =SUM(B30,D30,F30,J30,L30,N30,R30,T30,V30,Z30,AB30,AD30) -> 0 | AI30: =IFERROR(AH30/AH$19,0) -> 0
A31: COMISSÃO | B31: =IFERROR(VLOOKUP($A31,APOIO!$B:$N,MATCH(B$5,APOIO!$B$5:$N$5,0),FALSE),0) -> 0 | C31: =IFERROR(B31/B$19,0) -> 0 | D31: =IFERROR(VLOOKUP($A31,APOIO!$B:$N,MATCH(D$5,APOIO!$B$5:$N$5,0),FALSE),0) -> 0 | E31: =IFERROR(D31/D$19,0) -> 0 | F31: =IFERROR(VLOOKUP($A31,APOIO!$B:$N,MATCH(F$5,APOIO!$B$5:$N$5,0),FALSE),0) -> 0 | G31: =IFERROR(F31/F$19,0) -> 0 | H31: =SUM(B31,D31,F31) -> 0 | I31: =IFERROR(H31/H$19,0) -> 0 | J31: =IFERROR(VLOOKUP($A31,APOIO!$B:$N,MATCH(J$5,APOIO!$B$5:$N$5,0),FALSE),0) -> 0 | K31: =IFERROR(J31/J$19,0) -> 0 | L31: =IFERROR(VLOOKUP($A31,APOIO!$B:$N,MATCH(L$5,APOIO!$B$5:$N$5,0),FALSE),0) -> 0 | M31: =IFERROR(L31/L$19,0) -> 0 | N31: =IFERROR(VLOOKUP($A31,APOIO!$B:$N,MATCH(N$5,APOIO!$B$5:$N$5,0),FALSE),0) -> 0 | O31: =IFERROR(N31/N$19,0) -> 0 | P31: =SUM(J31,L31,N31) -> 0 | Q31: =IFERROR(P31/P$19,0) -> 0 | R31: =IFERROR(VLOOKUP($A31,APOIO!$B:$N,MATCH(R$5,APOIO!$B$5:$N$5,0),FALSE),0) -> 0 | S31: =IFERROR(R31/R$19,0) -> 0 | T31: =IFERROR(VLOOKUP($A31,APOIO!$B:$N,MATCH(T$5,APOIO!$B$5:$N$5,0),FALSE),0) -> 0 | U31: =IFERROR(T31/T$19,0) -> 0 | V31: =IFERROR(VLOOKUP($A31,APOIO!$B:$N,MATCH(V$5,APOIO!$B$5:$N$5,0),FALSE),0) -> 0 | W31: =IFERROR(V31/V$19,0) -> 0 | X31: =SUM(R31,T31,V31) -> 0 | Y31: =IFERROR(X31/X$19,0) -> 0 | Z31: =IFERROR(VLOOKUP($A31,APOIO!$B:$N,MATCH(Z$5,APOIO!$B$5:$N$5,0),FALSE),0) -> 0 | AA31: =IFERROR(Z31/Z$19,0) -> 0 | AB31: =IFERROR(VLOOKUP($A31,APOIO!$B:$N,MATCH(AB$5,APOIO!$B$5:$N$5,0),FALSE),0) -> 0 | AC31: =IFERROR(AB31/AB$19,0) -> 0 | AD31: =IFERROR(VLOOKUP($A31,APOIO!$B:$N,MATCH(AD$5,APOIO!$B$5:$N$5,0),FALSE),0) -> 0 | AE31: =IFERROR(AD31/AD$19,0) -> 0 | AF31: =SUM(Z31,AB31,AD31) -> 0 | AG31: =IFERROR(AF31/AF$19,0) -> 0 | AH31: =SUM(B31,D31,F31,J31,L31,N31,R31,T31,V31,Z31,AB31,AD31) -> 0 | AI31: =IFERROR(AH31/AH$19,0) -> 0
B32: =IFERROR(VLOOKUP($A32,APOIO!$B:$N,MATCH(B$5,APOIO!$B$5:$N$5,0),FALSE),0) -> 0 | C32: =IFERROR(B32/B$19,0) -> 0 | D32: =IFERROR(VLOOKUP($A32,APOIO!$B:$N,MATCH(D$5,APOIO!$B$5:$N$5,0),FALSE),0) -> 0 | E32: =IFERROR(D32/D$19,0) -> 0 | F32: =IFERROR(VLOOKUP($A32,APOIO!$B:$N,MATCH(F$5,APOIO!$B$5:$N$5,0),FALSE),0) -> 0 | G32: =IFERROR(F32/F$19,0) -> 0 | H32: =SUM(B32,D32,F32) -> 0 | I32: =IFERROR(H32/H$19,0) -> 0 | J32: =IFERROR(VLOOKUP($A32,APOIO!$B:$N,MATCH(J$5,APOIO!$B$5:$N$5,0),FALSE),0) -> 0 | K32: =IFERROR(J32/J$19,0) -> 0 | L32: =IFERROR(VLOOKUP($A32,APOIO!$B:$N,MATCH(L$5,APOIO!$B$5:$N$5,0),FALSE),0) -> 0 | M32: =IFERROR(L32/L$19,0) -> 0 | N32: =IFERROR(VLOOKUP($A32,APOIO!$B:$N,MATCH(N$5,APOIO!$B$5:$N$5,0),FALSE),0) -> 0 | O32: =IFERROR(N32/N$19,0) -> 0 | P32: =SUM(J32,L32,N32) -> 0 | Q32: =IFERROR(P32/P$19,0) -> 0 | R32: =IFERROR(VLOOKUP($A32,APOIO!$B:$N,MATCH(R$5,APOIO!$B$5:$N$5,0),FALSE),0) -> 0 | S32: =IFERROR(R32/R$19,0) -> 0 | T32: =IFERROR(VLOOKUP($A32,APOIO!$B:$N,MATCH(T$5,APOIO!$B$5:$N$5,0),FALSE),0) -> 0 | U32: =IFERROR(T32/T$19,0) -> 0 | V32: =IFERROR(VLOOKUP($A32,APOIO!$B:$N,MATCH(V$5,APOIO!$B$5:$N$5,0),FALSE),0) -> 0 | W32: =IFERROR(V32/V$19,0) -> 0 | X32: =SUM(R32,T32,V32) -> 0 | Y32: =IFERROR(X32/X$19,0) -> 0 | Z32: =IFERROR(VLOOKUP($A32,APOIO!$B:$N,MATCH(Z$5,APOIO!$B$5:$N$5,0),FALSE),0) -> 0 | AA32: =IFERROR(Z32/Z$19,0) -> 0 | AB32: =IFERROR(VLOOKUP($A32,APOIO!$B:$N,MATCH(AB$5,APOIO!$B$5:$N$5,0),FALSE),0) -> 0 | AC32: =IFERROR(AB32/AB$19,0) -> 0 | AD32: =IFERROR(VLOOKUP($A32,APOIO!$B:$N,MATCH(AD$5,APOIO!$B$5:$N$5,0),FALSE),0) -> 0 | AE32: =IFERROR(AD32/AD$19,0) -> 0 | AF32: =SUM(Z32,AB32,AD32) -> 0 | AG32: =IFERROR(AF32/AF$19,0) -> 0 | AH32: =SUM(B32,D32,F32,J32,L32,N32,R32,T32,V32,Z32,AB32,AD32) -> 0 | AI32: =IFERROR(AH32/AH$19,0) -> 0
B33: =IFERROR(VLOOKUP($A33,APOIO!$B:$N,MATCH(B$5,APOIO!$B$5:$N$5,0),FALSE),0) -> 0 | C33: =IFERROR(B33/B$19,0) -> 0 | D33: =IFERROR(VLOOKUP($A33,APOIO!$B:$N,MATCH(D$5,APOIO!$B$5:$N$5,0),FALSE),0) -> 0 | E33: =IFERROR(D33/D$19,0) -> 0 | F33: =IFERROR(VLOOKUP($A33,APOIO!$B:$N,MATCH(F$5,APOIO!$B$5:$N$5,0),FALSE),0) -> 0 | G33: =IFERROR(F33/F$19,0) -> 0 | H33: =SUM(B33,D33,F33) -> 0 | I33: =IFERROR(H33/H$19,0) -> 0 | J33: =IFERROR(VLOOKUP($A33,APOIO!$B:$N,MATCH(J$5,APOIO!$B$5:$N$5,0),FALSE),0) -> 0 | K33: =IFERROR(J33/J$19,0) -> 0 | L33: =IFERROR(VLOOKUP($A33,APOIO!$B:$N,MATCH(L$5,APOIO!$B$5:$N$5,0),FALSE),0) -> 0 | M33: =IFERROR(L33/L$19,0) -> 0 | N33: =IFERROR(VLOOKUP($A33,APOIO!$B:$N,MATCH(N$5,APOIO!$B$5:$N$5,0),FALSE),0) -> 0 | O33: =IFERROR(N33/N$19,0) -> 0 | P33: =SUM(J33,L33,N33) -> 0 | Q33: =IFERROR(P33/P$19,0) -> 0 | R33: =IFERROR(VLOOKUP($A33,APOIO!$B:$N,MATCH(R$5,APOIO!$B$5:$N$5,0),FALSE),0) -> 0 | S33: =IFERROR(R33/R$19,0) -> 0 | T33: =IFERROR(VLOOKUP($A33,APOIO!$B:$N,MATCH(T$5,APOIO!$B$5:$N$5,0),FALSE),0) -> 0 | U33: =IFERROR(T33/T$19,0) -> 0 | V33: =IFERROR(VLOOKUP($A33,APOIO!$B:$N,MATCH(V$5,APOIO!$B$5:$N$5,0),FALSE),0) -> 0 | W33: =IFERROR(V33/V$19,0) -> 0 | X33: =SUM(R33,T33,V33) -> 0 | Y33: =IFERROR(X33/X$19,0) -> 0 | Z33: =IFERROR(VLOOKUP($A33,APOIO!$B:$N,MATCH(Z$5,APOIO!$B$5:$N$5,0),FALSE),0) -> 0 | AA33: =IFERROR(Z33/Z$19,0) -> 0 | AB33: =IFERROR(VLOOKUP($A33,APOIO!$B:$N,MATCH(AB$5,APOIO!$B$5:$N$5,0),FALSE),0) -> 0 | AC33: =IFERROR(AB33/AB$19,0) -> 0 | AD33: =IFERROR(VLOOKUP($A33,APOIO!$B:$N,MATCH(AD$5,APOIO!$B$5:$N$5,0),FALSE),0) -> 0 | AE33: =IFERROR(AD33/AD$19,0) -> 0 | AF33: =SUM(Z33,AB33,AD33) -> 0 | AG33: =IFERROR(AF33/AF$19,0) -> 0 | AH33: =SUM(B33,D33,F33,J33,L33,N33,R33,T33,V33,Z33,AB33,AD33) -> 0 | AI33: =IFERROR(AH33/AH$19,0) -> 0
A34: (=)Margem de Contribuição | B34: =SUM(B19:B20) -> 153860.34 | C34: =IFERROR(B34/B$19,0) -> 0.99153134 | D34: =SUM(D19:D20) -> 344717.34 | E34: =IFERROR(D34/D$19,0) -> 0.94426609 | F34: =SUM(F19:F20) -> -1333.2045 | G34: =IFERROR(F34/F$19,0) -> 0 | H34: =SUM(B34,D34,F34) -> 497244.48 | I34: =IFERROR(H34/H$19,0) -> 0.95580149 | J34: =SUM(J19:J20) -> 0 | K34: =IFERROR(J34/J$19,0) -> 0 | L34: =SUM(L19:L20) -> -312.58 | M34: =IFERROR(L34/L$19,0) -> 0 | N34: =SUM(N19:N20) -> 0 | O34: =IFERROR(N34/N$19,0) -> 0 | P34: =SUM(J34,L34,N34) -> -312.58 | Q34: =IFERROR(P34/P$19,0) -> 0 | R34: =SUM(R19:R20) -> 0 | S34: =IFERROR(R34/R$19,0) -> 0 | T34: =SUM(T19:T20) -> 0 | U34: =IFERROR(T34/T$19,0) -> 0 | V34: =SUM(V19:V20) -> 0 | W34: =IFERROR(V34/V$19,0) -> 0 | X34: =SUM(R34,T34,V34) -> 0 | Y34: =IFERROR(X34/X$19,0) -> 0 | Z34: =SUM(Z19:Z20) -> 0 | AA34: =IFERROR(Z34/Z$19,0) -> 0 | AB34: =SUM(AB19:AB20) -> 0 | AC34: =IFERROR(AB34/AB$19,0) -> 0 | AD34: =SUM(AD19:AD20) -> 0 | AE34: =IFERROR(AD34/AD$19,0) -> 0 | AF34: =SUM(Z34,AB34,AD34) -> 0 | AG34: =IFERROR(AF34/AF$19,0) -> 0 | AH34: =SUM(B34,D34,F34,J34,L34,N34,R34,T34,V34,Z34,AB34,AD34) -> 496931.9 | AI34: =IFERROR(AH34/AH$19,0) -> 0.95520065
A35: (-)Gastos Fixos | B35: =IFERROR(VLOOKUP($A35,APOIO!$B:$N,MATCH(B$5,APOIO!$B$5:$N$5,0),FALSE),0) -> -264326.31 | C35: =IFERROR(B35/B$19,0) -> -1.7034138 | D35: =IFERROR(VLOOKUP($A35,APOIO!$B:$N,MATCH(D$5,APOIO!$B$5:$N$5,0),FALSE),0) -> -192424.63 | E35: =IFERROR(D35/D$19,0) -> -0.52709867 | F35: =IFERROR(VLOOKUP($A35,APOIO!$B:$N,MATCH(F$5,APOIO!$B$5:$N$5,0),FALSE),0) -> -85532.052 | G35: =IFERROR(F35/F$19,0) -> 0 | H35: =SUM(B35,D35,F35) -> -542282.99 | I35: =IFERROR(H35/H$19,0) -> -1.0423744 | J35: =IFERROR(VLOOKUP($A35,APOIO!$B:$N,MATCH(J$5,APOIO!$B$5:$N$5,0),FALSE),0) -> -65470.009 | K35: =IFERROR(J35/J$19,0) -> 0 | L35: =IFERROR(VLOOKUP($A35,APOIO!$B:$N,MATCH(L$5,APOIO!$B$5:$N$5,0),FALSE),0) -> -74641.516 | M35: =IFERROR(L35/L$19,0) -> 0 | N35: =IFERROR(VLOOKUP($A35,APOIO!$B:$N,MATCH(N$5,APOIO!$B$5:$N$5,0),FALSE),0) -> 0 | O35: =IFERROR(N35/N$19,0) -> 0 | P35: =SUM(J35,L35,N35) -> -140111.53 | Q35: =IFERROR(P35/P$19,0) -> 0 | R35: =IFERROR(VLOOKUP($A35,APOIO!$B:$N,MATCH(R$5,APOIO!$B$5:$N$5,0),FALSE),0) -> 0 | S35: =IFERROR(R35/R$19,0) -> 0 | T35: =IFERROR(VLOOKUP($A35,APOIO!$B:$N,MATCH(T$5,APOIO!$B$5:$N$5,0),FALSE),0) -> 0 | U35: =IFERROR(T35/T$19,0) -> 0 | V35: =IFERROR(VLOOKUP($A35,APOIO!$B:$N,MATCH(V$5,APOIO!$B$5:$N$5,0),FALSE),0) -> 0 | W35: =IFERROR(V35/V$19,0) -> 0 | X35: =SUM(R35,T35,V35) -> 0 | Y35: =IFERROR(X35/X$19,0) -> 0 | Z35: =IFERROR(VLOOKUP($A35,APOIO!$B:$N,MATCH(Z$5,APOIO!$B$5:$N$5,0),FALSE),0) -> 0 | AA35: =IFERROR(Z35/Z$19,0) -> 0 | AB35: =IFERROR(VLOOKUP($A35,APOIO!$B:$N,MATCH(AB$5,APOIO!$B$5:$N$5,0),FALSE),0) -> 0 | AC35: =IFERROR(AB35/AB$19,0) -> 0 | AD35: =IFERROR(VLOOKUP($A35,APOIO!$B:$N,MATCH(AD$5,APOIO!$B$5:$N$5,0),FALSE),0) -> 0 | AE35: =IFERROR(AD35/AD$19,0) -> 0 | AF35: =SUM(Z35,AB35,AD35) -> 0 | AG35: =IFERROR(AF35/AF$19,0) -> 0 | AH35: =SUM(B35,D35,F35,J35,L35,N35,R35,T35,V35,Z35,AB35,AD35) -> -682394.52 | AI35: =IFERROR(AH35/AH$19,0) -> -1.3116962
A36: Despesas com Pessoal | B36: =IFERROR(VLOOKUP($A36,APOIO!$B:$N,MATCH(B$5,APOIO!$B$5:$N$5,0),FALSE),0) -> -243857.98 | C36: =IFERROR(B36/B$19,0) -> -1.5715085 | D36: =IFERROR(VLOOKUP($A36,APOIO!$B:$N,MATCH(D$5,APOIO!$B$5:$N$5,0),FALSE),0) -> -175790.23 | E36: =IFERROR(D36/D$19,0) -> -0.48153294 | F36: =IFERROR(VLOOKUP($A36,APOIO!$B:$N,MATCH(F$5,APOIO!$B$5:$N$5,0),FALSE),0) -> -74082.832 | G36: =IFERROR(F36/F$19,0) -> 0 | H36: =SUM(B36,D36,F36) -> -493731.04 | I36: =IFERROR(H36/H$19,0) -> -0.94904798 | J36: =IFERROR(VLOOKUP($A36,APOIO!$B:$N,MATCH(J$5,APOIO!$B$5:$N$5,0),FALSE),0) -> -58484.918 | K36: =IFERROR(J36/J$19,0) -> 0 | L36: =IFERROR(VLOOKUP($A36,APOIO!$B:$N,MATCH(L$5,APOIO!$B$5:$N$5,0),FALSE),0) -> -63680.216 | M36: =IFERROR(L36/L$19,0) -> 0 | N36: =IFERROR(VLOOKUP($A36,APOIO!$B:$N,MATCH(N$5,APOIO!$B$5:$N$5,0),FALSE),0) -> 0 | O36: =IFERROR(N36/N$19,0) -> 0 | P36: =SUM(J36,L36,N36) -> -122165.13 | Q36: =IFERROR(P36/P$19,0) -> 0 | R36: =IFERROR(VLOOKUP($A36,APOIO!$B:$N,MATCH(R$5,APOIO!$B$5:$N$5,0),FALSE),0) -> 0 | S36: =IFERROR(R36/R$19,0) -> 0 | T36: =IFERROR(VLOOKUP($A36,APOIO!$B:$N,MATCH(T$5,APOIO!$B$5:$N$5,0),FALSE),0) -> 0 | U36: =IFERROR(T36/T$19,0) -> 0 | V36: =IFERROR(VLOOKUP($A36,APOIO!$B:$N,MATCH(V$5,APOIO!$B$5:$N$5,0),FALSE),0) -> 0 | W36: =IFERROR(V36/V$19,0) -> 0 | X36: =SUM(R36,T36,V36) -> 0 | Y36: =IFERROR(X36/X$19,0) -> 0 | Z36: =IFERROR(VLOOKUP($A36,APOIO!$B:$N,MATCH(Z$5,APOIO!$B$5:$N$5,0),FALSE),0) -> 0 | AA36: =IFERROR(Z36/Z$19,0) -> 0 | AB36: =IFERROR(VLOOKUP($A36,APOIO!$B:$N,MATCH(AB$5,APOIO!$B$5:$N$5,0),FALSE),0) -> 0 | AC36: =IFERROR(AB36/AB$19,0) -> 0 | AD36: =IFERROR(VLOOKUP($A36,APOIO!$B:$N,MATCH(AD$5,APOIO!$B$5:$N$5,0),FALSE),0) -> 0 | AE36: =IFERROR(AD36/AD$19,0) -> 0 | AF36: =SUM(Z36,AB36,AD36) -> 0 | AG36: =IFERROR(AF36/AF$19,0) -> 0 | AH36: =SUM(B36,D36,F36,J36,L36,N36,R36,T36,V36,Z36,AB36,AD36) -> -615896.17 | AI36: =IFERROR(AH36/AH$19,0) -> -1.1838733
A37: SALARIO | B37: =IFERROR(VLOOKUP($A37,APOIO!$B:$N,MATCH(B$5,APOIO!$B$5:$N$5,0),FALSE),0) -> -89957.13 | C37: =IFERROR(B37/B$19,0) -> -0.57971608 | D37: =IFERROR(VLOOKUP($A37,APOIO!$B:$N,MATCH(D$5,APOIO!$B$5:$N$5,0),FALSE),0) -> -78180.87 | E37: =IFERROR(D37/D$19,0) -> -0.21415675 | F37: =IFERROR(VLOOKUP($A37,APOIO!$B:$N,MATCH(F$5,APOIO!$B$5:$N$5,0),FALSE),0) -> -32628.441 | G37: =IFERROR(F37/F$19,0) -> 0 | H37: =SUM(B37,D37,F37) -> -200766.44 | I37: =IFERROR(H37/H$19,0) -> -0.38591251 | J37: =IFERROR(VLOOKUP($A37,APOIO!$B:$N,MATCH(J$5,APOIO!$B$5:$N$5,0),FALSE),0) -> -30150.883 | K37: =IFERROR(J37/J$19,0) -> 0 | L37: =IFERROR(VLOOKUP($A37,APOIO!$B:$N,MATCH(L$5,APOIO!$B$5:$N$5,0),FALSE),0) -> -29306.024 | M37: =IFERROR(L37/L$19,0) -> 0 | N37: =IFERROR(VLOOKUP($A37,APOIO!$B:$N,MATCH(N$5,APOIO!$B$5:$N$5,0),FALSE),0) -> 0 | O37: =IFERROR(N37/N$19,0) -> 0 | P37: =SUM(J37,L37,N37) -> -59456.907 | Q37: =IFERROR(P37/P$19,0) -> 0 | R37: =IFERROR(VLOOKUP($A37,APOIO!$B:$N,MATCH(R$5,APOIO!$B$5:$N$5,0),FALSE),0) -> 0 | S37: =IFERROR(R37/R$19,0) -> 0 | T37: =IFERROR(VLOOKUP($A37,APOIO!$B:$N,MATCH(T$5,APOIO!$B$5:$N$5,0),FALSE),0) -> 0 | U37: =IFERROR(T37/T$19,0) -> 0 | V37: =IFERROR(VLOOKUP($A37,APOIO!$B:$N,MATCH(V$5,APOIO!$B$5:$N$5,0),FALSE),0) -> 0 | W37: =IFERROR(V37/V$19,0) -> 0 | X37: =SUM(R37,T37,V37) -> 0 | Y37: =IFERROR(X37/X$19,0) -> 0 | Z37: =IFERROR(VLOOKUP($A37,APOIO!$B:$N,MATCH(Z$5,APOIO!$B$5:$N$5,0),FALSE),0) -> 0 | AA37: =IFERROR(Z37/Z$19,0) -> 0 | AB37: =IFERROR(VLOOKUP($A37,APOIO!$B:$N,MATCH(AB$5,APOIO!$B$5:$N$5,0),FALSE),0) -> 0 | AC37: =IFERROR(AB37/AB$19,0) -> 0 | AD37: =IFERROR(VLOOKUP($A37,APOIO!$B:$N,MATCH(AD$5,APOIO!$B$5:$N$5,0),FALSE),0) -> 0 | AE37: =IFERROR(AD37/AD$19,0) -> 0 | AF37: =SUM(Z37,AB37,AD37) -> 0 | AG37: =IFERROR(AF37/AF$19,0) -> 0 | AH37: =SUM(B37,D37,F37,J37,L37,N37,R37,T37,V37,Z37,AB37,AD37) -> -260223.35 | AI37: =IFERROR(AH37/AH$19,0) -> -0.50020036
A38: 13° SALARIO | B38: =IFERROR(VLOOKUP($A38,APOIO!$B:$N,MATCH(B$5,APOIO!$B$5:$N$5,0),FALSE),0) -> 0 | C38: =IFERROR(B38/B$19,0) -> 0 | D38: =IFERROR(VLOOKUP($A38,APOIO!$B:$N,MATCH(D$5,APOIO!$B$5:$N$5,0),FALSE),0) -> 0 | E38: =IFERROR(D38/D$19,0) -> 0 | F38: =IFERROR(VLOOKUP($A38,APOIO!$B:$N,MATCH(F$5,APOIO!$B$5:$N$5,0),FALSE),0) -> 0 | G38: =IFERROR(F38/F$19,0) -> 0 | H38: =SUM(B38,D38,F38) -> 0 | I38: =IFERROR(H38/H$19,0) -> 0 | J38: =IFERROR(VLOOKUP($A38,APOIO!$B:$N,MATCH(J$5,APOIO!$B$5:$N$5,0),FALSE),0) -> 0 | K38: =IFERROR(J38/J$19,0) -> 0 | L38: =IFERROR(VLOOKUP($A38,APOIO!$B:$N,MATCH(L$5,APOIO!$B$5:$N$5,0),FALSE),0) -> 0 | M38: =IFERROR(L38/L$19,0) -> 0 | N38: =IFERROR(VLOOKUP($A38,APOIO!$B:$N,MATCH(N$5,APOIO!$B$5:$N$5,0),FALSE),0) -> 0 | O38: =IFERROR(N38/N$19,0) -> 0 | P38: =SUM(J38,L38,N38) -> 0 | Q38: =IFERROR(P38/P$19,0) -> 0 | R38: =IFERROR(VLOOKUP($A38,APOIO!$B:$N,MATCH(R$5,APOIO!$B$5:$N$5,0),FALSE),0) -> 0 | S38: =IFERROR(R38/R$19,0) -> 0 | T38: =IFERROR(VLOOKUP($A38,APOIO!$B:$N,MATCH(T$5,APOIO!$B$5:$N$5,0),FALSE),0) -> 0 | U38: =IFERROR(T38/T$19,0) -> 0 | V38: =IFERROR(VLOOKUP($A38,APOIO!$B:$N,MATCH(V$5,APOIO!$B$5:$N$5,0),FALSE),0) -> 0 | W38: =IFERROR(V38/V$19,0) -> 0 | X38: =SUM(R38,T38,V38) -> 0 | Y38: =IFERROR(X38/X$19,0) -> 0 | Z38: =IFERROR(VLOOKUP($A38,APOIO!$B:$N,MATCH(Z$5,APOIO!$B$5:$N$5,0),FALSE),0) -> 0 | AA38: =IFERROR(Z38/Z$19,0) -> 0 | AB38: =IFERROR(VLOOKUP($A38,APOIO!$B:$N,MATCH(AB$5,APOIO!$B$5:$N$5,0),FALSE),0) -> 0 | AC38: =IFERROR(AB38/AB$19,0) -> 0 | AD38: =IFERROR(VLOOKUP($A38,APOIO!$B:$N,MATCH(AD$5,APOIO!$B$5:$N$5,0),FALSE),0) -> 0 | AE38: =IFERROR(AD38/AD$19,0) -> 0 | AF38: =SUM(Z38,AB38,AD38) -> 0 | AG38: =IFERROR(AF38/AF$19,0) -> 0 | AH38: =SUM(B38,D38,F38,J38,L38,N38,R38,T38,V38,Z38,AB38,AD38) -> 0 | AI38: =IFERROR(AH38/AH$19,0) -> 0
A39: 13° PREVISAO | B39: =IFERROR(VLOOKUP($A39,APOIO!$B:$N,MATCH(B$5,APOIO!$B$5:$N$5,0),FALSE),0) -> 0 | C39: =IFERROR(B39/B$19,0) -> 0 | D39: =IFERROR(VLOOKUP($A39,APOIO!$B:$N,MATCH(D$5,APOIO!$B$5:$N$5,0),FALSE),0) -> 0 | E39: =IFERROR(D39/D$19,0) -> 0 | F39: =IFERROR(VLOOKUP($A39,APOIO!$B:$N,MATCH(F$5,APOIO!$B$5:$N$5,0),FALSE),0) -> 0 | G39: =IFERROR(F39/F$19,0) -> 0 | H39: =SUM(B39,D39,F39) -> 0 | I39: =IFERROR(H39/H$19,0) -> 0 | J39: =IFERROR(VLOOKUP($A39,APOIO!$B:$N,MATCH(J$5,APOIO!$B$5:$N$5,0),FALSE),0) -> 0 | K39: =IFERROR(J39/J$19,0) -> 0 | L39: =IFERROR(VLOOKUP($A39,APOIO!$B:$N,MATCH(L$5,APOIO!$B$5:$N$5,0),FALSE),0) -> -2442.1686 | M39: =IFERROR(L39/L$19,0) -> 0 | N39: =IFERROR(VLOOKUP($A39,APOIO!$B:$N,MATCH(N$5,APOIO!$B$5:$N$5,0),FALSE),0) -> 0 | O39: =IFERROR(N39/N$19,0) -> 0 | P39: =SUM(J39,L39,N39) -> -2442.1686 | Q39: =IFERROR(P39/P$19,0) -> 0 | R39: =IFERROR(VLOOKUP($A39,APOIO!$B:$N,MATCH(R$5,APOIO!$B$5:$N$5,0),FALSE),0) -> 0 | S39: =IFERROR(R39/R$19,0) -> 0 | T39: =IFERROR(VLOOKUP($A39,APOIO!$B:$N,MATCH(T$5,APOIO!$B$5:$N$5,0),FALSE),0) -> 0 | U39: =IFERROR(T39/T$19,0) -> 0 | V39: =IFERROR(VLOOKUP($A39,APOIO!$B:$N,MATCH(V$5,APOIO!$B$5:$N$5,0),FALSE),0) -> 0 | W39: =IFERROR(V39/V$19,0) -> 0 | X39: =SUM(R39,T39,V39) -> 0 | Y39: =IFERROR(X39/X$19,0) -> 0 | Z39: =IFERROR(VLOOKUP($A39,APOIO!$B:$N,MATCH(Z$5,APOIO!$B$5:$N$5,0),FALSE),0) -> 0 | AA39: =IFERROR(Z39/Z$19,0) -> 0 | AB39: =IFERROR(VLOOKUP($A39,APOIO!$B:$N,MATCH(AB$5,APOIO!$B$5:$N$5,0),FALSE),0) -> 0 | AC39: =IFERROR(AB39/AB$19,0) -> 0 | AD39: =IFERROR(VLOOKUP($A39,APOIO!$B:$N,MATCH(AD$5,APOIO!$B$5:$N$5,0),FALSE),0) -> 0 | AE39: =IFERROR(AD39/AD$19,0) -> 0 | AF39: =SUM(Z39,AB39,AD39) -> 0 | AG39: =IFERROR(AF39/AF$19,0) -> 0 | AH39: =SUM(B39,D39,F39,J39,L39,N39,R39,T39,V39,Z39,AB39,AD39) -> -2442.1686 | AI39: =IFERROR(AH39/AH$19,0) -> -0.0046943275
A40: FERIAS | B40: =IFERROR(VLOOKUP($A40,APOIO!$B:$N,MATCH(B$5,APOIO!$B$5:$N$5,0),FALSE),0) -> -7414.52 | C40: =IFERROR(B40/B$19,0) -> -0.047781832 | D40: =IFERROR(VLOOKUP($A40,APOIO!$B:$N,MATCH(D$5,APOIO!$B$5:$N$5,0),FALSE),0) -> -3467.17 | E40: =IFERROR(D40/D$19,0) -> -0.0094974366 | F40: =IFERROR(VLOOKUP($A40,APOIO!$B:$N,MATCH(F$5,APOIO!$B$5:$N$5,0),FALSE),0) -> -3468.49 | G40: =IFERROR(F40/F$19,0) -> 0 | H40: =SUM(B40,D40,F40) -> -14350.18 | I40: =IFERROR(H40/H$19,0) -> -0.027583863 | J40: =IFERROR(VLOOKUP($A40,APOIO!$B:$N,MATCH(J$5,APOIO!$B$5:$N$5,0),FALSE),0) -> -8552.44 | K40: =IFERROR(J40/J$19,0) -> 0 | L40: =IFERROR(VLOOKUP($A40,APOIO!$B:$N,MATCH(L$5,APOIO!$B$5:$N$5,0),FALSE),0) -> 0 | M40: =IFERROR(L40/L$19,0) -> 0 | N40: =IFERROR(VLOOKUP($A40,APOIO!$B:$N,MATCH(N$5,APOIO!$B$5:$N$5,0),FALSE),0) -> 0 | O40: =IFERROR(N40/N$19,0) -> 0 | P40: =SUM(J40,L40,N40) -> -8552.44 | Q40: =IFERROR(P40/P$19,0) -> 0 | R40: =IFERROR(VLOOKUP($A40,APOIO!$B:$N,MATCH(R$5,APOIO!$B$5:$N$5,0),FALSE),0) -> 0 | S40: =IFERROR(R40/R$19,0) -> 0 | T40: =IFERROR(VLOOKUP($A40,APOIO!$B:$N,MATCH(T$5,APOIO!$B$5:$N$5,0),FALSE),0) -> 0 | U40: =IFERROR(T40/T$19,0) -> 0 | V40: =IFERROR(VLOOKUP($A40,APOIO!$B:$N,MATCH(V$5,APOIO!$B$5:$N$5,0),FALSE),0) -> 0 | W40: =IFERROR(V40/V$19,0) -> 0 | X40: =SUM(R40,T40,V40) -> 0 | Y40: =IFERROR(X40/X$19,0) -> 0 | Z40: =IFERROR(VLOOKUP($A40,APOIO!$B:$N,MATCH(Z$5,APOIO!$B$5:$N$5,0),FALSE),0) -> 0 | AA40: =IFERROR(Z40/Z$19,0) -> 0 | AB40: =IFERROR(VLOOKUP($A40,APOIO!$B:$N,MATCH(AB$5,APOIO!$B$5:$N$5,0),FALSE),0) -> 0 | AC40: =IFERROR(AB40/AB$19,0) -> 0 | AD40: =IFERROR(VLOOKUP($A40,APOIO!$B:$N,MATCH(AD$5,APOIO!$B$5:$N$5,0),FALSE),0) -> 0 | AE40: =IFERROR(AD40/AD$19,0) -> 0 | AF40: =SUM(Z40,AB40,AD40) -> 0 | AG40: =IFERROR(AF40/AF$19,0) -> 0 | AH40: =SUM(B40,D40,F40,J40,L40,N40,R40,T40,V40,Z40,AB40,AD40) -> -22902.62 | AI40: =IFERROR(AH40/AH$19,0) -> -0.044023331
A41: PREVISAO FÉRIAS | B41: =IFERROR(VLOOKUP($A41,APOIO!$B:$N,MATCH(B$5,APOIO!$B$5:$N$5,0),FALSE),0) -> 0 | C41: =IFERROR(B41/B$19,0) -> 0 | D41: =IFERROR(VLOOKUP($A41,APOIO!$B:$N,MATCH(D$5,APOIO!$B$5:$N$5,0),FALSE),0) -> 0 | E41: =IFERROR(D41/D$19,0) -> 0 | F41: =IFERROR(VLOOKUP($A41,APOIO!$B:$N,MATCH(F$5,APOIO!$B$5:$N$5,0),FALSE),0) -> 0 | G41: =IFERROR(F41/F$19,0) -> 0 | H41: =SUM(B41,D41,F41) -> 0 | I41: =IFERROR(H41/H$19,0) -> 0 | J41: =IFERROR(VLOOKUP($A41,APOIO!$B:$N,MATCH(J$5,APOIO!$B$5:$N$5,0),FALSE),0) -> 0 | K41: =IFERROR(J41/J$19,0) -> 0 | L41: =IFERROR(VLOOKUP($A41,APOIO!$B:$N,MATCH(L$5,APOIO!$B$5:$N$5,0),FALSE),0) -> -4319.9521 | M41: =IFERROR(L41/L$19,0) -> 0 | N41: =IFERROR(VLOOKUP($A41,APOIO!$B:$N,MATCH(N$5,APOIO!$B$5:$N$5,0),FALSE),0) -> 0 | O41: =IFERROR(N41/N$19,0) -> 0 | P41: =SUM(J41,L41,N41) -> -4319.9521 | Q41: =IFERROR(P41/P$19,0) -> 0 | R41: =IFERROR(VLOOKUP($A41,APOIO!$B:$N,MATCH(R$5,APOIO!$B$5:$N$5,0),FALSE),0) -> 0 | S41: =IFERROR(R41/R$19,0) -> 0 | T41: =IFERROR(VLOOKUP($A41,APOIO!$B:$N,MATCH(T$5,APOIO!$B$5:$N$5,0),FALSE),0) -> 0 | U41: =IFERROR(T41/T$19,0) -> 0 | V41: =IFERROR(VLOOKUP($A41,APOIO!$B:$N,MATCH(V$5,APOIO!$B$5:$N$5,0),FALSE),0) -> 0 | W41: =IFERROR(V41/V$19,0) -> 0 | X41: =SUM(R41,T41,V41) -> 0 | Y41: =IFERROR(X41/X$19,0) -> 0 | Z41: =IFERROR(VLOOKUP($A41,APOIO!$B:$N,MATCH(Z$5,APOIO!$B$5:$N$5,0),FALSE),0) -> 0 | AA41: =IFERROR(Z41/Z$19,0) -> 0 | AB41: =IFERROR(VLOOKUP($A41,APOIO!$B:$N,MATCH(AB$5,APOIO!$B$5:$N$5,0),FALSE),0) -> 0 | AC41: =IFERROR(AB41/AB$19,0) -> 0 | AD41: =IFERROR(VLOOKUP($A41,APOIO!$B:$N,MATCH(AD$5,APOIO!$B$5:$N$5,0),FALSE),0) -> 0 | AE41: =IFERROR(AD41/AD$19,0) -> 0 | AF41: =SUM(Z41,AB41,AD41) -> 0 | AG41: =IFERROR(AF41/AF$19,0) -> 0 | AH41: =SUM(B41,D41,F41,J41,L41,N41,R41,T41,V41,Z41,AB41,AD41) -> -4319.9521 | AI41: =IFERROR(AH41/AH$19,0) -> -0.0083037959
A42: MULTA RESCISORIAS FGTS | B42: =IFERROR(VLOOKUP($A42,APOIO!$B:$N,MATCH(B$5,APOIO!$B$5:$N$5,0),FALSE),0) -> -14369.81 | C42: =IFERROR(B42/B$19,0) -> -0.092604221 | D42: =IFERROR(VLOOKUP($A42,APOIO!$B:$N,MATCH(D$5,APOIO!$B$5:$N$5,0),FALSE),0) -> -13520.04 | E42: =IFERROR(D42/D$19,0) -> -0.037034735 | F42: =IFERROR(VLOOKUP($A42,APOIO!$B:$N,MATCH(F$5,APOIO!$B$5:$N$5,0),FALSE),0) -> 0 | G42: =IFERROR(F42/F$19,0) -> 0 | H42: =SUM(B42,D42,F42) -> -27889.85 | I42: =IFERROR(H42/H$19,0) -> -0.053609766 | J42: =IFERROR(VLOOKUP($A42,APOIO!$B:$N,MATCH(J$5,APOIO!$B$5:$N$5,0),FALSE),0) -> 0 | K42: =IFERROR(J42/J$19,0) -> 0 | L42: =IFERROR(VLOOKUP($A42,APOIO!$B:$N,MATCH(L$5,APOIO!$B$5:$N$5,0),FALSE),0) -> 0 | M42: =IFERROR(L42/L$19,0) -> 0 | N42: =IFERROR(VLOOKUP($A42,APOIO!$B:$N,MATCH(N$5,APOIO!$B$5:$N$5,0),FALSE),0) -> 0 | O42: =IFERROR(N42/N$19,0) -> 0 | P42: =SUM(J42,L42,N42) -> 0 | Q42: =IFERROR(P42/P$19,0) -> 0 | R42: =IFERROR(VLOOKUP($A42,APOIO!$B:$N,MATCH(R$5,APOIO!$B$5:$N$5,0),FALSE),0) -> 0 | S42: =IFERROR(R42/R$19,0) -> 0 | T42: =IFERROR(VLOOKUP($A42,APOIO!$B:$N,MATCH(T$5,APOIO!$B$5:$N$5,0),FALSE),0) -> 0 | U42: =IFERROR(T42/T$19,0) -> 0 | V42: =IFERROR(VLOOKUP($A42,APOIO!$B:$N,MATCH(V$5,APOIO!$B$5:$N$5,0),FALSE),0) -> 0 | W42: =IFERROR(V42/V$19,0) -> 0 | X42: =SUM(R42,T42,V42) -> 0 | Y42: =IFERROR(X42/X$19,0) -> 0 | Z42: =IFERROR(VLOOKUP($A42,APOIO!$B:$N,MATCH(Z$5,APOIO!$B$5:$N$5,0),FALSE),0) -> 0 | AA42: =IFERROR(Z42/Z$19,0) -> 0 | AB42: =IFERROR(VLOOKUP($A42,APOIO!$B:$N,MATCH(AB$5,APOIO!$B$5:$N$5,0),FALSE),0) -> 0 | AC42: =IFERROR(AB42/AB$19,0) -> 0 | AD42: =IFERROR(VLOOKUP($A42,APOIO!$B:$N,MATCH(AD$5,APOIO!$B$5:$N$5,0),FALSE),0) -> 0 | AE42: =IFERROR(AD42/AD$19,0) -> 0 | AF42: =SUM(Z42,AB42,AD42) -> 0 | AG42: =IFERROR(AF42/AF$19,0) -> 0 | AH42: =SUM(B42,D42,F42,J42,L42,N42,R42,T42,V42,Z42,AB42,AD42) -> -27889.85 | AI42: =IFERROR(AH42/AH$19,0) -> -0.053609766
A43: REFEIÇÕES COLABORADORES | B43: =IFERROR(VLOOKUP($A43,APOIO!$B:$N,MATCH(B$5,APOIO!$B$5:$N$5,0),FALSE),0) -> -37508 | C43: =IFERROR(B43/B$19,0) -> -0.24171503 | D43: =IFERROR(VLOOKUP($A43,APOIO!$B:$N,MATCH(D$5,APOIO!$B$5:$N$5,0),FALSE),0) -> -12531.145 | E43: =IFERROR(D43/D$19,0) -> -0.034325907 | F43: =IFERROR(VLOOKUP($A43,APOIO!$B:$N,MATCH(F$5,APOIO!$B$5:$N$5,0),FALSE),0) -> -11818 | G43: =IFERROR(F43/F$19,0) -> 0 | H43: =SUM(B43,D43,F43) -> -61857.145 | I43: =IFERROR(H43/H$19,0) -> -0.11890158 | J43: =IFERROR(VLOOKUP($A43,APOIO!$B:$N,MATCH(J$5,APOIO!$B$5:$N$5,0),FALSE),0) -> -6302.2125 | K43: =IFERROR(J43/J$19,0) -> 0 | L43: =IFERROR(VLOOKUP($A43,APOIO!$B:$N,MATCH(L$5,APOIO!$B$5:$N$5,0),FALSE),0) -> -12595 | M43: =IFERROR(L43/L$19,0) -> 0 | N43: =IFERROR(VLOOKUP($A43,APOIO!$B:$N,MATCH(N$5,APOIO!$B$5:$N$5,0),FALSE),0) -> 0 | O43: =IFERROR(N43/N$19,0) -> 0 | P43: =SUM(J43,L43,N43) -> -18897.213 | Q43: =IFERROR(P43/P$19,0) -> 0 | R43: =IFERROR(VLOOKUP($A43,APOIO!$B:$N,MATCH(R$5,APOIO!$B$5:$N$5,0),FALSE),0) -> 0 | S43: =IFERROR(R43/R$19,0) -> 0 | T43: =IFERROR(VLOOKUP($A43,APOIO!$B:$N,MATCH(T$5,APOIO!$B$5:$N$5,0),FALSE),0) -> 0 | U43: =IFERROR(T43/T$19,0) -> 0 | V43: =IFERROR(VLOOKUP($A43,APOIO!$B:$N,MATCH(V$5,APOIO!$B$5:$N$5,0),FALSE),0) -> 0 | W43: =IFERROR(V43/V$19,0) -> 0 | X43: =SUM(R43,T43,V43) -> 0 | Y43: =IFERROR(X43/X$19,0) -> 0 | Z43: =IFERROR(VLOOKUP($A43,APOIO!$B:$N,MATCH(Z$5,APOIO!$B$5:$N$5,0),FALSE),0) -> 0 | AA43: =IFERROR(Z43/Z$19,0) -> 0 | AB43: =IFERROR(VLOOKUP($A43,APOIO!$B:$N,MATCH(AB$5,APOIO!$B$5:$N$5,0),FALSE),0) -> 0 | AC43: =IFERROR(AB43/AB$19,0) -> 0 | AD43: =IFERROR(VLOOKUP($A43,APOIO!$B:$N,MATCH(AD$5,APOIO!$B$5:$N$5,0),FALSE),0) -> 0 | AE43: =IFERROR(AD43/AD$19,0) -> 0 | AF43: =SUM(Z43,AB43,AD43) -> 0 | AG43: =IFERROR(AF43/AF$19,0) -> 0 | AH43: =SUM(B43,D43,F43,J43,L43,N43,R43,T43,V43,Z43,AB43,AD43) -> -80754.358 | AI43: =IFERROR(AH43/AH$19,0) -> -0.15522573
A44: ALIMENTAÇÃO ADM | B44: =IFERROR(VLOOKUP($A44,APOIO!$B:$N,MATCH(B$5,APOIO!$B$5:$N$5,0),FALSE),0) -> 0 | C44: =IFERROR(B44/B$19,0) -> 0 | D44: =IFERROR(VLOOKUP($A44,APOIO!$B:$N,MATCH(D$5,APOIO!$B$5:$N$5,0),FALSE),0) -> 0 | E44: =IFERROR(D44/D$19,0) -> 0 | F44: =IFERROR(VLOOKUP($A44,APOIO!$B:$N,MATCH(F$5,APOIO!$B$5:$N$5,0),FALSE),0) -> 0 | G44: =IFERROR(F44/F$19,0) -> 0 | H44: =SUM(B44,D44,F44) -> 0 | I44: =IFERROR(H44/H$19,0) -> 0 | J44: =IFERROR(VLOOKUP($A44,APOIO!$B:$N,MATCH(J$5,APOIO!$B$5:$N$5,0),FALSE),0) -> 0 | K44: =IFERROR(J44/J$19,0) -> 0 | L44: =IFERROR(VLOOKUP($A44,APOIO!$B:$N,MATCH(L$5,APOIO!$B$5:$N$5,0),FALSE),0) -> 0 | M44: =IFERROR(L44/L$19,0) -> 0 | N44: =IFERROR(VLOOKUP($A44,APOIO!$B:$N,MATCH(N$5,APOIO!$B$5:$N$5,0),FALSE),0) -> 0 | O44: =IFERROR(N44/N$19,0) -> 0 | P44: =SUM(J44,L44,N44) -> 0 | Q44: =IFERROR(P44/P$19,0) -> 0 | R44: =IFERROR(VLOOKUP($A44,APOIO!$B:$N,MATCH(R$5,APOIO!$B$5:$N$5,0),FALSE),0) -> 0 | S44: =IFERROR(R44/R$19,0) -> 0 | T44: =IFERROR(VLOOKUP($A44,APOIO!$B:$N,MATCH(T$5,APOIO!$B$5:$N$5,0),FALSE),0) -> 0 | U44: =IFERROR(T44/T$19,0) -> 0 | V44: =IFERROR(VLOOKUP($A44,APOIO!$B:$N,MATCH(V$5,APOIO!$B$5:$N$5,0),FALSE),0) -> 0 | W44: =IFERROR(V44/V$19,0) -> 0 | X44: =SUM(R44,T44,V44) -> 0 | Y44: =IFERROR(X44/X$19,0) -> 0 | Z44: =IFERROR(VLOOKUP($A44,APOIO!$B:$N,MATCH(Z$5,APOIO!$B$5:$N$5,0),FALSE),0) -> 0 | AA44: =IFERROR(Z44/Z$19,0) -> 0 | AB44: =IFERROR(VLOOKUP($A44,APOIO!$B:$N,MATCH(AB$5,APOIO!$B$5:$N$5,0),FALSE),0) -> 0 | AC44: =IFERROR(AB44/AB$19,0) -> 0 | AD44: =IFERROR(VLOOKUP($A44,APOIO!$B:$N,MATCH(AD$5,APOIO!$B$5:$N$5,0),FALSE),0) -> 0 | AE44: =IFERROR(AD44/AD$19,0) -> 0 | AF44: =SUM(Z44,AB44,AD44) -> 0 | AG44: =IFERROR(AF44/AF$19,0) -> 0 | AH44: =SUM(B44,D44,F44,J44,L44,N44,R44,T44,V44,Z44,AB44,AD44) -> 0 | AI44: =IFERROR(AH44/AH$19,0) -> 0
A45: ACERTO RESCISORIOS | B45: =IFERROR(VLOOKUP($A45,APOIO!$B:$N,MATCH(B$5,APOIO!$B$5:$N$5,0),FALSE),0) -> -42449.76 | C45: =IFERROR(B45/B$19,0) -> -0.27356151 | D45: =IFERROR(VLOOKUP($A45,APOIO!$B:$N,MATCH(D$5,APOIO!$B$5:$N$5,0),FALSE),0) -> -32818.42 | E45: =IFERROR(D45/D$19,0) -> -0.089897773 | F45: =IFERROR(VLOOKUP($A45,APOIO!$B:$N,MATCH(F$5,APOIO!$B$5:$N$5,0),FALSE),0) -> 0 | G45: =IFERROR(F45/F$19,0) -> 0 | H45: =SUM(B45,D45,F45) -> -75268.18 | I45: =IFERROR(H45/H$19,0) -> -0.14468022 | J45: =IFERROR(VLOOKUP($A45,APOIO!$B:$N,MATCH(J$5,APOIO!$B$5:$N$5,0),FALSE),0) -> 0 | K45: =IFERROR(J45/J$19,0) -> 0 | L45: =IFERROR(VLOOKUP($A45,APOIO!$B:$N,MATCH(L$5,APOIO!$B$5:$N$5,0),FALSE),0) -> 0 | M45: =IFERROR(L45/L$19,0) -> 0 | N45: =IFERROR(VLOOKUP($A45,APOIO!$B:$N,MATCH(N$5,APOIO!$B$5:$N$5,0),FALSE),0) -> 0 | O45: =IFERROR(N45/N$19,0) -> 0 | P45: =SUM(J45,L45,N45) -> 0 | Q45: =IFERROR(P45/P$19,0) -> 0 | R45: =IFERROR(VLOOKUP($A45,APOIO!$B:$N,MATCH(R$5,APOIO!$B$5:$N$5,0),FALSE),0) -> 0 | S45: =IFERROR(R45/R$19,0) -> 0 | T45: =IFERROR(VLOOKUP($A45,APOIO!$B:$N,MATCH(T$5,APOIO!$B$5:$N$5,0),FALSE),0) -> 0 | U45: =IFERROR(T45/T$19,0) -> 0 | V45: =IFERROR(VLOOKUP($A45,APOIO!$B:$N,MATCH(V$5,APOIO!$B$5:$N$5,0),FALSE),0) -> 0 | W45: =IFERROR(V45/V$19,0) -> 0 | X45: =SUM(R45,T45,V45) -> 0 | Y45: =IFERROR(X45/X$19,0) -> 0 | Z45: =IFERROR(VLOOKUP($A45,APOIO!$B:$N,MATCH(Z$5,APOIO!$B$5:$N$5,0),FALSE),0) -> 0 | AA45: =IFERROR(Z45/Z$19,0) -> 0 | AB45: =IFERROR(VLOOKUP($A45,APOIO!$B:$N,MATCH(AB$5,APOIO!$B$5:$N$5,0),FALSE),0) -> 0 | AC45: =IFERROR(AB45/AB$19,0) -> 0 | AD45: =IFERROR(VLOOKUP($A45,APOIO!$B:$N,MATCH(AD$5,APOIO!$B$5:$N$5,0),FALSE),0) -> 0 | AE45: =IFERROR(AD45/AD$19,0) -> 0 | AF45: =SUM(Z45,AB45,AD45) -> 0 | AG45: =IFERROR(AF45/AF$19,0) -> 0 | AH45: =SUM(B45,D45,F45,J45,L45,N45,R45,T45,V45,Z45,AB45,AD45) -> -75268.18 | AI45: =IFERROR(AH45/AH$19,0) -> -0.14468022
A46: TRANSPORTE DE COLABORADORES | B46: =IFERROR(VLOOKUP($A46,APOIO!$B:$N,MATCH(B$5,APOIO!$B$5:$N$5,0),FALSE),0) -> 0 | C46: =IFERROR(B46/B$19,0) -> 0 | D46: =IFERROR(VLOOKUP($A46,APOIO!$B:$N,MATCH(D$5,APOIO!$B$5:$N$5,0),FALSE),0) -> 0 | E46: =IFERROR(D46/D$19,0) -> 0 | F46: =IFERROR(VLOOKUP($A46,APOIO!$B:$N,MATCH(F$5,APOIO!$B$5:$N$5,0),FALSE),0) -> 0 | G46: =IFERROR(F46/F$19,0) -> 0 | H46: =SUM(B46,D46,F46) -> 0 | I46: =IFERROR(H46/H$19,0) -> 0 | J46: =IFERROR(VLOOKUP($A46,APOIO!$B:$N,MATCH(J$5,APOIO!$B$5:$N$5,0),FALSE),0) -> 0 | K46: =IFERROR(J46/J$19,0) -> 0 | L46: =IFERROR(VLOOKUP($A46,APOIO!$B:$N,MATCH(L$5,APOIO!$B$5:$N$5,0),FALSE),0) -> -200 | M46: =IFERROR(L46/L$19,0) -> 0 | N46: =IFERROR(VLOOKUP($A46,APOIO!$B:$N,MATCH(N$5,APOIO!$B$5:$N$5,0),FALSE),0) -> 0 | O46: =IFERROR(N46/N$19,0) -> 0 | P46: =SUM(J46,L46,N46) -> -200 | Q46: =IFERROR(P46/P$19,0) -> 0 | R46: =IFERROR(VLOOKUP($A46,APOIO!$B:$N,MATCH(R$5,APOIO!$B$5:$N$5,0),FALSE),0) -> 0 | S46: =IFERROR(R46/R$19,0) -> 0 | T46: =IFERROR(VLOOKUP($A46,APOIO!$B:$N,MATCH(T$5,APOIO!$B$5:$N$5,0),FALSE),0) -> 0 | U46: =IFERROR(T46/T$19,0) -> 0 | V46: =IFERROR(VLOOKUP($A46,APOIO!$B:$N,MATCH(V$5,APOIO!$B$5:$N$5,0),FALSE),0) -> 0 | W46: =IFERROR(V46/V$19,0) -> 0 | X46: =SUM(R46,T46,V46) -> 0 | Y46: =IFERROR(X46/X$19,0) -> 0 | Z46: =IFERROR(VLOOKUP($A46,APOIO!$B:$N,MATCH(Z$5,APOIO!$B$5:$N$5,0),FALSE),0) -> 0 | AA46: =IFERROR(Z46/Z$19,0) -> 0 | AB46: =IFERROR(VLOOKUP($A46,APOIO!$B:$N,MATCH(AB$5,APOIO!$B$5:$N$5,0),FALSE),0) -> 0 | AC46: =IFERROR(AB46/AB$19,0) -> 0 | AD46: =IFERROR(VLOOKUP($A46,APOIO!$B:$N,MATCH(AD$5,APOIO!$B$5:$N$5,0),FALSE),0) -> 0 | AE46: =IFERROR(AD46/AD$19,0) -> 0 | AF46: =SUM(Z46,AB46,AD46) -> 0 | AG46: =IFERROR(AF46/AF$19,0) -> 0 | AH46: =SUM(B46,D46,F46,J46,L46,N46,R46,T46,V46,Z46,AB46,AD46) -> -200 | AI46: =IFERROR(AH46/AH$19,0) -> -0.00038443926
... A66: SERVIÇO LAUDO TECNICO | B66: =IFERROR(VLOOKUP($A66,APOIO!$B:$N,MATCH(B$5,APOIO!$B$5:$N$5,0),FALSE),0) -> 0 | C66: =IFERROR(B66/B$19,0) -> 0 | D66: =IFERROR(VLOOKUP($A66,APOIO!$B:$N,MATCH(D$5,APOIO!$B$5:$N$5,0),FALSE),0) -> 0 | E66: =IFERROR(D66/D$19,0) -> 0 | F66: =IFERROR(VLOOKUP($A66,APOIO!$B:$N,MATCH(F$5,APOIO!$B$5:$N$5,0),FALSE),0) -> 0 | G66: =IFERROR(F66/F$19,0) -> 0 | H66: =SUM(B66,D66,F66) -> 0 | I66: =IFERROR(H66/H$19,0) -> 0 | J66: =IFERROR(VLOOKUP($A66,APOIO!$B:$N,MATCH(J$5,APOIO!$B$5:$N$5,0),FALSE),0) -> 0 | K66: =IFERROR(J66/J$19,0) -> 0 | L66: =IFERROR(VLOOKUP($A66,APOIO!$B:$N,MATCH(L$5,APOIO!$B$5:$N$5,0),FALSE),0) -> 0 | M66: =IFERROR(L66/L$19,0) -> 0 | N66: =IFERROR(VLOOKUP($A66,APOIO!$B:$N,MATCH(N$5,APOIO!$B$5:$N$5,0),FALSE),0) -> 0 | O66: =IFERROR(N66/N$19,0) -> 0 | P66: =SUM(J66,L66,N66) -> 0 | Q66: =IFERROR(P66/P$19,0) -> 0 | R66: =IFERROR(VLOOKUP($A66,APOIO!$B:$N,MATCH(R$5,APOIO!$B$5:$N$5,0),FALSE),0) -> 0 | S66: =IFERROR(R66/R$19,0) -> 0 | T66: =IFERROR(VLOOKUP($A66,APOIO!$B:$N,MATCH(T$5,APOIO!$B$5:$N$5,0),FALSE),0) -> 0 | U66: =IFERROR(T66/T$19,0) -> 0 | V66: =IFERROR(VLOOKUP($A66,APOIO!$B:$N,MATCH(V$5,APOIO!$B$5:$N$5,0),FALSE),0) -> 0 | W66: =IFERROR(V66/V$19,0) -> 0 | X66: =SUM(R66,T66,V66) -> 0 | Y66: =IFERROR(X66/X$19,0) -> 0 | Z66: =IFERROR(VLOOKUP($A66,APOIO!$B:$N,MATCH(Z$5,APOIO!$B$5:$N$5,0),FALSE),0) -> 0 | AA66: =IFERROR(Z66/Z$19,0) -> 0 | AB66: =IFERROR(VLOOKUP($A66,APOIO!$B:$N,MATCH(AB$5,APOIO!$B$5:$N$5,0),FALSE),0) -> 0 | AC66: =IFERROR(AB66/AB$19,0) -> 0 | AD66: =IFERROR(VLOOKUP($A66,APOIO!$B:$N,MATCH(AD$5,APOIO!$B$5:$N$5,0),FALSE),0) -> 0 | AE66: =IFERROR(AD66/AD$19,0) -> 0 | AF66: =SUM(Z66,AB66,AD66) -> 0 | AG66: =IFERROR(AF66/AF$19,0) -> 0 | AH66: =SUM(B66,D66,F66,J66,L66,N66,R66,T66,V66,Z66,AB66,AD66) -> 0 | AI66: =IFERROR(AH66/AH$19,0) -> 0
B67: =IFERROR(VLOOKUP($A67,APOIO!$B:$N,MATCH(B$5,APOIO!$B$5:$N$5,0),FALSE),0) -> 0 | C67: =IFERROR(B67/B$19,0) -> 0 | D67: =IFERROR(VLOOKUP($A67,APOIO!$B:$N,MATCH(D$5,APOIO!$B$5:$N$5,0),FALSE),0) -> 0 | E67: =IFERROR(D67/D$19,0) -> 0 | F67: =IFERROR(VLOOKUP($A67,APOIO!$B:$N,MATCH(F$5,APOIO!$B$5:$N$5,0),FALSE),0) -> 0 | G67: =IFERROR(F67/F$19,0) -> 0 | H67: =SUM(B67,D67,F67) -> 0 | I67: =IFERROR(H67/H$19,0) -> 0 | J67: =IFERROR(VLOOKUP($A67,APOIO!$B:$N,MATCH(J$5,APOIO!$B$5:$N$5,0),FALSE),0) -> 0 | K67: =IFERROR(J67/J$19,0) -> 0 | L67: =IFERROR(VLOOKUP($A67,APOIO!$B:$N,MATCH(L$5,APOIO!$B$5:$N$5,0),FALSE),0) -> 0 | M67: =IFERROR(L67/L$19,0) -> 0 | N67: =IFERROR(VLOOKUP($A67,APOIO!$B:$N,MATCH(N$5,APOIO!$B$5:$N$5,0),FALSE),0) -> 0 | O67: =IFERROR(N67/N$19,0) -> 0 | P67: =SUM(J67,L67,N67) -> 0 | Q67: =IFERROR(P67/P$19,0) -> 0 | R67: =IFERROR(VLOOKUP($A67,APOIO!$B:$N,MATCH(R$5,APOIO!$B$5:$N$5,0),FALSE),0) -> 0 | S67: =IFERROR(R67/R$19,0) -> 0 | T67: =IFERROR(VLOOKUP($A67,APOIO!$B:$N,MATCH(T$5,APOIO!$B$5:$N$5,0),FALSE),0) -> 0 | U67: =IFERROR(T67/T$19,0) -> 0 | V67: =IFERROR(VLOOKUP($A67,APOIO!$B:$N,MATCH(V$5,APOIO!$B$5:$N$5,0),FALSE),0) -> 0 | W67: =IFERROR(V67/V$19,0) -> 0 | X67: =SUM(R67,T67,V67) -> 0 | Y67: =IFERROR(X67/X$19,0) -> 0 | Z67: =IFERROR(VLOOKUP($A67,APOIO!$B:$N,MATCH(Z$5,APOIO!$B$5:$N$5,0),FALSE),0) -> 0 | AA67: =IFERROR(Z67/Z$19,0) -> 0 | AB67: =IFERROR(VLOOKUP($A67,APOIO!$B:$N,MATCH(AB$5,APOIO!$B$5:$N$5,0),FALSE),0) -> 0 | AC67: =IFERROR(AB67/AB$19,0) -> 0 | AD67: =IFERROR(VLOOKUP($A67,APOIO!$B:$N,MATCH(AD$5,APOIO!$B$5:$N$5,0),FALSE),0) -> 0 | AE67: =IFERROR(AD67/AD$19,0) -> 0 | AF67: =SUM(Z67,AB67,AD67) -> 0 | AG67: =IFERROR(AF67/AF$19,0) -> 0 | AH67: =SUM(B67,D67,F67,J67,L67,N67,R67,T67,V67,Z67,AB67,AD67) -> 0 | AI67: =IFERROR(AH67/AH$19,0) -> 0
A68: Despesas Administrativas | B68: =IFERROR(VLOOKUP($A68,APOIO!$B:$N,MATCH(B$5,APOIO!$B$5:$N$5,0),FALSE),0) -> -1345.99 | C68: =IFERROR(B68/B$19,0) -> -0.0086740434 | D68: =IFERROR(VLOOKUP($A68,APOIO!$B:$N,MATCH(D$5,APOIO!$B$5:$N$5,0),FALSE),0) -> -104.05 | E68: =IFERROR(D68/D$19,0) -> -0.0002850187 | F68: =IFERROR(VLOOKUP($A68,APOIO!$B:$N,MATCH(F$5,APOIO!$B$5:$N$5,0),FALSE),0) -> -24 | G68: =IFERROR(F68/F$19,0) -> 0 | H68: =SUM(B68,D68,F68) -> -1474.04 | I68: =IFERROR(H68/H$19,0) -> -0.0028333942 | J68: =IFERROR(VLOOKUP($A68,APOIO!$B:$N,MATCH(J$5,APOIO!$B$5:$N$5,0),FALSE),0) -> -10.287621 | K68: =IFERROR(J68/J$19,0) -> 0 | L68: =IFERROR(VLOOKUP($A68,APOIO!$B:$N,MATCH(L$5,APOIO!$B$5:$N$5,0),FALSE),0) -> 0 | M68: =IFERROR(L68/L$19,0) -> 0 | N68: =IFERROR(VLOOKUP($A68,APOIO!$B:$N,MATCH(N$5,APOIO!$B$5:$N$5,0),FALSE),0) -> 0 | O68: =IFERROR(N68/N$19,0) -> 0 | P68: =SUM(J68,L68,N68) -> -10.287621 | Q68: =IFERROR(P68/P$19,0) -> 0 | R68: =IFERROR(VLOOKUP($A68,APOIO!$B:$N,MATCH(R$5,APOIO!$B$5:$N$5,0),FALSE),0) -> 0 | S68: =IFERROR(R68/R$19,0) -> 0 | T68: =IFERROR(VLOOKUP($A68,APOIO!$B:$N,MATCH(T$5,APOIO!$B$5:$N$5,0),FALSE),0) -> 0 | U68: =IFERROR(T68/T$19,0) -> 0 | V68: =IFERROR(VLOOKUP($A68,APOIO!$B:$N,MATCH(V$5,APOIO!$B$5:$N$5,0),FALSE),0) -> 0 | W68: =IFERROR(V68/V$19,0) -> 0 | X68: =SUM(R68,T68,V68) -> 0 | Y68: =IFERROR(X68/X$19,0) -> 0 | Z68: =IFERROR(VLOOKUP($A68,APOIO!$B:$N,MATCH(Z$5,APOIO!$B$5:$N$5,0),FALSE),0) -> 0 | AA68: =IFERROR(Z68/Z$19,0) -> 0 | AB68: =IFERROR(VLOOKUP($A68,APOIO!$B:$N,MATCH(AB$5,APOIO!$B$5:$N$5,0),FALSE),0) -> 0 | AC68: =IFERROR(AB68/AB$19,0) -> 0 | AD68: =IFERROR(VLOOKUP($A68,APOIO!$B:$N,MATCH(AD$5,APOIO!$B$5:$N$5,0),FALSE),0) -> 0 | AE68: =IFERROR(AD68/AD$19,0) -> 0 | AF68: =SUM(Z68,AB68,AD68) -> 0 | AG68: =IFERROR(AF68/AF$19,0) -> 0 | AH68: =SUM(B68,D68,F68,J68,L68,N68,R68,T68,V68,Z68,AB68,AD68) -> -1484.3276 | AI68: =IFERROR(AH68/AH$19,0) -> -0.0028531691
A69: SISTEMA / SERVIDOR | B69: =IFERROR(VLOOKUP($A69,APOIO!$B:$N,MATCH(B$5,APOIO!$B$5:$N$5,0),FALSE),0) -> 0 | C69: =IFERROR(B69/B$19,0) -> 0 | D69: =IFERROR(VLOOKUP($A69,APOIO!$B:$N,MATCH(D$5,APOIO!$B$5:$N$5,0),FALSE),0) -> 0 | E69: =IFERROR(D69/D$19,0) -> 0 | F69: =IFERROR(VLOOKUP($A69,APOIO!$B:$N,MATCH(F$5,APOIO!$B$5:$N$5,0),FALSE),0) -> 0 | G69: =IFERROR(F69/F$19,0) -> 0 | H69: =SUM(B69,D69,F69) -> 0 | I69: =IFERROR(H69/H$19,0) -> 0 | J69: =IFERROR(VLOOKUP($A69,APOIO!$B:$N,MATCH(J$5,APOIO!$B$5:$N$5,0),FALSE),0) -> 0 | K69: =IFERROR(J69/J$19,0) -> 0 | L69: =IFERROR(VLOOKUP($A69,APOIO!$B:$N,MATCH(L$5,APOIO!$B$5:$N$5,0),FALSE),0) -> 0 | M69: =IFERROR(L69/L$19,0) -> 0 | N69: =IFERROR(VLOOKUP($A69,APOIO!$B:$N,MATCH(N$5,APOIO!$B$5:$N$5,0),FALSE),0) -> 0 | O69: =IFERROR(N69/N$19,0) -> 0 | P69: =SUM(J69,L69,N69) -> 0 | Q69: =IFERROR(P69/P$19,0) -> 0 | R69: =IFERROR(VLOOKUP($A69,APOIO!$B:$N,MATCH(R$5,APOIO!$B$5:$N$5,0),FALSE),0) -> 0 | S69: =IFERROR(R69/R$19,0) -> 0 | T69: =IFERROR(VLOOKUP($A69,APOIO!$B:$N,MATCH(T$5,APOIO!$B$5:$N$5,0),FALSE),0) -> 0 | U69: =IFERROR(T69/T$19,0) -> 0 | V69: =IFERROR(VLOOKUP($A69,APOIO!$B:$N,MATCH(V$5,APOIO!$B$5:$N$5,0),FALSE),0) -> 0 | W69: =IFERROR(V69/V$19,0) -> 0 | X69: =SUM(R69,T69,V69) -> 0 | Y69: =IFERROR(X69/X$19,0) -> 0 | Z69: =IFERROR(VLOOKUP($A69,APOIO!$B:$N,MATCH(Z$5,APOIO!$B$5:$N$5,0),FALSE),0) -> 0 | AA69: =IFERROR(Z69/Z$19,0) -> 0 | AB69: =IFERROR(VLOOKUP($A69,APOIO!$B:$N,MATCH(AB$5,APOIO!$B$5:$N$5,0),FALSE),0) -> 0 | AC69: =IFERROR(AB69/AB$19,0) -> 0 | AD69: =IFERROR(VLOOKUP($A69,APOIO!$B:$N,MATCH(AD$5,APOIO!$B$5:$N$5,0),FALSE),0) -> 0 | AE69: =IFERROR(AD69/AD$19,0) -> 0 | AF69: =SUM(Z69,AB69,AD69) -> 0 | AG69: =IFERROR(AF69/AF$19,0) -> 0 | AH69: =SUM(B69,D69,F69,J69,L69,N69,R69,T69,V69,Z69,AB69,AD69) -> 0 | AI69: =IFERROR(AH69/AH$19,0) -> 0
A70: SERVIÇOS DE CONSULTORIA | B70: =IFERROR(VLOOKUP($A70,APOIO!$B:$N,MATCH(B$5,APOIO!$B$5:$N$5,0),FALSE),0) -> 0 | C70: =IFERROR(B70/B$19,0) -> 0 | D70: =IFERROR(VLOOKUP($A70,APOIO!$B:$N,MATCH(D$5,APOIO!$B$5:$N$5,0),FALSE),0) -> 0 | E70: =IFERROR(D70/D$19,0) -> 0 | F70: =IFERROR(VLOOKUP($A70,APOIO!$B:$N,MATCH(F$5,APOIO!$B$5:$N$5,0),FALSE),0) -> 0 | G70: =IFERROR(F70/F$19,0) -> 0 | H70: =SUM(B70,D70,F70) -> 0 | I70: =IFERROR(H70/H$19,0) -> 0 | J70: =IFERROR(VLOOKUP($A70,APOIO!$B:$N,MATCH(J$5,APOIO!$B$5:$N$5,0),FALSE),0) -> 0 | K70: =IFERROR(J70/J$19,0) -> 0 | L70: =IFERROR(VLOOKUP($A70,APOIO!$B:$N,MATCH(L$5,APOIO!$B$5:$N$5,0),FALSE),0) -> 0 | M70: =IFERROR(L70/L$19,0) -> 0 | N70: =IFERROR(VLOOKUP($A70,APOIO!$B:$N,MATCH(N$5,APOIO!$B$5:$N$5,0),FALSE),0) -> 0 | O70: =IFERROR(N70/N$19,0) -> 0 | P70: =SUM(J70,L70,N70) -> 0 | Q70: =IFERROR(P70/P$19,0) -> 0 | R70: =IFERROR(VLOOKUP($A70,APOIO!$B:$N,MATCH(R$5,APOIO!$B$5:$N$5,0),FALSE),0) -> 0 | S70: =IFERROR(R70/R$19,0) -> 0 | T70: =IFERROR(VLOOKUP($A70,APOIO!$B:$N,MATCH(T$5,APOIO!$B$5:$N$5,0),FALSE),0) -> 0 | U70: =IFERROR(T70/T$19,0) -> 0 | V70: =IFERROR(VLOOKUP($A70,APOIO!$B:$N,MATCH(V$5,APOIO!$B$5:$N$5,0),FALSE),0) -> 0 | W70: =IFERROR(V70/V$19,0) -> 0 | X70: =SUM(R70,T70,V70) -> 0 | Y70: =IFERROR(X70/X$19,0) -> 0 | Z70: =IFERROR(VLOOKUP($A70,APOIO!$B:$N,MATCH(Z$5,APOIO!$B$5:$N$5,0),FALSE),0) -> 0 | AA70: =IFERROR(Z70/Z$19,0) -> 0 | AB70: =IFERROR(VLOOKUP($A70,APOIO!$B:$N,MATCH(AB$5,APOIO!$B$5:$N$5,0),FALSE),0) -> 0 | AC70: =IFERROR(AB70/AB$19,0) -> 0 | AD70: =IFERROR(VLOOKUP($A70,APOIO!$B:$N,MATCH(AD$5,APOIO!$B$5:$N$5,0),FALSE),0) -> 0 | AE70: =IFERROR(AD70/AD$19,0) -> 0 | AF70: =SUM(Z70,AB70,AD70) -> 0 | AG70: =IFERROR(AF70/AF$19,0) -> 0 | AH70: =SUM(B70,D70,F70,J70,L70,N70,R70,T70,V70,Z70,AB70,AD70) -> 0 | AI70: =IFERROR(AH70/AH$19,0) -> 0
A71: HONORÁRIOS ADVOCATÍCIOS | B71: =IFERROR(VLOOKUP($A71,APOIO!$B:$N,MATCH(B$5,APOIO!$B$5:$N$5,0),FALSE),0) -> 0 | C71: =IFERROR(B71/B$19,0) -> 0 | D71: =IFERROR(VLOOKUP($A71,APOIO!$B:$N,MATCH(D$5,APOIO!$B$5:$N$5,0),FALSE),0) -> 0 | E71: =IFERROR(D71/D$19,0) -> 0 | F71: =IFERROR(VLOOKUP($A71,APOIO!$B:$N,MATCH(F$5,APOIO!$B$5:$N$5,0),FALSE),0) -> 0 | G71: =IFERROR(F71/F$19,0) -> 0 | H71: =SUM(B71,D71,F71) -> 0 | I71: =IFERROR(H71/H$19,0) -> 0 | J71: =IFERROR(VLOOKUP($A71,APOIO!$B:$N,MATCH(J$5,APOIO!$B$5:$N$5,0),FALSE),0) -> 0 | K71: =IFERROR(J71/J$19,0) -> 0 | L71: =IFERROR(VLOOKUP($A71,APOIO!$B:$N,MATCH(L$5,APOIO!$B$5:$N$5,0),FALSE),0) -> 0 | M71: =IFERROR(L71/L$19,0) -> 0 | N71: =IFERROR(VLOOKUP($A71,APOIO!$B:$N,MATCH(N$5,APOIO!$B$5:$N$5,0),FALSE),0) -> 0 | O71: =IFERROR(N71/N$19,0) -> 0 | P71: =SUM(J71,L71,N71) -> 0 | Q71: =IFERROR(P71/P$19,0) -> 0 | R71: =IFERROR(VLOOKUP($A71,APOIO!$B:$N,MATCH(R$5,APOIO!$B$5:$N$5,0),FALSE),0) -> 0 | S71: =IFERROR(R71/R$19,0) -> 0 | T71: =IFERROR(VLOOKUP($A71,APOIO!$B:$N,MATCH(T$5,APOIO!$B$5:$N$5,0),FALSE),0) -> 0 | U71: =IFERROR(T71/T$19,0) -> 0 | V71: =IFERROR(VLOOKUP($A71,APOIO!$B:$N,MATCH(V$5,APOIO!$B$5:$N$5,0),FALSE),0) -> 0 | W71: =IFERROR(V71/V$19,0) -> 0 | X71: =SUM(R71,T71,V71) -> 0 | Y71: =IFERROR(X71/X$19,0) -> 0 | Z71: =IFERROR(VLOOKUP($A71,APOIO!$B:$N,MATCH(Z$5,APOIO!$B$5:$N$5,0),FALSE),0) -> 0 | AA71: =IFERROR(Z71/Z$19,0) -> 0 | AB71: =IFERROR(VLOOKUP($A71,APOIO!$B:$N,MATCH(AB$5,APOIO!$B$5:$N$5,0),FALSE),0) -> 0 | AC71: =IFERROR(AB71/AB$19,0) -> 0 | AD71: =IFERROR(VLOOKUP($A71,APOIO!$B:$N,MATCH(AD$5,APOIO!$B$5:$N$5,0),FALSE),0) -> 0 | AE71: =IFERROR(AD71/AD$19,0) -> 0 | AF71: =SUM(Z71,AB71,AD71) -> 0 | AG71: =IFERROR(AF71/AF$19,0) -> 0 | AH71: =SUM(B71,D71,F71,J71,L71,N71,R71,T71,V71,Z71,AB71,AD71) -> 0 | AI71: =IFERROR(AH71/AH$19,0) -> 0
A72: HONORÁRIOS CONTÁBEIS | B72: =IFERROR(VLOOKUP($A72,APOIO!$B:$N,MATCH(B$5,APOIO!$B$5:$N$5,0),FALSE),0) -> 0 | C72: =IFERROR(B72/B$19,0) -> 0 | D72: =IFERROR(VLOOKUP($A72,APOIO!$B:$N,MATCH(D$5,APOIO!$B$5:$N$5,0),FALSE),0) -> 0 | E72: =IFERROR(D72/D$19,0) -> 0 | F72: =IFERROR(VLOOKUP($A72,APOIO!$B:$N,MATCH(F$5,APOIO!$B$5:$N$5,0),FALSE),0) -> 0 | G72: =IFERROR(F72/F$19,0) -> 0 | H72: =SUM(B72,D72,F72) -> 0 | I72: =IFERROR(H72/H$19,0) -> 0 | J72: =IFERROR(VLOOKUP($A72,APOIO!$B:$N,MATCH(J$5,APOIO!$B$5:$N$5,0),FALSE),0) -> 0 | K72: =IFERROR(J72/J$19,0) -> 0 | L72: =IFERROR(VLOOKUP($A72,APOIO!$B:$N,MATCH(L$5,APOIO!$B$5:$N$5,0),FALSE),0) -> 0 | M72: =IFERROR(L72/L$19,0) -> 0 | N72: =IFERROR(VLOOKUP($A72,APOIO!$B:$N,MATCH(N$5,APOIO!$B$5:$N$5,0),FALSE),0) -> 0 | O72: =IFERROR(N72/N$19,0) -> 0 | P72: =SUM(J72,L72,N72) -> 0 | Q72: =IFERROR(P72/P$19,0) -> 0 | R72: =IFERROR(VLOOKUP($A72,APOIO!$B:$N,MATCH(R$5,APOIO!$B$5:$N$5,0),FALSE),0) -> 0 | S72: =IFERROR(R72/R$19,0) -> 0 | T72: =IFERROR(VLOOKUP($A72,APOIO!$B:$N,MATCH(T$5,APOIO!$B$5:$N$5,0),FALSE),0) -> 0 | U72: =IFERROR(T72/T$19,0) -> 0 | V72: =IFERROR(VLOOKUP($A72,APOIO!$B:$N,MATCH(V$5,APOIO!$B$5:$N$5,0),FALSE),0) -> 0 | W72: =IFERROR(V72/V$19,0) -> 0 | X72: =SUM(R72,T72,V72) -> 0 | Y72: =IFERROR(X72/X$19,0) -> 0 | Z72: =IFERROR(VLOOKUP($A72,APOIO!$B:$N,MATCH(Z$5,APOIO!$B$5:$N$5,0),FALSE),0) -> 0 | AA72: =IFERROR(Z72/Z$19,0) -> 0 | AB72: =IFERROR(VLOOKUP($A72,APOIO!$B:$N,MATCH(AB$5,APOIO!$B$5:$N$5,0),FALSE),0) -> 0 | AC72: =IFERROR(AB72/AB$19,0) -> 0 | AD72: =IFERROR(VLOOKUP($A72,APOIO!$B:$N,MATCH(AD$5,APOIO!$B$5:$N$5,0),FALSE),0) -> 0 | AE72: =IFERROR(AD72/AD$19,0) -> 0 | AF72: =SUM(Z72,AB72,AD72) -> 0 | AG72: =IFERROR(AF72/AF$19,0) -> 0 | AH72: =SUM(B72,D72,F72,J72,L72,N72,R72,T72,V72,Z72,AB72,AD72) -> 0 | AI72: =IFERROR(AH72/AH$19,0) -> 0
A73: DESPESA CARTAO DE CREDITO | B73: =IFERROR(VLOOKUP($A73,APOIO!$B:$N,MATCH(B$5,APOIO!$B$5:$N$5,0),FALSE),0) -> 0 | C73: =IFERROR(B73/B$19,0) -> 0 | D73: =IFERROR(VLOOKUP($A73,APOIO!$B:$N,MATCH(D$5,APOIO!$B$5:$N$5,0),FALSE),0) -> 0 | E73: =IFERROR(D73/D$19,0) -> 0 | F73: =IFERROR(VLOOKUP($A73,APOIO!$B:$N,MATCH(F$5,APOIO!$B$5:$N$5,0),FALSE),0) -> 0 | G73: =IFERROR(F73/F$19,0) -> 0 | H73: =SUM(B73,D73,F73) -> 0 | I73: =IFERROR(H73/H$19,0) -> 0 | J73: =IFERROR(VLOOKUP($A73,APOIO!$B:$N,MATCH(J$5,APOIO!$B$5:$N$5,0),FALSE),0) -> 0 | K73: =IFERROR(J73/J$19,0) -> 0 | L73: =IFERROR(VLOOKUP($A73,APOIO!$B:$N,MATCH(L$5,APOIO!$B$5:$N$5,0),FALSE),0) -> 0 | M73: =IFERROR(L73/L$19,0) -> 0 | N73: =IFERROR(VLOOKUP($A73,APOIO!$B:$N,MATCH(N$5,APOIO!$B$5:$N$5,0),FALSE),0) -> 0 | O73: =IFERROR(N73/N$19,0) -> 0 | P73: =SUM(J73,L73,N73) -> 0 | Q73: =IFERROR(P73/P$19,0) -> 0 | R73: =IFERROR(VLOOKUP($A73,APOIO!$B:$N,MATCH(R$5,APOIO!$B$5:$N$5,0),FALSE),0) -> 0 | S73: =IFERROR(R73/R$19,0) -> 0 | T73: =IFERROR(VLOOKUP($A73,APOIO!$B:$N,MATCH(T$5,APOIO!$B$5:$N$5,0),FALSE),0) -> 0 | U73: =IFERROR(T73/T$19,0) -> 0 | V73: =IFERROR(VLOOKUP($A73,APOIO!$B:$N,MATCH(V$5,APOIO!$B$5:$N$5,0),FALSE),0) -> 0 | W73: =IFERROR(V73/V$19,0) -> 0 | X73: =SUM(R73,T73,V73) -> 0 | Y73: =IFERROR(X73/X$19,0) -> 0 | Z73: =IFERROR(VLOOKUP($A73,APOIO!$B:$N,MATCH(Z$5,APOIO!$B$5:$N$5,0),FALSE),0) -> 0 | AA73: =IFERROR(Z73/Z$19,0) -> 0 | AB73: =IFERROR(VLOOKUP($A73,APOIO!$B:$N,MATCH(AB$5,APOIO!$B$5:$N$5,0),FALSE),0) -> 0 | AC73: =IFERROR(AB73/AB$19,0) -> 0 | AD73: =IFERROR(VLOOKUP($A73,APOIO!$B:$N,MATCH(AD$5,APOIO!$B$5:$N$5,0),FALSE),0) -> 0 | AE73: =IFERROR(AD73/AD$19,0) -> 0 | AF73: =SUM(Z73,AB73,AD73) -> 0 | AG73: =IFERROR(AF73/AF$19,0) -> 0 | AH73: =SUM(B73,D73,F73,J73,L73,N73,R73,T73,V73,Z73,AB73,AD73) -> 0 | AI73: =IFERROR(AH73/AH$19,0) -> 0
A74: MATERIAIS DE INFORMATICA / COMPUTADOR | B74: =IFERROR(VLOOKUP($A74,APOIO!$B:$N,MATCH(B$5,APOIO!$B$5:$N$5,0),FALSE),0) -> 0 | C74: =IFERROR(B74/B$19,0) -> 0 | D74: =IFERROR(VLOOKUP($A74,APOIO!$B:$N,MATCH(D$5,APOIO!$B$5:$N$5,0),FALSE),0) -> 0 | E74: =IFERROR(D74/D$19,0) -> 0 | F74: =IFERROR(VLOOKUP($A74,APOIO!$B:$N,MATCH(F$5,APOIO!$B$5:$N$5,0),FALSE),0) -> 0 | G74: =IFERROR(F74/F$19,0) -> 0 | H74: =SUM(B74,D74,F74) -> 0 | I74: =IFERROR(H74/H$19,0) -> 0 | J74: =IFERROR(VLOOKUP($A74,APOIO!$B:$N,MATCH(J$5,APOIO!$B$5:$N$5,0),FALSE),0) -> 0 | K74: =IFERROR(J74/J$19,0) -> 0 | L74: =IFERROR(VLOOKUP($A74,APOIO!$B:$N,MATCH(L$5,APOIO!$B$5:$N$5,0),FALSE),0) -> 0 | M74: =IFERROR(L74/L$19,0) -> 0 | N74: =IFERROR(VLOOKUP($A74,APOIO!$B:$N,MATCH(N$5,APOIO!$B$5:$N$5,0),FALSE),0) -> 0 | O74: =IFERROR(N74/N$19,0) -> 0 | P74: =SUM(J74,L74,N74) -> 0 | Q74: =IFERROR(P74/P$19,0) -> 0 | R74: =IFERROR(VLOOKUP($A74,APOIO!$B:$N,MATCH(R$5,APOIO!$B$5:$N$5,0),FALSE),0) -> 0 | S74: =IFERROR(R74/R$19,0) -> 0 | T74: =IFERROR(VLOOKUP($A74,APOIO!$B:$N,MATCH(T$5,APOIO!$B$5:$N$5,0),FALSE),0) -> 0 | U74: =IFERROR(T74/T$19,0) -> 0 | V74: =IFERROR(VLOOKUP($A74,APOIO!$B:$N,MATCH(V$5,APOIO!$B$5:$N$5,0),FALSE),0) -> 0 | W74: =IFERROR(V74/V$19,0) -> 0 | X74: =SUM(R74,T74,V74) -> 0 | Y74: =IFERROR(X74/X$19,0) -> 0 | Z74: =IFERROR(VLOOKUP($A74,APOIO!$B:$N,MATCH(Z$5,APOIO!$B$5:$N$5,0),FALSE),0) -> 0 | AA74: =IFERROR(Z74/Z$19,0) -> 0 | AB74: =IFERROR(VLOOKUP($A74,APOIO!$B:$N,MATCH(AB$5,APOIO!$B$5:$N$5,0),FALSE),0) -> 0 | AC74: =IFERROR(AB74/AB$19,0) -> 0 | AD74: =IFERROR(VLOOKUP($A74,APOIO!$B:$N,MATCH(AD$5,APOIO!$B$5:$N$5,0),FALSE),0) -> 0 | AE74: =IFERROR(AD74/AD$19,0) -> 0 | AF74: =SUM(Z74,AB74,AD74) -> 0 | AG74: =IFERROR(AF74/AF$19,0) -> 0 | AH74: =SUM(B74,D74,F74,J74,L74,N74,R74,T74,V74,Z74,AB74,AD74) -> 0 | AI74: =IFERROR(AH74/AH$19,0) -> 0
A75: SERVIÇO SERASA | B75: =IFERROR(VLOOKUP($A75,APOIO!$B:$N,MATCH(B$5,APOIO!$B$5:$N$5,0),FALSE),0) -> 0 | C75: =IFERROR(B75/B$19,0) -> 0 | D75: =IFERROR(VLOOKUP($A75,APOIO!$B:$N,MATCH(D$5,APOIO!$B$5:$N$5,0),FALSE),0) -> 0 | E75: =IFERROR(D75/D$19,0) -> 0 | F75: =IFERROR(VLOOKUP($A75,APOIO!$B:$N,MATCH(F$5,APOIO!$B$5:$N$5,0),FALSE),0) -> 0 | G75: =IFERROR(F75/F$19,0) -> 0 | H75: =SUM(B75,D75,F75) -> 0 | I75: =IFERROR(H75/H$19,0) -> 0 | J75: =IFERROR(VLOOKUP($A75,APOIO!$B:$N,MATCH(J$5,APOIO!$B$5:$N$5,0),FALSE),0) -> 0 | K75: =IFERROR(J75/J$19,0) -> 0 | L75: =IFERROR(VLOOKUP($A75,APOIO!$B:$N,MATCH(L$5,APOIO!$B$5:$N$5,0),FALSE),0) -> 0 | M75: =IFERROR(L75/L$19,0) -> 0 | N75: =IFERROR(VLOOKUP($A75,APOIO!$B:$N,MATCH(N$5,APOIO!$B$5:$N$5,0),FALSE),0) -> 0 | O75: =IFERROR(N75/N$19,0) -> 0 | P75: =SUM(J75,L75,N75) -> 0 | Q75: =IFERROR(P75/P$19,0) -> 0 | R75: =IFERROR(VLOOKUP($A75,APOIO!$B:$N,MATCH(R$5,APOIO!$B$5:$N$5,0),FALSE),0) -> 0 | S75: =IFERROR(R75/R$19,0) -> 0 | T75: =IFERROR(VLOOKUP($A75,APOIO!$B:$N,MATCH(T$5,APOIO!$B$5:$N$5,0),FALSE),0) -> 0 | U75: =IFERROR(T75/T$19,0) -> 0 | V75: =IFERROR(VLOOKUP($A75,APOIO!$B:$N,MATCH(V$5,APOIO!$B$5:$N$5,0),FALSE),0) -> 0 | W75: =IFERROR(V75/V$19,0) -> 0 | X75: =SUM(R75,T75,V75) -> 0 | Y75: =IFERROR(X75/X$19,0) -> 0 | Z75: =IFERROR(VLOOKUP($A75,APOIO!$B:$N,MATCH(Z$5,APOIO!$B$5:$N$5,0),FALSE),0) -> 0 | AA75: =IFERROR(Z75/Z$19,0) -> 0 | AB75: =IFERROR(VLOOKUP($A75,APOIO!$B:$N,MATCH(AB$5,APOIO!$B$5:$N$5,0),FALSE),0) -> 0 | AC75: =IFERROR(AB75/AB$19,0) -> 0 | AD75: =IFERROR(VLOOKUP($A75,APOIO!$B:$N,MATCH(AD$5,APOIO!$B$5:$N$5,0),FALSE),0) -> 0 | AE75: =IFERROR(AD75/AD$19,0) -> 0 | AF75: =SUM(Z75,AB75,AD75) -> 0 | AG75: =IFERROR(AF75/AF$19,0) -> 0 | AH75: =SUM(B75,D75,F75,J75,L75,N75,R75,T75,V75,Z75,AB75,AD75) -> 0 | AI75: =IFERROR(AH75/AH$19,0) -> 0
A76: SERVIÇO GOOGLE ADS | B76: =IFERROR(VLOOKUP($A76,APOIO!$B:$N,MATCH(B$5,APOIO!$B$5:$N$5,0),FALSE),0) -> 0 | C76: =IFERROR(B76/B$19,0) -> 0 | D76: =IFERROR(VLOOKUP($A76,APOIO!$B:$N,MATCH(D$5,APOIO!$B$5:$N$5,0),FALSE),0) -> 0 | E76: =IFERROR(D76/D$19,0) -> 0 | F76: =IFERROR(VLOOKUP($A76,APOIO!$B:$N,MATCH(F$5,APOIO!$B$5:$N$5,0),FALSE),0) -> 0 | G76: =IFERROR(F76/F$19,0) -> 0 | H76: =SUM(B76,D76,F76) -> 0 | I76: =IFERROR(H76/H$19,0) -> 0 | J76: =IFERROR(VLOOKUP($A76,APOIO!$B:$N,MATCH(J$5,APOIO!$B$5:$N$5,0),FALSE),0) -> 0 | K76: =IFERROR(J76/J$19,0) -> 0 | L76: =IFERROR(VLOOKUP($A76,APOIO!$B:$N,MATCH(L$5,APOIO!$B$5:$N$5,0),FALSE),0) -> 0 | M76: =IFERROR(L76/L$19,0) -> 0 | N76: =IFERROR(VLOOKUP($A76,APOIO!$B:$N,MATCH(N$5,APOIO!$B$5:$N$5,0),FALSE),0) -> 0 | O76: =IFERROR(N76/N$19,0) -> 0 | P76: =SUM(J76,L76,N76) -> 0 | Q76: =IFERROR(P76/P$19,0) -> 0 | R76: =IFERROR(VLOOKUP($A76,APOIO!$B:$N,MATCH(R$5,APOIO!$B$5:$N$5,0),FALSE),0) -> 0 | S76: =IFERROR(R76/R$19,0) -> 0 | T76: =IFERROR(VLOOKUP($A76,APOIO!$B:$N,MATCH(T$5,APOIO!$B$5:$N$5,0),FALSE),0) -> 0 | U76: =IFERROR(T76/T$19,0) -> 0 | V76: =IFERROR(VLOOKUP($A76,APOIO!$B:$N,MATCH(V$5,APOIO!$B$5:$N$5,0),FALSE),0) -> 0 | W76: =IFERROR(V76/V$19,0) -> 0 | X76: =SUM(R76,T76,V76) -> 0 | Y76: =IFERROR(X76/X$19,0) -> 0 | Z76: =IFERROR(VLOOKUP($A76,APOIO!$B:$N,MATCH(Z$5,APOIO!$B$5:$N$5,0),FALSE),0) -> 0 | AA76: =IFERROR(Z76/Z$19,0) -> 0 | AB76: =IFERROR(VLOOKUP($A76,APOIO!$B:$N,MATCH(AB$5,APOIO!$B$5:$N$5,0),FALSE),0) -> 0 | AC76: =IFERROR(AB76/AB$19,0) -> 0 | AD76: =IFERROR(VLOOKUP($A76,APOIO!$B:$N,MATCH(AD$5,APOIO!$B$5:$N$5,0),FALSE),0) -> 0 | AE76: =IFERROR(AD76/AD$19,0) -> 0 | AF76: =SUM(Z76,AB76,AD76) -> 0 | AG76: =IFERROR(AF76/AF$19,0) -> 0 | AH76: =SUM(B76,D76,F76,J76,L76,N76,R76,T76,V76,Z76,AB76,AD76) -> 0 | AI76: =IFERROR(AH76/AH$19,0) -> 0
A77: SERVIÇO MOTOBOY / UBER | B77: =IFERROR(VLOOKUP($A77,APOIO!$B:$N,MATCH(B$5,APOIO!$B$5:$N$5,0),FALSE),0) -> 0 | C77: =IFERROR(B77/B$19,0) -> 0 | D77: =IFERROR(VLOOKUP($A77,APOIO!$B:$N,MATCH(D$5,APOIO!$B$5:$N$5,0),FALSE),0) -> 0 | E77: =IFERROR(D77/D$19,0) -> 0 | F77: =IFERROR(VLOOKUP($A77,APOIO!$B:$N,MATCH(F$5,APOIO!$B$5:$N$5,0),FALSE),0) -> 0 | G77: =IFERROR(F77/F$19,0) -> 0 | H77: =SUM(B77,D77,F77) -> 0 | I77: =IFERROR(H77/H$19,0) -> 0 | J77: =IFERROR(VLOOKUP($A77,APOIO!$B:$N,MATCH(J$5,APOIO!$B$5:$N$5,0),FALSE),0) -> 0 | K77: =IFERROR(J77/J$19,0) -> 0 | L77: =IFERROR(VLOOKUP($A77,APOIO!$B:$N,MATCH(L$5,APOIO!$B$5:$N$5,0),FALSE),0) -> 0 | M77: =IFERROR(L77/L$19,0) -> 0 | N77: =IFERROR(VLOOKUP($A77,APOIO!$B:$N,MATCH(N$5,APOIO!$B$5:$N$5,0),FALSE),0) -> 0 | O77: =IFERROR(N77/N$19,0) -> 0 | P77: =SUM(J77,L77,N77) -> 0 | Q77: =IFERROR(P77/P$19,0) -> 0 | R77: =IFERROR(VLOOKUP($A77,APOIO!$B:$N,MATCH(R$5,APOIO!$B$5:$N$5,0),FALSE),0) -> 0 | S77: =IFERROR(R77/R$19,0) -> 0 | T77: =IFERROR(VLOOKUP($A77,APOIO!$B:$N,MATCH(T$5,APOIO!$B$5:$N$5,0),FALSE),0) -> 0 | U77: =IFERROR(T77/T$19,0) -> 0 | V77: =IFERROR(VLOOKUP($A77,APOIO!$B:$N,MATCH(V$5,APOIO!$B$5:$N$5,0),FALSE),0) -> 0 | W77: =IFERROR(V77/V$19,0) -> 0 | X77: =SUM(R77,T77,V77) -> 0 | Y77: =IFERROR(X77/X$19,0) -> 0 | Z77: =IFERROR(VLOOKUP($A77,APOIO!$B:$N,MATCH(Z$5,APOIO!$B$5:$N$5,0),FALSE),0) -> 0 | AA77: =IFERROR(Z77/Z$19,0) -> 0 | AB77: =IFERROR(VLOOKUP($A77,APOIO!$B:$N,MATCH(AB$5,APOIO!$B$5:$N$5,0),FALSE),0) -> 0 | AC77: =IFERROR(AB77/AB$19,0) -> 0 | AD77: =IFERROR(VLOOKUP($A77,APOIO!$B:$N,MATCH(AD$5,APOIO!$B$5:$N$5,0),FALSE),0) -> 0 | AE77: =IFERROR(AD77/AD$19,0) -> 0 | AF77: =SUM(Z77,AB77,AD77) -> 0 | AG77: =IFERROR(AF77/AF$19,0) -> 0 | AH77: =SUM(B77,D77,F77,J77,L77,N77,R77,T77,V77,Z77,AB77,AD77) -> 0 | AI77: =IFERROR(AH77/AH$19,0) -> 0
A78: SERVIÇO GRAFICA / IMPRESSAO | B78: =IFERROR(VLOOKUP($A78,APOIO!$B:$N,MATCH(B$5,APOIO!$B$5:$N$5,0),FALSE),0) -> 0 | C78: =IFERROR(B78/B$19,0) -> 0 | D78: =IFERROR(VLOOKUP($A78,APOIO!$B:$N,MATCH(D$5,APOIO!$B$5:$N$5,0),FALSE),0) -> 0 | E78: =IFERROR(D78/D$19,0) -> 0 | F78: =IFERROR(VLOOKUP($A78,APOIO!$B:$N,MATCH(F$5,APOIO!$B$5:$N$5,0),FALSE),0) -> 0 | G78: =IFERROR(F78/F$19,0) -> 0 | H78: =SUM(B78,D78,F78) -> 0 | I78: =IFERROR(H78/H$19,0) -> 0 | J78: =IFERROR(VLOOKUP($A78,APOIO!$B:$N,MATCH(J$5,APOIO!$B$5:$N$5,0),FALSE),0) -> 0 | K78: =IFERROR(J78/J$19,0) -> 0 | L78: =IFERROR(VLOOKUP($A78,APOIO!$B:$N,MATCH(L$5,APOIO!$B$5:$N$5,0),FALSE),0) -> 0 | M78: =IFERROR(L78/L$19,0) -> 0 | N78: =IFERROR(VLOOKUP($A78,APOIO!$B:$N,MATCH(N$5,APOIO!$B$5:$N$5,0),FALSE),0) -> 0 | O78: =IFERROR(N78/N$19,0) -> 0 | P78: =SUM(J78,L78,N78) -> 0 | Q78: =IFERROR(P78/P$19,0) -> 0 | R78: =IFERROR(VLOOKUP($A78,APOIO!$B:$N,MATCH(R$5,APOIO!$B$5:$N$5,0),FALSE),0) -> 0 | S78: =IFERROR(R78/R$19,0) -> 0 | T78: =IFERROR(VLOOKUP($A78,APOIO!$B:$N,MATCH(T$5,APOIO!$B$5:$N$5,0),FALSE),0) -> 0 | U78: =IFERROR(T78/T$19,0) -> 0 | V78: =IFERROR(VLOOKUP($A78,APOIO!$B:$N,MATCH(V$5,APOIO!$B$5:$N$5,0),FALSE),0) -> 0 | W78: =IFERROR(V78/V$19,0) -> 0 | X78: =SUM(R78,T78,V78) -> 0 | Y78: =IFERROR(X78/X$19,0) -> 0 | Z78: =IFERROR(VLOOKUP($A78,APOIO!$B:$N,MATCH(Z$5,APOIO!$B$5:$N$5,0),FALSE),0) -> 0 | AA78: =IFERROR(Z78/Z$19,0) -> 0 | AB78: =IFERROR(VLOOKUP($A78,APOIO!$B:$N,MATCH(AB$5,APOIO!$B$5:$N$5,0),FALSE),0) -> 0 | AC78: =IFERROR(AB78/AB$19,0) -> 0 | AD78: =IFERROR(VLOOKUP($A78,APOIO!$B:$N,MATCH(AD$5,APOIO!$B$5:$N$5,0),FALSE),0) -> 0 | AE78: =IFERROR(AD78/AD$19,0) -> 0 | AF78: =SUM(Z78,AB78,AD78) -> 0 | AG78: =IFERROR(AF78/AF$19,0) -> 0 | AH78: =SUM(B78,D78,F78,J78,L78,N78,R78,T78,V78,Z78,AB78,AD78) -> 0 | AI78: =IFERROR(AH78/AH$19,0) -> 0
A79: SERVIÇO ART | B79: =IFERROR(VLOOKUP($A79,APOIO!$B:$N,MATCH(B$5,APOIO!$B$5:$N$5,0),FALSE),0) -> 0 | C79: =IFERROR(B79/B$19,0) -> 0 | D79: =IFERROR(VLOOKUP($A79,APOIO!$B:$N,MATCH(D$5,APOIO!$B$5:$N$5,0),FALSE),0) -> 0 | E79: =IFERROR(D79/D$19,0) -> 0 | F79: =IFERROR(VLOOKUP($A79,APOIO!$B:$N,MATCH(F$5,APOIO!$B$5:$N$5,0),FALSE),0) -> 0 | G79: =IFERROR(F79/F$19,0) -> 0 | H79: =SUM(B79,D79,F79) -> 0 | I79: =IFERROR(H79/H$19,0) -> 0 | J79: =IFERROR(VLOOKUP($A79,APOIO!$B:$N,MATCH(J$5,APOIO!$B$5:$N$5,0),FALSE),0) -> 0 | K79: =IFERROR(J79/J$19,0) -> 0 | L79: =IFERROR(VLOOKUP($A79,APOIO!$B:$N,MATCH(L$5,APOIO!$B$5:$N$5,0),FALSE),0) -> 0 | M79: =IFERROR(L79/L$19,0) -> 0 | N79: =IFERROR(VLOOKUP($A79,APOIO!$B:$N,MATCH(N$5,APOIO!$B$5:$N$5,0),FALSE),0) -> 0 | O79: =IFERROR(N79/N$19,0) -> 0 | P79: =SUM(J79,L79,N79) -> 0 | Q79: =IFERROR(P79/P$19,0) -> 0 | R79: =IFERROR(VLOOKUP($A79,APOIO!$B:$N,MATCH(R$5,APOIO!$B$5:$N$5,0),FALSE),0) -> 0 | S79: =IFERROR(R79/R$19,0) -> 0 | T79: =IFERROR(VLOOKUP($A79,APOIO!$B:$N,MATCH(T$5,APOIO!$B$5:$N$5,0),FALSE),0) -> 0 | U79: =IFERROR(T79/T$19,0) -> 0 | V79: =IFERROR(VLOOKUP($A79,APOIO!$B:$N,MATCH(V$5,APOIO!$B$5:$N$5,0),FALSE),0) -> 0 | W79: =IFERROR(V79/V$19,0) -> 0 | X79: =SUM(R79,T79,V79) -> 0 | Y79: =IFERROR(X79/X$19,0) -> 0 | Z79: =IFERROR(VLOOKUP($A79,APOIO!$B:$N,MATCH(Z$5,APOIO!$B$5:$N$5,0),FALSE),0) -> 0 | AA79: =IFERROR(Z79/Z$19,0) -> 0 | AB79: =IFERROR(VLOOKUP($A79,APOIO!$B:$N,MATCH(AB$5,APOIO!$B$5:$N$5,0),FALSE),0) -> 0 | AC79: =IFERROR(AB79/AB$19,0) -> 0 | AD79: =IFERROR(VLOOKUP($A79,APOIO!$B:$N,MATCH(AD$5,APOIO!$B$5:$N$5,0),FALSE),0) -> 0 | AE79: =IFERROR(AD79/AD$19,0) -> 0 | AF79: =SUM(Z79,AB79,AD79) -> 0 | AG79: =IFERROR(AF79/AF$19,0) -> 0 | AH79: =SUM(B79,D79,F79,J79,L79,N79,R79,T79,V79,Z79,AB79,AD79) -> 0 | AI79: =IFERROR(AH79/AH$19,0) -> 0
... A127: MANUTENÇÃO/PEÇAS MAQUINAS E EQUIPAMENTOS | B127: =IFERROR(VLOOKUP($A127,APOIO!$B:$N,MATCH(B$5,APOIO!$B$5:$N$5,0),FALSE),0) -> 0 | C127: =IFERROR(B127/B$19,0) -> 0 | D127: =IFERROR(VLOOKUP($A127,APOIO!$B:$N,MATCH(D$5,APOIO!$B$5:$N$5,0),FALSE),0) -> 0 | E127: =IFERROR(D127/D$19,0) -> 0 | F127: =IFERROR(VLOOKUP($A127,APOIO!$B:$N,MATCH(F$5,APOIO!$B$5:$N$5,0),FALSE),0) -> 0 | G127: =IFERROR(F127/F$19,0) -> 0 | H127: =SUM(B127,D127,F127) -> 0 | I127: =IFERROR(H127/H$19,0) -> 0 | J127: =IFERROR(VLOOKUP($A127,APOIO!$B:$N,MATCH(J$5,APOIO!$B$5:$N$5,0),FALSE),0) -> 0 | K127: =IFERROR(J127/J$19,0) -> 0 | L127: =IFERROR(VLOOKUP($A127,APOIO!$B:$N,MATCH(L$5,APOIO!$B$5:$N$5,0),FALSE),0) -> 0 | M127: =IFERROR(L127/L$19,0) -> 0 | N127: =IFERROR(VLOOKUP($A127,APOIO!$B:$N,MATCH(N$5,APOIO!$B$5:$N$5,0),FALSE),0) -> 0 | O127: =IFERROR(N127/N$19,0) -> 0 | P127: =SUM(J127,L127,N127) -> 0 | Q127: =IFERROR(P127/P$19,0) -> 0 | R127: =IFERROR(VLOOKUP($A127,APOIO!$B:$N,MATCH(R$5,APOIO!$B$5:$N$5,0),FALSE),0) -> 0 | S127: =IFERROR(R127/R$19,0) -> 0 | T127: =IFERROR(VLOOKUP($A127,APOIO!$B:$N,MATCH(T$5,APOIO!$B$5:$N$5,0),FALSE),0) -> 0 | U127: =IFERROR(T127/T$19,0) -> 0 | V127: =IFERROR(VLOOKUP($A127,APOIO!$B:$N,MATCH(V$5,APOIO!$B$5:$N$5,0),FALSE),0) -> 0 | W127: =IFERROR(V127/V$19,0) -> 0 | X127: =SUM(R127,T127,V127) -> 0 | Y127: =IFERROR(X127/X$19,0) -> 0 | Z127: =IFERROR(VLOOKUP($A127,APOIO!$B:$N,MATCH(Z$5,APOIO!$B$5:$N$5,0),FALSE),0) -> 0 | AA127: =IFERROR(Z127/Z$19,0) -> 0 | AB127: =IFERROR(VLOOKUP($A127,APOIO!$B:$N,MATCH(AB$5,APOIO!$B$5:$N$5,0),FALSE),0) -> 0 | AC127: =IFERROR(AB127/AB$19,0) -> 0 | AD127: =IFERROR(VLOOKUP($A127,APOIO!$B:$N,MATCH(AD$5,APOIO!$B$5:$N$5,0),FALSE),0) -> 0 | AE127: =IFERROR(AD127/AD$19,0) -> 0 | AF127: =SUM(Z127,AB127,AD127) -> 0 | AG127: =IFERROR(AF127/AF$19,0) -> 0 | AH127: =SUM(B127,D127,F127,J127,L127,N127,R127,T127,V127,Z127,AB127,AD127) -> 0 | AI127: =IFERROR(AH127/AH$19,0) -> 0
B128: =IFERROR(VLOOKUP($A128,APOIO!$B:$N,MATCH(B$5,APOIO!$B$5:$N$5,0),FALSE),0) -> 0 | C128: =IFERROR(B128/B$19,0) -> 0 | D128: =IFERROR(VLOOKUP($A128,APOIO!$B:$N,MATCH(D$5,APOIO!$B$5:$N$5,0),FALSE),0) -> 0 | E128: =IFERROR(D128/D$19,0) -> 0 | F128: =IFERROR(VLOOKUP($A128,APOIO!$B:$N,MATCH(F$5,APOIO!$B$5:$N$5,0),FALSE),0) -> 0 | G128: =IFERROR(F128/F$19,0) -> 0 | H128: =SUM(B128,D128,F128) -> 0 | I128: =IFERROR(H128/H$19,0) -> 0 | J128: =IFERROR(VLOOKUP($A128,APOIO!$B:$N,MATCH(J$5,APOIO!$B$5:$N$5,0),FALSE),0) -> 0 | K128: =IFERROR(J128/J$19,0) -> 0 | L128: =IFERROR(VLOOKUP($A128,APOIO!$B:$N,MATCH(L$5,APOIO!$B$5:$N$5,0),FALSE),0) -> 0 | M128: =IFERROR(L128/L$19,0) -> 0 | N128: =IFERROR(VLOOKUP($A128,APOIO!$B:$N,MATCH(N$5,APOIO!$B$5:$N$5,0),FALSE),0) -> 0 | O128: =IFERROR(N128/N$19,0) -> 0 | P128: =SUM(J128,L128,N128) -> 0 | Q128: =IFERROR(P128/P$19,0) -> 0 | R128: =IFERROR(VLOOKUP($A128,APOIO!$B:$N,MATCH(R$5,APOIO!$B$5:$N$5,0),FALSE),0) -> 0 | S128: =IFERROR(R128/R$19,0) -> 0 | T128: =IFERROR(VLOOKUP($A128,APOIO!$B:$N,MATCH(T$5,APOIO!$B$5:$N$5,0),FALSE),0) -> 0 | U128: =IFERROR(T128/T$19,0) -> 0 | V128: =IFERROR(VLOOKUP($A128,APOIO!$B:$N,MATCH(V$5,APOIO!$B$5:$N$5,0),FALSE),0) -> 0 | W128: =IFERROR(V128/V$19,0) -> 0 | X128: =SUM(R128,T128,V128) -> 0 | Y128: =IFERROR(X128/X$19,0) -> 0 | Z128: =IFERROR(VLOOKUP($A128,APOIO!$B:$N,MATCH(Z$5,APOIO!$B$5:$N$5,0),FALSE),0) -> 0 | AA128: =IFERROR(Z128/Z$19,0) -> 0 | AB128: =IFERROR(VLOOKUP($A128,APOIO!$B:$N,MATCH(AB$5,APOIO!$B$5:$N$5,0),FALSE),0) -> 0 | AC128: =IFERROR(AB128/AB$19,0) -> 0 | AD128: =IFERROR(VLOOKUP($A128,APOIO!$B:$N,MATCH(AD$5,APOIO!$B$5:$N$5,0),FALSE),0) -> 0 | AE128: =IFERROR(AD128/AD$19,0) -> 0 | AF128: =SUM(Z128,AB128,AD128) -> 0 | AG128: =IFERROR(AF128/AF$19,0) -> 0 | AH128: =SUM(B128,D128,F128,J128,L128,N128,R128,T128,V128,Z128,AB128,AD128) -> 0 | AI128: =IFERROR(AH128/AH$19,0) -> 0
A129: Despesas com Viagens e Hospedagens | B129: =IFERROR(VLOOKUP($A129,APOIO!$B:$N,MATCH(B$5,APOIO!$B$5:$N$5,0),FALSE),0) -> -720 | C129: =IFERROR(B129/B$19,0) -> -0.0046399388 | D129: =IFERROR(VLOOKUP($A129,APOIO!$B:$N,MATCH(D$5,APOIO!$B$5:$N$5,0),FALSE),0) -> -2379 | E129: =IFERROR(D129/D$19,0) -> -0.0065166697 | F129: =IFERROR(VLOOKUP($A129,APOIO!$B:$N,MATCH(F$5,APOIO!$B$5:$N$5,0),FALSE),0) -> -2050 | G129: =IFERROR(F129/F$19,0) -> 0 | H129: =SUM(B129,D129,F129) -> -5149 | I129: =IFERROR(H129/H$19,0) -> -0.0098973887 | J129: =IFERROR(VLOOKUP($A129,APOIO!$B:$N,MATCH(J$5,APOIO!$B$5:$N$5,0),FALSE),0) -> -1817 | K129: =IFERROR(J129/J$19,0) -> 0 | L129: =IFERROR(VLOOKUP($A129,APOIO!$B:$N,MATCH(L$5,APOIO!$B$5:$N$5,0),FALSE),0) -> -1424 | M129: =IFERROR(L129/L$19,0) -> 0 | N129: =IFERROR(VLOOKUP($A129,APOIO!$B:$N,MATCH(N$5,APOIO!$B$5:$N$5,0),FALSE),0) -> 0 | O129: =IFERROR(N129/N$19,0) -> 0 | P129: =SUM(J129,L129,N129) -> -3241 | Q129: =IFERROR(P129/P$19,0) -> 0 | R129: =IFERROR(VLOOKUP($A129,APOIO!$B:$N,MATCH(R$5,APOIO!$B$5:$N$5,0),FALSE),0) -> 0 | S129: =IFERROR(R129/R$19,0) -> 0 | T129: =IFERROR(VLOOKUP($A129,APOIO!$B:$N,MATCH(T$5,APOIO!$B$5:$N$5,0),FALSE),0) -> 0 | U129: =IFERROR(T129/T$19,0) -> 0 | V129: =IFERROR(VLOOKUP($A129,APOIO!$B:$N,MATCH(V$5,APOIO!$B$5:$N$5,0),FALSE),0) -> 0 | W129: =IFERROR(V129/V$19,0) -> 0 | X129: =SUM(R129,T129,V129) -> 0 | Y129: =IFERROR(X129/X$19,0) -> 0 | Z129: =IFERROR(VLOOKUP($A129,APOIO!$B:$N,MATCH(Z$5,APOIO!$B$5:$N$5,0),FALSE),0) -> 0 | AA129: =IFERROR(Z129/Z$19,0) -> 0 | AB129: =IFERROR(VLOOKUP($A129,APOIO!$B:$N,MATCH(AB$5,APOIO!$B$5:$N$5,0),FALSE),0) -> 0 | AC129: =IFERROR(AB129/AB$19,0) -> 0 | AD129: =IFERROR(VLOOKUP($A129,APOIO!$B:$N,MATCH(AD$5,APOIO!$B$5:$N$5,0),FALSE),0) -> 0 | AE129: =IFERROR(AD129/AD$19,0) -> 0 | AF129: =SUM(Z129,AB129,AD129) -> 0 | AG129: =IFERROR(AF129/AF$19,0) -> 0 | AH129: =SUM(B129,D129,F129,J129,L129,N129,R129,T129,V129,Z129,AB129,AD129) -> -8390 | AI129: =IFERROR(AH129/AH$19,0) -> -0.016127227
A130: HOTEL COLABORADORES | B130: =IFERROR(VLOOKUP($A130,APOIO!$B:$N,MATCH(B$5,APOIO!$B$5:$N$5,0),FALSE),0) -> -720 | C130: =IFERROR(B130/B$19,0) -> -0.0046399388 | D130: =IFERROR(VLOOKUP($A130,APOIO!$B:$N,MATCH(D$5,APOIO!$B$5:$N$5,0),FALSE),0) -> -2379 | E130: =IFERROR(D130/D$19,0) -> -0.0065166697 | F130: =IFERROR(VLOOKUP($A130,APOIO!$B:$N,MATCH(F$5,APOIO!$B$5:$N$5,0),FALSE),0) -> -2050 | G130: =IFERROR(F130/F$19,0) -> 0 | H130: =SUM(B130,D130,F130) -> -5149 | I130: =IFERROR(H130/H$19,0) -> -0.0098973887 | J130: =IFERROR(VLOOKUP($A130,APOIO!$B:$N,MATCH(J$5,APOIO!$B$5:$N$5,0),FALSE),0) -> -1817 | K130: =IFERROR(J130/J$19,0) -> 0 | L130: =IFERROR(VLOOKUP($A130,APOIO!$B:$N,MATCH(L$5,APOIO!$B$5:$N$5,0),FALSE),0) -> -1424 | M130: =IFERROR(L130/L$19,0) -> 0 | N130: =IFERROR(VLOOKUP($A130,APOIO!$B:$N,MATCH(N$5,APOIO!$B$5:$N$5,0),FALSE),0) -> 0 | O130: =IFERROR(N130/N$19,0) -> 0 | P130: =SUM(J130,L130,N130) -> -3241 | Q130: =IFERROR(P130/P$19,0) -> 0 | R130: =IFERROR(VLOOKUP($A130,APOIO!$B:$N,MATCH(R$5,APOIO!$B$5:$N$5,0),FALSE),0) -> 0 | S130: =IFERROR(R130/R$19,0) -> 0 | T130: =IFERROR(VLOOKUP($A130,APOIO!$B:$N,MATCH(T$5,APOIO!$B$5:$N$5,0),FALSE),0) -> 0 | U130: =IFERROR(T130/T$19,0) -> 0 | V130: =IFERROR(VLOOKUP($A130,APOIO!$B:$N,MATCH(V$5,APOIO!$B$5:$N$5,0),FALSE),0) -> 0 | W130: =IFERROR(V130/V$19,0) -> 0 | X130: =SUM(R130,T130,V130) -> 0 | Y130: =IFERROR(X130/X$19,0) -> 0 | Z130: =IFERROR(VLOOKUP($A130,APOIO!$B:$N,MATCH(Z$5,APOIO!$B$5:$N$5,0),FALSE),0) -> 0 | AA130: =IFERROR(Z130/Z$19,0) -> 0 | AB130: =IFERROR(VLOOKUP($A130,APOIO!$B:$N,MATCH(AB$5,APOIO!$B$5:$N$5,0),FALSE),0) -> 0 | AC130: =IFERROR(AB130/AB$19,0) -> 0 | AD130: =IFERROR(VLOOKUP($A130,APOIO!$B:$N,MATCH(AD$5,APOIO!$B$5:$N$5,0),FALSE),0) -> 0 | AE130: =IFERROR(AD130/AD$19,0) -> 0 | AF130: =SUM(Z130,AB130,AD130) -> 0 | AG130: =IFERROR(AF130/AF$19,0) -> 0 | AH130: =SUM(B130,D130,F130,J130,L130,N130,R130,T130,V130,Z130,AB130,AD130) -> -8390 | AI130: =IFERROR(AH130/AH$19,0) -> -0.016127227
A131: LAVANDERIA | B131: =IFERROR(VLOOKUP($A131,APOIO!$B:$N,MATCH(B$5,APOIO!$B$5:$N$5,0),FALSE),0) -> 0 | C131: =IFERROR(B131/B$19,0) -> 0 | D131: =IFERROR(VLOOKUP($A131,APOIO!$B:$N,MATCH(D$5,APOIO!$B$5:$N$5,0),FALSE),0) -> 0 | E131: =IFERROR(D131/D$19,0) -> 0 | F131: =IFERROR(VLOOKUP($A131,APOIO!$B:$N,MATCH(F$5,APOIO!$B$5:$N$5,0),FALSE),0) -> 0 | G131: =IFERROR(F131/F$19,0) -> 0 | H131: =SUM(B131,D131,F131) -> 0 | I131: =IFERROR(H131/H$19,0) -> 0 | J131: =IFERROR(VLOOKUP($A131,APOIO!$B:$N,MATCH(J$5,APOIO!$B$5:$N$5,0),FALSE),0) -> 0 | K131: =IFERROR(J131/J$19,0) -> 0 | L131: =IFERROR(VLOOKUP($A131,APOIO!$B:$N,MATCH(L$5,APOIO!$B$5:$N$5,0),FALSE),0) -> 0 | M131: =IFERROR(L131/L$19,0) -> 0 | N131: =IFERROR(VLOOKUP($A131,APOIO!$B:$N,MATCH(N$5,APOIO!$B$5:$N$5,0),FALSE),0) -> 0 | O131: =IFERROR(N131/N$19,0) -> 0 | P131: =SUM(J131,L131,N131) -> 0 | Q131: =IFERROR(P131/P$19,0) -> 0 | R131: =IFERROR(VLOOKUP($A131,APOIO!$B:$N,MATCH(R$5,APOIO!$B$5:$N$5,0),FALSE),0) -> 0 | S131: =IFERROR(R131/R$19,0) -> 0 | T131: =IFERROR(VLOOKUP($A131,APOIO!$B:$N,MATCH(T$5,APOIO!$B$5:$N$5,0),FALSE),0) -> 0 | U131: =IFERROR(T131/T$19,0) -> 0 | V131: =IFERROR(VLOOKUP($A131,APOIO!$B:$N,MATCH(V$5,APOIO!$B$5:$N$5,0),FALSE),0) -> 0 | W131: =IFERROR(V131/V$19,0) -> 0 | X131: =SUM(R131,T131,V131) -> 0 | Y131: =IFERROR(X131/X$19,0) -> 0 | Z131: =IFERROR(VLOOKUP($A131,APOIO!$B:$N,MATCH(Z$5,APOIO!$B$5:$N$5,0),FALSE),0) -> 0 | AA131: =IFERROR(Z131/Z$19,0) -> 0 | AB131: =IFERROR(VLOOKUP($A131,APOIO!$B:$N,MATCH(AB$5,APOIO!$B$5:$N$5,0),FALSE),0) -> 0 | AC131: =IFERROR(AB131/AB$19,0) -> 0 | AD131: =IFERROR(VLOOKUP($A131,APOIO!$B:$N,MATCH(AD$5,APOIO!$B$5:$N$5,0),FALSE),0) -> 0 | AE131: =IFERROR(AD131/AD$19,0) -> 0 | AF131: =SUM(Z131,AB131,AD131) -> 0 | AG131: =IFERROR(AF131/AF$19,0) -> 0 | AH131: =SUM(B131,D131,F131,J131,L131,N131,R131,T131,V131,Z131,AB131,AD131) -> 0 | AI131: =IFERROR(AH131/AH$19,0) -> 0
A132: Despesas Financeiras | B132: =IFERROR(VLOOKUP($A132,APOIO!$B:$N,MATCH(B$5,APOIO!$B$5:$N$5,0),FALSE),0) -> 0 | C132: =IFERROR(B132/B$19,0) -> 0 | D132: =IFERROR(VLOOKUP($A132,APOIO!$B:$N,MATCH(D$5,APOIO!$B$5:$N$5,0),FALSE),0) -> 0 | E132: =IFERROR(D132/D$19,0) -> 0 | F132: =IFERROR(VLOOKUP($A132,APOIO!$B:$N,MATCH(F$5,APOIO!$B$5:$N$5,0),FALSE),0) -> 0 | G132: =IFERROR(F132/F$19,0) -> 0 | H132: =SUM(B132,D132,F132) -> 0 | I132: =IFERROR(H132/H$19,0) -> 0 | J132: =IFERROR(VLOOKUP($A132,APOIO!$B:$N,MATCH(J$5,APOIO!$B$5:$N$5,0),FALSE),0) -> 0 | K132: =IFERROR(J132/J$19,0) -> 0 | L132: =IFERROR(VLOOKUP($A132,APOIO!$B:$N,MATCH(L$5,APOIO!$B$5:$N$5,0),FALSE),0) -> 0 | M132: =IFERROR(L132/L$19,0) -> 0 | N132: =IFERROR(VLOOKUP($A132,APOIO!$B:$N,MATCH(N$5,APOIO!$B$5:$N$5,0),FALSE),0) -> 0 | O132: =IFERROR(N132/N$19,0) -> 0 | P132: =SUM(J132,L132,N132) -> 0 | Q132: =IFERROR(P132/P$19,0) -> 0 | R132: =IFERROR(VLOOKUP($A132,APOIO!$B:$N,MATCH(R$5,APOIO!$B$5:$N$5,0),FALSE),0) -> 0 | S132: =IFERROR(R132/R$19,0) -> 0 | T132: =IFERROR(VLOOKUP($A132,APOIO!$B:$N,MATCH(T$5,APOIO!$B$5:$N$5,0),FALSE),0) -> 0 | U132: =IFERROR(T132/T$19,0) -> 0 | V132: =IFERROR(VLOOKUP($A132,APOIO!$B:$N,MATCH(V$5,APOIO!$B$5:$N$5,0),FALSE),0) -> 0 | W132: =IFERROR(V132/V$19,0) -> 0 | X132: =SUM(R132,T132,V132) -> 0 | Y132: =IFERROR(X132/X$19,0) -> 0 | Z132: =IFERROR(VLOOKUP($A132,APOIO!$B:$N,MATCH(Z$5,APOIO!$B$5:$N$5,0),FALSE),0) -> 0 | AA132: =IFERROR(Z132/Z$19,0) -> 0 | AB132: =IFERROR(VLOOKUP($A132,APOIO!$B:$N,MATCH(AB$5,APOIO!$B$5:$N$5,0),FALSE),0) -> 0 | AC132: =IFERROR(AB132/AB$19,0) -> 0 | AD132: =IFERROR(VLOOKUP($A132,APOIO!$B:$N,MATCH(AD$5,APOIO!$B$5:$N$5,0),FALSE),0) -> 0 | AE132: =IFERROR(AD132/AD$19,0) -> 0 | AF132: =SUM(Z132,AB132,AD132) -> 0 | AG132: =IFERROR(AF132/AF$19,0) -> 0 | AH132: =SUM(B132,D132,F132,J132,L132,N132,R132,T132,V132,Z132,AB132,AD132) -> 0 | AI132: =IFERROR(AH132/AH$19,0) -> 0
A133: TARIFAS BANCARIAS | B133: =IFERROR(VLOOKUP($A133,APOIO!$B:$N,MATCH(B$5,APOIO!$B$5:$N$5,0),FALSE),0) -> 0 | C133: =IFERROR(B133/B$19,0) -> 0 | D133: =IFERROR(VLOOKUP($A133,APOIO!$B:$N,MATCH(D$5,APOIO!$B$5:$N$5,0),FALSE),0) -> 0 | E133: =IFERROR(D133/D$19,0) -> 0 | F133: =IFERROR(VLOOKUP($A133,APOIO!$B:$N,MATCH(F$5,APOIO!$B$5:$N$5,0),FALSE),0) -> 0 | G133: =IFERROR(F133/F$19,0) -> 0 | H133: =SUM(B133,D133,F133) -> 0 | I133: =IFERROR(H133/H$19,0) -> 0 | J133: =IFERROR(VLOOKUP($A133,APOIO!$B:$N,MATCH(J$5,APOIO!$B$5:$N$5,0),FALSE),0) -> 0 | K133: =IFERROR(J133/J$19,0) -> 0 | L133: =IFERROR(VLOOKUP($A133,APOIO!$B:$N,MATCH(L$5,APOIO!$B$5:$N$5,0),FALSE),0) -> 0 | M133: =IFERROR(L133/L$19,0) -> 0 | N133: =IFERROR(VLOOKUP($A133,APOIO!$B:$N,MATCH(N$5,APOIO!$B$5:$N$5,0),FALSE),0) -> 0 | O133: =IFERROR(N133/N$19,0) -> 0 | P133: =SUM(J133,L133,N133) -> 0 | Q133: =IFERROR(P133/P$19,0) -> 0 | R133: =IFERROR(VLOOKUP($A133,APOIO!$B:$N,MATCH(R$5,APOIO!$B$5:$N$5,0),FALSE),0) -> 0 | S133: =IFERROR(R133/R$19,0) -> 0 | T133: =IFERROR(VLOOKUP($A133,APOIO!$B:$N,MATCH(T$5,APOIO!$B$5:$N$5,0),FALSE),0) -> 0 | U133: =IFERROR(T133/T$19,0) -> 0 | V133: =IFERROR(VLOOKUP($A133,APOIO!$B:$N,MATCH(V$5,APOIO!$B$5:$N$5,0),FALSE),0) -> 0 | W133: =IFERROR(V133/V$19,0) -> 0 | X133: =SUM(R133,T133,V133) -> 0 | Y133: =IFERROR(X133/X$19,0) -> 0 | Z133: =IFERROR(VLOOKUP($A133,APOIO!$B:$N,MATCH(Z$5,APOIO!$B$5:$N$5,0),FALSE),0) -> 0 | AA133: =IFERROR(Z133/Z$19,0) -> 0 | AB133: =IFERROR(VLOOKUP($A133,APOIO!$B:$N,MATCH(AB$5,APOIO!$B$5:$N$5,0),FALSE),0) -> 0 | AC133: =IFERROR(AB133/AB$19,0) -> 0 | AD133: =IFERROR(VLOOKUP($A133,APOIO!$B:$N,MATCH(AD$5,APOIO!$B$5:$N$5,0),FALSE),0) -> 0 | AE133: =IFERROR(AD133/AD$19,0) -> 0 | AF133: =SUM(Z133,AB133,AD133) -> 0 | AG133: =IFERROR(AF133/AF$19,0) -> 0 | AH133: =SUM(B133,D133,F133,J133,L133,N133,R133,T133,V133,Z133,AB133,AD133) -> 0 | AI133: =IFERROR(AH133/AH$19,0) -> 0
B134: =IFERROR(VLOOKUP($A134,APOIO!$B:$N,MATCH(B$5,APOIO!$B$5:$N$5,0),FALSE),0) -> 0 | C134: =IFERROR(B134/B$19,0) -> 0 | D134: =IFERROR(VLOOKUP($A134,APOIO!$B:$N,MATCH(D$5,APOIO!$B$5:$N$5,0),FALSE),0) -> 0 | E134: =IFERROR(D134/D$19,0) -> 0 | F134: =IFERROR(VLOOKUP($A134,APOIO!$B:$N,MATCH(F$5,APOIO!$B$5:$N$5,0),FALSE),0) -> 0 | G134: =IFERROR(F134/F$19,0) -> 0 | H134: =SUM(B134,D134,F134) -> 0 | I134: =IFERROR(H134/H$19,0) -> 0 | J134: =IFERROR(VLOOKUP($A134,APOIO!$B:$N,MATCH(J$5,APOIO!$B$5:$N$5,0),FALSE),0) -> 0 | K134: =IFERROR(J134/J$19,0) -> 0 | L134: =IFERROR(VLOOKUP($A134,APOIO!$B:$N,MATCH(L$5,APOIO!$B$5:$N$5,0),FALSE),0) -> 0 | M134: =IFERROR(L134/L$19,0) -> 0 | N134: =IFERROR(VLOOKUP($A134,APOIO!$B:$N,MATCH(N$5,APOIO!$B$5:$N$5,0),FALSE),0) -> 0 | O134: =IFERROR(N134/N$19,0) -> 0 | P134: =SUM(J134,L134,N134) -> 0 | Q134: =IFERROR(P134/P$19,0) -> 0 | R134: =IFERROR(VLOOKUP($A134,APOIO!$B:$N,MATCH(R$5,APOIO!$B$5:$N$5,0),FALSE),0) -> 0 | S134: =IFERROR(R134/R$19,0) -> 0 | T134: =IFERROR(VLOOKUP($A134,APOIO!$B:$N,MATCH(T$5,APOIO!$B$5:$N$5,0),FALSE),0) -> 0 | U134: =IFERROR(T134/T$19,0) -> 0 | V134: =IFERROR(VLOOKUP($A134,APOIO!$B:$N,MATCH(V$5,APOIO!$B$5:$N$5,0),FALSE),0) -> 0 | W134: =IFERROR(V134/V$19,0) -> 0 | X134: =SUM(R134,T134,V134) -> 0 | Y134: =IFERROR(X134/X$19,0) -> 0 | Z134: =IFERROR(VLOOKUP($A134,APOIO!$B:$N,MATCH(Z$5,APOIO!$B$5:$N$5,0),FALSE),0) -> 0 | AA134: =IFERROR(Z134/Z$19,0) -> 0 | AB134: =IFERROR(VLOOKUP($A134,APOIO!$B:$N,MATCH(AB$5,APOIO!$B$5:$N$5,0),FALSE),0) -> 0 | AC134: =IFERROR(AB134/AB$19,0) -> 0 | AD134: =IFERROR(VLOOKUP($A134,APOIO!$B:$N,MATCH(AD$5,APOIO!$B$5:$N$5,0),FALSE),0) -> 0 | AE134: =IFERROR(AD134/AD$19,0) -> 0 | AF134: =SUM(Z134,AB134,AD134) -> 0 | AG134: =IFERROR(AF134/AF$19,0) -> 0 | AH134: =SUM(B134,D134,F134,J134,L134,N134,R134,T134,V134,Z134,AB134,AD134) -> 0 | AI134: =IFERROR(AH134/AH$19,0) -> 0
A135: Despesas com Infraestrutura | B135: =IFERROR(VLOOKUP($A135,APOIO!$B:$N,MATCH(B$5,APOIO!$B$5:$N$5,0),FALSE),0) -> -2016.99 | C135: =IFERROR(B135/B$19,0) -> -0.012998209 | D135: =IFERROR(VLOOKUP($A135,APOIO!$B:$N,MATCH(D$5,APOIO!$B$5:$N$5,0),FALSE),0) -> -3185.57 | E135: =IFERROR(D135/D$19,0) -> -0.0087260645 | F135: =IFERROR(VLOOKUP($A135,APOIO!$B:$N,MATCH(F$5,APOIO!$B$5:$N$5,0),FALSE),0) -> -233.1 | G135: =IFERROR(F135/F$19,0) -> 0 | H135: =SUM(B135,D135,F135) -> -5435.66 | I135: =IFERROR(H135/H$19,0) -> -0.010448406 | J135: =IFERROR(VLOOKUP($A135,APOIO!$B:$N,MATCH(J$5,APOIO!$B$5:$N$5,0),FALSE),0) -> -2002.322 | K135: =IFERROR(J135/J$19,0) -> 0 | L135: =IFERROR(VLOOKUP($A135,APOIO!$B:$N,MATCH(L$5,APOIO!$B$5:$N$5,0),FALSE),0) -> -2547.76 | M135: =IFERROR(L135/L$19,0) -> 0 | N135: =IFERROR(VLOOKUP($A135,APOIO!$B:$N,MATCH(N$5,APOIO!$B$5:$N$5,0),FALSE),0) -> 0 | O135: =IFERROR(N135/N$19,0) -> 0 | P135: =SUM(J135,L135,N135) -> -4550.082 | Q135: =IFERROR(P135/P$19,0) -> 0 | R135: =IFERROR(VLOOKUP($A135,APOIO!$B:$N,MATCH(R$5,APOIO!$B$5:$N$5,0),FALSE),0) -> 0 | S135: =IFERROR(R135/R$19,0) -> 0 | T135: =IFERROR(VLOOKUP($A135,APOIO!$B:$N,MATCH(T$5,APOIO!$B$5:$N$5,0),FALSE),0) -> 0 | U135: =IFERROR(T135/T$19,0) -> 0 | V135: =IFERROR(VLOOKUP($A135,APOIO!$B:$N,MATCH(V$5,APOIO!$B$5:$N$5,0),FALSE),0) -> 0 | W135: =IFERROR(V135/V$19,0) -> 0 | X135: =SUM(R135,T135,V135) -> 0 | Y135: =IFERROR(X135/X$19,0) -> 0 | Z135: =IFERROR(VLOOKUP($A135,APOIO!$B:$N,MATCH(Z$5,APOIO!$B$5:$N$5,0),FALSE),0) -> 0 | AA135: =IFERROR(Z135/Z$19,0) -> 0 | AB135: =IFERROR(VLOOKUP($A135,APOIO!$B:$N,MATCH(AB$5,APOIO!$B$5:$N$5,0),FALSE),0) -> 0 | AC135: =IFERROR(AB135/AB$19,0) -> 0 | AD135: =IFERROR(VLOOKUP($A135,APOIO!$B:$N,MATCH(AD$5,APOIO!$B$5:$N$5,0),FALSE),0) -> 0 | AE135: =IFERROR(AD135/AD$19,0) -> 0 | AF135: =SUM(Z135,AB135,AD135) -> 0 | AG135: =IFERROR(AF135/AF$19,0) -> 0 | AH135: =SUM(B135,D135,F135,J135,L135,N135,R135,T135,V135,Z135,AB135,AD135) -> -9985.742 | AI135: =IFERROR(AH135/AH$19,0) -> -0.019194556
A136: ALUGUEL ALOJAMENTO | B136: =IFERROR(VLOOKUP($A136,APOIO!$B:$N,MATCH(B$5,APOIO!$B$5:$N$5,0),FALSE),0) -> -700 | C136: =IFERROR(B136/B$19,0) -> -0.0045110516 | D136: =IFERROR(VLOOKUP($A136,APOIO!$B:$N,MATCH(D$5,APOIO!$B$5:$N$5,0),FALSE),0) -> -2313 | E136: =IFERROR(D136/D$19,0) -> -0.0063358793 | F136: =IFERROR(VLOOKUP($A136,APOIO!$B:$N,MATCH(F$5,APOIO!$B$5:$N$5,0),FALSE),0) -> 0 | G136: =IFERROR(F136/F$19,0) -> 0 | H136: =SUM(B136,D136,F136) -> -3013 | I136: =IFERROR(H136/H$19,0) -> -0.0057915774 | J136: =IFERROR(VLOOKUP($A136,APOIO!$B:$N,MATCH(J$5,APOIO!$B$5:$N$5,0),FALSE),0) -> -2000 | K136: =IFERROR(J136/J$19,0) -> 0 | L136: =IFERROR(VLOOKUP($A136,APOIO!$B:$N,MATCH(L$5,APOIO!$B$5:$N$5,0),FALSE),0) -> -2100 | M136: =IFERROR(L136/L$19,0) -> 0 | N136: =IFERROR(VLOOKUP($A136,APOIO!$B:$N,MATCH(N$5,APOIO!$B$5:$N$5,0),FALSE),0) -> 0 | O136: =IFERROR(N136/N$19,0) -> 0 | P136: =SUM(J136,L136,N136) -> -4100 | Q136: =IFERROR(P136/P$19,0) -> 0 | R136: =IFERROR(VLOOKUP($A136,APOIO!$B:$N,MATCH(R$5,APOIO!$B$5:$N$5,0),FALSE),0) -> 0 | S136: =IFERROR(R136/R$19,0) -> 0 | T136: =IFERROR(VLOOKUP($A136,APOIO!$B:$N,MATCH(T$5,APOIO!$B$5:$N$5,0),FALSE),0) -> 0 | U136: =IFERROR(T136/T$19,0) -> 0 | V136: =IFERROR(VLOOKUP($A136,APOIO!$B:$N,MATCH(V$5,APOIO!$B$5:$N$5,0),FALSE),0) -> 0 | W136: =IFERROR(V136/V$19,0) -> 0 | X136: =SUM(R136,T136,V136) -> 0 | Y136: =IFERROR(X136/X$19,0) -> 0 | Z136: =IFERROR(VLOOKUP($A136,APOIO!$B:$N,MATCH(Z$5,APOIO!$B$5:$N$5,0),FALSE),0) -> 0 | AA136: =IFERROR(Z136/Z$19,0) -> 0 | AB136: =IFERROR(VLOOKUP($A136,APOIO!$B:$N,MATCH(AB$5,APOIO!$B$5:$N$5,0),FALSE),0) -> 0 | AC136: =IFERROR(AB136/AB$19,0) -> 0 | AD136: =IFERROR(VLOOKUP($A136,APOIO!$B:$N,MATCH(AD$5,APOIO!$B$5:$N$5,0),FALSE),0) -> 0 | AE136: =IFERROR(AD136/AD$19,0) -> 0 | AF136: =SUM(Z136,AB136,AD136) -> 0 | AG136: =IFERROR(AF136/AF$19,0) -> 0 | AH136: =SUM(B136,D136,F136,J136,L136,N136,R136,T136,V136,Z136,AB136,AD136) -> -7113 | AI136: =IFERROR(AH136/AH$19,0) -> -0.013672582
A137: AGUA ALOJAMENTO | B137: =IFERROR(VLOOKUP($A137,APOIO!$B:$N,MATCH(B$5,APOIO!$B$5:$N$5,0),FALSE),0) -> 0 | C137: =IFERROR(B137/B$19,0) -> 0 | D137: =IFERROR(VLOOKUP($A137,APOIO!$B:$N,MATCH(D$5,APOIO!$B$5:$N$5,0),FALSE),0) -> 0 | E137: =IFERROR(D137/D$19,0) -> 0 | F137: =IFERROR(VLOOKUP($A137,APOIO!$B:$N,MATCH(F$5,APOIO!$B$5:$N$5,0),FALSE),0) -> 0 | G137: =IFERROR(F137/F$19,0) -> 0 | H137: =SUM(B137,D137,F137) -> 0 | I137: =IFERROR(H137/H$19,0) -> 0 | J137: =IFERROR(VLOOKUP($A137,APOIO!$B:$N,MATCH(J$5,APOIO!$B$5:$N$5,0),FALSE),0) -> 0 | K137: =IFERROR(J137/J$19,0) -> 0 | L137: =IFERROR(VLOOKUP($A137,APOIO!$B:$N,MATCH(L$5,APOIO!$B$5:$N$5,0),FALSE),0) -> 0 | M137: =IFERROR(L137/L$19,0) -> 0 | N137: =IFERROR(VLOOKUP($A137,APOIO!$B:$N,MATCH(N$5,APOIO!$B$5:$N$5,0),FALSE),0) -> 0 | O137: =IFERROR(N137/N$19,0) -> 0 | P137: =SUM(J137,L137,N137) -> 0 | Q137: =IFERROR(P137/P$19,0) -> 0 | R137: =IFERROR(VLOOKUP($A137,APOIO!$B:$N,MATCH(R$5,APOIO!$B$5:$N$5,0),FALSE),0) -> 0 | S137: =IFERROR(R137/R$19,0) -> 0 | T137: =IFERROR(VLOOKUP($A137,APOIO!$B:$N,MATCH(T$5,APOIO!$B$5:$N$5,0),FALSE),0) -> 0 | U137: =IFERROR(T137/T$19,0) -> 0 | V137: =IFERROR(VLOOKUP($A137,APOIO!$B:$N,MATCH(V$5,APOIO!$B$5:$N$5,0),FALSE),0) -> 0 | W137: =IFERROR(V137/V$19,0) -> 0 | X137: =SUM(R137,T137,V137) -> 0 | Y137: =IFERROR(X137/X$19,0) -> 0 | Z137: =IFERROR(VLOOKUP($A137,APOIO!$B:$N,MATCH(Z$5,APOIO!$B$5:$N$5,0),FALSE),0) -> 0 | AA137: =IFERROR(Z137/Z$19,0) -> 0 | AB137: =IFERROR(VLOOKUP($A137,APOIO!$B:$N,MATCH(AB$5,APOIO!$B$5:$N$5,0),FALSE),0) -> 0 | AC137: =IFERROR(AB137/AB$19,0) -> 0 | AD137: =IFERROR(VLOOKUP($A137,APOIO!$B:$N,MATCH(AD$5,APOIO!$B$5:$N$5,0),FALSE),0) -> 0 | AE137: =IFERROR(AD137/AD$19,0) -> 0 | AF137: =SUM(Z137,AB137,AD137) -> 0 | AG137: =IFERROR(AF137/AF$19,0) -> 0 | AH137: =SUM(B137,D137,F137,J137,L137,N137,R137,T137,V137,Z137,AB137,AD137) -> 0 | AI137: =IFERROR(AH137/AH$19,0) -> 0
A138: ENERGIA ALOJAMENTO | B138: =IFERROR(VLOOKUP($A138,APOIO!$B:$N,MATCH(B$5,APOIO!$B$5:$N$5,0),FALSE),0) -> -1316.99 | C138: =IFERROR(B138/B$19,0) -> -0.008487157 | D138: =IFERROR(VLOOKUP($A138,APOIO!$B:$N,MATCH(D$5,APOIO!$B$5:$N$5,0),FALSE),0) -> -422.57 | E138: =IFERROR(D138/D$19,0) -> -0.0011575238 | F138: =IFERROR(VLOOKUP($A138,APOIO!$B:$N,MATCH(F$5,APOIO!$B$5:$N$5,0),FALSE),0) -> -233.1 | G138: =IFERROR(F138/F$19,0) -> 0 | H138: =SUM(B138,D138,F138) -> -1972.66 | I138: =IFERROR(H138/H$19,0) -> -0.0037918398 | J138: =IFERROR(VLOOKUP($A138,APOIO!$B:$N,MATCH(J$5,APOIO!$B$5:$N$5,0),FALSE),0) -> 0 | K138: =IFERROR(J138/J$19,0) -> 0 | L138: =IFERROR(VLOOKUP($A138,APOIO!$B:$N,MATCH(L$5,APOIO!$B$5:$N$5,0),FALSE),0) -> -447.76 | M138: =IFERROR(L138/L$19,0) -> 0 | N138: =IFERROR(VLOOKUP($A138,APOIO!$B:$N,MATCH(N$5,APOIO!$B$5:$N$5,0),FALSE),0) -> 0 | O138: =IFERROR(N138/N$19,0) -> 0 | P138: =SUM(J138,L138,N138) -> -447.76 | Q138: =IFERROR(P138/P$19,0) -> 0 | R138: =IFERROR(VLOOKUP($A138,APOIO!$B:$N,MATCH(R$5,APOIO!$B$5:$N$5,0),FALSE),0) -> 0 | S138: =IFERROR(R138/R$19,0) -> 0 | T138: =IFERROR(VLOOKUP($A138,APOIO!$B:$N,MATCH(T$5,APOIO!$B$5:$N$5,0),FALSE),0) -> 0 | U138: =IFERROR(T138/T$19,0) -> 0 | V138: =IFERROR(VLOOKUP($A138,APOIO!$B:$N,MATCH(V$5,APOIO!$B$5:$N$5,0),FALSE),0) -> 0 | W138: =IFERROR(V138/V$19,0) -> 0 | X138: =SUM(R138,T138,V138) -> 0 | Y138: =IFERROR(X138/X$19,0) -> 0 | Z138: =IFERROR(VLOOKUP($A138,APOIO!$B:$N,MATCH(Z$5,APOIO!$B$5:$N$5,0),FALSE),0) -> 0 | AA138: =IFERROR(Z138/Z$19,0) -> 0 | AB138: =IFERROR(VLOOKUP($A138,APOIO!$B:$N,MATCH(AB$5,APOIO!$B$5:$N$5,0),FALSE),0) -> 0 | AC138: =IFERROR(AB138/AB$19,0) -> 0 | AD138: =IFERROR(VLOOKUP($A138,APOIO!$B:$N,MATCH(AD$5,APOIO!$B$5:$N$5,0),FALSE),0) -> 0 | AE138: =IFERROR(AD138/AD$19,0) -> 0 | AF138: =SUM(Z138,AB138,AD138) -> 0 | AG138: =IFERROR(AF138/AF$19,0) -> 0 | AH138: =SUM(B138,D138,F138,J138,L138,N138,R138,T138,V138,Z138,AB138,AD138) -> -2420.42 | AI138: =IFERROR(AH138/AH$19,0) -> -0.0046525224
A139: MOVEIS OBRAS | B139: =IFERROR(VLOOKUP($A139,APOIO!$B:$N,MATCH(B$5,APOIO!$B$5:$N$5,0),FALSE),0) -> 0 | C139: =IFERROR(B139/B$19,0) -> 0 | D139: =IFERROR(VLOOKUP($A139,APOIO!$B:$N,MATCH(D$5,APOIO!$B$5:$N$5,0),FALSE),0) -> 0 | E139: =IFERROR(D139/D$19,0) -> 0 | F139: =IFERROR(VLOOKUP($A139,APOIO!$B:$N,MATCH(F$5,APOIO!$B$5:$N$5,0),FALSE),0) -> 0 | G139: =IFERROR(F139/F$19,0) -> 0 | H139: =SUM(B139,D139,F139) -> 0 | I139: =IFERROR(H139/H$19,0) -> 0 | J139: =IFERROR(VLOOKUP($A139,APOIO!$B:$N,MATCH(J$5,APOIO!$B$5:$N$5,0),FALSE),0) -> 0 | K139: =IFERROR(J139/J$19,0) -> 0 | L139: =IFERROR(VLOOKUP($A139,APOIO!$B:$N,MATCH(L$5,APOIO!$B$5:$N$5,0),FALSE),0) -> 0 | M139: =IFERROR(L139/L$19,0) -> 0 | N139: =IFERROR(VLOOKUP($A139,APOIO!$B:$N,MATCH(N$5,APOIO!$B$5:$N$5,0),FALSE),0) -> 0 | O139: =IFERROR(N139/N$19,0) -> 0 | P139: =SUM(J139,L139,N139) -> 0 | Q139: =IFERROR(P139/P$19,0) -> 0 | R139: =IFERROR(VLOOKUP($A139,APOIO!$B:$N,MATCH(R$5,APOIO!$B$5:$N$5,0),FALSE),0) -> 0 | S139: =IFERROR(R139/R$19,0) -> 0 | T139: =IFERROR(VLOOKUP($A139,APOIO!$B:$N,MATCH(T$5,APOIO!$B$5:$N$5,0),FALSE),0) -> 0 | U139: =IFERROR(T139/T$19,0) -> 0 | V139: =IFERROR(VLOOKUP($A139,APOIO!$B:$N,MATCH(V$5,APOIO!$B$5:$N$5,0),FALSE),0) -> 0 | W139: =IFERROR(V139/V$19,0) -> 0 | X139: =SUM(R139,T139,V139) -> 0 | Y139: =IFERROR(X139/X$19,0) -> 0 | Z139: =IFERROR(VLOOKUP($A139,APOIO!$B:$N,MATCH(Z$5,APOIO!$B$5:$N$5,0),FALSE),0) -> 0 | AA139: =IFERROR(Z139/Z$19,0) -> 0 | AB139: =IFERROR(VLOOKUP($A139,APOIO!$B:$N,MATCH(AB$5,APOIO!$B$5:$N$5,0),FALSE),0) -> 0 | AC139: =IFERROR(AB139/AB$19,0) -> 0 | AD139: =IFERROR(VLOOKUP($A139,APOIO!$B:$N,MATCH(AD$5,APOIO!$B$5:$N$5,0),FALSE),0) -> 0 | AE139: =IFERROR(AD139/AD$19,0) -> 0 | AF139: =SUM(Z139,AB139,AD139) -> 0 | AG139: =IFERROR(AF139/AF$19,0) -> 0 | AH139: =SUM(B139,D139,F139,J139,L139,N139,R139,T139,V139,Z139,AB139,AD139) -> 0 | AI139: =IFERROR(AH139/AH$19,0) -> 0
A140: SERVIÇO LIMPEZA ALOJAMENTO/ESCRITORIO | B140: =IFERROR(VLOOKUP($A140,APOIO!$B:$N,MATCH(B$5,APOIO!$B$5:$N$5,0),FALSE),0) -> 0 | C140: =IFERROR(B140/B$19,0) -> 0 | D140: =IFERROR(VLOOKUP($A140,APOIO!$B:$N,MATCH(D$5,APOIO!$B$5:$N$5,0),FALSE),0) -> -450 | E140: =IFERROR(D140/D$19,0) -> -0.0012326614 | F140: =IFERROR(VLOOKUP($A140,APOIO!$B:$N,MATCH(F$5,APOIO!$B$5:$N$5,0),FALSE),0) -> 0 | G140: =IFERROR(F140/F$19,0) -> 0 | H140: =SUM(B140,D140,F140) -> -450 | I140: =IFERROR(H140/H$19,0) -> -0.00086498833 | J140: =IFERROR(VLOOKUP($A140,APOIO!$B:$N,MATCH(J$5,APOIO!$B$5:$N$5,0),FALSE),0) -> 0 | K140: =IFERROR(J140/J$19,0) -> 0 | L140: =IFERROR(VLOOKUP($A140,APOIO!$B:$N,MATCH(L$5,APOIO!$B$5:$N$5,0),FALSE),0) -> 0 | M140: =IFERROR(L140/L$19,0) -> 0 | N140: =IFERROR(VLOOKUP($A140,APOIO!$B:$N,MATCH(N$5,APOIO!$B$5:$N$5,0),FALSE),0) -> 0 | O140: =IFERROR(N140/N$19,0) -> 0 | P140: =SUM(J140,L140,N140) -> 0 | Q140: =IFERROR(P140/P$19,0) -> 0 | R140: =IFERROR(VLOOKUP($A140,APOIO!$B:$N,MATCH(R$5,APOIO!$B$5:$N$5,0),FALSE),0) -> 0 | S140: =IFERROR(R140/R$19,0) -> 0 | T140: =IFERROR(VLOOKUP($A140,APOIO!$B:$N,MATCH(T$5,APOIO!$B$5:$N$5,0),FALSE),0) -> 0 | U140: =IFERROR(T140/T$19,0) -> 0 | V140: =IFERROR(VLOOKUP($A140,APOIO!$B:$N,MATCH(V$5,APOIO!$B$5:$N$5,0),FALSE),0) -> 0 | W140: =IFERROR(V140/V$19,0) -> 0 | X140: =SUM(R140,T140,V140) -> 0 | Y140: =IFERROR(X140/X$19,0) -> 0 | Z140: =IFERROR(VLOOKUP($A140,APOIO!$B:$N,MATCH(Z$5,APOIO!$B$5:$N$5,0),FALSE),0) -> 0 | AA140: =IFERROR(Z140/Z$19,0) -> 0 | AB140: =IFERROR(VLOOKUP($A140,APOIO!$B:$N,MATCH(AB$5,APOIO!$B$5:$N$5,0),FALSE),0) -> 0 | AC140: =IFERROR(AB140/AB$19,0) -> 0 | AD140: =IFERROR(VLOOKUP($A140,APOIO!$B:$N,MATCH(AD$5,APOIO!$B$5:$N$5,0),FALSE),0) -> 0 | AE140: =IFERROR(AD140/AD$19,0) -> 0 | AF140: =SUM(Z140,AB140,AD140) -> 0 | AG140: =IFERROR(AF140/AF$19,0) -> 0 | AH140: =SUM(B140,D140,F140,J140,L140,N140,R140,T140,V140,Z140,AB140,AD140) -> -450 | AI140: =IFERROR(AH140/AH$19,0) -> -0.00086498833
A141: ALUGUEIS ADM | B141: =IFERROR(VLOOKUP($A141,APOIO!$B:$N,MATCH(B$5,APOIO!$B$5:$N$5,0),FALSE),0) -> 0 | C141: =IFERROR(B141/B$19,0) -> 0 | D141: =IFERROR(VLOOKUP($A141,APOIO!$B:$N,MATCH(D$5,APOIO!$B$5:$N$5,0),FALSE),0) -> 0 | E141: =IFERROR(D141/D$19,0) -> 0 | F141: =IFERROR(VLOOKUP($A141,APOIO!$B:$N,MATCH(F$5,APOIO!$B$5:$N$5,0),FALSE),0) -> 0 | G141: =IFERROR(F141/F$19,0) -> 0 | H141: =SUM(B141,D141,F141) -> 0 | I141: =IFERROR(H141/H$19,0) -> 0 | J141: =IFERROR(VLOOKUP($A141,APOIO!$B:$N,MATCH(J$5,APOIO!$B$5:$N$5,0),FALSE),0) -> 0 | K141: =IFERROR(J141/J$19,0) -> 0 | L141: =IFERROR(VLOOKUP($A141,APOIO!$B:$N,MATCH(L$5,APOIO!$B$5:$N$5,0),FALSE),0) -> 0 | M141: =IFERROR(L141/L$19,0) -> 0 | N141: =IFERROR(VLOOKUP($A141,APOIO!$B:$N,MATCH(N$5,APOIO!$B$5:$N$5,0),FALSE),0) -> 0 | O141: =IFERROR(N141/N$19,0) -> 0 | P141: =SUM(J141,L141,N141) -> 0 | Q141: =IFERROR(P141/P$19,0) -> 0 | R141: =IFERROR(VLOOKUP($A141,APOIO!$B:$N,MATCH(R$5,APOIO!$B$5:$N$5,0),FALSE),0) -> 0 | S141: =IFERROR(R141/R$19,0) -> 0 | T141: =IFERROR(VLOOKUP($A141,APOIO!$B:$N,MATCH(T$5,APOIO!$B$5:$N$5,0),FALSE),0) -> 0 | U141: =IFERROR(T141/T$19,0) -> 0 | V141: =IFERROR(VLOOKUP($A141,APOIO!$B:$N,MATCH(V$5,APOIO!$B$5:$N$5,0),FALSE),0) -> 0 | W141: =IFERROR(V141/V$19,0) -> 0 | X141: =SUM(R141,T141,V141) -> 0 | Y141: =IFERROR(X141/X$19,0) -> 0 | Z141: =IFERROR(VLOOKUP($A141,APOIO!$B:$N,MATCH(Z$5,APOIO!$B$5:$N$5,0),FALSE),0) -> 0 | AA141: =IFERROR(Z141/Z$19,0) -> 0 | AB141: =IFERROR(VLOOKUP($A141,APOIO!$B:$N,MATCH(AB$5,APOIO!$B$5:$N$5,0),FALSE),0) -> 0 | AC141: =IFERROR(AB141/AB$19,0) -> 0 | AD141: =IFERROR(VLOOKUP($A141,APOIO!$B:$N,MATCH(AD$5,APOIO!$B$5:$N$5,0),FALSE),0) -> 0 | AE141: =IFERROR(AD141/AD$19,0) -> 0 | AF141: =SUM(Z141,AB141,AD141) -> 0 | AG141: =IFERROR(AF141/AF$19,0) -> 0 | AH141: =SUM(B141,D141,F141,J141,L141,N141,R141,T141,V141,Z141,AB141,AD141) -> 0 | AI141: =IFERROR(AH141/AH$19,0) -> 0
A142: AGUA ADM | B142: =IFERROR(VLOOKUP($A142,APOIO!$B:$N,MATCH(B$5,APOIO!$B$5:$N$5,0),FALSE),0) -> 0 | C142: =IFERROR(B142/B$19,0) -> 0 | D142: =IFERROR(VLOOKUP($A142,APOIO!$B:$N,MATCH(D$5,APOIO!$B$5:$N$5,0),FALSE),0) -> 0 | E142: =IFERROR(D142/D$19,0) -> 0 | F142: =IFERROR(VLOOKUP($A142,APOIO!$B:$N,MATCH(F$5,APOIO!$B$5:$N$5,0),FALSE),0) -> 0 | G142: =IFERROR(F142/F$19,0) -> 0 | H142: =SUM(B142,D142,F142) -> 0 | I142: =IFERROR(H142/H$19,0) -> 0 | J142: =IFERROR(VLOOKUP($A142,APOIO!$B:$N,MATCH(J$5,APOIO!$B$5:$N$5,0),FALSE),0) -> 0 | K142: =IFERROR(J142/J$19,0) -> 0 | L142: =IFERROR(VLOOKUP($A142,APOIO!$B:$N,MATCH(L$5,APOIO!$B$5:$N$5,0),FALSE),0) -> 0 | M142: =IFERROR(L142/L$19,0) -> 0 | N142: =IFERROR(VLOOKUP($A142,APOIO!$B:$N,MATCH(N$5,APOIO!$B$5:$N$5,0),FALSE),0) -> 0 | O142: =IFERROR(N142/N$19,0) -> 0 | P142: =SUM(J142,L142,N142) -> 0 | Q142: =IFERROR(P142/P$19,0) -> 0 | R142: =IFERROR(VLOOKUP($A142,APOIO!$B:$N,MATCH(R$5,APOIO!$B$5:$N$5,0),FALSE),0) -> 0 | S142: =IFERROR(R142/R$19,0) -> 0 | T142: =IFERROR(VLOOKUP($A142,APOIO!$B:$N,MATCH(T$5,APOIO!$B$5:$N$5,0),FALSE),0) -> 0 | U142: =IFERROR(T142/T$19,0) -> 0 | V142: =IFERROR(VLOOKUP($A142,APOIO!$B:$N,MATCH(V$5,APOIO!$B$5:$N$5,0),FALSE),0) -> 0 | W142: =IFERROR(V142/V$19,0) -> 0 | X142: =SUM(R142,T142,V142) -> 0 | Y142: =IFERROR(X142/X$19,0) -> 0 | Z142: =IFERROR(VLOOKUP($A142,APOIO!$B:$N,MATCH(Z$5,APOIO!$B$5:$N$5,0),FALSE),0) -> 0 | AA142: =IFERROR(Z142/Z$19,0) -> 0 | AB142: =IFERROR(VLOOKUP($A142,APOIO!$B:$N,MATCH(AB$5,APOIO!$B$5:$N$5,0),FALSE),0) -> 0 | AC142: =IFERROR(AB142/AB$19,0) -> 0 | AD142: =IFERROR(VLOOKUP($A142,APOIO!$B:$N,MATCH(AD$5,APOIO!$B$5:$N$5,0),FALSE),0) -> 0 | AE142: =IFERROR(AD142/AD$19,0) -> 0 | AF142: =SUM(Z142,AB142,AD142) -> 0 | AG142: =IFERROR(AF142/AF$19,0) -> 0 | AH142: =SUM(B142,D142,F142,J142,L142,N142,R142,T142,V142,Z142,AB142,AD142) -> 0 | AI142: =IFERROR(AH142/AH$19,0) -> 0
A143: ENERGIA ADM | B143: =IFERROR(VLOOKUP($A143,APOIO!$B:$N,MATCH(B$5,APOIO!$B$5:$N$5,0),FALSE),0) -> 0 | C143: =IFERROR(B143/B$19,0) -> 0 | D143: =IFERROR(VLOOKUP($A143,APOIO!$B:$N,MATCH(D$5,APOIO!$B$5:$N$5,0),FALSE),0) -> 0 | E143: =IFERROR(D143/D$19,0) -> 0 | F143: =IFERROR(VLOOKUP($A143,APOIO!$B:$N,MATCH(F$5,APOIO!$B$5:$N$5,0),FALSE),0) -> 0 | G143: =IFERROR(F143/F$19,0) -> 0 | H143: =SUM(B143,D143,F143) -> 0 | I143: =IFERROR(H143/H$19,0) -> 0 | J143: =IFERROR(VLOOKUP($A143,APOIO!$B:$N,MATCH(J$5,APOIO!$B$5:$N$5,0),FALSE),0) -> 0 | K143: =IFERROR(J143/J$19,0) -> 0 | L143: =IFERROR(VLOOKUP($A143,APOIO!$B:$N,MATCH(L$5,APOIO!$B$5:$N$5,0),FALSE),0) -> 0 | M143: =IFERROR(L143/L$19,0) -> 0 | N143: =IFERROR(VLOOKUP($A143,APOIO!$B:$N,MATCH(N$5,APOIO!$B$5:$N$5,0),FALSE),0) -> 0 | O143: =IFERROR(N143/N$19,0) -> 0 | P143: =SUM(J143,L143,N143) -> 0 | Q143: =IFERROR(P143/P$19,0) -> 0 | R143: =IFERROR(VLOOKUP($A143,APOIO!$B:$N,MATCH(R$5,APOIO!$B$5:$N$5,0),FALSE),0) -> 0 | S143: =IFERROR(R143/R$19,0) -> 0 | T143: =IFERROR(VLOOKUP($A143,APOIO!$B:$N,MATCH(T$5,APOIO!$B$5:$N$5,0),FALSE),0) -> 0 | U143: =IFERROR(T143/T$19,0) -> 0 | V143: =IFERROR(VLOOKUP($A143,APOIO!$B:$N,MATCH(V$5,APOIO!$B$5:$N$5,0),FALSE),0) -> 0 | W143: =IFERROR(V143/V$19,0) -> 0 | X143: =SUM(R143,T143,V143) -> 0 | Y143: =IFERROR(X143/X$19,0) -> 0 | Z143: =IFERROR(VLOOKUP($A143,APOIO!$B:$N,MATCH(Z$5,APOIO!$B$5:$N$5,0),FALSE),0) -> 0 | AA143: =IFERROR(Z143/Z$19,0) -> 0 | AB143: =IFERROR(VLOOKUP($A143,APOIO!$B:$N,MATCH(AB$5,APOIO!$B$5:$N$5,0),FALSE),0) -> 0 | AC143: =IFERROR(AB143/AB$19,0) -> 0 | AD143: =IFERROR(VLOOKUP($A143,APOIO!$B:$N,MATCH(AD$5,APOIO!$B$5:$N$5,0),FALSE),0) -> 0 | AE143: =IFERROR(AD143/AD$19,0) -> 0 | AF143: =SUM(Z143,AB143,AD143) -> 0 | AG143: =IFERROR(AF143/AF$19,0) -> 0 | AH143: =SUM(B143,D143,F143,J143,L143,N143,R143,T143,V143,Z143,AB143,AD143) -> 0 | AI143: =IFERROR(AH143/AH$19,0) -> 0
A144: IPTU | B144: =IFERROR(VLOOKUP($A144,APOIO!$B:$N,MATCH(B$5,APOIO!$B$5:$N$5,0),FALSE),0) -> 0 | C144: =IFERROR(B144/B$19,0) -> 0 | D144: =IFERROR(VLOOKUP($A144,APOIO!$B:$N,MATCH(D$5,APOIO!$B$5:$N$5,0),FALSE),0) -> 0 | E144: =IFERROR(D144/D$19,0) -> 0 | F144: =IFERROR(VLOOKUP($A144,APOIO!$B:$N,MATCH(F$5,APOIO!$B$5:$N$5,0),FALSE),0) -> 0 | G144: =IFERROR(F144/F$19,0) -> 0 | H144: =SUM(B144,D144,F144) -> 0 | I144: =IFERROR(H144/H$19,0) -> 0 | J144: =IFERROR(VLOOKUP($A144,APOIO!$B:$N,MATCH(J$5,APOIO!$B$5:$N$5,0),FALSE),0) -> 0 | K144: =IFERROR(J144/J$19,0) -> 0 | L144: =IFERROR(VLOOKUP($A144,APOIO!$B:$N,MATCH(L$5,APOIO!$B$5:$N$5,0),FALSE),0) -> 0 | M144: =IFERROR(L144/L$19,0) -> 0 | N144: =IFERROR(VLOOKUP($A144,APOIO!$B:$N,MATCH(N$5,APOIO!$B$5:$N$5,0),FALSE),0) -> 0 | O144: =IFERROR(N144/N$19,0) -> 0 | P144: =SUM(J144,L144,N144) -> 0 | Q144: =IFERROR(P144/P$19,0) -> 0 | R144: =IFERROR(VLOOKUP($A144,APOIO!$B:$N,MATCH(R$5,APOIO!$B$5:$N$5,0),FALSE),0) -> 0 | S144: =IFERROR(R144/R$19,0) -> 0 | T144: =IFERROR(VLOOKUP($A144,APOIO!$B:$N,MATCH(T$5,APOIO!$B$5:$N$5,0),FALSE),0) -> 0 | U144: =IFERROR(T144/T$19,0) -> 0 | V144: =IFERROR(VLOOKUP($A144,APOIO!$B:$N,MATCH(V$5,APOIO!$B$5:$N$5,0),FALSE),0) -> 0 | W144: =IFERROR(V144/V$19,0) -> 0 | X144: =SUM(R144,T144,V144) -> 0 | Y144: =IFERROR(X144/X$19,0) -> 0 | Z144: =IFERROR(VLOOKUP($A144,APOIO!$B:$N,MATCH(Z$5,APOIO!$B$5:$N$5,0),FALSE),0) -> 0 | AA144: =IFERROR(Z144/Z$19,0) -> 0 | AB144: =IFERROR(VLOOKUP($A144,APOIO!$B:$N,MATCH(AB$5,APOIO!$B$5:$N$5,0),FALSE),0) -> 0 | AC144: =IFERROR(AB144/AB$19,0) -> 0 | AD144: =IFERROR(VLOOKUP($A144,APOIO!$B:$N,MATCH(AD$5,APOIO!$B$5:$N$5,0),FALSE),0) -> 0 | AE144: =IFERROR(AD144/AD$19,0) -> 0 | AF144: =SUM(Z144,AB144,AD144) -> 0 | AG144: =IFERROR(AF144/AF$19,0) -> 0 | AH144: =SUM(B144,D144,F144,J144,L144,N144,R144,T144,V144,Z144,AB144,AD144) -> 0 | AI144: =IFERROR(AH144/AH$19,0) -> 0
A145: INTERNET / TELEFONE ADM | B145: =IFERROR(VLOOKUP($A145,APOIO!$B:$N,MATCH(B$5,APOIO!$B$5:$N$5,0),FALSE),0) -> 0 | C145: =IFERROR(B145/B$19,0) -> 0 | D145: =IFERROR(VLOOKUP($A145,APOIO!$B:$N,MATCH(D$5,APOIO!$B$5:$N$5,0),FALSE),0) -> 0 | E145: =IFERROR(D145/D$19,0) -> 0 | F145: =IFERROR(VLOOKUP($A145,APOIO!$B:$N,MATCH(F$5,APOIO!$B$5:$N$5,0),FALSE),0) -> 0 | G145: =IFERROR(F145/F$19,0) -> 0 | H145: =SUM(B145,D145,F145) -> 0 | I145: =IFERROR(H145/H$19,0) -> 0 | J145: =IFERROR(VLOOKUP($A145,APOIO!$B:$N,MATCH(J$5,APOIO!$B$5:$N$5,0),FALSE),0) -> -2.322 | K145: =IFERROR(J145/J$19,0) -> 0 | L145: =IFERROR(VLOOKUP($A145,APOIO!$B:$N,MATCH(L$5,APOIO!$B$5:$N$5,0),FALSE),0) -> 0 | M145: =IFERROR(L145/L$19,0) -> 0 | N145: =IFERROR(VLOOKUP($A145,APOIO!$B:$N,MATCH(N$5,APOIO!$B$5:$N$5,0),FALSE),0) -> 0 | O145: =IFERROR(N145/N$19,0) -> 0 | P145: =SUM(J145,L145,N145) -> -2.322 | Q145: =IFERROR(P145/P$19,0) -> 0 | R145: =IFERROR(VLOOKUP($A145,APOIO!$B:$N,MATCH(R$5,APOIO!$B$5:$N$5,0),FALSE),0) -> 0 | S145: =IFERROR(R145/R$19,0) -> 0 | T145: =IFERROR(VLOOKUP($A145,APOIO!$B:$N,MATCH(T$5,APOIO!$B$5:$N$5,0),FALSE),0) -> 0 | U145: =IFERROR(T145/T$19,0) -> 0 | V145: =IFERROR(VLOOKUP($A145,APOIO!$B:$N,MATCH(V$5,APOIO!$B$5:$N$5,0),FALSE),0) -> 0 | W145: =IFERROR(V145/V$19,0) -> 0 | X145: =SUM(R145,T145,V145) -> 0 | Y145: =IFERROR(X145/X$19,0) -> 0 | Z145: =IFERROR(VLOOKUP($A145,APOIO!$B:$N,MATCH(Z$5,APOIO!$B$5:$N$5,0),FALSE),0) -> 0 | AA145: =IFERROR(Z145/Z$19,0) -> 0 | AB145: =IFERROR(VLOOKUP($A145,APOIO!$B:$N,MATCH(AB$5,APOIO!$B$5:$N$5,0),FALSE),0) -> 0 | AC145: =IFERROR(AB145/AB$19,0) -> 0 | AD145: =IFERROR(VLOOKUP($A145,APOIO!$B:$N,MATCH(AD$5,APOIO!$B$5:$N$5,0),FALSE),0) -> 0 | AE145: =IFERROR(AD145/AD$19,0) -> 0 | AF145: =SUM(Z145,AB145,AD145) -> 0 | AG145: =IFERROR(AF145/AF$19,0) -> 0 | AH145: =SUM(B145,D145,F145,J145,L145,N145,R145,T145,V145,Z145,AB145,AD145) -> -2.322 | AI145: =IFERROR(AH145/AH$19,0) -> -4.4633398e-06
A146: INTERNET OBRAS | B146: =IFERROR(VLOOKUP($A146,APOIO!$B:$N,MATCH(B$5,APOIO!$B$5:$N$5,0),FALSE),0) -> 0 | C146: =IFERROR(B146/B$19,0) -> 0 | D146: =IFERROR(VLOOKUP($A146,APOIO!$B:$N,MATCH(D$5,APOIO!$B$5:$N$5,0),FALSE),0) -> 0 | E146: =IFERROR(D146/D$19,0) -> 0 | F146: =IFERROR(VLOOKUP($A146,APOIO!$B:$N,MATCH(F$5,APOIO!$B$5:$N$5,0),FALSE),0) -> 0 | G146: =IFERROR(F146/F$19,0) -> 0 | H146: =SUM(B146,D146,F146) -> 0 | I146: =IFERROR(H146/H$19,0) -> 0 | J146: =IFERROR(VLOOKUP($A146,APOIO!$B:$N,MATCH(J$5,APOIO!$B$5:$N$5,0),FALSE),0) -> 0 | K146: =IFERROR(J146/J$19,0) -> 0 | L146: =IFERROR(VLOOKUP($A146,APOIO!$B:$N,MATCH(L$5,APOIO!$B$5:$N$5,0),FALSE),0) -> 0 | M146: =IFERROR(L146/L$19,0) -> 0 | N146: =IFERROR(VLOOKUP($A146,APOIO!$B:$N,MATCH(N$5,APOIO!$B$5:$N$5,0),FALSE),0) -> 0 | O146: =IFERROR(N146/N$19,0) -> 0 | P146: =SUM(J146,L146,N146) -> 0 | Q146: =IFERROR(P146/P$19,0) -> 0 | R146: =IFERROR(VLOOKUP($A146,APOIO!$B:$N,MATCH(R$5,APOIO!$B$5:$N$5,0),FALSE),0) -> 0 | S146: =IFERROR(R146/R$19,0) -> 0 | T146: =IFERROR(VLOOKUP($A146,APOIO!$B:$N,MATCH(T$5,APOIO!$B$5:$N$5,0),FALSE),0) -> 0 | U146: =IFERROR(T146/T$19,0) -> 0 | V146: =IFERROR(VLOOKUP($A146,APOIO!$B:$N,MATCH(V$5,APOIO!$B$5:$N$5,0),FALSE),0) -> 0 | W146: =IFERROR(V146/V$19,0) -> 0 | X146: =SUM(R146,T146,V146) -> 0 | Y146: =IFERROR(X146/X$19,0) -> 0 | Z146: =IFERROR(VLOOKUP($A146,APOIO!$B:$N,MATCH(Z$5,APOIO!$B$5:$N$5,0),FALSE),0) -> 0 | AA146: =IFERROR(Z146/Z$19,0) -> 0 | AB146: =IFERROR(VLOOKUP($A146,APOIO!$B:$N,MATCH(AB$5,APOIO!$B$5:$N$5,0),FALSE),0) -> 0 | AC146: =IFERROR(AB146/AB$19,0) -> 0 | AD146: =IFERROR(VLOOKUP($A146,APOIO!$B:$N,MATCH(AD$5,APOIO!$B$5:$N$5,0),FALSE),0) -> 0 | AE146: =IFERROR(AD146/AD$19,0) -> 0 | AF146: =SUM(Z146,AB146,AD146) -> 0 | AG146: =IFERROR(AF146/AF$19,0) -> 0 | AH146: =SUM(B146,D146,F146,J146,L146,N146,R146,T146,V146,Z146,AB146,AD146) -> 0 | AI146: =IFERROR(AH146/AH$19,0) -> 0
B147: =IFERROR(VLOOKUP($A147,APOIO!$B:$N,MATCH(B$5,APOIO!$B$5:$N$5,0),FALSE),0) -> 0 | C147: =IFERROR(B147/B$19,0) -> 0 | D147: =IFERROR(VLOOKUP($A147,APOIO!$B:$N,MATCH(D$5,APOIO!$B$5:$N$5,0),FALSE),0) -> 0 | E147: =IFERROR(D147/D$19,0) -> 0 | F147: =IFERROR(VLOOKUP($A147,APOIO!$B:$N,MATCH(F$5,APOIO!$B$5:$N$5,0),FALSE),0) -> 0 | G147: =IFERROR(F147/F$19,0) -> 0 | H147: =SUM(B147,D147,F147) -> 0 | I147: =IFERROR(H147/H$19,0) -> 0 | J147: =IFERROR(VLOOKUP($A147,APOIO!$B:$N,MATCH(J$5,APOIO!$B$5:$N$5,0),FALSE),0) -> 0 | K147: =IFERROR(J147/J$19,0) -> 0 | L147: =IFERROR(VLOOKUP($A147,APOIO!$B:$N,MATCH(L$5,APOIO!$B$5:$N$5,0),FALSE),0) -> 0 | M147: =IFERROR(L147/L$19,0) -> 0 | N147: =IFERROR(VLOOKUP($A147,APOIO!$B:$N,MATCH(N$5,APOIO!$B$5:$N$5,0),FALSE),0) -> 0 | O147: =IFERROR(N147/N$19,0) -> 0 | P147: =SUM(J147,L147,N147) -> 0 | Q147: =IFERROR(P147/P$19,0) -> 0 | R147: =IFERROR(VLOOKUP($A147,APOIO!$B:$N,MATCH(R$5,APOIO!$B$5:$N$5,0),FALSE),0) -> 0 | S147: =IFERROR(R147/R$19,0) -> 0 | T147: =IFERROR(VLOOKUP($A147,APOIO!$B:$N,MATCH(T$5,APOIO!$B$5:$N$5,0),FALSE),0) -> 0 | U147: =IFERROR(T147/T$19,0) -> 0 | V147: =IFERROR(VLOOKUP($A147,APOIO!$B:$N,MATCH(V$5,APOIO!$B$5:$N$5,0),FALSE),0) -> 0 | W147: =IFERROR(V147/V$19,0) -> 0 | X147: =SUM(R147,T147,V147) -> 0 | Y147: =IFERROR(X147/X$19,0) -> 0 | Z147: =IFERROR(VLOOKUP($A147,APOIO!$B:$N,MATCH(Z$5,APOIO!$B$5:$N$5,0),FALSE),0) -> 0 | AA147: =IFERROR(Z147/Z$19,0) -> 0 | AB147: =IFERROR(VLOOKUP($A147,APOIO!$B:$N,MATCH(AB$5,APOIO!$B$5:$N$5,0),FALSE),0) -> 0 | AC147: =IFERROR(AB147/AB$19,0) -> 0 | AD147: =IFERROR(VLOOKUP($A147,APOIO!$B:$N,MATCH(AD$5,APOIO!$B$5:$N$5,0),FALSE),0) -> 0 | AE147: =IFERROR(AD147/AD$19,0) -> 0 | AF147: =SUM(Z147,AB147,AD147) -> 0 | AG147: =IFERROR(AF147/AF$19,0) -> 0 | AH147: =SUM(B147,D147,F147,J147,L147,N147,R147,T147,V147,Z147,AB147,AD147) -> 0 | AI147: =IFERROR(AH147/AH$19,0) -> 0
A148: (=)RESULTADO OPERACIONAL | B148: =SUM(B34:B35) -> -110465.97 | C148: =IFERROR(B148/B$19,0) -> -0.71188242 | D148: =SUM(D34:D35) -> 152292.71 | E148: =IFERROR(D148/D$19,0) -> 0.41716742 | F148: =SUM(F34:F35) -> -86865.256 | G148: =IFERROR(F148/F$19,0) -> 0 | H148: =SUM(B148,D148,F148) -> -45038.515 | I148: =IFERROR(H148/H$19,0) -> -0.086572866 | J148: =SUM(J34:J35) -> -65470.009 | K148: =IFERROR(J148/J$19,0) -> 0 | L148: =SUM(L34:L35) -> -74954.096 | M148: =IFERROR(L148/L$19,0) -> 0 | N148: =SUM(N34:N35) -> 0 | O148: =IFERROR(N148/N$19,0) -> 0 | P148: =SUM(J148,L148,N148) -> -140424.11 | Q148: =IFERROR(P148/P$19,0) -> 0 | R148: =SUM(R34:R35) -> 0 | S148: =IFERROR(R148/R$19,0) -> 0 | T148: =SUM(T34:T35) -> 0 | U148: =IFERROR(T148/T$19,0) -> 0 | V148: =SUM(V34:V35) -> 0 | W148: =IFERROR(V148/V$19,0) -> 0 | X148: =SUM(R148,T148,V148) -> 0 | Y148: =IFERROR(X148/X$19,0) -> 0 | Z148: =SUM(Z34:Z35) -> 0 | AA148: =IFERROR(Z148/Z$19,0) -> 0 | AB148: =SUM(AB34:AB35) -> 0 | AC148: =IFERROR(AB148/AB$19,0) -> 0 | AD148: =SUM(AD34:AD35) -> 0 | AE148: =IFERROR(AD148/AD$19,0) -> 0 | AF148: =SUM(Z148,AB148,AD148) -> 0 | AG148: =IFERROR(AF148/AF$19,0) -> 0 | AH148: =SUM(B148,D148,F148,J148,L148,N148,R148,T148,V148,Z148,AB148,AD148) -> -185462.62 | AI148: =IFERROR(AH148/AH$19,0) -> -0.35649556
A149: (-)Depreciação Imobilizado | B149: =IFERROR(VLOOKUP($A149,APOIO!$B:$N,MATCH(B$5,APOIO!$B$5:$N$5,0),FALSE),0) -> 0 | C149: =IFERROR(B149/B$19,0) -> 0 | D149: =IFERROR(VLOOKUP($A149,APOIO!$B:$N,MATCH(D$5,APOIO!$B$5:$N$5,0),FALSE),0) -> 0 | E149: =IFERROR(D149/D$19,0) -> 0 | F149: =IFERROR(VLOOKUP($A149,APOIO!$B:$N,MATCH(F$5,APOIO!$B$5:$N$5,0),FALSE),0) -> 0 | G149: =IFERROR(F149/F$19,0) -> 0 | H149: =SUM(B149,D149,F149) -> 0 | I149: =IFERROR(H149/H$19,0) -> 0 | J149: =IFERROR(VLOOKUP($A149,APOIO!$B:$N,MATCH(J$5,APOIO!$B$5:$N$5,0),FALSE),0) -> 0 | K149: =IFERROR(J149/J$19,0) -> 0 | L149: =IFERROR(VLOOKUP($A149,APOIO!$B:$N,MATCH(L$5,APOIO!$B$5:$N$5,0),FALSE),0) -> 0 | M149: =IFERROR(L149/L$19,0) -> 0 | N149: =IFERROR(VLOOKUP($A149,APOIO!$B:$N,MATCH(N$5,APOIO!$B$5:$N$5,0),FALSE),0) -> 0 | O149: =IFERROR(N149/N$19,0) -> 0 | P149: =SUM(J149,L149,N149) -> 0 | Q149: =IFERROR(P149/P$19,0) -> 0 | R149: =IFERROR(VLOOKUP($A149,APOIO!$B:$N,MATCH(R$5,APOIO!$B$5:$N$5,0),FALSE),0) -> 0 | S149: =IFERROR(R149/R$19,0) -> 0 | T149: =IFERROR(VLOOKUP($A149,APOIO!$B:$N,MATCH(T$5,APOIO!$B$5:$N$5,0),FALSE),0) -> 0 | U149: =IFERROR(T149/T$19,0) -> 0 | V149: =IFERROR(VLOOKUP($A149,APOIO!$B:$N,MATCH(V$5,APOIO!$B$5:$N$5,0),FALSE),0) -> 0 | W149: =IFERROR(V149/V$19,0) -> 0 | X149: =SUM(R149,T149,V149) -> 0 | Y149: =IFERROR(X149/X$19,0) -> 0 | Z149: =IFERROR(VLOOKUP($A149,APOIO!$B:$N,MATCH(Z$5,APOIO!$B$5:$N$5,0),FALSE),0) -> 0 | AA149: =IFERROR(Z149/Z$19,0) -> 0 | AB149: =IFERROR(VLOOKUP($A149,APOIO!$B:$N,MATCH(AB$5,APOIO!$B$5:$N$5,0),FALSE),0) -> 0 | AC149: =IFERROR(AB149/AB$19,0) -> 0 | AD149: =IFERROR(VLOOKUP($A149,APOIO!$B:$N,MATCH(AD$5,APOIO!$B$5:$N$5,0),FALSE),0) -> 0 | AE149: =IFERROR(AD149/AD$19,0) -> 0 | AF149: =SUM(Z149,AB149,AD149) -> 0 | AG149: =IFERROR(AF149/AF$19,0) -> 0 | AH149: =SUM(B149,D149,F149,J149,L149,N149,R149,T149,V149,Z149,AB149,AD149) -> 0 | AI149: =IFERROR(AH149/AH$19,0) -> 0
A150: (+/-)Despesas e Receitas Financeiras | B150: =IFERROR(VLOOKUP($A150,APOIO!$B:$N,MATCH(B$5,APOIO!$B$5:$N$5,0),FALSE),0) -> 0 | C150: =IFERROR(B150/B$19,0) -> 0 | D150: =IFERROR(VLOOKUP($A150,APOIO!$B:$N,MATCH(D$5,APOIO!$B$5:$N$5,0),FALSE),0) -> 0 | E150: =IFERROR(D150/D$19,0) -> 0 | F150: =IFERROR(VLOOKUP($A150,APOIO!$B:$N,MATCH(F$5,APOIO!$B$5:$N$5,0),FALSE),0) -> 0 | G150: =IFERROR(F150/F$19,0) -> 0 | H150: =SUM(B150,D150,F150) -> 0 | I150: =IFERROR(H150/H$19,0) -> 0 | J150: =IFERROR(VLOOKUP($A150,APOIO!$B:$N,MATCH(J$5,APOIO!$B$5:$N$5,0),FALSE),0) -> -31.571073 | K150: =IFERROR(J150/J$19,0) -> 0 | L150: =IFERROR(VLOOKUP($A150,APOIO!$B:$N,MATCH(L$5,APOIO!$B$5:$N$5,0),FALSE),0) -> 0 | M150: =IFERROR(L150/L$19,0) -> 0 | N150: =IFERROR(VLOOKUP($A150,APOIO!$B:$N,MATCH(N$5,APOIO!$B$5:$N$5,0),FALSE),0) -> 0 | O150: =IFERROR(N150/N$19,0) -> 0 | P150: =SUM(J150,L150,N150) -> -31.571073 | Q150: =IFERROR(P150/P$19,0) -> 0 | R150: =IFERROR(VLOOKUP($A150,APOIO!$B:$N,MATCH(R$5,APOIO!$B$5:$N$5,0),FALSE),0) -> 0 | S150: =IFERROR(R150/R$19,0) -> 0 | T150: =IFERROR(VLOOKUP($A150,APOIO!$B:$N,MATCH(T$5,APOIO!$B$5:$N$5,0),FALSE),0) -> 0 | U150: =IFERROR(T150/T$19,0) -> 0 | V150: =IFERROR(VLOOKUP($A150,APOIO!$B:$N,MATCH(V$5,APOIO!$B$5:$N$5,0),FALSE),0) -> 0 | W150: =IFERROR(V150/V$19,0) -> 0 | X150: =SUM(R150,T150,V150) -> 0 | Y150: =IFERROR(X150/X$19,0) -> 0 | Z150: =IFERROR(VLOOKUP($A150,APOIO!$B:$N,MATCH(Z$5,APOIO!$B$5:$N$5,0),FALSE),0) -> 0 | AA150: =IFERROR(Z150/Z$19,0) -> 0 | AB150: =IFERROR(VLOOKUP($A150,APOIO!$B:$N,MATCH(AB$5,APOIO!$B$5:$N$5,0),FALSE),0) -> 0 | AC150: =IFERROR(AB150/AB$19,0) -> 0 | AD150: =IFERROR(VLOOKUP($A150,APOIO!$B:$N,MATCH(AD$5,APOIO!$B$5:$N$5,0),FALSE),0) -> 0 | AE150: =IFERROR(AD150/AD$19,0) -> 0 | AF150: =SUM(Z150,AB150,AD150) -> 0 | AG150: =IFERROR(AF150/AF$19,0) -> 0 | AH150: =SUM(B150,D150,F150,J150,L150,N150,R150,T150,V150,Z150,AB150,AD150) -> -31.571073 | AI150: =IFERROR(AH150/AH$19,0) -> -6.06858e-05
A151: (+) Receitas Financeiras | B151: =IFERROR(VLOOKUP($A151,APOIO!$B:$N,MATCH(B$5,APOIO!$B$5:$N$5,0),FALSE),0) -> 0 | C151: =IFERROR(B151/B$19,0) -> 0 | D151: =IFERROR(VLOOKUP($A151,APOIO!$B:$N,MATCH(D$5,APOIO!$B$5:$N$5,0),FALSE),0) -> 0 | E151: =IFERROR(D151/D$19,0) -> 0 | F151: =IFERROR(VLOOKUP($A151,APOIO!$B:$N,MATCH(F$5,APOIO!$B$5:$N$5,0),FALSE),0) -> 0 | G151: =IFERROR(F151/F$19,0) -> 0 | H151: =SUM(B151,D151,F151) -> 0 | I151: =IFERROR(H151/H$19,0) -> 0 | J151: =IFERROR(VLOOKUP($A151,APOIO!$B:$N,MATCH(J$5,APOIO!$B$5:$N$5,0),FALSE),0) -> 0 | K151: =IFERROR(J151/J$19,0) -> 0 | L151: =IFERROR(VLOOKUP($A151,APOIO!$B:$N,MATCH(L$5,APOIO!$B$5:$N$5,0),FALSE),0) -> 0 | M151: =IFERROR(L151/L$19,0) -> 0 | N151: =IFERROR(VLOOKUP($A151,APOIO!$B:$N,MATCH(N$5,APOIO!$B$5:$N$5,0),FALSE),0) -> 0 | O151: =IFERROR(N151/N$19,0) -> 0 | P151: =SUM(J151,L151,N151) -> 0 | Q151: =IFERROR(P151/P$19,0) -> 0 | R151: =IFERROR(VLOOKUP($A151,APOIO!$B:$N,MATCH(R$5,APOIO!$B$5:$N$5,0),FALSE),0) -> 0 | S151: =IFERROR(R151/R$19,0) -> 0 | T151: =IFERROR(VLOOKUP($A151,APOIO!$B:$N,MATCH(T$5,APOIO!$B$5:$N$5,0),FALSE),0) -> 0 | U151: =IFERROR(T151/T$19,0) -> 0 | V151: =IFERROR(VLOOKUP($A151,APOIO!$B:$N,MATCH(V$5,APOIO!$B$5:$N$5,0),FALSE),0) -> 0 | W151: =IFERROR(V151/V$19,0) -> 0 | X151: =SUM(R151,T151,V151) -> 0 | Y151: =IFERROR(X151/X$19,0) -> 0 | Z151: =IFERROR(VLOOKUP($A151,APOIO!$B:$N,MATCH(Z$5,APOIO!$B$5:$N$5,0),FALSE),0) -> 0 | AA151: =IFERROR(Z151/Z$19,0) -> 0 | AB151: =IFERROR(VLOOKUP($A151,APOIO!$B:$N,MATCH(AB$5,APOIO!$B$5:$N$5,0),FALSE),0) -> 0 | AC151: =IFERROR(AB151/AB$19,0) -> 0 | AD151: =IFERROR(VLOOKUP($A151,APOIO!$B:$N,MATCH(AD$5,APOIO!$B$5:$N$5,0),FALSE),0) -> 0 | AE151: =IFERROR(AD151/AD$19,0) -> 0 | AF151: =SUM(Z151,AB151,AD151) -> 0 | AG151: =IFERROR(AF151/AF$19,0) -> 0 | AH151: =SUM(B151,D151,F151,J151,L151,N151,R151,T151,V151,Z151,AB151,AD151) -> 0 | AI151: =IFERROR(AH151/AH$19,0) -> 0
A152: Recebimentos de emprestimos | B152: 229.96 | C152: 0.00029138183 | D152: 5.33 | E152: 3.5451395e-06 | F152: 0 | G152: 0 | H152: 235.29 | I152: 0.00010262698 | J152: 0 | K152: 0 | L152: 0 | M152: 0 | N152: 0 | O152: 0 | P152: 0 | Q152: 0 | R152: 0 | S152: 0 | T152: 0 | U152: 0 | V152: 0 | W152: 0 | X152: 0 | Y152: 0 | Z152: 0 | AA152: 0 | AB152: 0 | AC152: 0 | AD152: 0 | AE152: 0 | AF152: 0 | AG152: 0 | AH152: 235.29 | AI152: 0.00010262698
A153: Entrada emprestimos | B153: 229.96 | C153: 0.00029138183 | D153: 5.33 | E153: 3.5451395e-06 | F153: 0 | G153: 0 | H153: 235.29 | I153: 0.00010262698 | J153: 0 | K153: 0 | L153: 0 | M153: 0 | N153: 0 | O153: 0 | P153: 0 | Q153: 0 | R153: 0 | S153: 0 | T153: 0 | U153: 0 | V153: 0 | W153: 0 | X153: 0 | Y153: 0 | Z153: 0 | AA153: 0 | AB153: 0 | AC153: 0 | AD153: 0 | AE153: 0 | AF153: 0 | AG153: 0 | AH153: 235.29 | AI153: 0.00010262698
A154: Juros Recebidos | B154: =IFERROR(VLOOKUP($A154,APOIO!$B:$N,MATCH(B$5,APOIO!$B$5:$N$5,0),FALSE),0) -> 0 | C154: =IFERROR(B154/B$19,0) -> 0 | D154: =IFERROR(VLOOKUP($A154,APOIO!$B:$N,MATCH(D$5,APOIO!$B$5:$N$5,0),FALSE),0) -> 0 | E154: =IFERROR(D154/D$19,0) -> 0 | F154: =IFERROR(VLOOKUP($A154,APOIO!$B:$N,MATCH(F$5,APOIO!$B$5:$N$5,0),FALSE),0) -> 0 | G154: =IFERROR(F154/F$19,0) -> 0 | H154: =SUM(B154,D154,F154) -> 0 | I154: =IFERROR(H154/H$19,0) -> 0 | J154: =IFERROR(VLOOKUP($A154,APOIO!$B:$N,MATCH(J$5,APOIO!$B$5:$N$5,0),FALSE),0) -> 0 | K154: =IFERROR(J154/J$19,0) -> 0 | L154: =IFERROR(VLOOKUP($A154,APOIO!$B:$N,MATCH(L$5,APOIO!$B$5:$N$5,0),FALSE),0) -> 0 | M154: =IFERROR(L154/L$19,0) -> 0 | N154: =IFERROR(VLOOKUP($A154,APOIO!$B:$N,MATCH(N$5,APOIO!$B$5:$N$5,0),FALSE),0) -> 0 | O154: =IFERROR(N154/N$19,0) -> 0 | P154: =SUM(J154,L154,N154) -> 0 | Q154: =IFERROR(P154/P$19,0) -> 0 | R154: =IFERROR(VLOOKUP($A154,APOIO!$B:$N,MATCH(R$5,APOIO!$B$5:$N$5,0),FALSE),0) -> 0 | S154: =IFERROR(R154/R$19,0) -> 0 | T154: =IFERROR(VLOOKUP($A154,APOIO!$B:$N,MATCH(T$5,APOIO!$B$5:$N$5,0),FALSE),0) -> 0 | U154: =IFERROR(T154/T$19,0) -> 0 | V154: =IFERROR(VLOOKUP($A154,APOIO!$B:$N,MATCH(V$5,APOIO!$B$5:$N$5,0),FALSE),0) -> 0 | W154: =IFERROR(V154/V$19,0) -> 0 | X154: =SUM(R154,T154,V154) -> 0 | Y154: =IFERROR(X154/X$19,0) -> 0 | Z154: =IFERROR(VLOOKUP($A154,APOIO!$B:$N,MATCH(Z$5,APOIO!$B$5:$N$5,0),FALSE),0) -> 0 | AA154: =IFERROR(Z154/Z$19,0) -> 0 | AB154: =IFERROR(VLOOKUP($A154,APOIO!$B:$N,MATCH(AB$5,APOIO!$B$5:$N$5,0),FALSE),0) -> 0 | AC154: =IFERROR(AB154/AB$19,0) -> 0 | AD154: =IFERROR(VLOOKUP($A154,APOIO!$B:$N,MATCH(AD$5,APOIO!$B$5:$N$5,0),FALSE),0) -> 0 | AE154: =IFERROR(AD154/AD$19,0) -> 0 | AF154: =SUM(Z154,AB154,AD154) -> 0 | AG154: =IFERROR(AF154/AF$19,0) -> 0 | AH154: =SUM(B154,D154,F154,J154,L154,N154,R154,T154,V154,Z154,AB154,AD154) -> 0 | AI154: =IFERROR(AH154/AH$19,0) -> 0
A155: (-) Despesas Financeiras | B155: =IFERROR(VLOOKUP($A155,APOIO!$B:$N,MATCH(B$5,APOIO!$B$5:$N$5,0),FALSE),0) -> 0 | C155: =IFERROR(B155/B$19,0) -> 0 | D155: =IFERROR(VLOOKUP($A155,APOIO!$B:$N,MATCH(D$5,APOIO!$B$5:$N$5,0),FALSE),0) -> 0 | E155: =IFERROR(D155/D$19,0) -> 0 | F155: =IFERROR(VLOOKUP($A155,APOIO!$B:$N,MATCH(F$5,APOIO!$B$5:$N$5,0),FALSE),0) -> 0 | G155: =IFERROR(F155/F$19,0) -> 0 | H155: =SUM(B155,D155,F155) -> 0 | I155: =IFERROR(H155/H$19,0) -> 0 | J155: =IFERROR(VLOOKUP($A155,APOIO!$B:$N,MATCH(J$5,APOIO!$B$5:$N$5,0),FALSE),0) -> -31.571073 | K155: =IFERROR(J155/J$19,0) -> 0 | L155: =IFERROR(VLOOKUP($A155,APOIO!$B:$N,MATCH(L$5,APOIO!$B$5:$N$5,0),FALSE),0) -> 0 | M155: =IFERROR(L155/L$19,0) -> 0 | N155: =IFERROR(VLOOKUP($A155,APOIO!$B:$N,MATCH(N$5,APOIO!$B$5:$N$5,0),FALSE),0) -> 0 | O155: =IFERROR(N155/N$19,0) -> 0 | P155: =SUM(J155,L155,N155) -> -31.571073 | Q155: =IFERROR(P155/P$19,0) -> 0 | R155: =IFERROR(VLOOKUP($A155,APOIO!$B:$N,MATCH(R$5,APOIO!$B$5:$N$5,0),FALSE),0) -> 0 | S155: =IFERROR(R155/R$19,0) -> 0 | T155: =IFERROR(VLOOKUP($A155,APOIO!$B:$N,MATCH(T$5,APOIO!$B$5:$N$5,0),FALSE),0) -> 0 | U155: =IFERROR(T155/T$19,0) -> 0 | V155: =IFERROR(VLOOKUP($A155,APOIO!$B:$N,MATCH(V$5,APOIO!$B$5:$N$5,0),FALSE),0) -> 0 | W155: =IFERROR(V155/V$19,0) -> 0 | X155: =SUM(R155,T155,V155) -> 0 | Y155: =IFERROR(X155/X$19,0) -> 0 | Z155: =IFERROR(VLOOKUP($A155,APOIO!$B:$N,MATCH(Z$5,APOIO!$B$5:$N$5,0),FALSE),0) -> 0 | AA155: =IFERROR(Z155/Z$19,0) -> 0 | AB155: =IFERROR(VLOOKUP($A155,APOIO!$B:$N,MATCH(AB$5,APOIO!$B$5:$N$5,0),FALSE),0) -> 0 | AC155: =IFERROR(AB155/AB$19,0) -> 0 | AD155: =IFERROR(VLOOKUP($A155,APOIO!$B:$N,MATCH(AD$5,APOIO!$B$5:$N$5,0),FALSE),0) -> 0 | AE155: =IFERROR(AD155/AD$19,0) -> 0 | AF155: =SUM(Z155,AB155,AD155) -> 0 | AG155: =IFERROR(AF155/AF$19,0) -> 0 | AH155: =SUM(B155,D155,F155,J155,L155,N155,R155,T155,V155,Z155,AB155,AD155) -> -31.571073 | AI155: =IFERROR(AH155/AH$19,0) -> -6.06858e-05
A156: Empréstimos de Terceiros | B156: =IFERROR(VLOOKUP($A156,APOIO!$B:$N,MATCH(B$5,APOIO!$B$5:$N$5,0),FALSE),0) -> 0 | C156: =IFERROR(B156/B$19,0) -> 0 | D156: =IFERROR(VLOOKUP($A156,APOIO!$B:$N,MATCH(D$5,APOIO!$B$5:$N$5,0),FALSE),0) -> 0 | E156: =IFERROR(D156/D$19,0) -> 0 | F156: =IFERROR(VLOOKUP($A156,APOIO!$B:$N,MATCH(F$5,APOIO!$B$5:$N$5,0),FALSE),0) -> 0 | G156: =IFERROR(F156/F$19,0) -> 0 | H156: =SUM(B156,D156,F156) -> 0 | I156: =IFERROR(H156/H$19,0) -> 0 | J156: =IFERROR(VLOOKUP($A156,APOIO!$B:$N,MATCH(J$5,APOIO!$B$5:$N$5,0),FALSE),0) -> 0 | K156: =IFERROR(J156/J$19,0) -> 0 | L156: =IFERROR(VLOOKUP($A156,APOIO!$B:$N,MATCH(L$5,APOIO!$B$5:$N$5,0),FALSE),0) -> 0 | M156: =IFERROR(L156/L$19,0) -> 0 | N156: =IFERROR(VLOOKUP($A156,APOIO!$B:$N,MATCH(N$5,APOIO!$B$5:$N$5,0),FALSE),0) -> 0 | O156: =IFERROR(N156/N$19,0) -> 0 | P156: =SUM(J156,L156,N156) -> 0 | Q156: =IFERROR(P156/P$19,0) -> 0 | R156: =IFERROR(VLOOKUP($A156,APOIO!$B:$N,MATCH(R$5,APOIO!$B$5:$N$5,0),FALSE),0) -> 0 | S156: =IFERROR(R156/R$19,0) -> 0 | T156: =IFERROR(VLOOKUP($A156,APOIO!$B:$N,MATCH(T$5,APOIO!$B$5:$N$5,0),FALSE),0) -> 0 | U156: =IFERROR(T156/T$19,0) -> 0 | V156: =IFERROR(VLOOKUP($A156,APOIO!$B:$N,MATCH(V$5,APOIO!$B$5:$N$5,0),FALSE),0) -> 0 | W156: =IFERROR(V156/V$19,0) -> 0 | X156: =SUM(R156,T156,V156) -> 0 | Y156: =IFERROR(X156/X$19,0) -> 0 | Z156: =IFERROR(VLOOKUP($A156,APOIO!$B:$N,MATCH(Z$5,APOIO!$B$5:$N$5,0),FALSE),0) -> 0 | AA156: =IFERROR(Z156/Z$19,0) -> 0 | AB156: =IFERROR(VLOOKUP($A156,APOIO!$B:$N,MATCH(AB$5,APOIO!$B$5:$N$5,0),FALSE),0) -> 0 | AC156: =IFERROR(AB156/AB$19,0) -> 0 | AD156: =IFERROR(VLOOKUP($A156,APOIO!$B:$N,MATCH(AD$5,APOIO!$B$5:$N$5,0),FALSE),0) -> 0 | AE156: =IFERROR(AD156/AD$19,0) -> 0 | AF156: =SUM(Z156,AB156,AD156) -> 0 | AG156: =IFERROR(AF156/AF$19,0) -> 0 | AH156: =SUM(B156,D156,F156,J156,L156,N156,R156,T156,V156,Z156,AB156,AD156) -> 0 | AI156: =IFERROR(AH156/AH$19,0) -> 0
A157: Juros Bancários | B157: =IFERROR(VLOOKUP($A157,APOIO!$B:$N,MATCH(B$5,APOIO!$B$5:$N$5,0),FALSE),0) -> 0 | C157: =IFERROR(B157/B$19,0) -> 0 | D157: =IFERROR(VLOOKUP($A157,APOIO!$B:$N,MATCH(D$5,APOIO!$B$5:$N$5,0),FALSE),0) -> 0 | E157: =IFERROR(D157/D$19,0) -> 0 | F157: =IFERROR(VLOOKUP($A157,APOIO!$B:$N,MATCH(F$5,APOIO!$B$5:$N$5,0),FALSE),0) -> 0 | G157: =IFERROR(F157/F$19,0) -> 0 | H157: =SUM(B157,D157,F157) -> 0 | I157: =IFERROR(H157/H$19,0) -> 0 | J157: =IFERROR(VLOOKUP($A157,APOIO!$B:$N,MATCH(J$5,APOIO!$B$5:$N$5,0),FALSE),0) -> -31.571073 | K157: =IFERROR(J157/J$19,0) -> 0 | L157: =IFERROR(VLOOKUP($A157,APOIO!$B:$N,MATCH(L$5,APOIO!$B$5:$N$5,0),FALSE),0) -> 0 | M157: =IFERROR(L157/L$19,0) -> 0 | N157: =IFERROR(VLOOKUP($A157,APOIO!$B:$N,MATCH(N$5,APOIO!$B$5:$N$5,0),FALSE),0) -> 0 | O157: =IFERROR(N157/N$19,0) -> 0 | P157: =SUM(J157,L157,N157) -> -31.571073 | Q157: =IFERROR(P157/P$19,0) -> 0 | R157: =IFERROR(VLOOKUP($A157,APOIO!$B:$N,MATCH(R$5,APOIO!$B$5:$N$5,0),FALSE),0) -> 0 | S157: =IFERROR(R157/R$19,0) -> 0 | T157: =IFERROR(VLOOKUP($A157,APOIO!$B:$N,MATCH(T$5,APOIO!$B$5:$N$5,0),FALSE),0) -> 0 | U157: =IFERROR(T157/T$19,0) -> 0 | V157: =IFERROR(VLOOKUP($A157,APOIO!$B:$N,MATCH(V$5,APOIO!$B$5:$N$5,0),FALSE),0) -> 0 | W157: =IFERROR(V157/V$19,0) -> 0 | X157: =SUM(R157,T157,V157) -> 0 | Y157: =IFERROR(X157/X$19,0) -> 0 | Z157: =IFERROR(VLOOKUP($A157,APOIO!$B:$N,MATCH(Z$5,APOIO!$B$5:$N$5,0),FALSE),0) -> 0 | AA157: =IFERROR(Z157/Z$19,0) -> 0 | AB157: =IFERROR(VLOOKUP($A157,APOIO!$B:$N,MATCH(AB$5,APOIO!$B$5:$N$5,0),FALSE),0) -> 0 | AC157: =IFERROR(AB157/AB$19,0) -> 0 | AD157: =IFERROR(VLOOKUP($A157,APOIO!$B:$N,MATCH(AD$5,APOIO!$B$5:$N$5,0),FALSE),0) -> 0 | AE157: =IFERROR(AD157/AD$19,0) -> 0 | AF157: =SUM(Z157,AB157,AD157) -> 0 | AG157: =IFERROR(AF157/AF$19,0) -> 0 | AH157: =SUM(B157,D157,F157,J157,L157,N157,R157,T157,V157,Z157,AB157,AD157) -> -31.571073 | AI157: =IFERROR(AH157/AH$19,0) -> -6.06858e-05
A158: Consorcios | B158: =IFERROR(VLOOKUP($A158,APOIO!$B:$N,MATCH(B$5,APOIO!$B$5:$N$5,0),FALSE),0) -> 0 | C158: =IFERROR(B158/B$19,0) -> 0 | D158: =IFERROR(VLOOKUP($A158,APOIO!$B:$N,MATCH(D$5,APOIO!$B$5:$N$5,0),FALSE),0) -> 0 | E158: =IFERROR(D158/D$19,0) -> 0 | F158: =IFERROR(VLOOKUP($A158,APOIO!$B:$N,MATCH(F$5,APOIO!$B$5:$N$5,0),FALSE),0) -> 0 | G158: =IFERROR(F158/F$19,0) -> 0 | H158: =SUM(B158,D158,F158) -> 0 | I158: =IFERROR(H158/H$19,0) -> 0 | J158: =IFERROR(VLOOKUP($A158,APOIO!$B:$N,MATCH(J$5,APOIO!$B$5:$N$5,0),FALSE),0) -> 0 | K158: =IFERROR(J158/J$19,0) -> 0 | L158: =IFERROR(VLOOKUP($A158,APOIO!$B:$N,MATCH(L$5,APOIO!$B$5:$N$5,0),FALSE),0) -> 0 | M158: =IFERROR(L158/L$19,0) -> 0 | N158: =IFERROR(VLOOKUP($A158,APOIO!$B:$N,MATCH(N$5,APOIO!$B$5:$N$5,0),FALSE),0) -> 0 | O158: =IFERROR(N158/N$19,0) -> 0 | P158: =SUM(J158,L158,N158) -> 0 | Q158: =IFERROR(P158/P$19,0) -> 0 | R158: =IFERROR(VLOOKUP($A158,APOIO!$B:$N,MATCH(R$5,APOIO!$B$5:$N$5,0),FALSE),0) -> 0 | S158: =IFERROR(R158/R$19,0) -> 0 | T158: =IFERROR(VLOOKUP($A158,APOIO!$B:$N,MATCH(T$5,APOIO!$B$5:$N$5,0),FALSE),0) -> 0 | U158: =IFERROR(T158/T$19,0) -> 0 | V158: =IFERROR(VLOOKUP($A158,APOIO!$B:$N,MATCH(V$5,APOIO!$B$5:$N$5,0),FALSE),0) -> 0 | W158: =IFERROR(V158/V$19,0) -> 0 | X158: =SUM(R158,T158,V158) -> 0 | Y158: =IFERROR(X158/X$19,0) -> 0 | Z158: =IFERROR(VLOOKUP($A158,APOIO!$B:$N,MATCH(Z$5,APOIO!$B$5:$N$5,0),FALSE),0) -> 0 | AA158: =IFERROR(Z158/Z$19,0) -> 0 | AB158: =IFERROR(VLOOKUP($A158,APOIO!$B:$N,MATCH(AB$5,APOIO!$B$5:$N$5,0),FALSE),0) -> 0 | AC158: =IFERROR(AB158/AB$19,0) -> 0 | AD158: =IFERROR(VLOOKUP($A158,APOIO!$B:$N,MATCH(AD$5,APOIO!$B$5:$N$5,0),FALSE),0) -> 0 | AE158: =IFERROR(AD158/AD$19,0) -> 0 | AF158: =SUM(Z158,AB158,AD158) -> 0 | AG158: =IFERROR(AF158/AF$19,0) -> 0 | AH158: =SUM(B158,D158,F158,J158,L158,N158,R158,T158,V158,Z158,AB158,AD158) -> 0 | AI158: =IFERROR(AH158/AH$19,0) -> 0
A159: Financiamento | B159: =IFERROR(VLOOKUP($A159,APOIO!$B:$N,MATCH(B$5,APOIO!$B$5:$N$5,0),FALSE),0) -> 0 | C159: =IFERROR(B159/B$19,0) -> 0 | D159: =IFERROR(VLOOKUP($A159,APOIO!$B:$N,MATCH(D$5,APOIO!$B$5:$N$5,0),FALSE),0) -> 0 | E159: =IFERROR(D159/D$19,0) -> 0 | F159: =IFERROR(VLOOKUP($A159,APOIO!$B:$N,MATCH(F$5,APOIO!$B$5:$N$5,0),FALSE),0) -> 0 | G159: =IFERROR(F159/F$19,0) -> 0 | H159: =SUM(B159,D159,F159) -> 0 | I159: =IFERROR(H159/H$19,0) -> 0 | J159: =IFERROR(VLOOKUP($A159,APOIO!$B:$N,MATCH(J$5,APOIO!$B$5:$N$5,0),FALSE),0) -> 0 | K159: =IFERROR(J159/J$19,0) -> 0 | L159: =IFERROR(VLOOKUP($A159,APOIO!$B:$N,MATCH(L$5,APOIO!$B$5:$N$5,0),FALSE),0) -> 0 | M159: =IFERROR(L159/L$19,0) -> 0 | N159: =IFERROR(VLOOKUP($A159,APOIO!$B:$N,MATCH(N$5,APOIO!$B$5:$N$5,0),FALSE),0) -> 0 | O159: =IFERROR(N159/N$19,0) -> 0 | P159: =SUM(J159,L159,N159) -> 0 | Q159: =IFERROR(P159/P$19,0) -> 0 | R159: =IFERROR(VLOOKUP($A159,APOIO!$B:$N,MATCH(R$5,APOIO!$B$5:$N$5,0),FALSE),0) -> 0 | S159: =IFERROR(R159/R$19,0) -> 0 | T159: =IFERROR(VLOOKUP($A159,APOIO!$B:$N,MATCH(T$5,APOIO!$B$5:$N$5,0),FALSE),0) -> 0 | U159: =IFERROR(T159/T$19,0) -> 0 | V159: =IFERROR(VLOOKUP($A159,APOIO!$B:$N,MATCH(V$5,APOIO!$B$5:$N$5,0),FALSE),0) -> 0 | W159: =IFERROR(V159/V$19,0) -> 0 | X159: =SUM(R159,T159,V159) -> 0 | Y159: =IFERROR(X159/X$19,0) -> 0 | Z159: =IFERROR(VLOOKUP($A159,APOIO!$B:$N,MATCH(Z$5,APOIO!$B$5:$N$5,0),FALSE),0) -> 0 | AA159: =IFERROR(Z159/Z$19,0) -> 0 | AB159: =IFERROR(VLOOKUP($A159,APOIO!$B:$N,MATCH(AB$5,APOIO!$B$5:$N$5,0),FALSE),0) -> 0 | AC159: =IFERROR(AB159/AB$19,0) -> 0 | AD159: =IFERROR(VLOOKUP($A159,APOIO!$B:$N,MATCH(AD$5,APOIO!$B$5:$N$5,0),FALSE),0) -> 0 | AE159: =IFERROR(AD159/AD$19,0) -> 0 | AF159: =SUM(Z159,AB159,AD159) -> 0 | AG159: =IFERROR(AF159/AF$19,0) -> 0 | AH159: =SUM(B159,D159,F159,J159,L159,N159,R159,T159,V159,Z159,AB159,AD159) -> 0 | AI159: =IFERROR(AH159/AH$19,0) -> 0
A160: Empréstimos Bancários | B160: =IFERROR(VLOOKUP($A160,APOIO!$B:$N,MATCH(B$5,APOIO!$B$5:$N$5,0),FALSE),0) -> 0 | C160: =IFERROR(B160/B$19,0) -> 0 | D160: =IFERROR(VLOOKUP($A160,APOIO!$B:$N,MATCH(D$5,APOIO!$B$5:$N$5,0),FALSE),0) -> 0 | E160: =IFERROR(D160/D$19,0) -> 0 | F160: =IFERROR(VLOOKUP($A160,APOIO!$B:$N,MATCH(F$5,APOIO!$B$5:$N$5,0),FALSE),0) -> 0 | G160: =IFERROR(F160/F$19,0) -> 0 | H160: =SUM(B160,D160,F160) -> 0 | I160: =IFERROR(H160/H$19,0) -> 0 | J160: =IFERROR(VLOOKUP($A160,APOIO!$B:$N,MATCH(J$5,APOIO!$B$5:$N$5,0),FALSE),0) -> 0 | K160: =IFERROR(J160/J$19,0) -> 0 | L160: =IFERROR(VLOOKUP($A160,APOIO!$B:$N,MATCH(L$5,APOIO!$B$5:$N$5,0),FALSE),0) -> 0 | M160: =IFERROR(L160/L$19,0) -> 0 | N160: =IFERROR(VLOOKUP($A160,APOIO!$B:$N,MATCH(N$5,APOIO!$B$5:$N$5,0),FALSE),0) -> 0 | O160: =IFERROR(N160/N$19,0) -> 0 | P160: =SUM(J160,L160,N160) -> 0 | Q160: =IFERROR(P160/P$19,0) -> 0 | R160: =IFERROR(VLOOKUP($A160,APOIO!$B:$N,MATCH(R$5,APOIO!$B$5:$N$5,0),FALSE),0) -> 0 | S160: =IFERROR(R160/R$19,0) -> 0 | T160: =IFERROR(VLOOKUP($A160,APOIO!$B:$N,MATCH(T$5,APOIO!$B$5:$N$5,0),FALSE),0) -> 0 | U160: =IFERROR(T160/T$19,0) -> 0 | V160: =IFERROR(VLOOKUP($A160,APOIO!$B:$N,MATCH(V$5,APOIO!$B$5:$N$5,0),FALSE),0) -> 0 | W160: =IFERROR(V160/V$19,0) -> 0 | X160: =SUM(R160,T160,V160) -> 0 | Y160: =IFERROR(X160/X$19,0) -> 0 | Z160: =IFERROR(VLOOKUP($A160,APOIO!$B:$N,MATCH(Z$5,APOIO!$B$5:$N$5,0),FALSE),0) -> 0 | AA160: =IFERROR(Z160/Z$19,0) -> 0 | AB160: =IFERROR(VLOOKUP($A160,APOIO!$B:$N,MATCH(AB$5,APOIO!$B$5:$N$5,0),FALSE),0) -> 0 | AC160: =IFERROR(AB160/AB$19,0) -> 0 | AD160: =IFERROR(VLOOKUP($A160,APOIO!$B:$N,MATCH(AD$5,APOIO!$B$5:$N$5,0),FALSE),0) -> 0 | AE160: =IFERROR(AD160/AD$19,0) -> 0 | AF160: =SUM(Z160,AB160,AD160) -> 0 | AG160: =IFERROR(AF160/AF$19,0) -> 0 | AH160: =SUM(B160,D160,F160,J160,L160,N160,R160,T160,V160,Z160,AB160,AD160) -> 0 | AI160: =IFERROR(AH160/AH$19,0) -> 0
B161: =IFERROR(VLOOKUP($A161,APOIO!$B:$N,MATCH(B$5,APOIO!$B$5:$N$5,0),FALSE),0) -> 0 | C161: =IFERROR(B161/B$19,0) -> 0 | D161: =IFERROR(VLOOKUP($A161,APOIO!$B:$N,MATCH(D$5,APOIO!$B$5:$N$5,0),FALSE),0) -> 0 | E161: =IFERROR(D161/D$19,0) -> 0 | F161: =IFERROR(VLOOKUP($A161,APOIO!$B:$N,MATCH(F$5,APOIO!$B$5:$N$5,0),FALSE),0) -> 0 | G161: =IFERROR(F161/F$19,0) -> 0 | H161: =SUM(B161,D161,F161) -> 0 | I161: =IFERROR(H161/H$19,0) -> 0 | J161: =IFERROR(VLOOKUP($A161,APOIO!$B:$N,MATCH(J$5,APOIO!$B$5:$N$5,0),FALSE),0) -> 0 | K161: =IFERROR(J161/J$19,0) -> 0 | L161: =IFERROR(VLOOKUP($A161,APOIO!$B:$N,MATCH(L$5,APOIO!$B$5:$N$5,0),FALSE),0) -> 0 | M161: =IFERROR(L161/L$19,0) -> 0 | N161: =IFERROR(VLOOKUP($A161,APOIO!$B:$N,MATCH(N$5,APOIO!$B$5:$N$5,0),FALSE),0) -> 0 | O161: =IFERROR(N161/N$19,0) -> 0 | P161: =SUM(J161,L161,N161) -> 0 | Q161: =IFERROR(P161/P$19,0) -> 0 | R161: =IFERROR(VLOOKUP($A161,APOIO!$B:$N,MATCH(R$5,APOIO!$B$5:$N$5,0),FALSE),0) -> 0 | S161: =IFERROR(R161/R$19,0) -> 0 | T161: =IFERROR(VLOOKUP($A161,APOIO!$B:$N,MATCH(T$5,APOIO!$B$5:$N$5,0),FALSE),0) -> 0 | U161: =IFERROR(T161/T$19,0) -> 0 | V161: =IFERROR(VLOOKUP($A161,APOIO!$B:$N,MATCH(V$5,APOIO!$B$5:$N$5,0),FALSE),0) -> 0 | W161: =IFERROR(V161/V$19,0) -> 0 | X161: =SUM(R161,T161,V161) -> 0 | Y161: =IFERROR(X161/X$19,0) -> 0 | Z161: =IFERROR(VLOOKUP($A161,APOIO!$B:$N,MATCH(Z$5,APOIO!$B$5:$N$5,0),FALSE),0) -> 0 | AA161: =IFERROR(Z161/Z$19,0) -> 0 | AB161: =IFERROR(VLOOKUP($A161,APOIO!$B:$N,MATCH(AB$5,APOIO!$B$5:$N$5,0),FALSE),0) -> 0 | AC161: =IFERROR(AB161/AB$19,0) -> 0 | AD161: =IFERROR(VLOOKUP($A161,APOIO!$B:$N,MATCH(AD$5,APOIO!$B$5:$N$5,0),FALSE),0) -> 0 | AE161: =IFERROR(AD161/AD$19,0) -> 0 | AF161: =SUM(Z161,AB161,AD161) -> 0 | AG161: =IFERROR(AF161/AF$19,0) -> 0 | AH161: =SUM(B161,D161,F161,J161,L161,N161,R161,T161,V161,Z161,AB161,AD161) -> 0 | AI161: =IFERROR(AH161/AH$19,0) -> 0
B162: =IFERROR(VLOOKUP($A162,APOIO!$B:$N,MATCH(B$5,APOIO!$B$5:$N$5,0),FALSE),0) -> 0 | C162: =IFERROR(B162/B$19,0) -> 0 | D162: =IFERROR(VLOOKUP($A162,APOIO!$B:$N,MATCH(D$5,APOIO!$B$5:$N$5,0),FALSE),0) -> 0 | E162: =IFERROR(D162/D$19,0) -> 0 | F162: =IFERROR(VLOOKUP($A162,APOIO!$B:$N,MATCH(F$5,APOIO!$B$5:$N$5,0),FALSE),0) -> 0 | G162: =IFERROR(F162/F$19,0) -> 0 | H162: =SUM(B162,D162,F162) -> 0 | I162: =IFERROR(H162/H$19,0) -> 0 | J162: =IFERROR(VLOOKUP($A162,APOIO!$B:$N,MATCH(J$5,APOIO!$B$5:$N$5,0),FALSE),0) -> 0 | K162: =IFERROR(J162/J$19,0) -> 0 | L162: =IFERROR(VLOOKUP($A162,APOIO!$B:$N,MATCH(L$5,APOIO!$B$5:$N$5,0),FALSE),0) -> 0 | M162: =IFERROR(L162/L$19,0) -> 0 | N162: =IFERROR(VLOOKUP($A162,APOIO!$B:$N,MATCH(N$5,APOIO!$B$5:$N$5,0),FALSE),0) -> 0 | O162: =IFERROR(N162/N$19,0) -> 0 | P162: =SUM(J162,L162,N162) -> 0 | Q162: =IFERROR(P162/P$19,0) -> 0 | R162: =IFERROR(VLOOKUP($A162,APOIO!$B:$N,MATCH(R$5,APOIO!$B$5:$N$5,0),FALSE),0) -> 0 | S162: =IFERROR(R162/R$19,0) -> 0 | T162: =IFERROR(VLOOKUP($A162,APOIO!$B:$N,MATCH(T$5,APOIO!$B$5:$N$5,0),FALSE),0) -> 0 | U162: =IFERROR(T162/T$19,0) -> 0 | V162: =IFERROR(VLOOKUP($A162,APOIO!$B:$N,MATCH(V$5,APOIO!$B$5:$N$5,0),FALSE),0) -> 0 | W162: =IFERROR(V162/V$19,0) -> 0 | X162: =SUM(R162,T162,V162) -> 0 | Y162: =IFERROR(X162/X$19,0) -> 0 | Z162: =IFERROR(VLOOKUP($A162,APOIO!$B:$N,MATCH(Z$5,APOIO!$B$5:$N$5,0),FALSE),0) -> 0 | AA162: =IFERROR(Z162/Z$19,0) -> 0 | AB162: =IFERROR(VLOOKUP($A162,APOIO!$B:$N,MATCH(AB$5,APOIO!$B$5:$N$5,0),FALSE),0) -> 0 | AC162: =IFERROR(AB162/AB$19,0) -> 0 | AD162: =IFERROR(VLOOKUP($A162,APOIO!$B:$N,MATCH(AD$5,APOIO!$B$5:$N$5,0),FALSE),0) -> 0 | AE162: =IFERROR(AD162/AD$19,0) -> 0 | AF162: =SUM(Z162,AB162,AD162) -> 0 | AG162: =IFERROR(AF162/AF$19,0) -> 0 | AH162: =SUM(B162,D162,F162,J162,L162,N162,R162,T162,V162,Z162,AB162,AD162) -> 0 | AI162: =IFERROR(AH162/AH$19,0) -> 0
A163: (+/-)Despesas e Recebimentos Não Operacionais | B163: =IFERROR(VLOOKUP($A163,APOIO!$B:$N,MATCH(B$5,APOIO!$B$5:$N$5,0),FALSE),0) -> 0 | C163: =IFERROR(B163/B$19,0) -> 0 | D163: =IFERROR(VLOOKUP($A163,APOIO!$B:$N,MATCH(D$5,APOIO!$B$5:$N$5,0),FALSE),0) -> 0 | E163: =IFERROR(D163/D$19,0) -> 0 | F163: =IFERROR(VLOOKUP($A163,APOIO!$B:$N,MATCH(F$5,APOIO!$B$5:$N$5,0),FALSE),0) -> 0 | G163: =IFERROR(F163/F$19,0) -> 0 | H163: =SUM(B163,D163,F163) -> 0 | I163: =IFERROR(H163/H$19,0) -> 0 | J163: =IFERROR(VLOOKUP($A163,APOIO!$B:$N,MATCH(J$5,APOIO!$B$5:$N$5,0),FALSE),0) -> 0 | K163: =IFERROR(J163/J$19,0) -> 0 | L163: =IFERROR(VLOOKUP($A163,APOIO!$B:$N,MATCH(L$5,APOIO!$B$5:$N$5,0),FALSE),0) -> 0 | M163: =IFERROR(L163/L$19,0) -> 0 | N163: =IFERROR(VLOOKUP($A163,APOIO!$B:$N,MATCH(N$5,APOIO!$B$5:$N$5,0),FALSE),0) -> 0 | O163: =IFERROR(N163/N$19,0) -> 0 | P163: =SUM(J163,L163,N163) -> 0 | Q163: =IFERROR(P163/P$19,0) -> 0 | R163: =IFERROR(VLOOKUP($A163,APOIO!$B:$N,MATCH(R$5,APOIO!$B$5:$N$5,0),FALSE),0) -> 0 | S163: =IFERROR(R163/R$19,0) -> 0 | T163: =IFERROR(VLOOKUP($A163,APOIO!$B:$N,MATCH(T$5,APOIO!$B$5:$N$5,0),FALSE),0) -> 0 | U163: =IFERROR(T163/T$19,0) -> 0 | V163: =IFERROR(VLOOKUP($A163,APOIO!$B:$N,MATCH(V$5,APOIO!$B$5:$N$5,0),FALSE),0) -> 0 | W163: =IFERROR(V163/V$19,0) -> 0 | X163: =SUM(R163,T163,V163) -> 0 | Y163: =IFERROR(X163/X$19,0) -> 0 | Z163: =IFERROR(VLOOKUP($A163,APOIO!$B:$N,MATCH(Z$5,APOIO!$B$5:$N$5,0),FALSE),0) -> 0 | AA163: =IFERROR(Z163/Z$19,0) -> 0 | AB163: =IFERROR(VLOOKUP($A163,APOIO!$B:$N,MATCH(AB$5,APOIO!$B$5:$N$5,0),FALSE),0) -> 0 | AC163: =IFERROR(AB163/AB$19,0) -> 0 | AD163: =IFERROR(VLOOKUP($A163,APOIO!$B:$N,MATCH(AD$5,APOIO!$B$5:$N$5,0),FALSE),0) -> 0 | AE163: =IFERROR(AD163/AD$19,0) -> 0 | AF163: =SUM(Z163,AB163,AD163) -> 0 | AG163: =IFERROR(AF163/AF$19,0) -> 0 | AH163: =SUM(B163,D163,F163,J163,L163,N163,R163,T163,V163,Z163,AB163,AD163) -> 0 | AI163: =IFERROR(AH163/AH$19,0) -> 0
A164: (+) Recebimentos Não Operacionais | B164: =IFERROR(VLOOKUP($A164,APOIO!$B:$N,MATCH(B$5,APOIO!$B$5:$N$5,0),FALSE),0) -> 0 | C164: =IFERROR(B164/B$19,0) -> 0 | D164: =IFERROR(VLOOKUP($A164,APOIO!$B:$N,MATCH(D$5,APOIO!$B$5:$N$5,0),FALSE),0) -> 0 | E164: =IFERROR(D164/D$19,0) -> 0 | F164: =IFERROR(VLOOKUP($A164,APOIO!$B:$N,MATCH(F$5,APOIO!$B$5:$N$5,0),FALSE),0) -> 0 | G164: =IFERROR(F164/F$19,0) -> 0 | H164: =SUM(B164,D164,F164) -> 0 | I164: =IFERROR(H164/H$19,0) -> 0 | J164: =IFERROR(VLOOKUP($A164,APOIO!$B:$N,MATCH(J$5,APOIO!$B$5:$N$5,0),FALSE),0) -> 0 | K164: =IFERROR(J164/J$19,0) -> 0 | L164: =IFERROR(VLOOKUP($A164,APOIO!$B:$N,MATCH(L$5,APOIO!$B$5:$N$5,0),FALSE),0) -> 0 | M164: =IFERROR(L164/L$19,0) -> 0 | N164: =IFERROR(VLOOKUP($A164,APOIO!$B:$N,MATCH(N$5,APOIO!$B$5:$N$5,0),FALSE),0) -> 0 | O164: =IFERROR(N164/N$19,0) -> 0 | P164: =SUM(J164,L164,N164) -> 0 | Q164: =IFERROR(P164/P$19,0) -> 0 | R164: =IFERROR(VLOOKUP($A164,APOIO!$B:$N,MATCH(R$5,APOIO!$B$5:$N$5,0),FALSE),0) -> 0 | S164: =IFERROR(R164/R$19,0) -> 0 | T164: =IFERROR(VLOOKUP($A164,APOIO!$B:$N,MATCH(T$5,APOIO!$B$5:$N$5,0),FALSE),0) -> 0 | U164: =IFERROR(T164/T$19,0) -> 0 | V164: =IFERROR(VLOOKUP($A164,APOIO!$B:$N,MATCH(V$5,APOIO!$B$5:$N$5,0),FALSE),0) -> 0 | W164: =IFERROR(V164/V$19,0) -> 0 | X164: =SUM(R164,T164,V164) -> 0 | Y164: =IFERROR(X164/X$19,0) -> 0 | Z164: =IFERROR(VLOOKUP($A164,APOIO!$B:$N,MATCH(Z$5,APOIO!$B$5:$N$5,0),FALSE),0) -> 0 | AA164: =IFERROR(Z164/Z$19,0) -> 0 | AB164: =IFERROR(VLOOKUP($A164,APOIO!$B:$N,MATCH(AB$5,APOIO!$B$5:$N$5,0),FALSE),0) -> 0 | AC164: =IFERROR(AB164/AB$19,0) -> 0 | AD164: =IFERROR(VLOOKUP($A164,APOIO!$B:$N,MATCH(AD$5,APOIO!$B$5:$N$5,0),FALSE),0) -> 0 | AE164: =IFERROR(AD164/AD$19,0) -> 0 | AF164: =SUM(Z164,AB164,AD164) -> 0 | AG164: =IFERROR(AF164/AF$19,0) -> 0 | AH164: =SUM(B164,D164,F164,J164,L164,N164,R164,T164,V164,Z164,AB164,AD164) -> 0 | AI164: =IFERROR(AH164/AH$19,0) -> 0
A165: Recebimentos Não Operacionais | B165: =IFERROR(VLOOKUP($A165,APOIO!$B:$N,MATCH(B$5,APOIO!$B$5:$N$5,0),FALSE),0) -> 0 | C165: =IFERROR(B165/B$19,0) -> 0 | D165: =IFERROR(VLOOKUP($A165,APOIO!$B:$N,MATCH(D$5,APOIO!$B$5:$N$5,0),FALSE),0) -> 0 | E165: =IFERROR(D165/D$19,0) -> 0 | F165: =IFERROR(VLOOKUP($A165,APOIO!$B:$N,MATCH(F$5,APOIO!$B$5:$N$5,0),FALSE),0) -> 0 | G165: =IFERROR(F165/F$19,0) -> 0 | H165: =SUM(B165,D165,F165) -> 0 | I165: =IFERROR(H165/H$19,0) -> 0 | J165: =IFERROR(VLOOKUP($A165,APOIO!$B:$N,MATCH(J$5,APOIO!$B$5:$N$5,0),FALSE),0) -> 0 | K165: =IFERROR(J165/J$19,0) -> 0 | L165: =IFERROR(VLOOKUP($A165,APOIO!$B:$N,MATCH(L$5,APOIO!$B$5:$N$5,0),FALSE),0) -> 0 | M165: =IFERROR(L165/L$19,0) -> 0 | N165: =IFERROR(VLOOKUP($A165,APOIO!$B:$N,MATCH(N$5,APOIO!$B$5:$N$5,0),FALSE),0) -> 0 | O165: =IFERROR(N165/N$19,0) -> 0 | P165: =SUM(J165,L165,N165) -> 0 | Q165: =IFERROR(P165/P$19,0) -> 0 | R165: =IFERROR(VLOOKUP($A165,APOIO!$B:$N,MATCH(R$5,APOIO!$B$5:$N$5,0),FALSE),0) -> 0 | S165: =IFERROR(R165/R$19,0) -> 0 | T165: =IFERROR(VLOOKUP($A165,APOIO!$B:$N,MATCH(T$5,APOIO!$B$5:$N$5,0),FALSE),0) -> 0 | U165: =IFERROR(T165/T$19,0) -> 0 | V165: =IFERROR(VLOOKUP($A165,APOIO!$B:$N,MATCH(V$5,APOIO!$B$5:$N$5,0),FALSE),0) -> 0 | W165: =IFERROR(V165/V$19,0) -> 0 | X165: =SUM(R165,T165,V165) -> 0 | Y165: =IFERROR(X165/X$19,0) -> 0 | Z165: =IFERROR(VLOOKUP($A165,APOIO!$B:$N,MATCH(Z$5,APOIO!$B$5:$N$5,0),FALSE),0) -> 0 | AA165: =IFERROR(Z165/Z$19,0) -> 0 | AB165: =IFERROR(VLOOKUP($A165,APOIO!$B:$N,MATCH(AB$5,APOIO!$B$5:$N$5,0),FALSE),0) -> 0 | AC165: =IFERROR(AB165/AB$19,0) -> 0 | AD165: =IFERROR(VLOOKUP($A165,APOIO!$B:$N,MATCH(AD$5,APOIO!$B$5:$N$5,0),FALSE),0) -> 0 | AE165: =IFERROR(AD165/AD$19,0) -> 0 | AF165: =SUM(Z165,AB165,AD165) -> 0 | AG165: =IFERROR(AF165/AF$19,0) -> 0 | AH165: =SUM(B165,D165,F165,J165,L165,N165,R165,T165,V165,Z165,AB165,AD165) -> 0 | AI165: =IFERROR(AH165/AH$19,0) -> 0
A166: Outros Recebimentos Não Operacionais | B166: =IFERROR(VLOOKUP($A166,APOIO!$B:$N,MATCH(B$5,APOIO!$B$5:$N$5,0),FALSE),0) -> 0 | C166: =IFERROR(B166/B$19,0) -> 0 | D166: =IFERROR(VLOOKUP($A166,APOIO!$B:$N,MATCH(D$5,APOIO!$B$5:$N$5,0),FALSE),0) -> 0 | E166: =IFERROR(D166/D$19,0) -> 0 | F166: =IFERROR(VLOOKUP($A166,APOIO!$B:$N,MATCH(F$5,APOIO!$B$5:$N$5,0),FALSE),0) -> 0 | G166: =IFERROR(F166/F$19,0) -> 0 | H166: =SUM(B166,D166,F166) -> 0 | I166: =IFERROR(H166/H$19,0) -> 0 | J166: =IFERROR(VLOOKUP($A166,APOIO!$B:$N,MATCH(J$5,APOIO!$B$5:$N$5,0),FALSE),0) -> 0 | K166: =IFERROR(J166/J$19,0) -> 0 | L166: =IFERROR(VLOOKUP($A166,APOIO!$B:$N,MATCH(L$5,APOIO!$B$5:$N$5,0),FALSE),0) -> 0 | M166: =IFERROR(L166/L$19,0) -> 0 | N166: =IFERROR(VLOOKUP($A166,APOIO!$B:$N,MATCH(N$5,APOIO!$B$5:$N$5,0),FALSE),0) -> 0 | O166: =IFERROR(N166/N$19,0) -> 0 | P166: =SUM(J166,L166,N166) -> 0 | Q166: =IFERROR(P166/P$19,0) -> 0 | R166: =IFERROR(VLOOKUP($A166,APOIO!$B:$N,MATCH(R$5,APOIO!$B$5:$N$5,0),FALSE),0) -> 0 | S166: =IFERROR(R166/R$19,0) -> 0 | T166: =IFERROR(VLOOKUP($A166,APOIO!$B:$N,MATCH(T$5,APOIO!$B$5:$N$5,0),FALSE),0) -> 0 | U166: =IFERROR(T166/T$19,0) -> 0 | V166: =IFERROR(VLOOKUP($A166,APOIO!$B:$N,MATCH(V$5,APOIO!$B$5:$N$5,0),FALSE),0) -> 0 | W166: =IFERROR(V166/V$19,0) -> 0 | X166: =SUM(R166,T166,V166) -> 0 | Y166: =IFERROR(X166/X$19,0) -> 0 | Z166: =IFERROR(VLOOKUP($A166,APOIO!$B:$N,MATCH(Z$5,APOIO!$B$5:$N$5,0),FALSE),0) -> 0 | AA166: =IFERROR(Z166/Z$19,0) -> 0 | AB166: =IFERROR(VLOOKUP($A166,APOIO!$B:$N,MATCH(AB$5,APOIO!$B$5:$N$5,0),FALSE),0) -> 0 | AC166: =IFERROR(AB166/AB$19,0) -> 0 | AD166: =IFERROR(VLOOKUP($A166,APOIO!$B:$N,MATCH(AD$5,APOIO!$B$5:$N$5,0),FALSE),0) -> 0 | AE166: =IFERROR(AD166/AD$19,0) -> 0 | AF166: =SUM(Z166,AB166,AD166) -> 0 | AG166: =IFERROR(AF166/AF$19,0) -> 0 | AH166: =SUM(B166,D166,F166,J166,L166,N166,R166,T166,V166,Z166,AB166,AD166) -> 0 | AI166: =IFERROR(AH166/AH$19,0) -> 0
A167: (-) Despesas Não Operacionais | B167: =IFERROR(VLOOKUP($A167,APOIO!$B:$N,MATCH(B$5,APOIO!$B$5:$N$5,0),FALSE),0) -> 0 | C167: =IFERROR(B167/B$19,0) -> 0 | D167: =IFERROR(VLOOKUP($A167,APOIO!$B:$N,MATCH(D$5,APOIO!$B$5:$N$5,0),FALSE),0) -> 0 | E167: =IFERROR(D167/D$19,0) -> 0 | F167: =IFERROR(VLOOKUP($A167,APOIO!$B:$N,MATCH(F$5,APOIO!$B$5:$N$5,0),FALSE),0) -> 0 | G167: =IFERROR(F167/F$19,0) -> 0 | H167: =SUM(B167,D167,F167) -> 0 | I167: =IFERROR(H167/H$19,0) -> 0 | J167: =IFERROR(VLOOKUP($A167,APOIO!$B:$N,MATCH(J$5,APOIO!$B$5:$N$5,0),FALSE),0) -> 0 | K167: =IFERROR(J167/J$19,0) -> 0 | L167: =IFERROR(VLOOKUP($A167,APOIO!$B:$N,MATCH(L$5,APOIO!$B$5:$N$5,0),FALSE),0) -> 0 | M167: =IFERROR(L167/L$19,0) -> 0 | N167: =IFERROR(VLOOKUP($A167,APOIO!$B:$N,MATCH(N$5,APOIO!$B$5:$N$5,0),FALSE),0) -> 0 | O167: =IFERROR(N167/N$19,0) -> 0 | P167: =SUM(J167,L167,N167) -> 0 | Q167: =IFERROR(P167/P$19,0) -> 0 | R167: =IFERROR(VLOOKUP($A167,APOIO!$B:$N,MATCH(R$5,APOIO!$B$5:$N$5,0),FALSE),0) -> 0 | S167: =IFERROR(R167/R$19,0) -> 0 | T167: =IFERROR(VLOOKUP($A167,APOIO!$B:$N,MATCH(T$5,APOIO!$B$5:$N$5,0),FALSE),0) -> 0 | U167: =IFERROR(T167/T$19,0) -> 0 | V167: =IFERROR(VLOOKUP($A167,APOIO!$B:$N,MATCH(V$5,APOIO!$B$5:$N$5,0),FALSE),0) -> 0 | W167: =IFERROR(V167/V$19,0) -> 0 | X167: =SUM(R167,T167,V167) -> 0 | Y167: =IFERROR(X167/X$19,0) -> 0 | Z167: =IFERROR(VLOOKUP($A167,APOIO!$B:$N,MATCH(Z$5,APOIO!$B$5:$N$5,0),FALSE),0) -> 0 | AA167: =IFERROR(Z167/Z$19,0) -> 0 | AB167: =IFERROR(VLOOKUP($A167,APOIO!$B:$N,MATCH(AB$5,APOIO!$B$5:$N$5,0),FALSE),0) -> 0 | AC167: =IFERROR(AB167/AB$19,0) -> 0 | AD167: =IFERROR(VLOOKUP($A167,APOIO!$B:$N,MATCH(AD$5,APOIO!$B$5:$N$5,0),FALSE),0) -> 0 | AE167: =IFERROR(AD167/AD$19,0) -> 0 | AF167: =SUM(Z167,AB167,AD167) -> 0 | AG167: =IFERROR(AF167/AF$19,0) -> 0 | AH167: =SUM(B167,D167,F167,J167,L167,N167,R167,T167,V167,Z167,AB167,AD167) -> 0 | AI167: =IFERROR(AH167/AH$19,0) -> 0
A168: Despesas Não Operacionais | B168: =IFERROR(VLOOKUP($A168,APOIO!$B:$N,MATCH(B$5,APOIO!$B$5:$N$5,0),FALSE),0) -> 0 | C168: =IFERROR(B168/B$19,0) -> 0 | D168: =IFERROR(VLOOKUP($A168,APOIO!$B:$N,MATCH(D$5,APOIO!$B$5:$N$5,0),FALSE),0) -> 0 | E168: =IFERROR(D168/D$19,0) -> 0 | F168: =IFERROR(VLOOKUP($A168,APOIO!$B:$N,MATCH(F$5,APOIO!$B$5:$N$5,0),FALSE),0) -> 0 | G168: =IFERROR(F168/F$19,0) -> 0 | H168: =SUM(B168,D168,F168) -> 0 | I168: =IFERROR(H168/H$19,0) -> 0 | J168: =IFERROR(VLOOKUP($A168,APOIO!$B:$N,MATCH(J$5,APOIO!$B$5:$N$5,0),FALSE),0) -> 0 | K168: =IFERROR(J168/J$19,0) -> 0 | L168: =IFERROR(VLOOKUP($A168,APOIO!$B:$N,MATCH(L$5,APOIO!$B$5:$N$5,0),FALSE),0) -> 0 | M168: =IFERROR(L168/L$19,0) -> 0 | N168: =IFERROR(VLOOKUP($A168,APOIO!$B:$N,MATCH(N$5,APOIO!$B$5:$N$5,0),FALSE),0) -> 0 | O168: =IFERROR(N168/N$19,0) -> 0 | P168: =SUM(J168,L168,N168) -> 0 | Q168: =IFERROR(P168/P$19,0) -> 0 | R168: =IFERROR(VLOOKUP($A168,APOIO!$B:$N,MATCH(R$5,APOIO!$B$5:$N$5,0),FALSE),0) -> 0 | S168: =IFERROR(R168/R$19,0) -> 0 | T168: =IFERROR(VLOOKUP($A168,APOIO!$B:$N,MATCH(T$5,APOIO!$B$5:$N$5,0),FALSE),0) -> 0 | U168: =IFERROR(T168/T$19,0) -> 0 | V168: =IFERROR(VLOOKUP($A168,APOIO!$B:$N,MATCH(V$5,APOIO!$B$5:$N$5,0),FALSE),0) -> 0 | W168: =IFERROR(V168/V$19,0) -> 0 | X168: =SUM(R168,T168,V168) -> 0 | Y168: =IFERROR(X168/X$19,0) -> 0 | Z168: =IFERROR(VLOOKUP($A168,APOIO!$B:$N,MATCH(Z$5,APOIO!$B$5:$N$5,0),FALSE),0) -> 0 | AA168: =IFERROR(Z168/Z$19,0) -> 0 | AB168: =IFERROR(VLOOKUP($A168,APOIO!$B:$N,MATCH(AB$5,APOIO!$B$5:$N$5,0),FALSE),0) -> 0 | AC168: =IFERROR(AB168/AB$19,0) -> 0 | AD168: =IFERROR(VLOOKUP($A168,APOIO!$B:$N,MATCH(AD$5,APOIO!$B$5:$N$5,0),FALSE),0) -> 0 | AE168: =IFERROR(AD168/AD$19,0) -> 0 | AF168: =SUM(Z168,AB168,AD168) -> 0 | AG168: =IFERROR(AF168/AF$19,0) -> 0 | AH168: =SUM(B168,D168,F168,J168,L168,N168,R168,T168,V168,Z168,AB168,AD168) -> 0 | AI168: =IFERROR(AH168/AH$19,0) -> 0
A169: Parcelamento impostos exercicios anteriores | B169: =IFERROR(VLOOKUP($A169,APOIO!$B:$N,MATCH(B$5,APOIO!$B$5:$N$5,0),FALSE),0) -> 0 | C169: =IFERROR(B169/B$19,0) -> 0 | D169: =IFERROR(VLOOKUP($A169,APOIO!$B:$N,MATCH(D$5,APOIO!$B$5:$N$5,0),FALSE),0) -> 0 | E169: =IFERROR(D169/D$19,0) -> 0 | F169: =IFERROR(VLOOKUP($A169,APOIO!$B:$N,MATCH(F$5,APOIO!$B$5:$N$5,0),FALSE),0) -> 0 | G169: =IFERROR(F169/F$19,0) -> 0 | H169: =SUM(B169,D169,F169) -> 0 | I169: =IFERROR(H169/H$19,0) -> 0 | J169: =IFERROR(VLOOKUP($A169,APOIO!$B:$N,MATCH(J$5,APOIO!$B$5:$N$5,0),FALSE),0) -> 0 | K169: =IFERROR(J169/J$19,0) -> 0 | L169: =IFERROR(VLOOKUP($A169,APOIO!$B:$N,MATCH(L$5,APOIO!$B$5:$N$5,0),FALSE),0) -> 0 | M169: =IFERROR(L169/L$19,0) -> 0 | N169: =IFERROR(VLOOKUP($A169,APOIO!$B:$N,MATCH(N$5,APOIO!$B$5:$N$5,0),FALSE),0) -> 0 | O169: =IFERROR(N169/N$19,0) -> 0 | P169: =SUM(J169,L169,N169) -> 0 | Q169: =IFERROR(P169/P$19,0) -> 0 | R169: =IFERROR(VLOOKUP($A169,APOIO!$B:$N,MATCH(R$5,APOIO!$B$5:$N$5,0),FALSE),0) -> 0 | S169: =IFERROR(R169/R$19,0) -> 0 | T169: =IFERROR(VLOOKUP($A169,APOIO!$B:$N,MATCH(T$5,APOIO!$B$5:$N$5,0),FALSE),0) -> 0 | U169: =IFERROR(T169/T$19,0) -> 0 | V169: =IFERROR(VLOOKUP($A169,APOIO!$B:$N,MATCH(V$5,APOIO!$B$5:$N$5,0),FALSE),0) -> 0 | W169: =IFERROR(V169/V$19,0) -> 0 | X169: =SUM(R169,T169,V169) -> 0 | Y169: =IFERROR(X169/X$19,0) -> 0 | Z169: =IFERROR(VLOOKUP($A169,APOIO!$B:$N,MATCH(Z$5,APOIO!$B$5:$N$5,0),FALSE),0) -> 0 | AA169: =IFERROR(Z169/Z$19,0) -> 0 | AB169: =IFERROR(VLOOKUP($A169,APOIO!$B:$N,MATCH(AB$5,APOIO!$B$5:$N$5,0),FALSE),0) -> 0 | AC169: =IFERROR(AB169/AB$19,0) -> 0 | AD169: =IFERROR(VLOOKUP($A169,APOIO!$B:$N,MATCH(AD$5,APOIO!$B$5:$N$5,0),FALSE),0) -> 0 | AE169: =IFERROR(AD169/AD$19,0) -> 0 | AF169: =SUM(Z169,AB169,AD169) -> 0 | AG169: =IFERROR(AF169/AF$19,0) -> 0 | AH169: =SUM(B169,D169,F169,J169,L169,N169,R169,T169,V169,Z169,AB169,AD169) -> 0 | AI169: =IFERROR(AH169/AH$19,0) -> 0
...

Sheet BD_FLUXO
A1: Data | B1: Histórico | C1: Crédito | D1: Débito | E1: Saldo | F1: Natureza | G1: Centro de Custo - Obra | H1: Ano Fluxo | I1: C. Mês | J1: Mês | K1: Banco | L1: Empresa | M1: Valor | N1: Rubrica | O1: Conta Filho | P1: Conta Pai | Q1: Cod | R1: Ano
A2: 45809 | B2: ALUGUEIS OBRAS | D2: 850 | E2: -850 | F2: 5.3 - ALUGUEL ALOJAMENTO | G2: FOSFATO CMOC CONTRAT | H2: 2025 | I2: 6 | J2: Jun | M2: -850 | N2: ALUGUEL ALOJAMENTO | O2: Despesas com Infraestrutura | P2: (-)Gastos Fixos | Q2: 4 | R2: 2025
A3: 45809 | B3: ALUGUEIS OBRAS | D3: 1100 | E3: -1100 | F3: 5.3 - ALUGUEL ALOJAMENTO | G3: FOSFATO CMOC CONTRAT | H3: 2025 | I3: 6 | J3: Jun | M3: -1100 | N3: ALUGUEL ALOJAMENTO | O3: Despesas com Infraestrutura | P3: (-)Gastos Fixos | Q3: 4 | R3: 2025
A4: 45809 | B4: ALUGUEIS OBRAS | D4: 1200 | E4: -1200 | F4: 5.3 - ALUGUEL ALOJAMENTO | G4: NIOBIO CMOC CONTRATO | H4: 2025 | I4: 6 | J4: Jun | M4: -1200 | N4: ALUGUEL ALOJAMENTO | O4: Despesas com Infraestrutura | P4: (-)Gastos Fixos | Q4: 4 | R4: 2025
A5: 45809 | B5: ALUGUEIS OBRAS | D5: 1000 | E5: -1000 | F5: 5.3 - ALUGUEL ALOJAMENTO | G5: NIOBIO CMOC CONTRATO | H5: 2025 | I5: 6 | J5: Jun | M5: -1000 | N5: ALUGUEL ALOJAMENTO | O5: Despesas com Infraestrutura | P5: (-)Gastos Fixos | Q5: 4 | R5: 2025
A6: 45809 | B6: 74 - MATA FOME REFEICAO COLETIVA LTDA | D6: 6040 | E6: -6040 | F6: 12.5 - REFEIÇÕES FUNCIONARIOS | G6: VLI PINTURA | H6: 2025 | I6: 6 | J6: Jun | M6: -6040 | N6: 12.5 - REFEIÇÕES FUNCIONARIOS | R6: 2025
A7: 45809 | B7: 4947 - LOC RADIO - LOCAÇAO E SERVIÇOS | D7: 390 | E7: -390 | F7: 7.10 - LOCAÇAO RADIOS DE COMUNICAÇÃO | G7: FOSFATO CMOC CONTRAT | H7: 2025 | I7: 6 | J7: Jun | M7: -390 | N7: LOCAÇAO RADIOS DE COMUNICAÇÃO | O7: Despesas com Locações | P7: (-)Gastos Fixos | Q7: 4 | R7: 2025
A8: 45809 | B8: 4947 - LOC RADIO - LOCAÇAO E SERVIÇOS | D8: 390 | E8: -390 | F8: 7.10 - LOCAÇAO RADIOS DE COMUNICAÇÃO | G8: NIOBIO CMOC CONTRATO | H8: 2025 | I8: 6 | J8: Jun | M8: -390 | N8: LOCAÇAO RADIOS DE COMUNICAÇÃO | O8: Despesas com Locações | P8: (-)Gastos Fixos | Q8: 4 | R8: 2025
A9: 45809 | B9: LOC BEM - VILMAR | D9: 1600 | E9: -1600 | F9: 7.2 - LOCAÇÃO COMPRESSORES | G9: MOSAIC ARAXA | H9: 2025 | I9: 6 | J9: Jun | M9: -1600 | N9: LOCAÇÃO COMPRESSORES | O9: Despesas com Locações | P9: (-)Gastos Fixos | Q9: 4 | R9: 2025
A10: 45809 | B10: LOC BEM - VILMAR | D10: 7500 | E10: -7500 | F10: 7.2 - LOCAÇÃO COMPRESSORES | G10: MOSAIC UBERABA CONTRAT0 3 ANOS | H10: 2025 | I10: 6 | J10: Jun | M10: -7500 | N10: LOCAÇÃO COMPRESSORES | O10: Despesas com Locações | P10: (-)Gastos Fixos | Q10: 4 | R10: 2025
A11: 45809 | B11: LOC BEM - VILMAR | D11: 15000 | E11: -15000 | F11: 7.2 - LOCAÇÃO COMPRESSORES | G11: EUROCHEM SERRA DO SALITRE | H11: 2025 | I11: 6 | J11: Jun | M11: -15000 | N11: LOCAÇÃO COMPRESSORES | O11: Despesas com Locações | P11: (-)Gastos Fixos | Q11: 4 | R11: 2025
A12: 45809 | B12: 23923 - SUPORTE LOCAÇOES E SERVIÇOS LTDA | D12: 1350 | E12: -1350 | F12: 7.6 - LOCAÇÃO CONTAINER | G12: MOSAIC UBERABA CONTRAT0 3 ANOS | H12: 2025 | I12: 6 | J12: Jun | M12: -1350 | N12: LOCAÇÃO CONTAINER | O12: Despesas com Locações | P12: (-)Gastos Fixos | Q12: 4 | R12: 2025
A13: 45810 | B13: 811 - CONTEINERES BARRO ALTO LTDA | D13: 1500 | E13: -1500 | F13: 7.6 - LOCAÇÃO CONTAINER | G13: ANGLO AMERICAN | H13: 2025 | I13: 6 | J13: Jun | M13: -1500 | N13: LOCAÇÃO CONTAINER | O13: Despesas com Locações | P13: (-)Gastos Fixos | Q13: 4 | R13: 2025
A14: 45810 | B14: ENCOMENDA DE CATALAO | D14: 220 | E14: -220 | F14: 10.4 - FRETE TRANSPORTADORA | G14: NIOBIO CMOC CONTRATO | H14: 2025 | I14: 6 | J14: Jun | M14: -220 | N14: FRETE TRANSPORTADORA | O14: Fornecedores | P14: (-)Custos Variavéis | Q14: 3 | R14: 2025
A15: 45810 | B15: 1040 - AQUARELA LANCHONETE E CONVENIENCIA LTDA | D15: 3228 | E15: -3228 | F15: 12.5 - REFEIÇÕES FUNCIONARIOS | G15: ANGLO AMERICAN | H15: 2025 | I15: 6 | J15: Jun | M15: -3228 | N15: 12.5 - REFEIÇÕES FUNCIONARIOS | R15: 2025
A16: 45810 | B16: RESTAURANTE EL SHADAY | D16: 64 | E16: -64 | F16: 11.5 - ALIMENTAÇÃO ADM | G16: ADMINISTRATIVO | H16: 2025 | I16: 6 | J16: Jun | M16: -64 | N16: ALIMENTAÇÃO ADM | O16: Despesas com Pessoal | P16: (-)Gastos Fixos | Q16: 4 | R16: 2025
A17: 45810 | B17: REFEIÇÃO OBRAS | D17: 4490 | E17: -4490 | F17: 12.5 - REFEIÇÕES FUNCIONARIOS | G17: NIOBIO CMOC CONTRATO | H17: 2025 | I17: 6 | J17: Jun | M17: -4490 | N17: 12.5 - REFEIÇÕES FUNCIONARIOS | R17: 2025
A18: 45810 | B18: REFEIÇÃO OBRAS | D18: 1896 | E18: -1896 | F18: 12.5 - REFEIÇÕES FUNCIONARIOS | G18: SERENA 21 TORRES 2024 | H18: 2025 | I18: 6 | J18: Jun | M18: -1896 | N18: 12.5 - REFEIÇÕES FUNCIONARIOS | R18: 2025
A19: 45810 | B19: REFEIÇÃO OBRAS | D19: 6700 | E19: -6700 | F19: 12.5 - REFEIÇÕES FUNCIONARIOS | G19: MOSAIC UBERABA CONTRAT0 3 ANOS | H19: 2025 | I19: 6 | J19: Jun | M19: -6700 | N19: 12.5 - REFEIÇÕES FUNCIONARIOS | R19: 2025
A20: 45810 | B20: REFEIÇÃO OBRAS | D20: 3075 | E20: -3075 | F20: 12.5 - REFEIÇÕES FUNCIONARIOS | G20: ANGLO AMERICAN | H20: 2025 | I20: 6 | J20: Jun | M20: -3075 | N20: 12.5 - REFEIÇÕES FUNCIONARIOS | R20: 2025
A21: 45810 | B21: REFEIÇÃO OBRAS | D21: 5817.5 | E21: -5817.5 | F21: 12.5 - REFEIÇÕES FUNCIONARIOS | G21: FOSFATO CMOC CONTRAT | H21: 2025 | I21: 6 | J21: Jun | M21: -5817.5 | N21: 12.5 - REFEIÇÕES FUNCIONARIOS | R21: 2025
A22: 45810 | B22: REFEIÇÃO OBRAS | D22: 3587.5 | E22: -3587.5 | F22: 12.5 - REFEIÇÕES FUNCIONARIOS | G22: EUROCHEM SERRA DO SALITRE | H22: 2025 | I22: 6 | J22: Jun | M22: -3587.5 | N22: 12.5 - REFEIÇÕES FUNCIONARIOS | R22: 2025
A23: 45810 | B23: REFEIÇÃO OBRAS | D23: 12.52 | E23: -12.52 | F23: 11.5 - ALIMENTAÇÃO ADM | G23: ADMINISTRATIVO | H23: 2025 | I23: 6 | J23: Jun | M23: -12.52 | N23: ALIMENTAÇÃO ADM | O23: Despesas com Pessoal | P23: (-)Gastos Fixos | Q23: 4 | R23: 2025
A24: 45810 | B24: PLANETA EMBALAGENS | D24: 355 | E24: -355 | F24: 8.8 - MATERIAIS DE CONSUMO EM OBRAS | G24: ADMINISTRATIVO | H24: 2025 | I24: 6 | J24: Jun | M24: -355 | N24: MATERIAIS DE CONSUMO EM OBRAS | O24: Despesas com Máquinas e Equipamentos | P24: (-)Gastos Fixos | Q24: 4 | R24: 2025
A25: 45810 | B25: 289 - RESTAURANTE MARINA LTDA | D25: 2708 | E25: -2708 | F25: 12.5 - REFEIÇÕES FUNCIONARIOS | G25: VLI PINTURA | H25: 2025 | I25: 6 | J25: Jun | M25: -2708 | N25: 12.5 - REFEIÇÕES FUNCIONARIOS | R25: 2025
A26: 45810 | B26: RIBEIRO REMOÇOES LEVES E PESADOS | D26: 500 | E26: -500 | F26: 10.1 - FRETE MATERIAIS E EQUIPAMENTOS | G26: FOSFATO CMOC CONTRAT | H26: 2025 | I26: 6 | J26: Jun | M26: -500 | N26: FRETE MATERIAIS E EQUIPAMENTOS | O26: Fornecedores | P26: (-)Custos Variavéis | Q26: 3 | R26: 2025
A27: 45810 | B27: GERENCIE SOLUCOES ONLINE LTDA | D27: 195.9 | E27: -195.9 | F27: 11.8 - SISTEMA / SERVIDOR | G27: ADMINISTRATIVO | H27: 2025 | I27: 6 | J27: Jun | M27: -195.9 | N27: SISTEMA / SERVIDOR | O27: Despesas Administrativas | P27: (-)Gastos Fixos | Q27: 4 | R27: 2025
A28: 45810 | B28: IPOG | D28: 1105 | E28: -1105 | F28: 14.2 - CURSOS / TREINAMENTOS | G28: ADMINISTRATIVO | H28: 2025 | I28: 6 | J28: Jun | M28: -1105 | N28: CURSOS / TREINAMENTOS | O28: Despesas com Pessoal | P28: (-)Gastos Fixos | Q28: 4 | R28: 2025
A29: 45810 | B29: IPOG | D29: 1105 | E29: -1105 | F29: 14.2 - CURSOS / TREINAMENTOS | G29: ADMINISTRATIVO | H29: 2025 | I29: 6 | J29: Jun | M29: -1105 | N29: CURSOS / TREINAMENTOS | O29: Despesas com Pessoal | P29: (-)Gastos Fixos | Q29: 4 | R29: 2025
A30: 45810 | B30: 16410 - ENERMONT COMERCIO LTDA | D30: 258.45 | E30: -258.45 | F30: 8.8 - MATERIAIS DE CONSUMO EM OBRAS | G30: MOSAIC UBERABA CONTRAT0 3 ANOS | H30: 2025 | I30: 6 | J30: Jun | M30: -258.45 | N30: MATERIAIS DE CONSUMO EM OBRAS | O30: Despesas com Máquinas e Equipamentos | P30: (-)Gastos Fixos | Q30: 4 | R30: 2025
A31: 45810 | B31: 242 - 52891012 ERIKA BARBOSA DE MENEZES | D31: 175 | E31: -175 | F31: 12.5 - REFEIÇÕES FUNCIONARIOS | G31: MOSAIC ARAXA | H31: 2025 | I31: 6 | J31: Jun | M31: -175 | N31: 12.5 - REFEIÇÕES FUNCIONARIOS | R31: 2025
A32: 45810 | B32: 15847 - QUALI TINTAS | D32: 77.75 | E32: -77.75 | F32: 4.1 - TINTAS E SOLVENTES | G32: ADMINISTRATIVO | H32: 2025 | I32: 6 | J32: Jun | M32: -77.75 | N32: TINTAS E SOLVENTES | O32: Fornecedores | P32: (-)Custos Variavéis | Q32: 3 | R32: 2025
A33: 45810 | B33: 1344 - MATRIX CONSULTORIA E GESTAO DE TREINAMENTO EIRELI | D33: 894.35 | E33: -894.35 | F33: 14.2 - CURSOS / TREINAMENTOS | G33: ANGLO AMERICAN | H33: 2025 | I33: 6 | J33: Jun | M33: -894.35 | N33: CURSOS / TREINAMENTOS | O33: Despesas com Pessoal | P33: (-)Gastos Fixos | Q33: 4 | R33: 2025
A34: 45810 | B34: 1344 - MATRIX CONSULTORIA E GESTAO DE TREINAMENTO EIRELI | D34: 894.35 | E34: -894.35 | F34: 14.2 - CURSOS / TREINAMENTOS | G34: ANGLO AMERICAN | H34: 2025 | I34: 6 | J34: Jun | M34: -894.35 | N34: CURSOS / TREINAMENTOS | O34: Despesas com Pessoal | P34: (-)Gastos Fixos | Q34: 4 | R34: 2025
A35: 45810 | B35: 19020 - POSTO A+ COMERCIO DE COMBUSTIVEL LTDA | D35: 1067.87 | E35: -1067.87 | F35: 8.13 - COMBUSTIVEL EQUIPAMENTOS | G35: VLI PINTURA | H35: 2025 | I35: 6 | J35: Jun | M35: -1067.87 | N35: COMBUSTIVEL EQUIPAMENTOS | O35: Despesas com Máquinas e Equipamentos | P35: (-)Gastos Fixos | Q35: 4 | R35: 2025
A36: 45810 | B36: 19020 - POSTO A+ COMERCIO DE COMBUSTIVEL LTDA | D36: 1457.31 | E36: -1457.31 | F36: 6.4 - COMBUSTIVEL VEICULOS | G36: VLI PINTURA | H36: 2025 | I36: 6 | J36: Jun | M36: -1457.31 | N36: COMBUSTIVEL VEICULOS | O36: Despesas com Veículos e Equipamentos | P36: (-)Gastos Fixos | Q36: 4 | R36: 2025
A37: 45810 | B37: DESPESAS VEICULOS | D37: 250 | E37: -250 | F37: 6.3 - MANUTENÇÃO/PEÇAS VEICULOS | G37: FOSFATO CMOC CONTRAT | H37: 2025 | I37: 6 | J37: Jun | M37: -250 | N37: MANUTENÇÃO/PEÇAS VEICULOS | O37: Despesas com Veículos e Equipamentos | P37: (-)Gastos Fixos | Q37: 4 | R37: 2025
A38: 45810 | B38: FRETE OBRAS | D38: 3200 | E38: -3200 | F38: 10.1 - FRETE MATERIAIS E EQUIPAMENTOS | G38: ADMINISTRATIVO | H38: 2025 | I38: 6 | J38: Jun | M38: -3200 | N38: FRETE MATERIAIS E EQUIPAMENTOS | O38: Fornecedores | P38: (-)Custos Variavéis | Q38: 3 | R38: 2025
A39: 45810 | B39: 12284 - MARCOS CONTAINER LTDA M.E | D39: 500 | E39: -500 | F39: 7.6 - LOCAÇÃO CONTAINER | G39: FOSFATO CMOC CONTRAT | H39: 2025 | I39: 6 | J39: Jun | M39: -500 | N39: LOCAÇÃO CONTAINER | O39: Despesas com Locações | P39: (-)Gastos Fixos | Q39: 4 | R39: 2025
A40: 45810 | B40: 30174 - REDE MAQUINAS COMERCIO E SERVIÇOS DE MAQUINAS | D40: 633.54 | E40: -633.54 | F40: 7.6 - LOCAÇÃO CONTAINER | G40: SERENA 21 TORRES 2024 | H40: 2025 | I40: 6 | J40: Jun | M40: -633.54 | N40: LOCAÇÃO CONTAINER | O40: Despesas com Locações | P40: (-)Gastos Fixos | Q40: 4 | R40: 2025
A41: 45810 | B41: 25122484501 - CAIXA CARTÕES PRÉ-PAGOS S.A | D41: 257.38 | E41: -257.38 | F41: 6.6 - PEDAGIOS | G41: VEICULOS | H41: 2025 | I41: 6 | J41: Jun | M41: -257.38 | N41: PEDAGIOS | O41: Despesas com Veículos e Equipamentos | P41: (-)Gastos Fixos | Q41: 4 | R41: 2025
A42: 45810 | B42: 17043 - POSTO FERREIRA MATIAS COMBUSTIVEL LTDA | D42: 572.22 | E42: -572.22 | F42: 6.4 - COMBUSTIVEL VEICULOS | G42: ANGLO AMERICAN | H42: 2025 | I42: 6 | J42: Jun | M42: -572.22 | N42: COMBUSTIVEL VEICULOS | O42: Despesas com Veículos e Equipamentos | P42: (-)Gastos Fixos | Q42: 4 | R42: 2025
A43: 45810 | B43: BANCO CAIXA | D43: 287.49 | E43: -287.49 | F43: 18.1 - JUROS BANCARIOS | G43: ADMINISTRATIVO | H43: 2025 | I43: 6 | J43: Jun | M43: -287.49 | N43: Juros Bancários | O43: (-) Despesas Financeiras | P43: (+/-)Despesas e Receitas Financeiras | Q43: 6 | R43: 2025
... A45: 45810 | B45: BANCO MERCANTIL | D45: 586.78 | E45: -586.78 | F45: 18.1 - JUROS BANCARIOS | G45: ADMINISTRATIVO | H45: 2025 | I45: 6 | J45: Jun | M45: -586.78 | N45: Juros Bancários | O45: (-) Despesas Financeiras | P45: (+/-)Despesas e Receitas Financeiras | Q45: 6 | R45: 2025
A46: 45810 | B46: 204245 - SODEXO DO BRASIL COMERCIAL S.A | D46: 2540.14 | E46: -2540.14 | F46: 12.5 - REFEIÇÕES FUNCIONARIOS | G46: EUROCHEM SERRA DO SALITRE | H46: 2025 | I46: 6 | J46: Jun | M46: -2540.14 | N46: 12.5 - REFEIÇÕES FUNCIONARIOS | R46: 2025
A47: 45810 | B47: 208746 - ALCON ENGENHARIA DE SISTEMA LTDA | D47: 903.54 | E47: -903.54 | F47: 7.10 - LOCAÇAO RADIOS DE COMUNICAÇÃO | G47: VLI PINTURA | H47: 2025 | I47: 6 | J47: Jun | M47: -903.54 | N47: LOCAÇAO RADIOS DE COMUNICAÇÃO | O47: Despesas com Locações | P47: (-)Gastos Fixos | Q47: 4 | R47: 2025
A48: 45810 | B48: 3337 - JC RESTAURANTE INDUSTRIAL NIQUELANDIA LTDA | D48: 4102.4 | E48: -4102.4 | F48: 12.5 - REFEIÇÕES FUNCIONARIOS | G48: NIOBIO CMOC CONTRATO | H48: 2025 | I48: 6 | J48: Jun | M48: -4102.4 | N48: 12.5 - REFEIÇÕES FUNCIONARIOS | R48: 2025
A49: 45810 | B49: 3338 - JC RESTAURANTE INDUSTRIAL NIQUELANDIA LTDA | D49: 2522 | E49: -2522 | F49: 12.5 - REFEIÇÕES FUNCIONARIOS | G49: FOSFATO CMOC CONTRAT | H49: 2025 | I49: 6 | J49: Jun | M49: -2522 | N49: 12.5 - REFEIÇÕES FUNCIONARIOS | R49: 2025
A50: 45810 | B50: 3339 - JC RESTAURANTE INDUSTRIAL NIQUELANDIA LTDA | D50: 529.4 | E50: -529.4 | F50: 12.5 - REFEIÇÕES FUNCIONARIOS | G50: NIOBIO CMOC CONTRATO | H50: 2025 | I50: 6 | J50: Jun | M50: -529.4 | N50: 12.5 - REFEIÇÕES FUNCIONARIOS | R50: 2025
A51: 45810 | B51: 73287775 - HAPVIDA ASSISTENCIA MEDICA S.A. | D51: 10350.2 | E51: -10350.2 | F51: 12.10 - PLANO DE SAUDE | G51: VLI PINTURA | H51: 2025 | I51: 6 | J51: Jun | M51: -10350.2 | N51: PLANO DE SAUDE | O51: Despesas com Pessoal | P51: (-)Gastos Fixos | Q51: 4 | R51: 2025
A52: 45810 | B52: 247730 - CONCIERGE BLINDADO SERVICOS AUTOMOTIVOS LTDA | D52: 1820.93 | E52: -1820.93 | F52: 3.14 - SERVIÇO TELEMETRIA / FADIGA | G52: VEICULOS | H52: 2025 | I52: 6 | J52: Jun | M52: -1820.93 | N52: SERVIÇO TELEMETRIA / FADIGA | O52: Despesas Administrativas | P52: (-)Gastos Fixos | Q52: 4 | R52: 2025
A53: 45811 | B53: CLINICA OBRAS | D53: 200 | E53: -200 | F53: 3.3 - SERVIÇOS DE CONSULTORIA | G53: ANGLO AMERICAN | H53: 2025 | I53: 6 | J53: Jun | M53: -200 | N53: SERVIÇOS DE CONSULTORIA | O53: Despesas Administrativas | P53: (-)Gastos Fixos | Q53: 4 | R53: 2025
A54: 45811 | B54: ENCOMENDA GOIANÉSIA | D54: 100 | E54: -100 | F54: 12.9 - PASSAGENS FUNCIONARIOS | G54: ANGLO AMERICAN | H54: 2025 | I54: 6 | J54: Jun | M54: -100 | N54: 12.9 - PASSAGENS FUNCIONARIOS | R54: 2025
A55: 45811 | B55: UBER OBRAS | D55: 16.39 | E55: -16.39 | F55: 12.7 - TRANSPORTE FUNCIONARIOS | G55: ADMINISTRATIVO | H55: 2025 | I55: 6 | J55: Jun | M55: -16.39 | N55: 12.7 - TRANSPORTE FUNCIONARIOS | R55: 2025
A56: 45811 | B56: DESPESAS VEICULOS | D56: 40 | E56: -40 | F56: 6.3 - MANUTENÇÃO/PEÇAS VEICULOS | G56: SERENA 21 TORRES 2024 | H56: 2025 | I56: 6 | J56: Jun | M56: -40 | N56: MANUTENÇÃO/PEÇAS VEICULOS | O56: Despesas com Veículos e Equipamentos | P56: (-)Gastos Fixos | Q56: 4 | R56: 2025
A57: 45811 | B57: DESPESAS LOTE TRINDADE AIDEAL | D57: 1100 | E57: -1100 | F57: 15.7 - DESPESAS C/ GALPÃO ALMOXARIFADO | G57: LOTE TRINDADE | H57: 2025 | I57: 6 | J57: Jun | M57: -1100 | N57: Construção da Nova Sede | O57: Investimentos | P57: (-)Investimentos | Q57: 8 | R57: 2025
A58: 45811 | B58: HELIO APARECIDO BIAQUINI | D58: 380 | E58: -380 | F58: 11.14 - INTERNET OBRAS | G58: MOSAIC UBERABA CONTRAT0 3 ANOS | H58: 2025 | I58: 6 | J58: Jun | M58: -380 | N58: INTERNET OBRAS | O58: Despesas com Infraestrutura | P58: (-)Gastos Fixos | Q58: 4 | R58: 2025
A59: 45811 | B59: 982 - SH LOCACAO DE ANDAIMES | D59: 27463.12 | E59: -27463.12 | F59: 7.7 - LOCAÇÃO ANDAIMES | G59: VLI PINTURA | H59: 2025 | I59: 6 | J59: Jun | M59: -27463.12 | N59: LOCAÇÃO ANDAIMES | O59: Despesas com Locações | P59: (-)Gastos Fixos | Q59: 4 | R59: 2025
A60: 45811 | B60: 73590 - CAB INDUSTRIAL LTDA | D60: 152.54 | E60: -152.54 | F60: 13.1 - EPIS | G60: MOSAIC UBERABA CONTRAT0 3 ANOS | H60: 2025 | I60: 6 | J60: Jun | M60: -152.54 | N60: EPIS | O60: Despesas com Pessoal | P60: (-)Gastos Fixos | Q60: 4 | R60: 2025
A61: 45811 | B61: AUTO SOCORRO EZEQUIEL HIDRAULICA | D61: 250 | E61: -250 | F61: 6.3 - MANUTENÇÃO/PEÇAS VEICULOS | G61: FOSFATO CMOC CONTRAT | H61: 2025 | I61: 6 | J61: Jun | M61: -250 | N61: MANUTENÇÃO/PEÇAS VEICULOS | O61: Despesas com Veículos e Equipamentos | P61: (-)Gastos Fixos | Q61: 4 | R61: 2025
A62: 45811 | B62: ALUGUEIS OBRAS | D62: 250 | E62: -250 | F62: 5.5 - ENERGIA ALOJAMENTO | G62: ADMINISTRATIVO | H62: 2025 | I62: 6 | J62: Jun | M62: -250 | N62: ENERGIA ALOJAMENTO | O62: Despesas com Infraestrutura | P62: (-)Gastos Fixos | Q62: 4 | R62: 2025
A63: 45811 | B63: YCARO GOMES | D63: 13.678205 | E63: -13.678205 | F63: 8.10 - MATERIAS DE ESCRITORIO | G63: VLI PINTURA | H63: 2025 | I63: 6 | J63: Jun | M63: -13.678205 | N63: MATERIAS DE ESCRITORIO / PAPELARIA | O63: Despesas Administrativas | P63: (-)Gastos Fixos | Q63: 4 | R63: 2025
A64: 45811 | B64: YCARO GOMES | D64: 64.417357 | E64: -64.417357 | F64: 6.10 - SERVIÇO LAVA JATO | G64: VLI PINTURA | H64: 2025 | I64: 6 | J64: Jun | M64: -64.417357 | N64: SERVIÇO LAVA JATO | O64: Despesas com Veículos e Equipamentos | P64: (-)Gastos Fixos | Q64: 4 | R64: 2025
A65: 45811 | B65: YCARO GOMES | D65: 65.895003 | E65: -65.895003 | F65: 8.14 - MANUTENÇÃO/PEÇAS MAQUINAS E EQUIPAMENTOS | G65: VLI PINTURA | H65: 2025 | I65: 6 | J65: Jun | M65: -65.895003 | N65: MANUTENÇÃO/PEÇAS MAQUINAS E EQUIPAMENTOS | O65: Despesas com Máquinas e Equipamentos | P65: (-)Gastos Fixos | Q65: 4 | R65: 2025
A66: 45811 | B66: YCARO GOMES | D66: 91.354436 | E66: -91.354436 | F66: 5.1 - HOTEL FUNCIONARIOS | G66: VLI PINTURA | H66: 2025 | I66: 6 | J66: Jun | M66: -91.354436 | N66: 5.1 - HOTEL FUNCIONARIOS | R66: 2025
A67: 45811 | B67: YCARO GOMES | D67: 99.840914 | E67: -99.840914 | F67: 3.7 - SERVIÇO LIMPEZA ALOJAMENTO/ESCRITORIO | G67: VLI PINTURA | H67: 2025 | I67: 6 | J67: Jun | M67: -99.840914 | N67: SERVIÇO LIMPEZA ALOJAMENTO/ESCRITORIO | O67: Despesas com Infraestrutura | P67: (-)Gastos Fixos | Q67: 4 | R67: 2025
A68: 45811 | B68: YCARO GOMES | D68: 124.49164 | E68: -124.49164 | F68: 5.5 - ENERGIA ALOJAMENTO | G68: VLI PINTURA | H68: 2025 | I68: 6 | J68: Jun | M68: -124.49164 | N68: ENERGIA ALOJAMENTO | O68: Despesas com Infraestrutura | P68: (-)Gastos Fixos | Q68: 4 | R68: 2025
A69: 45811 | B69: YCARO GOMES | D69: 134.07636 | E69: -134.07636 | F69: 12.5 - REFEIÇÕES FUNCIONARIOS | G69: VLI PINTURA | H69: 2025 | I69: 6 | J69: Jun | M69: -134.07636 | N69: 12.5 - REFEIÇÕES FUNCIONARIOS | R69: 2025
A70: 45811 | B70: YCARO GOMES | D70: 193.32695 | E70: -193.32695 | F70: 11.14 - INTERNET OBRAS | G70: VLI PINTURA | H70: 2025 | I70: 6 | J70: Jun | M70: -193.32695 | N70: INTERNET OBRAS | O70: Despesas com Infraestrutura | P70: (-)Gastos Fixos | Q70: 4 | R70: 2025
A71: 45811 | B71: YCARO GOMES | D71: 237.33683 | E71: -237.33683 | F71: 14.2 - CURSOS / TREINAMENTOS | G71: VLI PINTURA | H71: 2025 | I71: 6 | J71: Jun | M71: -237.33683 | N71: CURSOS / TREINAMENTOS | O71: Despesas com Pessoal | P71: (-)Gastos Fixos | Q71: 4 | R71: 2025
A72: 45811 | B72: YCARO GOMES | D72: 689.29668 | E72: -689.29668 | F72: 6.4 - COMBUSTIVEL VEICULOS | G72: VLI PINTURA | H72: 2025 | I72: 6 | J72: Jun | M72: -689.29668 | N72: COMBUSTIVEL VEICULOS | O72: Despesas com Veículos e Equipamentos | P72: (-)Gastos Fixos | Q72: 4 | R72: 2025
A73: 45811 | B73: YCARO GOMES | D73: 1178.1228 | E73: -1178.1228 | F73: 13.1 - EPIS | G73: VLI PINTURA | H73: 2025 | I73: 6 | J73: Jun | M73: -1178.1228 | N73: EPIS | O73: Despesas com Pessoal | P73: (-)Gastos Fixos | Q73: 4 | R73: 2025
A74: 45811 | B74: YCARO GOMES | D74: 3089.1028 | E74: -3089.1028 | F74: 6.3 - MANUTENÇÃO/PEÇAS VEICULOS | G74: VLI PINTURA | H74: 2025 | I74: 6 | J74: Jun | M74: -3089.1028 | N74: MANUTENÇÃO/PEÇAS VEICULOS | O74: Despesas com Veículos e Equipamentos | P74: (-)Gastos Fixos | Q74: 4 | R74: 2025
A75: 45811 | B75: YCARO GOMES | D75: 13.721794 | E75: -13.721794 | F75: 8.10 - MATERIAS DE ESCRITORIO | G75: VLI PINTURA | H75: 2025 | I75: 6 | J75: Jun | M75: -13.721794 | N75: MATERIAS DE ESCRITORIO / PAPELARIA | O75: Despesas Administrativas | P75: (-)Gastos Fixos | Q75: 4 | R75: 2025
A76: 45811 | B76: YCARO GOMES | D76: 64.622642 | E76: -64.622642 | F76: 6.10 - SERVIÇO LAVA JATO | G76: VLI PINTURA | H76: 2025 | I76: 6 | J76: Jun | M76: -64.622642 | N76: SERVIÇO LAVA JATO | O76: Despesas com Veículos e Equipamentos | P76: (-)Gastos Fixos | Q76: 4 | R76: 2025
A77: 45811 | B77: YCARO GOMES | D77: 66.104996 | E77: -66.104996 | F77: 8.14 - MANUTENÇÃO/PEÇAS MAQUINAS E EQUIPAMENTOS | G77: VLI PINTURA | H77: 2025 | I77: 6 | J77: Jun | M77: -66.104996 | N77: MANUTENÇÃO/PEÇAS MAQUINAS E EQUIPAMENTOS | O77: Despesas com Máquinas e Equipamentos | P77: (-)Gastos Fixos | Q77: 4 | R77: 2025
