Workbook
Name SegmentaçãodeDados_Ano: #N/A
Name SegmentaçãodeDados_Banco: #N/A
Name SegmentaçãodeDados_Empresa: #N/A

Sheet Painel

Sheet Fluxo de Caixa 
B5: FLUXO DE CAIXA DIRETO | D5: JANEIRO | E5: FEVEREIRO | F5: MARÇO | G5: ABRIL | H5: MAIO | I5: JUNHO | J5: JULHO | K5: AGOSTO | L5: SETEMBRO | M5: OUTUBRO | N5: NOVEMBRO | O5: DEZEMBRO | Q5: ACUMULADO
B7: (+) SALDO INICIAL | D7: =SUM(D9:D18) | E7: =D227 | F7: =E227 | G7: =F227 | H7: =G227 | I7: =H227 | J7: =I227 | K7: =J227 | L7: =K227 | ... O7: =N227 | Q7: =D7
C8: Saldo Inicial Aplicações | D8: =IFERROR(INDEX(Apoio!$B:$AB,MATCH($C8,Apoio!$B$1:$B$176,0),MATCH('Fluxo de Caixa '!D$5,Apoio!$B$4:$AB$4,0)),0) | E8: =D228 | F8: =E228 | G8: =F228 | H8: =G228 | I8: =H228 | J8: =I228 | K8: =J228 | L8: =K228 | ... O8: =N228 | Q8: =D8
C9: Saldo Inicial BB | D9: =IFERROR(INDEX(Apoio!$B:$AB,MATCH($C9,Apoio!$B$1:$B$176,0),MATCH('Fluxo de Caixa '!D$5,Apoio!$B$4:$AB$4,0)),0) | E9: =D229 | F9: =E229 | G9: =F229 | H9: =G229 | I9: =H229 | J9: =I229 | K9: =J229 | L9: =K229 | ... O9: =N229 | Q9: =D9
C10: Saldo Inicial CEF | D10: =IFERROR(INDEX(Apoio!$B:$AB,MATCH($C10,Apoio!$B$1:$B$176,0),MATCH('Fluxo de Caixa '!D$5,Apoio!$B$4:$AB$4,0)),0) | E10: =D230 | F10: =E230 | G10: =F230 | H10: =G230 | I10: =H230 | J10: =I230 | K10: =J230 | L10: =K230 | ... O10: =N230 | Q10: =D10
C11: Saldo Inicial Mercantil | D11: =IFERROR(INDEX(Apoio!$B:$AB,MATCH($C11,Apoio!$B$1:$B$176,0),MATCH('Fluxo de Caixa '!D$5,Apoio!$B$4:$AB$4,0)),0) | E11: =IFERROR(INDEX(Apoio!$B:$AB,MATCH($C11,Apoio!$B$1:$B$176,0),MATCH('Fluxo de Caixa '!E$5,Apoio!$B$4:$AB$4,0)),0) | F11: =IFERROR(INDEX(Apoio!$B:$AB,MATCH($C11,Apoio!$B$1:$B$176,0),MATCH('Fluxo de Caixa '!F$5,Apoio!$B$4:$AB$4,0)),0) | G11: =IFERROR(INDEX(Apoio!$B:$AB,MATCH($C11,Apoio!$B$1:$B$176,0),MATCH('Fluxo de Caixa '!G$5,Apoio!$B$4:$AB$4,0)),0) | H11: =IFERROR(INDEX(Apoio!$B:$AB,MATCH($C11,Apoio!$B$1:$B$176,0),MATCH('Fluxo de Caixa '!H$5,Apoio!$B$4:$AB$4,0)),0) | I11: =IFERROR(INDEX(Apoio!$B:$AB,MATCH($C11,Apoio!$B$1:$B$176,0),MATCH('Fluxo de Caixa '!I$5,Apoio!$B$4:$AB$4,0)),0) | J11: =IFERROR(INDEX(Apoio!$B:$AB,MATCH($C11,Apoio!$B$1:$B$176,0),MATCH('Fluxo de Caixa '!J$5,Apoio!$B$4:$AB$4,0)),0) | K11: =IFERROR(INDEX(Apoio!$B:$AB,MATCH($C11,Apoio!$B$1:$B$176,0),MATCH('Fluxo de Caixa '!K$5,Apoio!$B$4:$AB$4,0)),0) | ... P11: =IFERROR(INDEX(Apoio!$B:$AB,MATCH($C11,Apoio!$B$1:$B$176,0),MATCH('Fluxo de Caixa '!P$5,Apoio!$B$4:$AB$4,0)),0) | Q11: =D11
C12: Saldo inicial GC Pay | D12: =IFERROR(INDEX(Apoio!$B:$AB,MATCH($C12,Apoio!$B$1:$B$176,0),MATCH('Fluxo de Caixa '!D$5,Apoio!$B$4:$AB$4,0)),0) | E12: =IFERROR(INDEX(Apoio!$B:$AB,MATCH($C12,Apoio!$B$1:$B$176,0),MATCH('Fluxo de Caixa '!E$5,Apoio!$B$4:$AB$4,0)),0) | F12: =IFERROR(INDEX(Apoio!$B:$AB,MATCH($C12,Apoio!$B$1:$B$176,0),MATCH('Fluxo de Caixa '!F$5,Apoio!$B$4:$AB$4,0)),0) | G12: =IFERROR(INDEX(Apoio!$B:$AB,MATCH($C12,Apoio!$B$1:$B$176,0),MATCH('Fluxo de Caixa '!G$5,Apoio!$B$4:$AB$4,0)),0) | H12: =IFERROR(INDEX(Apoio!$B:$AB,MATCH($C12,Apoio!$B$1:$B$176,0),MATCH('Fluxo de Caixa '!H$5,Apoio!$B$4:$AB$4,0)),0) | I12: =IFERROR(INDEX(Apoio!$B:$AB,MATCH($C12,Apoio!$B$1:$B$176,0),MATCH('Fluxo de Caixa '!I$5,Apoio!$B$4:$AB$4,0)),0) | J12: =IFERROR(INDEX(Apoio!$B:$AB,MATCH($C12,Apoio!$B$1:$B$176,0),MATCH('Fluxo de Caixa '!J$5,Apoio!$B$4:$AB$4,0)),0) | K12: =IFERROR(INDEX(Apoio!$B:$AB,MATCH($C12,Apoio!$B$1:$B$176,0),MATCH('Fluxo de Caixa '!K$5,Apoio!$B$4:$AB$4,0)),0) | ... O12: =IFERROR(INDEX(Apoio!$B:$AB,MATCH($C12,Apoio!$B$1:$B$176,0),MATCH('Fluxo de Caixa '!O$5,Apoio!$B$4:$AB$4,0)),0) | Q12: =D12
C13: Saldo inicial Itau Isolamento | D13: =IFERROR(INDEX(Apoio!$B:$AB,MATCH($C13,Apoio!$B$1:$B$176,0),MATCH('Fluxo de Caixa '!D$5,Apoio!$B$4:$AB$4,0)),0) | E13: =IFERROR(INDEX(Apoio!$B:$AB,MATCH($C13,Apoio!$B$1:$B$176,0),MATCH('Fluxo de Caixa '!E$5,Apoio!$B$4:$AB$4,0)),0) | F13: =IFERROR(INDEX(Apoio!$B:$AB,MATCH($C13,Apoio!$B$1:$B$176,0),MATCH('Fluxo de Caixa '!F$5,Apoio!$B$4:$AB$4,0)),0) | G13: =IFERROR(INDEX(Apoio!$B:$AB,MATCH($C13,Apoio!$B$1:$B$176,0),MATCH('Fluxo de Caixa '!G$5,Apoio!$B$4:$AB$4,0)),0) | H13: =IFERROR(INDEX(Apoio!$B:$AB,MATCH($C13,Apoio!$B$1:$B$176,0),MATCH('Fluxo de Caixa '!H$5,Apoio!$B$4:$AB$4,0)),0) | I13: =IFERROR(INDEX(Apoio!$B:$AB,MATCH($C13,Apoio!$B$1:$B$176,0),MATCH('Fluxo de Caixa '!I$5,Apoio!$B$4:$AB$4,0)),0) | J13: =IFERROR(INDEX(Apoio!$B:$AB,MATCH($C13,Apoio!$B$1:$B$176,0),MATCH('Fluxo de Caixa '!J$5,Apoio!$B$4:$AB$4,0)),0) | K13: =IFERROR(INDEX(Apoio!$B:$AB,MATCH($C13,Apoio!$B$1:$B$176,0),MATCH('Fluxo de Caixa '!K$5,Apoio!$B$4:$AB$4,0)),0) | ... O13: =IFERROR(INDEX(Apoio!$B:$AB,MATCH($C13,Apoio!$B$1:$B$176,0),MATCH('Fluxo de Caixa '!O$5,Apoio!$B$4:$AB$4,0)),0) | Q13: =D13
C14: Saldo inicial permuta | D14: =IFERROR(INDEX(Apoio!$B:$AB,MATCH($C14,Apoio!$B$1:$B$176,0),MATCH('Fluxo de Caixa '!D$5,Apoio!$B$4:$AB$4,0)),0) | E14: =IFERROR(INDEX(Apoio!$B:$AB,MATCH($C14,Apoio!$B$1:$B$176,0),MATCH('Fluxo de Caixa '!E$5,Apoio!$B$4:$AB$4,0)),0) | F14: =IFERROR(INDEX(Apoio!$B:$AB,MATCH($C14,Apoio!$B$1:$B$176,0),MATCH('Fluxo de Caixa '!F$5,Apoio!$B$4:$AB$4,0)),0) | G14: =IFERROR(INDEX(Apoio!$B:$AB,MATCH($C14,Apoio!$B$1:$B$176,0),MATCH('Fluxo de Caixa '!G$5,Apoio!$B$4:$AB$4,0)),0) | H14: =IFERROR(INDEX(Apoio!$B:$AB,MATCH($C14,Apoio!$B$1:$B$176,0),MATCH('Fluxo de Caixa '!H$5,Apoio!$B$4:$AB$4,0)),0) | I14: =IFERROR(INDEX(Apoio!$B:$AB,MATCH($C14,Apoio!$B$1:$B$176,0),MATCH('Fluxo de Caixa '!I$5,Apoio!$B$4:$AB$4,0)),0) | J14: =IFERROR(INDEX(Apoio!$B:$AB,MATCH($C14,Apoio!$B$1:$B$176,0),MATCH('Fluxo de Caixa '!J$5,Apoio!$B$4:$AB$4,0)),0) | K14: =IFERROR(INDEX(Apoio!$B:$AB,MATCH($C14,Apoio!$B$1:$B$176,0),MATCH('Fluxo de Caixa '!K$5,Apoio!$B$4:$AB$4,0)),0) | ... O14: =IFERROR(INDEX(Apoio!$B:$AB,MATCH($C14,Apoio!$B$1:$B$176,0),MATCH('Fluxo de Caixa '!O$5,Apoio!$B$4:$AB$4,0)),0) | Q14: =D14
C15: Saldo Inicial Safra | D15: =IFERROR(INDEX(Apoio!$B:$AB,MATCH($C15,Apoio!$B$1:$B$176,0),MATCH('Fluxo de Caixa '!D$5,Apoio!$B$4:$AB$4,0)),0) | E15: =D235 | F15: =E235 | G15: =F235 | H15: =G235 | I15: =H235 | J15: =I235 | K15: =J235 | L15: =K235 | ... O15: =N235 | Q15: =D15
C16: Saldo Inicial Itau | D16: =IFERROR(INDEX(Apoio!$B:$AB,MATCH($C16,Apoio!$B$1:$B$176,0),MATCH('Fluxo de Caixa '!D$5,Apoio!$B$4:$AB$4,0)),0) | E16: =D236 | F16: =E236 | G16: =F236 | H16: =G236 | I16: =H236 | J16: =I236 | K16: =J236 | L16: =K236 | ... O16: =N236 | Q16: =D16
C17: Saldo Inicial SICOOB | D17: =IFERROR(INDEX(Apoio!$B:$AB,MATCH($C17,Apoio!$B$1:$B$176,0),MATCH('Fluxo de Caixa '!D$5,Apoio!$B$4:$AB$4,0)),0) | E17: =D237 | F17: =E237 | G17: =F237 | H17: =G237 | I17: =H237 | J17: =I237 | K17: =J237 | L17: =K237 | ... O17: =N237
C18: Saldo Inicial Dinheiro | D18: =IFERROR(INDEX(Apoio!$B:$AB,MATCH($C18,Apoio!$B$1:$B$176,0),MATCH('Fluxo de Caixa '!D$5,Apoio!$B$4:$AB$4,0)),0) | E18: =D238 | F18: =E238 | G18: =F238 | H18: =G238 | I18: =H238 | J18: =I238 | K18: =J238 | L18: =K238 | ... O18: =N238 | Q18: =D18
B20: (+) Recebimentos Operacionais | D20: =SUM(D21:D26) | E20: =SUM(E21:E26) | F20: =SUM(F21:F26) | G20: =SUM(G21:G26) | H20: =SUM(H21:H26) | I20: =SUM(I21:I26) | J20: =SUM(J21:J26) | K20: =SUM(K21:K26) | ... O20: =SUM(O21:O26) | Q20: =SUM(Q21:Q26)
C21: Recebimento de Clientes | D21: =IFERROR(INDEX(Apoio!$B:$AB,MATCH($C21,Apoio!$B$1:$B$176,0),MATCH('Fluxo de Caixa '!D$5,Apoio!$B$4:$AB$4,0)),0) | E21: =IFERROR(INDEX(Apoio!$B:$AB,MATCH($C21,Apoio!$B$1:$B$176,0),MATCH('Fluxo de Caixa '!E$5,Apoio!$B$4:$AB$4,0)),0) | F21: =IFERROR(INDEX(Apoio!$B:$AB,MATCH($C21,Apoio!$B$1:$B$176,0),MATCH('Fluxo de Caixa '!F$5,Apoio!$B$4:$AB$4,0)),0) | G21: =IFERROR(INDEX(Apoio!$B:$AB,MATCH($C21,Apoio!$B$1:$B$176,0),MATCH('Fluxo de Caixa '!G$5,Apoio!$B$4:$AB$4,0)),0) | H21: =IFERROR(INDEX(Apoio!$B:$AB,MATCH($C21,Apoio!$B$1:$B$176,0),MATCH('Fluxo de Caixa '!H$5,Apoio!$B$4:$AB$4,0)),0) | I21: =IFERROR(INDEX(Apoio!$B:$AB,MATCH($C21,Apoio!$B$1:$B$176,0),MATCH('Fluxo de Caixa '!I$5,Apoio!$B$4:$AB$4,0)),0) | J21: =IFERROR(INDEX(Apoio!$B:$AB,MATCH($C21,Apoio!$B$1:$B$176,0),MATCH('Fluxo de Caixa '!J$5,Apoio!$B$4:$AB$4,0)),0) | K21: =IFERROR(INDEX(Apoio!$B:$AB,MATCH($C21,Apoio!$B$1:$B$176,0),MATCH('Fluxo de Caixa '!K$5,Apoio!$B$4:$AB$4,0)),0) | ... O21: =IFERROR(INDEX(Apoio!$B:$AB,MATCH($C21,Apoio!$B$1:$B$176,0),MATCH('Fluxo de Caixa '!O$5,Apoio!$B$4:$AB$4,0)),0) | Q21: =SUM(D21:P21)
C22: Serviços Prestados | D22: =IFERROR(INDEX(Apoio!$B:$AB,MATCH($C22,Apoio!$B$1:$B$176,0),MATCH('Fluxo de Caixa '!D$5,Apoio!$B$4:$AB$4,0)),0) | E22: =IFERROR(INDEX(Apoio!$B:$AB,MATCH($C22,Apoio!$B$1:$B$176,0),MATCH('Fluxo de Caixa '!E$5,Apoio!$B$4:$AB$4,0)),0) | F22: =IFERROR(INDEX(Apoio!$B:$AB,MATCH($C22,Apoio!$B$1:$B$176,0),MATCH('Fluxo de Caixa '!F$5,Apoio!$B$4:$AB$4,0)),0) | G22: =IFERROR(INDEX(Apoio!$B:$AB,MATCH($C22,Apoio!$B$1:$B$176,0),MATCH('Fluxo de Caixa '!G$5,Apoio!$B$4:$AB$4,0)),0) | H22: =IFERROR(INDEX(Apoio!$B:$AB,MATCH($C22,Apoio!$B$1:$B$176,0),MATCH('Fluxo de Caixa '!H$5,Apoio!$B$4:$AB$4,0)),0) | I22: =IFERROR(INDEX(Apoio!$B:$AB,MATCH($C22,Apoio!$B$1:$B$176,0),MATCH('Fluxo de Caixa '!I$5,Apoio!$B$4:$AB$4,0)),0) | J22: =IFERROR(INDEX(Apoio!$B:$AB,MATCH($C22,Apoio!$B$1:$B$176,0),MATCH('Fluxo de Caixa '!J$5,Apoio!$B$4:$AB$4,0)),0) | K22: =IFERROR(INDEX(Apoio!$B:$AB,MATCH($C22,Apoio!$B$1:$B$176,0),MATCH('Fluxo de Caixa '!K$5,Apoio!$B$4:$AB$4,0)),0) | ... O22: =IFERROR(INDEX(Apoio!$B:$AB,MATCH($C22,Apoio!$B$1:$B$176,0),MATCH('Fluxo de Caixa '!O$5,Apoio!$B$4:$AB$4,0)),0) | Q22: =SUM(D22:P22)
C23: Dinheiro | D23: =IFERROR(INDEX(Apoio!$B:$AB,MATCH($C23,Apoio!$B$1:$B$176,0),MATCH('Fluxo de Caixa '!D$5,Apoio!$B$4:$AB$4,0)),0) | E23: =IFERROR(INDEX(Apoio!$B:$AB,MATCH($C23,Apoio!$B$1:$B$176,0),MATCH('Fluxo de Caixa '!E$5,Apoio!$B$4:$AB$4,0)),0) | F23: =IFERROR(INDEX(Apoio!$B:$AB,MATCH($C23,Apoio!$B$1:$B$176,0),MATCH('Fluxo de Caixa '!F$5,Apoio!$B$4:$AB$4,0)),0) | G23: =IFERROR(INDEX(Apoio!$B:$AB,MATCH($C23,Apoio!$B$1:$B$176,0),MATCH('Fluxo de Caixa '!G$5,Apoio!$B$4:$AB$4,0)),0) | H23: =IFERROR(INDEX(Apoio!$B:$AB,MATCH($C23,Apoio!$B$1:$B$176,0),MATCH('Fluxo de Caixa '!H$5,Apoio!$B$4:$AB$4,0)),0) | I23: =IFERROR(INDEX(Apoio!$B:$AB,MATCH($C23,Apoio!$B$1:$B$176,0),MATCH('Fluxo de Caixa '!I$5,Apoio!$B$4:$AB$4,0)),0) | J23: =IFERROR(INDEX(Apoio!$B:$AB,MATCH($C23,Apoio!$B$1:$B$176,0),MATCH('Fluxo de Caixa '!J$5,Apoio!$B$4:$AB$4,0)),0) | K23: =IFERROR(INDEX(Apoio!$B:$AB,MATCH($C23,Apoio!$B$1:$B$176,0),MATCH('Fluxo de Caixa '!K$5,Apoio!$B$4:$AB$4,0)),0) | ... O23: =IFERROR(INDEX(Apoio!$B:$AB,MATCH($C23,Apoio!$B$1:$B$176,0),MATCH('Fluxo de Caixa '!O$5,Apoio!$B$4:$AB$4,0)),0) | Q23: =SUM(D23:P23)
C24: Antecipação de Recebíveis | D24: =IFERROR(INDEX(Apoio!$B:$AB,MATCH($C24,Apoio!$B$1:$B$176,0),MATCH('Fluxo de Caixa '!D$5,Apoio!$B$4:$AB$4,0)),0) | E24: =IFERROR(INDEX(Apoio!$B:$AB,MATCH($C24,Apoio!$B$1:$B$176,0),MATCH('Fluxo de Caixa '!E$5,Apoio!$B$4:$AB$4,0)),0) | F24: =IFERROR(INDEX(Apoio!$B:$AB,MATCH($C24,Apoio!$B$1:$B$176,0),MATCH('Fluxo de Caixa '!F$5,Apoio!$B$4:$AB$4,0)),0) | G24: =IFERROR(INDEX(Apoio!$B:$AB,MATCH($C24,Apoio!$B$1:$B$176,0),MATCH('Fluxo de Caixa '!G$5,Apoio!$B$4:$AB$4,0)),0) | H24: =IFERROR(INDEX(Apoio!$B:$AB,MATCH($C24,Apoio!$B$1:$B$176,0),MATCH('Fluxo de Caixa '!H$5,Apoio!$B$4:$AB$4,0)),0) | I24: =IFERROR(INDEX(Apoio!$B:$AB,MATCH($C24,Apoio!$B$1:$B$176,0),MATCH('Fluxo de Caixa '!I$5,Apoio!$B$4:$AB$4,0)),0) | J24: =IFERROR(INDEX(Apoio!$B:$AB,MATCH($C24,Apoio!$B$1:$B$176,0),MATCH('Fluxo de Caixa '!J$5,Apoio!$B$4:$AB$4,0)),0) | K24: =IFERROR(INDEX(Apoio!$B:$AB,MATCH($C24,Apoio!$B$1:$B$176,0),MATCH('Fluxo de Caixa '!K$5,Apoio!$B$4:$AB$4,0)),0) | ... O24: =IFERROR(INDEX(Apoio!$B:$AB,MATCH($C24,Apoio!$B$1:$B$176,0),MATCH('Fluxo de Caixa '!O$5,Apoio!$B$4:$AB$4,0)),0) | Q24: =SUM(D24:P24)
C25: Outras Entradas Operacionais | D25: =IFERROR(INDEX(Apoio!$B:$AB,MATCH($C25,Apoio!$B$1:$B$176,0),MATCH('Fluxo de Caixa '!D$5,Apoio!$B$4:$AB$4,0)),0) | E25: =IFERROR(INDEX(Apoio!$B:$AB,MATCH($C25,Apoio!$B$1:$B$176,0),MATCH('Fluxo de Caixa '!E$5,Apoio!$B$4:$AB$4,0)),0) | F25: =IFERROR(INDEX(Apoio!$B:$AB,MATCH($C25,Apoio!$B$1:$B$176,0),MATCH('Fluxo de Caixa '!F$5,Apoio!$B$4:$AB$4,0)),0) | G25: =IFERROR(INDEX(Apoio!$B:$AB,MATCH($C25,Apoio!$B$1:$B$176,0),MATCH('Fluxo de Caixa '!G$5,Apoio!$B$4:$AB$4,0)),0) | H25: =IFERROR(INDEX(Apoio!$B:$AB,MATCH($C25,Apoio!$B$1:$B$176,0),MATCH('Fluxo de Caixa '!H$5,Apoio!$B$4:$AB$4,0)),0) | I25: =IFERROR(INDEX(Apoio!$B:$AB,MATCH($C25,Apoio!$B$1:$B$176,0),MATCH('Fluxo de Caixa '!I$5,Apoio!$B$4:$AB$4,0)),0) | J25: =IFERROR(INDEX(Apoio!$B:$AB,MATCH($C25,Apoio!$B$1:$B$176,0),MATCH('Fluxo de Caixa '!J$5,Apoio!$B$4:$AB$4,0)),0) | K25: =IFERROR(INDEX(Apoio!$B:$AB,MATCH($C25,Apoio!$B$1:$B$176,0),MATCH('Fluxo de Caixa '!K$5,Apoio!$B$4:$AB$4,0)),0) | ... O25: =IFERROR(INDEX(Apoio!$B:$AB,MATCH($C25,Apoio!$B$1:$B$176,0),MATCH('Fluxo de Caixa '!O$5,Apoio!$B$4:$AB$4,0)),0) | Q25: =SUM(D25:P25)
C26: Ajustes | D26: =IFERROR(INDEX(Apoio!$B:$AB,MATCH($C26,Apoio!$B$1:$B$176,0),MATCH('Fluxo de Caixa '!D$5,Apoio!$B$4:$AB$4,0)),0) | E26: =IFERROR(INDEX(Apoio!$B:$AB,MATCH($C26,Apoio!$B$1:$B$176,0),MATCH('Fluxo de Caixa '!E$5,Apoio!$B$4:$AB$4,0)),0) | F26: =IFERROR(INDEX(Apoio!$B:$AB,MATCH($C26,Apoio!$B$1:$B$176,0),MATCH('Fluxo de Caixa '!F$5,Apoio!$B$4:$AB$4,0)),0) | G26: =IFERROR(INDEX(Apoio!$B:$AB,MATCH($C26,Apoio!$B$1:$B$176,0),MATCH('Fluxo de Caixa '!G$5,Apoio!$B$4:$AB$4,0)),0) | H26: =IFERROR(INDEX(Apoio!$B:$AB,MATCH($C26,Apoio!$B$1:$B$176,0),MATCH('Fluxo de Caixa '!H$5,Apoio!$B$4:$AB$4,0)),0) | I26: =IFERROR(INDEX(Apoio!$B:$AB,MATCH($C26,Apoio!$B$1:$B$176,0),MATCH('Fluxo de Caixa '!I$5,Apoio!$B$4:$AB$4,0)),0) | J26: =IFERROR(INDEX(Apoio!$B:$AB,MATCH($C26,Apoio!$B$1:$B$176,0),MATCH('Fluxo de Caixa '!J$5,Apoio!$B$4:$AB$4,0)),0) | K26: =IFERROR(INDEX(Apoio!$B:$AB,MATCH($C26,Apoio!$B$1:$B$176,0),MATCH('Fluxo de Caixa '!K$5,Apoio!$B$4:$AB$4,0)),0) | ... O26: =IFERROR(INDEX(Apoio!$B:$AB,MATCH($C26,Apoio!$B$1:$B$176,0),MATCH('Fluxo de Caixa '!O$5,Apoio!$B$4:$AB$4,0)),0) | Q26: =SUM(D26:P26)
D27: 0 | Q27: =SUM(D27:P27)
B28: (-) Pagamentos Operacionais | D28: =SUM(D29,D55,D68,D74,D83,D95,D126,D132,D137,D140,D144,D110) | E28: =SUM(E29,E55,E68,E74,E83,E95,E126,E132,E137,E140,E144,E110) | F28: =SUM(F29,F55,F68,F74,F83,F95,F126,F132,F137,F140,F144,F110) | G28: =SUM(G29,G55,G68,G74,G83,G95,G126,G132,G137,G140,G144,G110) | H28: =SUM(H29,H55,H68,H74,H83,H95,H126,H132,H137,H140,H144,H110) | I28: =SUM(I29,I55,I68,I74,I83,I95,I126,I132,I137,I140,I144,I110) | J28: =SUM(J29,J55,J68,J74,J83,J95,J126,J132,J137,J140,J144,J110) | K28: =SUM(K29,K55,K68,K74,K83,K95,K126,K132,K137,K140,K144,K110) | ... O28: =SUM(O29,O55,O68,O74,O83,O95,O126,O132,O137,O140,O144,O110) | Q28: =SUM(Q29,Q55,Q68,Q74,Q83,Q95,Q126,Q132,Q137,Q140,Q144,Q110)
C29: Gastos com Pessoal | D29: =SUM(D30:D53) | E29: =SUM(E30:E53) | F29: =SUM(F30:F53) | G29: =SUM(G30:G53) | H29: =SUM(H30:H53) | I29: =SUM(I30:I53) | J29: =SUM(J30:J53) | K29: =SUM(K30:K53) | ... O29: =SUM(O30:O53) | Q29: =SUM(Q30:Q53)
C30: SALARIO | D30: =IFERROR(INDEX(Apoio!$B:$AB,MATCH($C30,Apoio!$B$1:$B$176,0),MATCH('Fluxo de Caixa '!D$5,Apoio!$B$4:$AB$4,0)+1),0) | E30: =IFERROR(INDEX(Apoio!$B:$AB,MATCH($C30,Apoio!$B$1:$B$176,0),MATCH('Fluxo de Caixa '!E$5,Apoio!$B$4:$AB$4,0)+1),0) | F30: =IFERROR(INDEX(Apoio!$B:$AB,MATCH($C30,Apoio!$B$1:$B$176,0),MATCH('Fluxo de Caixa '!F$5,Apoio!$B$4:$AB$4,0)+1),0) | G30: =IFERROR(INDEX(Apoio!$B:$AB,MATCH($C30,Apoio!$B$1:$B$176,0),MATCH('Fluxo de Caixa '!G$5,Apoio!$B$4:$AB$4,0)+1),0) | H30: =IFERROR(INDEX(Apoio!$B:$AB,MATCH($C30,Apoio!$B$1:$B$176,0),MATCH('Fluxo de Caixa '!H$5,Apoio!$B$4:$AB$4,0)+1),0) | I30: =IFERROR(INDEX(Apoio!$B:$AB,MATCH($C30,Apoio!$B$1:$B$176,0),MATCH('Fluxo de Caixa '!I$5,Apoio!$B$4:$AB$4,0)+1),0) | J30: =IFERROR(INDEX(Apoio!$B:$AB,MATCH($C30,Apoio!$B$1:$B$176,0),MATCH('Fluxo de Caixa '!J$5,Apoio!$B$4:$AB$4,0)+1),0) | K30: =IFERROR(INDEX(Apoio!$B:$AB,MATCH($C30,Apoio!$B$1:$B$176,0),MATCH('Fluxo de Caixa '!K$5,Apoio!$B$4:$AB$4,0)+1),0) | ... O30: =IFERROR(INDEX(Apoio!$B:$AB,MATCH($C30,Apoio!$B$1:$B$176,0),MATCH('Fluxo de Caixa '!O$5,Apoio!$B$4:$AB$4,0)+1),0) | Q30: =SUM(D30:P30)
C31: 13° SALARIO | D31: =IFERROR(INDEX(Apoio!$B:$AB,MATCH($C31,Apoio!$B$1:$B$176,0),MATCH('Fluxo de Caixa '!D$5,Apoio!$B$4:$AB$4,0)+1),0) | E31: =IFERROR(INDEX(Apoio!$B:$AB,MATCH($C31,Apoio!$B$1:$B$176,0),MATCH('Fluxo de Caixa '!E$5,Apoio!$B$4:$AB$4,0)+1),0) | F31: =IFERROR(INDEX(Apoio!$B:$AB,MATCH($C31,Apoio!$B$1:$B$176,0),MATCH('Fluxo de Caixa '!F$5,Apoio!$B$4:$AB$4,0)+1),0) | G31: =IFERROR(INDEX(Apoio!$B:$AB,MATCH($C31,Apoio!$B$1:$B$176,0),MATCH('Fluxo de Caixa '!G$5,Apoio!$B$4:$AB$4,0)+1),0) | H31: =IFERROR(INDEX(Apoio!$B:$AB,MATCH($C31,Apoio!$B$1:$B$176,0),MATCH('Fluxo de Caixa '!H$5,Apoio!$B$4:$AB$4,0)+1),0) | I31: =IFERROR(INDEX(Apoio!$B:$AB,MATCH($C31,Apoio!$B$1:$B$176,0),MATCH('Fluxo de Caixa '!I$5,Apoio!$B$4:$AB$4,0)+1),0) | J31: =IFERROR(INDEX(Apoio!$B:$AB,MATCH($C31,Apoio!$B$1:$B$176,0),MATCH('Fluxo de Caixa '!J$5,Apoio!$B$4:$AB$4,0)+1),0) | K31: =IFERROR(INDEX(Apoio!$B:$AB,MATCH($C31,Apoio!$B$1:$B$176,0),MATCH('Fluxo de Caixa '!K$5,Apoio!$B$4:$AB$4,0)+1),0) | ... O31: =IFERROR(INDEX(Apoio!$B:$AB,MATCH($C31,Apoio!$B$1:$B$176,0),MATCH('Fluxo de Caixa '!O$5,Apoio!$B$4:$AB$4,0)+1),0) | Q31: =SUM(D31:P31)
C32: FERIAS | D32: =IFERROR(INDEX(Apoio!$B:$AB,MATCH($C32,Apoio!$B$1:$B$176,0),MATCH('Fluxo de Caixa '!D$5,Apoio!$B$4:$AB$4,0)+1),0) | E32: =IFERROR(INDEX(Apoio!$B:$AB,MATCH($C32,Apoio!$B$1:$B$176,0),MATCH('Fluxo de Caixa '!E$5,Apoio!$B$4:$AB$4,0)+1),0) | F32: =IFERROR(INDEX(Apoio!$B:$AB,MATCH($C32,Apoio!$B$1:$B$176,0),MATCH('Fluxo de Caixa '!F$5,Apoio!$B$4:$AB$4,0)+1),0) | G32: =IFERROR(INDEX(Apoio!$B:$AB,MATCH($C32,Apoio!$B$1:$B$176,0),MATCH('Fluxo de Caixa '!G$5,Apoio!$B$4:$AB$4,0)+1),0) | H32: =IFERROR(INDEX(Apoio!$B:$AB,MATCH($C32,Apoio!$B$1:$B$176,0),MATCH('Fluxo de Caixa '!H$5,Apoio!$B$4:$AB$4,0)+1),0) | I32: =IFERROR(INDEX(Apoio!$B:$AB,MATCH($C32,Apoio!$B$1:$B$176,0),MATCH('Fluxo de Caixa '!I$5,Apoio!$B$4:$AB$4,0)+1),0) | J32: =IFERROR(INDEX(Apoio!$B:$AB,MATCH($C32,Apoio!$B$1:$B$176,0),MATCH('Fluxo de Caixa '!J$5,Apoio!$B$4:$AB$4,0)+1),0) | K32: =IFERROR(INDEX(Apoio!$B:$AB,MATCH($C32,Apoio!$B$1:$B$176,0),MATCH('Fluxo de Caixa '!K$5,Apoio!$B$4:$AB$4,0)+1),0) | ... O32: =IFERROR(INDEX(Apoio!$B:$AB,MATCH($C32,Apoio!$B$1:$B$176,0),MATCH('Fluxo de Caixa '!O$5,Apoio!$B$4:$AB$4,0)+1),0) | Q32: =SUM(D32:P32)
C33: MULTA RESCISORIAS FGTS | D33: =IFERROR(INDEX(Apoio!$B:$AB,MATCH($C33,Apoio!$B$1:$B$176,0),MATCH('Fluxo de Caixa '!D$5,Apoio!$B$4:$AB$4,0)+1),0) | E33: =IFERROR(INDEX(Apoio!$B:$AB,MATCH($C33,Apoio!$B$1:$B$176,0),MATCH('Fluxo de Caixa '!E$5,Apoio!$B$4:$AB$4,0)+1),0) | F33: =IFERROR(INDEX(Apoio!$B:$AB,MATCH($C33,Apoio!$B$1:$B$176,0),MATCH('Fluxo de Caixa '!F$5,Apoio!$B$4:$AB$4,0)+1),0) | G33: =IFERROR(INDEX(Apoio!$B:$AB,MATCH($C33,Apoio!$B$1:$B$176,0),MATCH('Fluxo de Caixa '!G$5,Apoio!$B$4:$AB$4,0)+1),0) | H33: =IFERROR(INDEX(Apoio!$B:$AB,MATCH($C33,Apoio!$B$1:$B$176,0),MATCH('Fluxo de Caixa '!H$5,Apoio!$B$4:$AB$4,0)+1),0) | I33: =IFERROR(INDEX(Apoio!$B:$AB,MATCH($C33,Apoio!$B$1:$B$176,0),MATCH('Fluxo de Caixa '!I$5,Apoio!$B$4:$AB$4,0)+1),0) | J33: =IFERROR(INDEX(Apoio!$B:$AB,MATCH($C33,Apoio!$B$1:$B$176,0),MATCH('Fluxo de Caixa '!J$5,Apoio!$B$4:$AB$4,0)+1),0) | K33: =IFERROR(INDEX(Apoio!$B:$AB,MATCH($C33,Apoio!$B$1:$B$176,0),MATCH('Fluxo de Caixa '!K$5,Apoio!$B$4:$AB$4,0)+1),0) | ... O33: =IFERROR(INDEX(Apoio!$B:$AB,MATCH($C33,Apoio!$B$1:$B$176,0),MATCH('Fluxo de Caixa '!O$5,Apoio!$B$4:$AB$4,0)+1),0) | Q33: =SUM(D33:P33)
C34: REFEIÇÕES COLABORADORES | D34: =IFERROR(INDEX(Apoio!$B:$AB,MATCH($C34,Apoio!$B$1:$B$176,0),MATCH('Fluxo de Caixa '!D$5,Apoio!$B$4:$AB$4,0)+1),0) | E34: =IFERROR(INDEX(Apoio!$B:$AB,MATCH($C34,Apoio!$B$1:$B$176,0),MATCH('Fluxo de Caixa '!E$5,Apoio!$B$4:$AB$4,0)+1),0) | F34: =IFERROR(INDEX(Apoio!$B:$AB,MATCH($C34,Apoio!$B$1:$B$176,0),MATCH('Fluxo de Caixa '!F$5,Apoio!$B$4:$AB$4,0)+1),0) | G34: =IFERROR(INDEX(Apoio!$B:$AB,MATCH($C34,Apoio!$B$1:$B$176,0),MATCH('Fluxo de Caixa '!G$5,Apoio!$B$4:$AB$4,0)+1),0) | H34: =IFERROR(INDEX(Apoio!$B:$AB,MATCH($C34,Apoio!$B$1:$B$176,0),MATCH('Fluxo de Caixa '!H$5,Apoio!$B$4:$AB$4,0)+1),0) | I34: =IFERROR(INDEX(Apoio!$B:$AB,MATCH($C34,Apoio!$B$1:$B$176,0),MATCH('Fluxo de Caixa '!I$5,Apoio!$B$4:$AB$4,0)+1),0) | J34: =IFERROR(INDEX(Apoio!$B:$AB,MATCH($C34,Apoio!$B$1:$B$176,0),MATCH('Fluxo de Caixa '!J$5,Apoio!$B$4:$AB$4,0)+1),0) | K34: =IFERROR(INDEX(Apoio!$B:$AB,MATCH($C34,Apoio!$B$1:$B$176,0),MATCH('Fluxo de Caixa '!K$5,Apoio!$B$4:$AB$4,0)+1),0) | ... O34: =IFERROR(INDEX(Apoio!$B:$AB,MATCH($C34,Apoio!$B$1:$B$176,0),MATCH('Fluxo de Caixa '!O$5,Apoio!$B$4:$AB$4,0)+1),0) | Q34: =SUM(D34:P34)
C35: ALIMENTAÇÃO ADM | D35: =IFERROR(INDEX(Apoio!$B:$AB,MATCH($C35,Apoio!$B$1:$B$176,0),MATCH('Fluxo de Caixa '!D$5,Apoio!$B$4:$AB$4,0)+1),0) | E35: =IFERROR(INDEX(Apoio!$B:$AB,MATCH($C35,Apoio!$B$1:$B$176,0),MATCH('Fluxo de Caixa '!E$5,Apoio!$B$4:$AB$4,0)+1),0) | F35: =IFERROR(INDEX(Apoio!$B:$AB,MATCH($C35,Apoio!$B$1:$B$176,0),MATCH('Fluxo de Caixa '!F$5,Apoio!$B$4:$AB$4,0)+1),0) | G35: =IFERROR(INDEX(Apoio!$B:$AB,MATCH($C35,Apoio!$B$1:$B$176,0),MATCH('Fluxo de Caixa '!G$5,Apoio!$B$4:$AB$4,0)+1),0) | H35: =IFERROR(INDEX(Apoio!$B:$AB,MATCH($C35,Apoio!$B$1:$B$176,0),MATCH('Fluxo de Caixa '!H$5,Apoio!$B$4:$AB$4,0)+1),0) | I35: =IFERROR(INDEX(Apoio!$B:$AB,MATCH($C35,Apoio!$B$1:$B$176,0),MATCH('Fluxo de Caixa '!I$5,Apoio!$B$4:$AB$4,0)+1),0) | J35: =IFERROR(INDEX(Apoio!$B:$AB,MATCH($C35,Apoio!$B$1:$B$176,0),MATCH('Fluxo de Caixa '!J$5,Apoio!$B$4:$AB$4,0)+1),0) | K35: =IFERROR(INDEX(Apoio!$B:$AB,MATCH($C35,Apoio!$B$1:$B$176,0),MATCH('Fluxo de Caixa '!K$5,Apoio!$B$4:$AB$4,0)+1),0) | ... O35: =IFERROR(INDEX(Apoio!$B:$AB,MATCH($C35,Apoio!$B$1:$B$176,0),MATCH('Fluxo de Caixa '!O$5,Apoio!$B$4:$AB$4,0)+1),0) | Q35: =SUM(D35:P35)
C36: ACERTO RESCISORIOS | D36: =IFERROR(INDEX(Apoio!$B:$AB,MATCH($C36,Apoio!$B$1:$B$176,0),MATCH('Fluxo de Caixa '!D$5,Apoio!$B$4:$AB$4,0)+1),0) | E36: =IFERROR(INDEX(Apoio!$B:$AB,MATCH($C36,Apoio!$B$1:$B$176,0),MATCH('Fluxo de Caixa '!E$5,Apoio!$B$4:$AB$4,0)+1),0) | F36: =IFERROR(INDEX(Apoio!$B:$AB,MATCH($C36,Apoio!$B$1:$B$176,0),MATCH('Fluxo de Caixa '!F$5,Apoio!$B$4:$AB$4,0)+1),0) | G36: =IFERROR(INDEX(Apoio!$B:$AB,MATCH($C36,Apoio!$B$1:$B$176,0),MATCH('Fluxo de Caixa '!G$5,Apoio!$B$4:$AB$4,0)+1),0) | H36: =IFERROR(INDEX(Apoio!$B:$AB,MATCH($C36,Apoio!$B$1:$B$176,0),MATCH('Fluxo de Caixa '!H$5,Apoio!$B$4:$AB$4,0)+1),0) | I36: =IFERROR(INDEX(Apoio!$B:$AB,MATCH($C36,Apoio!$B$1:$B$176,0),MATCH('Fluxo de Caixa '!I$5,Apoio!$B$4:$AB$4,0)+1),0) | J36: =IFERROR(INDEX(Apoio!$B:$AB,MATCH($C36,Apoio!$B$1:$B$176,0),MATCH('Fluxo de Caixa '!J$5,Apoio!$B$4:$AB$4,0)+1),0) | K36: =IFERROR(INDEX(Apoio!$B:$AB,MATCH($C36,Apoio!$B$1:$B$176,0),MATCH('Fluxo de Caixa '!K$5,Apoio!$B$4:$AB$4,0)+1),0) | ... O36: =IFERROR(INDEX(Apoio!$B:$AB,MATCH($C36,Apoio!$B$1:$B$176,0),MATCH('Fluxo de Caixa '!O$5,Apoio!$B$4:$AB$4,0)+1),0) | Q36: =SUM(D36:P36)
C37: TRANSPORTE DE COLABORADORES | D37: =IFERROR(INDEX(Apoio!$B:$AB,MATCH($C37,Apoio!$B$1:$B$176,0),MATCH('Fluxo de Caixa '!D$5,Apoio!$B$4:$AB$4,0)+1),0) | E37: =IFERROR(INDEX(Apoio!$B:$AB,MATCH($C37,Apoio!$B$1:$B$176,0),MATCH('Fluxo de Caixa '!E$5,Apoio!$B$4:$AB$4,0)+1),0) | F37: =IFERROR(INDEX(Apoio!$B:$AB,MATCH($C37,Apoio!$B$1:$B$176,0),MATCH('Fluxo de Caixa '!F$5,Apoio!$B$4:$AB$4,0)+1),0) | G37: =IFERROR(INDEX(Apoio!$B:$AB,MATCH($C37,Apoio!$B$1:$B$176,0),MATCH('Fluxo de Caixa '!G$5,Apoio!$B$4:$AB$4,0)+1),0) | H37: =IFERROR(INDEX(Apoio!$B:$AB,MATCH($C37,Apoio!$B$1:$B$176,0),MATCH('Fluxo de Caixa '!H$5,Apoio!$B$4:$AB$4,0)+1),0) | I37: =IFERROR(INDEX(Apoio!$B:$AB,MATCH($C37,Apoio!$B$1:$B$176,0),MATCH('Fluxo de Caixa '!I$5,Apoio!$B$4:$AB$4,0)+1),0) | J37: =IFERROR(INDEX(Apoio!$B:$AB,MATCH($C37,Apoio!$B$1:$B$176,0),MATCH('Fluxo de Caixa '!J$5,Apoio!$B$4:$AB$4,0)+1),0) | K37: =IFERROR(INDEX(Apoio!$B:$AB,MATCH($C37,Apoio!$B$1:$B$176,0),MATCH('Fluxo de Caixa '!K$5,Apoio!$B$4:$AB$4,0)+1),0) | ... O37: =IFERROR(INDEX(Apoio!$B:$AB,MATCH($C37,Apoio!$B$1:$B$176,0),MATCH('Fluxo de Caixa '!O$5,Apoio!$B$4:$AB$4,0)+1),0) | Q37: =SUM(D37:P37)
C38: SINDICATO | D38: =IFERROR(INDEX(Apoio!$B:$AB,MATCH($C38,Apoio!$B$1:$B$176,0),MATCH('Fluxo de Caixa '!D$5,Apoio!$B$4:$AB$4,0)+1),0) | E38: =IFERROR(INDEX(Apoio!$B:$AB,MATCH($C38,Apoio!$B$1:$B$176,0),MATCH('Fluxo de Caixa '!E$5,Apoio!$B$4:$AB$4,0)+1),0) | F38: =IFERROR(INDEX(Apoio!$B:$AB,MATCH($C38,Apoio!$B$1:$B$176,0),MATCH('Fluxo de Caixa '!F$5,Apoio!$B$4:$AB$4,0)+1),0) | G38: =IFERROR(INDEX(Apoio!$B:$AB,MATCH($C38,Apoio!$B$1:$B$176,0),MATCH('Fluxo de Caixa '!G$5,Apoio!$B$4:$AB$4,0)+1),0) | H38: =IFERROR(INDEX(Apoio!$B:$AB,MATCH($C38,Apoio!$B$1:$B$176,0),MATCH('Fluxo de Caixa '!H$5,Apoio!$B$4:$AB$4,0)+1),0) | I38: =IFERROR(INDEX(Apoio!$B:$AB,MATCH($C38,Apoio!$B$1:$B$176,0),MATCH('Fluxo de Caixa '!I$5,Apoio!$B$4:$AB$4,0)+1),0) | J38: =IFERROR(INDEX(Apoio!$B:$AB,MATCH($C38,Apoio!$B$1:$B$176,0),MATCH('Fluxo de Caixa '!J$5,Apoio!$B$4:$AB$4,0)+1),0) | K38: =IFERROR(INDEX(Apoio!$B:$AB,MATCH($C38,Apoio!$B$1:$B$176,0),MATCH('Fluxo de Caixa '!K$5,Apoio!$B$4:$AB$4,0)+1),0) | ... O38: =IFERROR(INDEX(Apoio!$B:$AB,MATCH($C38,Apoio!$B$1:$B$176,0),MATCH('Fluxo de Caixa '!O$5,Apoio!$B$4:$AB$4,0)+1),0) | Q38: =SUM(D38:P38)
C39: PASSAGENS COLABORADORES | D39: =IFERROR(INDEX(Apoio!$B:$AB,MATCH($C39,Apoio!$B$1:$B$176,0),MATCH('Fluxo de Caixa '!D$5,Apoio!$B$4:$AB$4,0)+1),0) | E39: =IFERROR(INDEX(Apoio!$B:$AB,MATCH($C39,Apoio!$B$1:$B$176,0),MATCH('Fluxo de Caixa '!E$5,Apoio!$B$4:$AB$4,0)+1),0) | F39: =IFERROR(INDEX(Apoio!$B:$AB,MATCH($C39,Apoio!$B$1:$B$176,0),MATCH('Fluxo de Caixa '!F$5,Apoio!$B$4:$AB$4,0)+1),0) | G39: =IFERROR(INDEX(Apoio!$B:$AB,MATCH($C39,Apoio!$B$1:$B$176,0),MATCH('Fluxo de Caixa '!G$5,Apoio!$B$4:$AB$4,0)+1),0) | H39: =IFERROR(INDEX(Apoio!$B:$AB,MATCH($C39,Apoio!$B$1:$B$176,0),MATCH('Fluxo de Caixa '!H$5,Apoio!$B$4:$AB$4,0)+1),0) | I39: =IFERROR(INDEX(Apoio!$B:$AB,MATCH($C39,Apoio!$B$1:$B$176,0),MATCH('Fluxo de Caixa '!I$5,Apoio!$B$4:$AB$4,0)+1),0) | J39: =IFERROR(INDEX(Apoio!$B:$AB,MATCH($C39,Apoio!$B$1:$B$176,0),MATCH('Fluxo de Caixa '!J$5,Apoio!$B$4:$AB$4,0)+1),0) | K39: =IFERROR(INDEX(Apoio!$B:$AB,MATCH($C39,Apoio!$B$1:$B$176,0),MATCH('Fluxo de Caixa '!K$5,Apoio!$B$4:$AB$4,0)+1),0) | ... O39: =IFERROR(INDEX(Apoio!$B:$AB,MATCH($C39,Apoio!$B$1:$B$176,0),MATCH('Fluxo de Caixa '!O$5,Apoio!$B$4:$AB$4,0)+1),0) | Q39: =SUM(D39:P39)
C40: PLANO DE SAUDE | D40: =IFERROR(INDEX(Apoio!$B:$AB,MATCH($C40,Apoio!$B$1:$B$176,0),MATCH('Fluxo de Caixa '!D$5,Apoio!$B$4:$AB$4,0)+1),0) | E40: =IFERROR(INDEX(Apoio!$B:$AB,MATCH($C40,Apoio!$B$1:$B$176,0),MATCH('Fluxo de Caixa '!E$5,Apoio!$B$4:$AB$4,0)+1),0) | F40: =IFERROR(INDEX(Apoio!$B:$AB,MATCH($C40,Apoio!$B$1:$B$176,0),MATCH('Fluxo de Caixa '!F$5,Apoio!$B$4:$AB$4,0)+1),0) | G40: =IFERROR(INDEX(Apoio!$B:$AB,MATCH($C40,Apoio!$B$1:$B$176,0),MATCH('Fluxo de Caixa '!G$5,Apoio!$B$4:$AB$4,0)+1),0) | H40: =IFERROR(INDEX(Apoio!$B:$AB,MATCH($C40,Apoio!$B$1:$B$176,0),MATCH('Fluxo de Caixa '!H$5,Apoio!$B$4:$AB$4,0)+1),0) | I40: =IFERROR(INDEX(Apoio!$B:$AB,MATCH($C40,Apoio!$B$1:$B$176,0),MATCH('Fluxo de Caixa '!I$5,Apoio!$B$4:$AB$4,0)+1),0) | J40: =IFERROR(INDEX(Apoio!$B:$AB,MATCH($C40,Apoio!$B$1:$B$176,0),MATCH('Fluxo de Caixa '!J$5,Apoio!$B$4:$AB$4,0)+1),0) | K40: =IFERROR(INDEX(Apoio!$B:$AB,MATCH($C40,Apoio!$B$1:$B$176,0),MATCH('Fluxo de Caixa '!K$5,Apoio!$B$4:$AB$4,0)+1),0) | ... O40: =IFERROR(INDEX(Apoio!$B:$AB,MATCH($C40,Apoio!$B$1:$B$176,0),MATCH('Fluxo de Caixa '!O$5,Apoio!$B$4:$AB$4,0)+1),0) | Q40: =SUM(D40:P40)
C41: ASSISTENCIA MEDICA ADM | D41: =IFERROR(INDEX(Apoio!$B:$AB,MATCH($C41,Apoio!$B$1:$B$176,0),MATCH('Fluxo de Caixa '!D$5,Apoio!$B$4:$AB$4,0)+1),0) | E41: =IFERROR(INDEX(Apoio!$B:$AB,MATCH($C41,Apoio!$B$1:$B$176,0),MATCH('Fluxo de Caixa '!E$5,Apoio!$B$4:$AB$4,0)+1),0) | F41: =IFERROR(INDEX(Apoio!$B:$AB,MATCH($C41,Apoio!$B$1:$B$176,0),MATCH('Fluxo de Caixa '!F$5,Apoio!$B$4:$AB$4,0)+1),0) | G41: =IFERROR(INDEX(Apoio!$B:$AB,MATCH($C41,Apoio!$B$1:$B$176,0),MATCH('Fluxo de Caixa '!G$5,Apoio!$B$4:$AB$4,0)+1),0) | H41: =IFERROR(INDEX(Apoio!$B:$AB,MATCH($C41,Apoio!$B$1:$B$176,0),MATCH('Fluxo de Caixa '!H$5,Apoio!$B$4:$AB$4,0)+1),0) | I41: =IFERROR(INDEX(Apoio!$B:$AB,MATCH($C41,Apoio!$B$1:$B$176,0),MATCH('Fluxo de Caixa '!I$5,Apoio!$B$4:$AB$4,0)+1),0) | J41: =IFERROR(INDEX(Apoio!$B:$AB,MATCH($C41,Apoio!$B$1:$B$176,0),MATCH('Fluxo de Caixa '!J$5,Apoio!$B$4:$AB$4,0)+1),0) | K41: =IFERROR(INDEX(Apoio!$B:$AB,MATCH($C41,Apoio!$B$1:$B$176,0),MATCH('Fluxo de Caixa '!K$5,Apoio!$B$4:$AB$4,0)+1),0) | ... O41: =IFERROR(INDEX(Apoio!$B:$AB,MATCH($C41,Apoio!$B$1:$B$176,0),MATCH('Fluxo de Caixa '!O$5,Apoio!$B$4:$AB$4,0)+1),0) | Q41: =SUM(D41:P41)
... C53: PROGRAMA DE SEGURANÇA DO TRABALHO | D53: =IFERROR(INDEX(Apoio!$B:$AB,MATCH($C53,Apoio!$B$1:$B$176,0),MATCH('Fluxo de Caixa '!D$5,Apoio!$B$4:$AB$4,0)+1),0) | E53: =IFERROR(INDEX(Apoio!$B:$AB,MATCH($C53,Apoio!$B$1:$B$176,0),MATCH('Fluxo de Caixa '!E$5,Apoio!$B$4:$AB$4,0)+1),0) | F53: =IFERROR(INDEX(Apoio!$B:$AB,MATCH($C53,Apoio!$B$1:$B$176,0),MATCH('Fluxo de Caixa '!F$5,Apoio!$B$4:$AB$4,0)+1),0) | G53: =IFERROR(INDEX(Apoio!$B:$AB,MATCH($C53,Apoio!$B$1:$B$176,0),MATCH('Fluxo de Caixa '!G$5,Apoio!$B$4:$AB$4,0)+1),0) | H53: =IFERROR(INDEX(Apoio!$B:$AB,MATCH($C53,Apoio!$B$1:$B$176,0),MATCH('Fluxo de Caixa '!H$5,Apoio!$B$4:$AB$4,0)+1),0) | I53: =IFERROR(INDEX(Apoio!$B:$AB,MATCH($C53,Apoio!$B$1:$B$176,0),MATCH('Fluxo de Caixa '!I$5,Apoio!$B$4:$AB$4,0)+1),0) | J53: =IFERROR(INDEX(Apoio!$B:$AB,MATCH($C53,Apoio!$B$1:$B$176,0),MATCH('Fluxo de Caixa '!J$5,Apoio!$B$4:$AB$4,0)+1),0) | K53: =IFERROR(INDEX(Apoio!$B:$AB,MATCH($C53,Apoio!$B$1:$B$176,0),MATCH('Fluxo de Caixa '!K$5,Apoio!$B$4:$AB$4,0)+1),0) | ... O53: =IFERROR(INDEX(Apoio!$B:$AB,MATCH($C53,Apoio!$B$1:$B$176,0),MATCH('Fluxo de Caixa '!O$5,Apoio!$B$4:$AB$4,0)+1),0) | Q53: =SUM(D53:P53)
C55: Gastos com Instalações | D55: =SUM(D56:D66) | E55: =SUM(E56:E66) | F55: =SUM(F56:F66) | G55: =SUM(G56:G66) | H55: =SUM(H56:H66) | I55: =SUM(I56:I66) | J55: =SUM(J56:J66) | K55: =SUM(K56:K66) | ... O55: =SUM(O56:O66) | Q55: =SUM(Q56:Q66)
C56: ALUGUEL ALOJAMENTO | D56: =IFERROR(INDEX(Apoio!$B:$AB,MATCH($C56,Apoio!$B$1:$B$176,0),MATCH('Fluxo de Caixa '!D$5,Apoio!$B$4:$AB$4,0)+1),0) | E56: =IFERROR(INDEX(Apoio!$B:$AB,MATCH($C56,Apoio!$B$1:$B$176,0),MATCH('Fluxo de Caixa '!E$5,Apoio!$B$4:$AB$4,0)+1),0) | F56: =IFERROR(INDEX(Apoio!$B:$AB,MATCH($C56,Apoio!$B$1:$B$176,0),MATCH('Fluxo de Caixa '!F$5,Apoio!$B$4:$AB$4,0)+1),0) | G56: =IFERROR(INDEX(Apoio!$B:$AB,MATCH($C56,Apoio!$B$1:$B$176,0),MATCH('Fluxo de Caixa '!G$5,Apoio!$B$4:$AB$4,0)+1),0) | H56: =IFERROR(INDEX(Apoio!$B:$AB,MATCH($C56,Apoio!$B$1:$B$176,0),MATCH('Fluxo de Caixa '!H$5,Apoio!$B$4:$AB$4,0)+1),0) | I56: =IFERROR(INDEX(Apoio!$B:$AB,MATCH($C56,Apoio!$B$1:$B$176,0),MATCH('Fluxo de Caixa '!I$5,Apoio!$B$4:$AB$4,0)+1),0) | J56: =IFERROR(INDEX(Apoio!$B:$AB,MATCH($C56,Apoio!$B$1:$B$176,0),MATCH('Fluxo de Caixa '!J$5,Apoio!$B$4:$AB$4,0)+1),0) | K56: =IFERROR(INDEX(Apoio!$B:$AB,MATCH($C56,Apoio!$B$1:$B$176,0),MATCH('Fluxo de Caixa '!K$5,Apoio!$B$4:$AB$4,0)+1),0) | ... O56: =IFERROR(INDEX(Apoio!$B:$AB,MATCH($C56,Apoio!$B$1:$B$176,0),MATCH('Fluxo de Caixa '!O$5,Apoio!$B$4:$AB$4,0)+1),0) | Q56: =SUM(D56:P56)
C57: AGUA ALOJAMENTO | D57: =IFERROR(INDEX(Apoio!$B:$AB,MATCH($C57,Apoio!$B$1:$B$176,0),MATCH('Fluxo de Caixa '!D$5,Apoio!$B$4:$AB$4,0)+1),0) | E57: =IFERROR(INDEX(Apoio!$B:$AB,MATCH($C57,Apoio!$B$1:$B$176,0),MATCH('Fluxo de Caixa '!E$5,Apoio!$B$4:$AB$4,0)+1),0) | F57: =IFERROR(INDEX(Apoio!$B:$AB,MATCH($C57,Apoio!$B$1:$B$176,0),MATCH('Fluxo de Caixa '!F$5,Apoio!$B$4:$AB$4,0)+1),0) | G57: =IFERROR(INDEX(Apoio!$B:$AB,MATCH($C57,Apoio!$B$1:$B$176,0),MATCH('Fluxo de Caixa '!G$5,Apoio!$B$4:$AB$4,0)+1),0) | H57: =IFERROR(INDEX(Apoio!$B:$AB,MATCH($C57,Apoio!$B$1:$B$176,0),MATCH('Fluxo de Caixa '!H$5,Apoio!$B$4:$AB$4,0)+1),0) | I57: =IFERROR(INDEX(Apoio!$B:$AB,MATCH($C57,Apoio!$B$1:$B$176,0),MATCH('Fluxo de Caixa '!I$5,Apoio!$B$4:$AB$4,0)+1),0) | J57: =IFERROR(INDEX(Apoio!$B:$AB,MATCH($C57,Apoio!$B$1:$B$176,0),MATCH('Fluxo de Caixa '!J$5,Apoio!$B$4:$AB$4,0)+1),0) | K57: =IFERROR(INDEX(Apoio!$B:$AB,MATCH($C57,Apoio!$B$1:$B$176,0),MATCH('Fluxo de Caixa '!K$5,Apoio!$B$4:$AB$4,0)+1),0) | ... O57: =IFERROR(INDEX(Apoio!$B:$AB,MATCH($C57,Apoio!$B$1:$B$176,0),MATCH('Fluxo de Caixa '!O$5,Apoio!$B$4:$AB$4,0)+1),0) | Q57: =SUM(D57:P57)
C58: ENERGIA ALOJAMENTO | D58: =IFERROR(INDEX(Apoio!$B:$AB,MATCH($C58,Apoio!$B$1:$B$176,0),MATCH('Fluxo de Caixa '!D$5,Apoio!$B$4:$AB$4,0)+1),0) | E58: =IFERROR(INDEX(Apoio!$B:$AB,MATCH($C58,Apoio!$B$1:$B$176,0),MATCH('Fluxo de Caixa '!E$5,Apoio!$B$4:$AB$4,0)+1),0) | F58: =IFERROR(INDEX(Apoio!$B:$AB,MATCH($C58,Apoio!$B$1:$B$176,0),MATCH('Fluxo de Caixa '!F$5,Apoio!$B$4:$AB$4,0)+1),0) | G58: =IFERROR(INDEX(Apoio!$B:$AB,MATCH($C58,Apoio!$B$1:$B$176,0),MATCH('Fluxo de Caixa '!G$5,Apoio!$B$4:$AB$4,0)+1),0) | H58: =IFERROR(INDEX(Apoio!$B:$AB,MATCH($C58,Apoio!$B$1:$B$176,0),MATCH('Fluxo de Caixa '!H$5,Apoio!$B$4:$AB$4,0)+1),0) | I58: =IFERROR(INDEX(Apoio!$B:$AB,MATCH($C58,Apoio!$B$1:$B$176,0),MATCH('Fluxo de Caixa '!I$5,Apoio!$B$4:$AB$4,0)+1),0) | J58: =IFERROR(INDEX(Apoio!$B:$AB,MATCH($C58,Apoio!$B$1:$B$176,0),MATCH('Fluxo de Caixa '!J$5,Apoio!$B$4:$AB$4,0)+1),0) | K58: =IFERROR(INDEX(Apoio!$B:$AB,MATCH($C58,Apoio!$B$1:$B$176,0),MATCH('Fluxo de Caixa '!K$5,Apoio!$B$4:$AB$4,0)+1),0) | ... O58: =IFERROR(INDEX(Apoio!$B:$AB,MATCH($C58,Apoio!$B$1:$B$176,0),MATCH('Fluxo de Caixa '!O$5,Apoio!$B$4:$AB$4,0)+1),0) | Q58: =SUM(D58:P58)
C59: MOVEIS OBRAS | D59: =IFERROR(INDEX(Apoio!$B:$AB,MATCH($C59,Apoio!$B$1:$B$176,0),MATCH('Fluxo de Caixa '!D$5,Apoio!$B$4:$AB$4,0)+1),0) | E59: =IFERROR(INDEX(Apoio!$B:$AB,MATCH($C59,Apoio!$B$1:$B$176,0),MATCH('Fluxo de Caixa '!E$5,Apoio!$B$4:$AB$4,0)+1),0) | F59: =IFERROR(INDEX(Apoio!$B:$AB,MATCH($C59,Apoio!$B$1:$B$176,0),MATCH('Fluxo de Caixa '!F$5,Apoio!$B$4:$AB$4,0)+1),0) | G59: =IFERROR(INDEX(Apoio!$B:$AB,MATCH($C59,Apoio!$B$1:$B$176,0),MATCH('Fluxo de Caixa '!G$5,Apoio!$B$4:$AB$4,0)+1),0) | H59: =IFERROR(INDEX(Apoio!$B:$AB,MATCH($C59,Apoio!$B$1:$B$176,0),MATCH('Fluxo de Caixa '!H$5,Apoio!$B$4:$AB$4,0)+1),0) | I59: =IFERROR(INDEX(Apoio!$B:$AB,MATCH($C59,Apoio!$B$1:$B$176,0),MATCH('Fluxo de Caixa '!I$5,Apoio!$B$4:$AB$4,0)+1),0) | J59: =IFERROR(INDEX(Apoio!$B:$AB,MATCH($C59,Apoio!$B$1:$B$176,0),MATCH('Fluxo de Caixa '!J$5,Apoio!$B$4:$AB$4,0)+1),0) | K59: =IFERROR(INDEX(Apoio!$B:$AB,MATCH($C59,Apoio!$B$1:$B$176,0),MATCH('Fluxo de Caixa '!K$5,Apoio!$B$4:$AB$4,0)+1),0) | ... O59: =IFERROR(INDEX(Apoio!$B:$AB,MATCH($C59,Apoio!$B$1:$B$176,0),MATCH('Fluxo de Caixa '!O$5,Apoio!$B$4:$AB$4,0)+1),0) | Q59: =SUM(D59:P59)
C60: SERVIÇO LIMPEZA ALOJAMENTO/ESCRITORIO | D60: =IFERROR(INDEX(Apoio!$B:$AB,MATCH($C60,Apoio!$B$1:$B$176,0),MATCH('Fluxo de Caixa '!D$5,Apoio!$B$4:$AB$4,0)+1),0) | E60: =IFERROR(INDEX(Apoio!$B:$AB,MATCH($C60,Apoio!$B$1:$B$176,0),MATCH('Fluxo de Caixa '!E$5,Apoio!$B$4:$AB$4,0)+1),0) | F60: =IFERROR(INDEX(Apoio!$B:$AB,MATCH($C60,Apoio!$B$1:$B$176,0),MATCH('Fluxo de Caixa '!F$5,Apoio!$B$4:$AB$4,0)+1),0) | G60: =IFERROR(INDEX(Apoio!$B:$AB,MATCH($C60,Apoio!$B$1:$B$176,0),MATCH('Fluxo de Caixa '!G$5,Apoio!$B$4:$AB$4,0)+1),0) | H60: =IFERROR(INDEX(Apoio!$B:$AB,MATCH($C60,Apoio!$B$1:$B$176,0),MATCH('Fluxo de Caixa '!H$5,Apoio!$B$4:$AB$4,0)+1),0) | I60: =IFERROR(INDEX(Apoio!$B:$AB,MATCH($C60,Apoio!$B$1:$B$176,0),MATCH('Fluxo de Caixa '!I$5,Apoio!$B$4:$AB$4,0)+1),0) | J60: =IFERROR(INDEX(Apoio!$B:$AB,MATCH($C60,Apoio!$B$1:$B$176,0),MATCH('Fluxo de Caixa '!J$5,Apoio!$B$4:$AB$4,0)+1),0) | K60: =IFERROR(INDEX(Apoio!$B:$AB,MATCH($C60,Apoio!$B$1:$B$176,0),MATCH('Fluxo de Caixa '!K$5,Apoio!$B$4:$AB$4,0)+1),0) | ... O60: =IFERROR(INDEX(Apoio!$B:$AB,MATCH($C60,Apoio!$B$1:$B$176,0),MATCH('Fluxo de Caixa '!O$5,Apoio!$B$4:$AB$4,0)+1),0) | Q60: =SUM(D60:P60)
C61: ALUGUEIS ADM | D61: =IFERROR(INDEX(Apoio!$B:$AB,MATCH($C61,Apoio!$B$1:$B$176,0),MATCH('Fluxo de Caixa '!D$5,Apoio!$B$4:$AB$4,0)+1),0) | E61: =IFERROR(INDEX(Apoio!$B:$AB,MATCH($C61,Apoio!$B$1:$B$176,0),MATCH('Fluxo de Caixa '!E$5,Apoio!$B$4:$AB$4,0)+1),0) | F61: =IFERROR(INDEX(Apoio!$B:$AB,MATCH($C61,Apoio!$B$1:$B$176,0),MATCH('Fluxo de Caixa '!F$5,Apoio!$B$4:$AB$4,0)+1),0) | G61: =IFERROR(INDEX(Apoio!$B:$AB,MATCH($C61,Apoio!$B$1:$B$176,0),MATCH('Fluxo de Caixa '!G$5,Apoio!$B$4:$AB$4,0)+1),0) | H61: =IFERROR(INDEX(Apoio!$B:$AB,MATCH($C61,Apoio!$B$1:$B$176,0),MATCH('Fluxo de Caixa '!H$5,Apoio!$B$4:$AB$4,0)+1),0) | I61: =IFERROR(INDEX(Apoio!$B:$AB,MATCH($C61,Apoio!$B$1:$B$176,0),MATCH('Fluxo de Caixa '!I$5,Apoio!$B$4:$AB$4,0)+1),0) | J61: =IFERROR(INDEX(Apoio!$B:$AB,MATCH($C61,Apoio!$B$1:$B$176,0),MATCH('Fluxo de Caixa '!J$5,Apoio!$B$4:$AB$4,0)+1),0) | K61: =IFERROR(INDEX(Apoio!$B:$AB,MATCH($C61,Apoio!$B$1:$B$176,0),MATCH('Fluxo de Caixa '!K$5,Apoio!$B$4:$AB$4,0)+1),0) | ... O61: =IFERROR(INDEX(Apoio!$B:$AB,MATCH($C61,Apoio!$B$1:$B$176,0),MATCH('Fluxo de Caixa '!O$5,Apoio!$B$4:$AB$4,0)+1),0) | Q61: =SUM(D61:P61)
C62: AGUA ADM | D62: =IFERROR(INDEX(Apoio!$B:$AB,MATCH($C62,Apoio!$B$1:$B$176,0),MATCH('Fluxo de Caixa '!D$5,Apoio!$B$4:$AB$4,0)+1),0) | E62: =IFERROR(INDEX(Apoio!$B:$AB,MATCH($C62,Apoio!$B$1:$B$176,0),MATCH('Fluxo de Caixa '!E$5,Apoio!$B$4:$AB$4,0)+1),0) | F62: =IFERROR(INDEX(Apoio!$B:$AB,MATCH($C62,Apoio!$B$1:$B$176,0),MATCH('Fluxo de Caixa '!F$5,Apoio!$B$4:$AB$4,0)+1),0) | G62: =IFERROR(INDEX(Apoio!$B:$AB,MATCH($C62,Apoio!$B$1:$B$176,0),MATCH('Fluxo de Caixa '!G$5,Apoio!$B$4:$AB$4,0)+1),0) | H62: =IFERROR(INDEX(Apoio!$B:$AB,MATCH($C62,Apoio!$B$1:$B$176,0),MATCH('Fluxo de Caixa '!H$5,Apoio!$B$4:$AB$4,0)+1),0) | I62: =IFERROR(INDEX(Apoio!$B:$AB,MATCH($C62,Apoio!$B$1:$B$176,0),MATCH('Fluxo de Caixa '!I$5,Apoio!$B$4:$AB$4,0)+1),0) | J62: =IFERROR(INDEX(Apoio!$B:$AB,MATCH($C62,Apoio!$B$1:$B$176,0),MATCH('Fluxo de Caixa '!J$5,Apoio!$B$4:$AB$4,0)+1),0) | K62: =IFERROR(INDEX(Apoio!$B:$AB,MATCH($C62,Apoio!$B$1:$B$176,0),MATCH('Fluxo de Caixa '!K$5,Apoio!$B$4:$AB$4,0)+1),0) | ... O62: =IFERROR(INDEX(Apoio!$B:$AB,MATCH($C62,Apoio!$B$1:$B$176,0),MATCH('Fluxo de Caixa '!O$5,Apoio!$B$4:$AB$4,0)+1),0) | Q62: =SUM(D62:P62)
C63: ENERGIA ADM | D63: =IFERROR(INDEX(Apoio!$B:$AB,MATCH($C63,Apoio!$B$1:$B$176,0),MATCH('Fluxo de Caixa '!D$5,Apoio!$B$4:$AB$4,0)+1),0) | E63: =IFERROR(INDEX(Apoio!$B:$AB,MATCH($C63,Apoio!$B$1:$B$176,0),MATCH('Fluxo de Caixa '!E$5,Apoio!$B$4:$AB$4,0)+1),0) | F63: =IFERROR(INDEX(Apoio!$B:$AB,MATCH($C63,Apoio!$B$1:$B$176,0),MATCH('Fluxo de Caixa '!F$5,Apoio!$B$4:$AB$4,0)+1),0) | G63: =IFERROR(INDEX(Apoio!$B:$AB,MATCH($C63,Apoio!$B$1:$B$176,0),MATCH('Fluxo de Caixa '!G$5,Apoio!$B$4:$AB$4,0)+1),0) | H63: =IFERROR(INDEX(Apoio!$B:$AB,MATCH($C63,Apoio!$B$1:$B$176,0),MATCH('Fluxo de Caixa '!H$5,Apoio!$B$4:$AB$4,0)+1),0) | I63: =IFERROR(INDEX(Apoio!$B:$AB,MATCH($C63,Apoio!$B$1:$B$176,0),MATCH('Fluxo de Caixa '!I$5,Apoio!$B$4:$AB$4,0)+1),0) | J63: =IFERROR(INDEX(Apoio!$B:$AB,MATCH($C63,Apoio!$B$1:$B$176,0),MATCH('Fluxo de Caixa '!J$5,Apoio!$B$4:$AB$4,0)+1),0) | K63: =IFERROR(INDEX(Apoio!$B:$AB,MATCH($C63,Apoio!$B$1:$B$176,0),MATCH('Fluxo de Caixa '!K$5,Apoio!$B$4:$AB$4,0)+1),0) | ... O63: =IFERROR(INDEX(Apoio!$B:$AB,MATCH($C63,Apoio!$B$1:$B$176,0),MATCH('Fluxo de Caixa '!O$5,Apoio!$B$4:$AB$4,0)+1),0) | Q63: =SUM(D63:P63)
C64: IPTU | D64: =IFERROR(INDEX(Apoio!$B:$AB,MATCH($C64,Apoio!$B$1:$B$176,0),MATCH('Fluxo de Caixa '!D$5,Apoio!$B$4:$AB$4,0)+1),0) | E64: =IFERROR(INDEX(Apoio!$B:$AB,MATCH($C64,Apoio!$B$1:$B$176,0),MATCH('Fluxo de Caixa '!E$5,Apoio!$B$4:$AB$4,0)+1),0) | F64: =IFERROR(INDEX(Apoio!$B:$AB,MATCH($C64,Apoio!$B$1:$B$176,0),MATCH('Fluxo de Caixa '!F$5,Apoio!$B$4:$AB$4,0)+1),0) | G64: =IFERROR(INDEX(Apoio!$B:$AB,MATCH($C64,Apoio!$B$1:$B$176,0),MATCH('Fluxo de Caixa '!G$5,Apoio!$B$4:$AB$4,0)+1),0) | H64: =IFERROR(INDEX(Apoio!$B:$AB,MATCH($C64,Apoio!$B$1:$B$176,0),MATCH('Fluxo de Caixa '!H$5,Apoio!$B$4:$AB$4,0)+1),0) | I64: =IFERROR(INDEX(Apoio!$B:$AB,MATCH($C64,Apoio!$B$1:$B$176,0),MATCH('Fluxo de Caixa '!I$5,Apoio!$B$4:$AB$4,0)+1),0) | J64: =IFERROR(INDEX(Apoio!$B:$AB,MATCH($C64,Apoio!$B$1:$B$176,0),MATCH('Fluxo de Caixa '!J$5,Apoio!$B$4:$AB$4,0)+1),0) | K64: =IFERROR(INDEX(Apoio!$B:$AB,MATCH($C64,Apoio!$B$1:$B$176,0),MATCH('Fluxo de Caixa '!K$5,Apoio!$B$4:$AB$4,0)+1),0) | ... O64: =IFERROR(INDEX(Apoio!$B:$AB,MATCH($C64,Apoio!$B$1:$B$176,0),MATCH('Fluxo de Caixa '!O$5,Apoio!$B$4:$AB$4,0)+1),0) | Q64: =SUM(D64:P64)
C65: INTERNET / TELEFONE ADM | D65: =IFERROR(INDEX(Apoio!$B:$AB,MATCH($C65,Apoio!$B$1:$B$176,0),MATCH('Fluxo de Caixa '!D$5,Apoio!$B$4:$AB$4,0)+1),0) | E65: =IFERROR(INDEX(Apoio!$B:$AB,MATCH($C65,Apoio!$B$1:$B$176,0),MATCH('Fluxo de Caixa '!E$5,Apoio!$B$4:$AB$4,0)+1),0) | F65: =IFERROR(INDEX(Apoio!$B:$AB,MATCH($C65,Apoio!$B$1:$B$176,0),MATCH('Fluxo de Caixa '!F$5,Apoio!$B$4:$AB$4,0)+1),0) | G65: =IFERROR(INDEX(Apoio!$B:$AB,MATCH($C65,Apoio!$B$1:$B$176,0),MATCH('Fluxo de Caixa '!G$5,Apoio!$B$4:$AB$4,0)+1),0) | H65: =IFERROR(INDEX(Apoio!$B:$AB,MATCH($C65,Apoio!$B$1:$B$176,0),MATCH('Fluxo de Caixa '!H$5,Apoio!$B$4:$AB$4,0)+1),0) | I65: =IFERROR(INDEX(Apoio!$B:$AB,MATCH($C65,Apoio!$B$1:$B$176,0),MATCH('Fluxo de Caixa '!I$5,Apoio!$B$4:$AB$4,0)+1),0) | J65: =IFERROR(INDEX(Apoio!$B:$AB,MATCH($C65,Apoio!$B$1:$B$176,0),MATCH('Fluxo de Caixa '!J$5,Apoio!$B$4:$AB$4,0)+1),0) | K65: =IFERROR(INDEX(Apoio!$B:$AB,MATCH($C65,Apoio!$B$1:$B$176,0),MATCH('Fluxo de Caixa '!K$5,Apoio!$B$4:$AB$4,0)+1),0) | ... O65: =IFERROR(INDEX(Apoio!$B:$AB,MATCH($C65,Apoio!$B$1:$B$176,0),MATCH('Fluxo de Caixa '!O$5,Apoio!$B$4:$AB$4,0)+1),0) | Q65: =SUM(D65:P65)
C66: INTERNET OBRAS | D66: =IFERROR(INDEX(Apoio!$B:$AB,MATCH($C66,Apoio!$B$1:$B$176,0),MATCH('Fluxo de Caixa '!D$5,Apoio!$B$4:$AB$4,0)+1),0) | E66: =IFERROR(INDEX(Apoio!$B:$AB,MATCH($C66,Apoio!$B$1:$B$176,0),MATCH('Fluxo de Caixa '!E$5,Apoio!$B$4:$AB$4,0)+1),0) | F66: =IFERROR(INDEX(Apoio!$B:$AB,MATCH($C66,Apoio!$B$1:$B$176,0),MATCH('Fluxo de Caixa '!F$5,Apoio!$B$4:$AB$4,0)+1),0) | G66: =IFERROR(INDEX(Apoio!$B:$AB,MATCH($C66,Apoio!$B$1:$B$176,0),MATCH('Fluxo de Caixa '!G$5,Apoio!$B$4:$AB$4,0)+1),0) | H66: =IFERROR(INDEX(Apoio!$B:$AB,MATCH($C66,Apoio!$B$1:$B$176,0),MATCH('Fluxo de Caixa '!H$5,Apoio!$B$4:$AB$4,0)+1),0) | I66: =IFERROR(INDEX(Apoio!$B:$AB,MATCH($C66,Apoio!$B$1:$B$176,0),MATCH('Fluxo de Caixa '!I$5,Apoio!$B$4:$AB$4,0)+1),0) | J66: =IFERROR(INDEX(Apoio!$B:$AB,MATCH($C66,Apoio!$B$1:$B$176,0),MATCH('Fluxo de Caixa '!J$5,Apoio!$B$4:$AB$4,0)+1),0) | K66: =IFERROR(INDEX(Apoio!$B:$AB,MATCH($C66,Apoio!$B$1:$B$176,0),MATCH('Fluxo de Caixa '!K$5,Apoio!$B$4:$AB$4,0)+1),0) | ... O66: =IFERROR(INDEX(Apoio!$B:$AB,MATCH($C66,Apoio!$B$1:$B$176,0),MATCH('Fluxo de Caixa '!O$5,Apoio!$B$4:$AB$4,0)+1),0) | Q66: =SUM(D66:P66)
C68: Gastos com Serviços de Terceiros | D68: =SUM(D69:D72) | E68: =SUM(E69:E72) | F68: =SUM(F69:F72) | G68: =SUM(G69:G72) | H68: =SUM(H69:H72) | I68: =SUM(I69:I72) | J68: =SUM(J69:J72) | K68: =SUM(K69:K72) | ... O68: =SUM(O69:O72) | Q68: =SUM(Q69:Q72)
C69: SERVIÇO MECANICO | D69: =IFERROR(INDEX(Apoio!$B:$AB,MATCH($C69,Apoio!$B$1:$B$176,0),MATCH('Fluxo de Caixa '!D$5,Apoio!$B$4:$AB$4,0)+1),0) | E69: =IFERROR(INDEX(Apoio!$B:$AB,MATCH($C69,Apoio!$B$1:$B$176,0),MATCH('Fluxo de Caixa '!E$5,Apoio!$B$4:$AB$4,0)+1),0) | F69: =IFERROR(INDEX(Apoio!$B:$AB,MATCH($C69,Apoio!$B$1:$B$176,0),MATCH('Fluxo de Caixa '!F$5,Apoio!$B$4:$AB$4,0)+1),0) | G69: =IFERROR(INDEX(Apoio!$B:$AB,MATCH($C69,Apoio!$B$1:$B$176,0),MATCH('Fluxo de Caixa '!G$5,Apoio!$B$4:$AB$4,0)+1),0) | H69: =IFERROR(INDEX(Apoio!$B:$AB,MATCH($C69,Apoio!$B$1:$B$176,0),MATCH('Fluxo de Caixa '!H$5,Apoio!$B$4:$AB$4,0)+1),0) | I69: =IFERROR(INDEX(Apoio!$B:$AB,MATCH($C69,Apoio!$B$1:$B$176,0),MATCH('Fluxo de Caixa '!I$5,Apoio!$B$4:$AB$4,0)+1),0) | J69: =IFERROR(INDEX(Apoio!$B:$AB,MATCH($C69,Apoio!$B$1:$B$176,0),MATCH('Fluxo de Caixa '!J$5,Apoio!$B$4:$AB$4,0)+1),0) | K69: =IFERROR(INDEX(Apoio!$B:$AB,MATCH($C69,Apoio!$B$1:$B$176,0),MATCH('Fluxo de Caixa '!K$5,Apoio!$B$4:$AB$4,0)+1),0) | ... O69: =IFERROR(INDEX(Apoio!$B:$AB,MATCH($C69,Apoio!$B$1:$B$176,0),MATCH('Fluxo de Caixa '!O$5,Apoio!$B$4:$AB$4,0)+1),0) | Q69: =SUM(D69:P69)
C70: SERVIÇO ELETRICO | D70: =IFERROR(INDEX(Apoio!$B:$AB,MATCH($C70,Apoio!$B$1:$B$176,0),MATCH('Fluxo de Caixa '!D$5,Apoio!$B$4:$AB$4,0)+1),0) | E70: =IFERROR(INDEX(Apoio!$B:$AB,MATCH($C70,Apoio!$B$1:$B$176,0),MATCH('Fluxo de Caixa '!E$5,Apoio!$B$4:$AB$4,0)+1),0) | F70: =IFERROR(INDEX(Apoio!$B:$AB,MATCH($C70,Apoio!$B$1:$B$176,0),MATCH('Fluxo de Caixa '!F$5,Apoio!$B$4:$AB$4,0)+1),0) | G70: =IFERROR(INDEX(Apoio!$B:$AB,MATCH($C70,Apoio!$B$1:$B$176,0),MATCH('Fluxo de Caixa '!G$5,Apoio!$B$4:$AB$4,0)+1),0) | H70: =IFERROR(INDEX(Apoio!$B:$AB,MATCH($C70,Apoio!$B$1:$B$176,0),MATCH('Fluxo de Caixa '!H$5,Apoio!$B$4:$AB$4,0)+1),0) | I70: =IFERROR(INDEX(Apoio!$B:$AB,MATCH($C70,Apoio!$B$1:$B$176,0),MATCH('Fluxo de Caixa '!I$5,Apoio!$B$4:$AB$4,0)+1),0) | J70: =IFERROR(INDEX(Apoio!$B:$AB,MATCH($C70,Apoio!$B$1:$B$176,0),MATCH('Fluxo de Caixa '!J$5,Apoio!$B$4:$AB$4,0)+1),0) | K70: =IFERROR(INDEX(Apoio!$B:$AB,MATCH($C70,Apoio!$B$1:$B$176,0),MATCH('Fluxo de Caixa '!K$5,Apoio!$B$4:$AB$4,0)+1),0) | ... O70: =IFERROR(INDEX(Apoio!$B:$AB,MATCH($C70,Apoio!$B$1:$B$176,0),MATCH('Fluxo de Caixa '!O$5,Apoio!$B$4:$AB$4,0)+1),0) | Q70: =SUM(D70:P70)
C71: SERVIÇO SERRALHEIRO | D71: =IFERROR(INDEX(Apoio!$B:$AB,MATCH($C71,Apoio!$B$1:$B$176,0),MATCH('Fluxo de Caixa '!D$5,Apoio!$B$4:$AB$4,0)+1),0) | E71: =IFERROR(INDEX(Apoio!$B:$AB,MATCH($C71,Apoio!$B$1:$B$176,0),MATCH('Fluxo de Caixa '!E$5,Apoio!$B$4:$AB$4,0)+1),0) | F71: =IFERROR(INDEX(Apoio!$B:$AB,MATCH($C71,Apoio!$B$1:$B$176,0),MATCH('Fluxo de Caixa '!F$5,Apoio!$B$4:$AB$4,0)+1),0) | G71: =IFERROR(INDEX(Apoio!$B:$AB,MATCH($C71,Apoio!$B$1:$B$176,0),MATCH('Fluxo de Caixa '!G$5,Apoio!$B$4:$AB$4,0)+1),0) | H71: =IFERROR(INDEX(Apoio!$B:$AB,MATCH($C71,Apoio!$B$1:$B$176,0),MATCH('Fluxo de Caixa '!H$5,Apoio!$B$4:$AB$4,0)+1),0) | I71: =IFERROR(INDEX(Apoio!$B:$AB,MATCH($C71,Apoio!$B$1:$B$176,0),MATCH('Fluxo de Caixa '!I$5,Apoio!$B$4:$AB$4,0)+1),0) | J71: =IFERROR(INDEX(Apoio!$B:$AB,MATCH($C71,Apoio!$B$1:$B$176,0),MATCH('Fluxo de Caixa '!J$5,Apoio!$B$4:$AB$4,0)+1),0) | K71: =IFERROR(INDEX(Apoio!$B:$AB,MATCH($C71,Apoio!$B$1:$B$176,0),MATCH('Fluxo de Caixa '!K$5,Apoio!$B$4:$AB$4,0)+1),0) | ... O71: =IFERROR(INDEX(Apoio!$B:$AB,MATCH($C71,Apoio!$B$1:$B$176,0),MATCH('Fluxo de Caixa '!O$5,Apoio!$B$4:$AB$4,0)+1),0) | Q71: =SUM(D71:P71)
C72: SERVIÇO LAUDO TECNICO | D72: =IFERROR(INDEX(Apoio!$B:$AB,MATCH($C72,Apoio!$B$1:$B$176,0),MATCH('Fluxo de Caixa '!D$5,Apoio!$B$4:$AB$4,0)+1),0) | E72: =IFERROR(INDEX(Apoio!$B:$AB,MATCH($C72,Apoio!$B$1:$B$176,0),MATCH('Fluxo de Caixa '!E$5,Apoio!$B$4:$AB$4,0)+1),0) | F72: =IFERROR(INDEX(Apoio!$B:$AB,MATCH($C72,Apoio!$B$1:$B$176,0),MATCH('Fluxo de Caixa '!F$5,Apoio!$B$4:$AB$4,0)+1),0) | G72: =IFERROR(INDEX(Apoio!$B:$AB,MATCH($C72,Apoio!$B$1:$B$176,0),MATCH('Fluxo de Caixa '!G$5,Apoio!$B$4:$AB$4,0)+1),0) | H72: =IFERROR(INDEX(Apoio!$B:$AB,MATCH($C72,Apoio!$B$1:$B$176,0),MATCH('Fluxo de Caixa '!H$5,Apoio!$B$4:$AB$4,0)+1),0) | I72: =IFERROR(INDEX(Apoio!$B:$AB,MATCH($C72,Apoio!$B$1:$B$176,0),MATCH('Fluxo de Caixa '!I$5,Apoio!$B$4:$AB$4,0)+1),0) | J72: =IFERROR(INDEX(Apoio!$B:$AB,MATCH($C72,Apoio!$B$1:$B$176,0),MATCH('Fluxo de Caixa '!J$5,Apoio!$B$4:$AB$4,0)+1),0) | K72: =IFERROR(INDEX(Apoio!$B:$AB,MATCH($C72,Apoio!$B$1:$B$176,0),MATCH('Fluxo de Caixa '!K$5,Apoio!$B$4:$AB$4,0)+1),0) | ... O72: =IFERROR(INDEX(Apoio!$B:$AB,MATCH($C72,Apoio!$B$1:$B$176,0),MATCH('Fluxo de Caixa '!O$5,Apoio!$B$4:$AB$4,0)+1),0) | Q72: =SUM(D72:P72)
C74: Gastos com Impostos e Tributos | D74: =SUM(D75:D81) | E74: =SUM(E75:E81) | F74: =SUM(F75:F81) | G74: =SUM(G75:G81) | H74: =SUM(H75:H81) | I74: =SUM(I75:I81) | J74: =SUM(J75:J81) | K74: =SUM(K75:K81) | ... O74: =SUM(O75:O81) | Q74: =SUM(Q75:Q81)
C75: PIS | D75: =IFERROR(INDEX(Apoio!$B:$AB,MATCH($C75,Apoio!$B$1:$B$176,0),MATCH('Fluxo de Caixa '!D$5,Apoio!$B$4:$AB$4,0)+1),0) | E75: =IFERROR(INDEX(Apoio!$B:$AB,MATCH($C75,Apoio!$B$1:$B$176,0),MATCH('Fluxo de Caixa '!E$5,Apoio!$B$4:$AB$4,0)+1),0) | F75: =IFERROR(INDEX(Apoio!$B:$AB,MATCH($C75,Apoio!$B$1:$B$176,0),MATCH('Fluxo de Caixa '!F$5,Apoio!$B$4:$AB$4,0)+1),0) | G75: =IFERROR(INDEX(Apoio!$B:$AB,MATCH($C75,Apoio!$B$1:$B$176,0),MATCH('Fluxo de Caixa '!G$5,Apoio!$B$4:$AB$4,0)+1),0) | H75: =IFERROR(INDEX(Apoio!$B:$AB,MATCH($C75,Apoio!$B$1:$B$176,0),MATCH('Fluxo de Caixa '!H$5,Apoio!$B$4:$AB$4,0)+1),0) | I75: =IFERROR(INDEX(Apoio!$B:$AB,MATCH($C75,Apoio!$B$1:$B$176,0),MATCH('Fluxo de Caixa '!I$5,Apoio!$B$4:$AB$4,0)+1),0) | J75: =IFERROR(INDEX(Apoio!$B:$AB,MATCH($C75,Apoio!$B$1:$B$176,0),MATCH('Fluxo de Caixa '!J$5,Apoio!$B$4:$AB$4,0)+1),0) | K75: =IFERROR(INDEX(Apoio!$B:$AB,MATCH($C75,Apoio!$B$1:$B$176,0),MATCH('Fluxo de Caixa '!K$5,Apoio!$B$4:$AB$4,0)+1),0) | ... O75: =IFERROR(INDEX(Apoio!$B:$AB,MATCH($C75,Apoio!$B$1:$B$176,0),MATCH('Fluxo de Caixa '!O$5,Apoio!$B$4:$AB$4,0)+1),0) | Q75: =SUM(D75:P75)
C76: COFINS | D76: =IFERROR(INDEX(Apoio!$B:$AB,MATCH($C76,Apoio!$B$1:$B$176,0),MATCH('Fluxo de Caixa '!D$5,Apoio!$B$4:$AB$4,0)+1),0) | E76: =IFERROR(INDEX(Apoio!$B:$AB,MATCH($C76,Apoio!$B$1:$B$176,0),MATCH('Fluxo de Caixa '!E$5,Apoio!$B$4:$AB$4,0)+1),0) | F76: =IFERROR(INDEX(Apoio!$B:$AB,MATCH($C76,Apoio!$B$1:$B$176,0),MATCH('Fluxo de Caixa '!F$5,Apoio!$B$4:$AB$4,0)+1),0) | G76: =IFERROR(INDEX(Apoio!$B:$AB,MATCH($C76,Apoio!$B$1:$B$176,0),MATCH('Fluxo de Caixa '!G$5,Apoio!$B$4:$AB$4,0)+1),0) | H76: =IFERROR(INDEX(Apoio!$B:$AB,MATCH($C76,Apoio!$B$1:$B$176,0),MATCH('Fluxo de Caixa '!H$5,Apoio!$B$4:$AB$4,0)+1),0) | I76: =IFERROR(INDEX(Apoio!$B:$AB,MATCH($C76,Apoio!$B$1:$B$176,0),MATCH('Fluxo de Caixa '!I$5,Apoio!$B$4:$AB$4,0)+1),0) | J76: =IFERROR(INDEX(Apoio!$B:$AB,MATCH($C76,Apoio!$B$1:$B$176,0),MATCH('Fluxo de Caixa '!J$5,Apoio!$B$4:$AB$4,0)+1),0) | K76: =IFERROR(INDEX(Apoio!$B:$AB,MATCH($C76,Apoio!$B$1:$B$176,0),MATCH('Fluxo de Caixa '!K$5,Apoio!$B$4:$AB$4,0)+1),0) | ... O76: =IFERROR(INDEX(Apoio!$B:$AB,MATCH($C76,Apoio!$B$1:$B$176,0),MATCH('Fluxo de Caixa '!O$5,Apoio!$B$4:$AB$4,0)+1),0) | Q76: =SUM(D76:P76)
C77: IRPJ | D77: =IFERROR(INDEX(Apoio!$B:$AB,MATCH($C77,Apoio!$B$1:$B$176,0),MATCH('Fluxo de Caixa '!D$5,Apoio!$B$4:$AB$4,0)+1),0) | E77: =IFERROR(INDEX(Apoio!$B:$AB,MATCH($C77,Apoio!$B$1:$B$176,0),MATCH('Fluxo de Caixa '!E$5,Apoio!$B$4:$AB$4,0)+1),0) | F77: =IFERROR(INDEX(Apoio!$B:$AB,MATCH($C77,Apoio!$B$1:$B$176,0),MATCH('Fluxo de Caixa '!F$5,Apoio!$B$4:$AB$4,0)+1),0) | G77: =IFERROR(INDEX(Apoio!$B:$AB,MATCH($C77,Apoio!$B$1:$B$176,0),MATCH('Fluxo de Caixa '!G$5,Apoio!$B$4:$AB$4,0)+1),0) | H77: =IFERROR(INDEX(Apoio!$B:$AB,MATCH($C77,Apoio!$B$1:$B$176,0),MATCH('Fluxo de Caixa '!H$5,Apoio!$B$4:$AB$4,0)+1),0) | I77: =IFERROR(INDEX(Apoio!$B:$AB,MATCH($C77,Apoio!$B$1:$B$176,0),MATCH('Fluxo de Caixa '!I$5,Apoio!$B$4:$AB$4,0)+1),0) | J77: =IFERROR(INDEX(Apoio!$B:$AB,MATCH($C77,Apoio!$B$1:$B$176,0),MATCH('Fluxo de Caixa '!J$5,Apoio!$B$4:$AB$4,0)+1),0) | K77: =IFERROR(INDEX(Apoio!$B:$AB,MATCH($C77,Apoio!$B$1:$B$176,0),MATCH('Fluxo de Caixa '!K$5,Apoio!$B$4:$AB$4,0)+1),0) | ... O77: =IFERROR(INDEX(Apoio!$B:$AB,MATCH($C77,Apoio!$B$1:$B$176,0),MATCH('Fluxo de Caixa '!O$5,Apoio!$B$4:$AB$4,0)+1),0) | Q77: =SUM(D77:P77)
C78: CSLL | D78: =IFERROR(INDEX(Apoio!$B:$AB,MATCH($C78,Apoio!$B$1:$B$176,0),MATCH('Fluxo de Caixa '!D$5,Apoio!$B$4:$AB$4,0)+1),0) | E78: =IFERROR(INDEX(Apoio!$B:$AB,MATCH($C78,Apoio!$B$1:$B$176,0),MATCH('Fluxo de Caixa '!E$5,Apoio!$B$4:$AB$4,0)+1),0) | F78: =IFERROR(INDEX(Apoio!$B:$AB,MATCH($C78,Apoio!$B$1:$B$176,0),MATCH('Fluxo de Caixa '!F$5,Apoio!$B$4:$AB$4,0)+1),0) | G78: =IFERROR(INDEX(Apoio!$B:$AB,MATCH($C78,Apoio!$B$1:$B$176,0),MATCH('Fluxo de Caixa '!G$5,Apoio!$B$4:$AB$4,0)+1),0) | H78: =IFERROR(INDEX(Apoio!$B:$AB,MATCH($C78,Apoio!$B$1:$B$176,0),MATCH('Fluxo de Caixa '!H$5,Apoio!$B$4:$AB$4,0)+1),0) | I78: =IFERROR(INDEX(Apoio!$B:$AB,MATCH($C78,Apoio!$B$1:$B$176,0),MATCH('Fluxo de Caixa '!I$5,Apoio!$B$4:$AB$4,0)+1),0) | J78: =IFERROR(INDEX(Apoio!$B:$AB,MATCH($C78,Apoio!$B$1:$B$176,0),MATCH('Fluxo de Caixa '!J$5,Apoio!$B$4:$AB$4,0)+1),0) | K78: =IFERROR(INDEX(Apoio!$B:$AB,MATCH($C78,Apoio!$B$1:$B$176,0),MATCH('Fluxo de Caixa '!K$5,Apoio!$B$4:$AB$4,0)+1),0) | ... O78: =IFERROR(INDEX(Apoio!$B:$AB,MATCH($C78,Apoio!$B$1:$B$176,0),MATCH('Fluxo de Caixa '!O$5,Apoio!$B$4:$AB$4,0)+1),0) | Q78: =SUM(D78:P78)
C79: ITBI | D79: =IFERROR(INDEX(Apoio!$B:$AB,MATCH($C79,Apoio!$B$1:$B$176,0),MATCH('Fluxo de Caixa '!D$5,Apoio!$B$4:$AB$4,0)+1),0) | E79: =IFERROR(INDEX(Apoio!$B:$AB,MATCH($C79,Apoio!$B$1:$B$176,0),MATCH('Fluxo de Caixa '!E$5,Apoio!$B$4:$AB$4,0)+1),0) | F79: =IFERROR(INDEX(Apoio!$B:$AB,MATCH($C79,Apoio!$B$1:$B$176,0),MATCH('Fluxo de Caixa '!F$5,Apoio!$B$4:$AB$4,0)+1),0) | G79: =IFERROR(INDEX(Apoio!$B:$AB,MATCH($C79,Apoio!$B$1:$B$176,0),MATCH('Fluxo de Caixa '!G$5,Apoio!$B$4:$AB$4,0)+1),0) | H79: =IFERROR(INDEX(Apoio!$B:$AB,MATCH($C79,Apoio!$B$1:$B$176,0),MATCH('Fluxo de Caixa '!H$5,Apoio!$B$4:$AB$4,0)+1),0) | I79: =IFERROR(INDEX(Apoio!$B:$AB,MATCH($C79,Apoio!$B$1:$B$176,0),MATCH('Fluxo de Caixa '!I$5,Apoio!$B$4:$AB$4,0)+1),0) | J79: =IFERROR(INDEX(Apoio!$B:$AB,MATCH($C79,Apoio!$B$1:$B$176,0),MATCH('Fluxo de Caixa '!J$5,Apoio!$B$4:$AB$4,0)+1),0) | K79: =IFERROR(INDEX(Apoio!$B:$AB,MATCH($C79,Apoio!$B$1:$B$176,0),MATCH('Fluxo de Caixa '!K$5,Apoio!$B$4:$AB$4,0)+1),0) | ... O79: =IFERROR(INDEX(Apoio!$B:$AB,MATCH($C79,Apoio!$B$1:$B$176,0),MATCH('Fluxo de Caixa '!O$5,Apoio!$B$4:$AB$4,0)+1),0) | Q79: =SUM(D79:P79)
C80: SIMPLES NASCIONAL | D80: =IFERROR(INDEX(Apoio!$B:$AB,MATCH($C80,Apoio!$B$1:$B$176,0),MATCH('Fluxo de Caixa '!D$5,Apoio!$B$4:$AB$4,0)+1),0) | E80: =IFERROR(INDEX(Apoio!$B:$AB,MATCH($C80,Apoio!$B$1:$B$176,0),MATCH('Fluxo de Caixa '!E$5,Apoio!$B$4:$AB$4,0)+1),0) | F80: =IFERROR(INDEX(Apoio!$B:$AB,MATCH($C80,Apoio!$B$1:$B$176,0),MATCH('Fluxo de Caixa '!F$5,Apoio!$B$4:$AB$4,0)+1),0) | G80: =IFERROR(INDEX(Apoio!$B:$AB,MATCH($C80,Apoio!$B$1:$B$176,0),MATCH('Fluxo de Caixa '!G$5,Apoio!$B$4:$AB$4,0)+1),0) | H80: =IFERROR(INDEX(Apoio!$B:$AB,MATCH($C80,Apoio!$B$1:$B$176,0),MATCH('Fluxo de Caixa '!H$5,Apoio!$B$4:$AB$4,0)+1),0) | I80: =IFERROR(INDEX(Apoio!$B:$AB,MATCH($C80,Apoio!$B$1:$B$176,0),MATCH('Fluxo de Caixa '!I$5,Apoio!$B$4:$AB$4,0)+1),0) | J80: =IFERROR(INDEX(Apoio!$B:$AB,MATCH($C80,Apoio!$B$1:$B$176,0),MATCH('Fluxo de Caixa '!J$5,Apoio!$B$4:$AB$4,0)+1),0) | K80: =IFERROR(INDEX(Apoio!$B:$AB,MATCH($C80,Apoio!$B$1:$B$176,0),MATCH('Fluxo de Caixa '!K$5,Apoio!$B$4:$AB$4,0)+1),0) | ... O80: =IFERROR(INDEX(Apoio!$B:$AB,MATCH($C80,Apoio!$B$1:$B$176,0),MATCH('Fluxo de Caixa '!O$5,Apoio!$B$4:$AB$4,0)+1),0) | Q80: =SUM(D80:P80)
C81: ISS | D81: =IFERROR(INDEX(Apoio!$B:$AB,MATCH($C81,Apoio!$B$1:$B$176,0),MATCH('Fluxo de Caixa '!D$5,Apoio!$B$4:$AB$4,0)+1),0) | E81: =IFERROR(INDEX(Apoio!$B:$AB,MATCH($C81,Apoio!$B$1:$B$176,0),MATCH('Fluxo de Caixa '!E$5,Apoio!$B$4:$AB$4,0)+1),0) | F81: =IFERROR(INDEX(Apoio!$B:$AB,MATCH($C81,Apoio!$B$1:$B$176,0),MATCH('Fluxo de Caixa '!F$5,Apoio!$B$4:$AB$4,0)+1),0) | G81: =IFERROR(INDEX(Apoio!$B:$AB,MATCH($C81,Apoio!$B$1:$B$176,0),MATCH('Fluxo de Caixa '!G$5,Apoio!$B$4:$AB$4,0)+1),0) | H81: =IFERROR(INDEX(Apoio!$B:$AB,MATCH($C81,Apoio!$B$1:$B$176,0),MATCH('Fluxo de Caixa '!H$5,Apoio!$B$4:$AB$4,0)+1),0) | I81: =IFERROR(INDEX(Apoio!$B:$AB,MATCH($C81,Apoio!$B$1:$B$176,0),MATCH('Fluxo de Caixa '!I$5,Apoio!$B$4:$AB$4,0)+1),0) | J81: =IFERROR(INDEX(Apoio!$B:$AB,MATCH($C81,Apoio!$B$1:$B$176,0),MATCH('Fluxo de Caixa '!J$5,Apoio!$B$4:$AB$4,0)+1),0) | K81: =IFERROR(INDEX(Apoio!$B:$AB,MATCH($C81,Apoio!$B$1:$B$176,0),MATCH('Fluxo de Caixa '!K$5,Apoio!$B$4:$AB$4,0)+1),0) | ... O81: =IFERROR(INDEX(Apoio!$B:$AB,MATCH($C81,Apoio!$B$1:$B$176,0),MATCH('Fluxo de Caixa '!O$5,Apoio!$B$4:$AB$4,0)+1),0) | Q81: =SUM(D81:P81)
C83: Gastos com Veículos | D83: =SUM(D84:D93) | E83: =SUM(E84:E93) | F83: =SUM(F84:F93) | G83: =SUM(G84:G93) | H83: =SUM(H84:H93) | I83: =SUM(I84:I93) | J83: =SUM(J84:J93) | K83: =SUM(K84:K93) | ... O83: =SUM(O84:O93) | Q83: =SUM(Q84:Q93)
C84: IPVA | D84: =IFERROR(INDEX(Apoio!$B:$AB,MATCH($C84,Apoio!$B$1:$B$176,0),MATCH('Fluxo de Caixa '!D$5,Apoio!$B$4:$AB$4,0)+1),0) | E84: =IFERROR(INDEX(Apoio!$B:$AB,MATCH($C84,Apoio!$B$1:$B$176,0),MATCH('Fluxo de Caixa '!E$5,Apoio!$B$4:$AB$4,0)+1),0) | F84: =IFERROR(INDEX(Apoio!$B:$AB,MATCH($C84,Apoio!$B$1:$B$176,0),MATCH('Fluxo de Caixa '!F$5,Apoio!$B$4:$AB$4,0)+1),0) | G84: =IFERROR(INDEX(Apoio!$B:$AB,MATCH($C84,Apoio!$B$1:$B$176,0),MATCH('Fluxo de Caixa '!G$5,Apoio!$B$4:$AB$4,0)+1),0) | H84: =IFERROR(INDEX(Apoio!$B:$AB,MATCH($C84,Apoio!$B$1:$B$176,0),MATCH('Fluxo de Caixa '!H$5,Apoio!$B$4:$AB$4,0)+1),0) | I84: =IFERROR(INDEX(Apoio!$B:$AB,MATCH($C84,Apoio!$B$1:$B$176,0),MATCH('Fluxo de Caixa '!I$5,Apoio!$B$4:$AB$4,0)+1),0) | J84: =IFERROR(INDEX(Apoio!$B:$AB,MATCH($C84,Apoio!$B$1:$B$176,0),MATCH('Fluxo de Caixa '!J$5,Apoio!$B$4:$AB$4,0)+1),0) | K84: =IFERROR(INDEX(Apoio!$B:$AB,MATCH($C84,Apoio!$B$1:$B$176,0),MATCH('Fluxo de Caixa '!K$5,Apoio!$B$4:$AB$4,0)+1),0) | ... O84: =IFERROR(INDEX(Apoio!$B:$AB,MATCH($C84,Apoio!$B$1:$B$176,0),MATCH('Fluxo de Caixa '!O$5,Apoio!$B$4:$AB$4,0)+1),0) | Q84: =SUM(D84:P84)
C85: MULTAS DE TRANSITO | D85: =IFERROR(INDEX(Apoio!$B:$AB,MATCH($C85,Apoio!$B$1:$B$176,0),MATCH('Fluxo de Caixa '!D$5,Apoio!$B$4:$AB$4,0)+1),0) | E85: =IFERROR(INDEX(Apoio!$B:$AB,MATCH($C85,Apoio!$B$1:$B$176,0),MATCH('Fluxo de Caixa '!E$5,Apoio!$B$4:$AB$4,0)+1),0) | F85: =IFERROR(INDEX(Apoio!$B:$AB,MATCH($C85,Apoio!$B$1:$B$176,0),MATCH('Fluxo de Caixa '!F$5,Apoio!$B$4:$AB$4,0)+1),0) | G85: =IFERROR(INDEX(Apoio!$B:$AB,MATCH($C85,Apoio!$B$1:$B$176,0),MATCH('Fluxo de Caixa '!G$5,Apoio!$B$4:$AB$4,0)+1),0) | H85: =IFERROR(INDEX(Apoio!$B:$AB,MATCH($C85,Apoio!$B$1:$B$176,0),MATCH('Fluxo de Caixa '!H$5,Apoio!$B$4:$AB$4,0)+1),0) | I85: =IFERROR(INDEX(Apoio!$B:$AB,MATCH($C85,Apoio!$B$1:$B$176,0),MATCH('Fluxo de Caixa '!I$5,Apoio!$B$4:$AB$4,0)+1),0) | J85: =IFERROR(INDEX(Apoio!$B:$AB,MATCH($C85,Apoio!$B$1:$B$176,0),MATCH('Fluxo de Caixa '!J$5,Apoio!$B$4:$AB$4,0)+1),0) | K85: =IFERROR(INDEX(Apoio!$B:$AB,MATCH($C85,Apoio!$B$1:$B$176,0),MATCH('Fluxo de Caixa '!K$5,Apoio!$B$4:$AB$4,0)+1),0) | ... O85: =IFERROR(INDEX(Apoio!$B:$AB,MATCH($C85,Apoio!$B$1:$B$176,0),MATCH('Fluxo de Caixa '!O$5,Apoio!$B$4:$AB$4,0)+1),0) | Q85: =SUM(D85:P85)
C86: MANUTENÇÃO/PEÇAS VEICULOS | D86: =IFERROR(INDEX(Apoio!$B:$AB,MATCH($C86,Apoio!$B$1:$B$176,0),MATCH('Fluxo de Caixa '!D$5,Apoio!$B$4:$AB$4,0)+1),0) | E86: =IFERROR(INDEX(Apoio!$B:$AB,MATCH($C86,Apoio!$B$1:$B$176,0),MATCH('Fluxo de Caixa '!E$5,Apoio!$B$4:$AB$4,0)+1),0) | F86: =IFERROR(INDEX(Apoio!$B:$AB,MATCH($C86,Apoio!$B$1:$B$176,0),MATCH('Fluxo de Caixa '!F$5,Apoio!$B$4:$AB$4,0)+1),0) | G86: =IFERROR(INDEX(Apoio!$B:$AB,MATCH($C86,Apoio!$B$1:$B$176,0),MATCH('Fluxo de Caixa '!G$5,Apoio!$B$4:$AB$4,0)+1),0) | H86: =IFERROR(INDEX(Apoio!$B:$AB,MATCH($C86,Apoio!$B$1:$B$176,0),MATCH('Fluxo de Caixa '!H$5,Apoio!$B$4:$AB$4,0)+1),0) | I86: =IFERROR(INDEX(Apoio!$B:$AB,MATCH($C86,Apoio!$B$1:$B$176,0),MATCH('Fluxo de Caixa '!I$5,Apoio!$B$4:$AB$4,0)+1),0) | J86: =IFERROR(INDEX(Apoio!$B:$AB,MATCH($C86,Apoio!$B$1:$B$176,0),MATCH('Fluxo de Caixa '!J$5,Apoio!$B$4:$AB$4,0)+1),0) | K86: =IFERROR(INDEX(Apoio!$B:$AB,MATCH($C86,Apoio!$B$1:$B$176,0),MATCH('Fluxo de Caixa '!K$5,Apoio!$B$4:$AB$4,0)+1),0) | ... O86: =IFERROR(INDEX(Apoio!$B:$AB,MATCH($C86,Apoio!$B$1:$B$176,0),MATCH('Fluxo de Caixa '!O$5,Apoio!$B$4:$AB$4,0)+1),0) | Q86: =SUM(D86:P86)
C87: COMBUSTIVEL VEICULOS | D87: =IFERROR(INDEX(Apoio!$B:$AB,MATCH($C87,Apoio!$B$1:$B$176,0),MATCH('Fluxo de Caixa '!D$5,Apoio!$B$4:$AB$4,0)+1),0) | E87: =IFERROR(INDEX(Apoio!$B:$AB,MATCH($C87,Apoio!$B$1:$B$176,0),MATCH('Fluxo de Caixa '!E$5,Apoio!$B$4:$AB$4,0)+1),0) | F87: =IFERROR(INDEX(Apoio!$B:$AB,MATCH($C87,Apoio!$B$1:$B$176,0),MATCH('Fluxo de Caixa '!F$5,Apoio!$B$4:$AB$4,0)+1),0) | G87: =IFERROR(INDEX(Apoio!$B:$AB,MATCH($C87,Apoio!$B$1:$B$176,0),MATCH('Fluxo de Caixa '!G$5,Apoio!$B$4:$AB$4,0)+1),0) | H87: =IFERROR(INDEX(Apoio!$B:$AB,MATCH($C87,Apoio!$B$1:$B$176,0),MATCH('Fluxo de Caixa '!H$5,Apoio!$B$4:$AB$4,0)+1),0) | I87: =IFERROR(INDEX(Apoio!$B:$AB,MATCH($C87,Apoio!$B$1:$B$176,0),MATCH('Fluxo de Caixa '!I$5,Apoio!$B$4:$AB$4,0)+1),0) | J87: =IFERROR(INDEX(Apoio!$B:$AB,MATCH($C87,Apoio!$B$1:$B$176,0),MATCH('Fluxo de Caixa '!J$5,Apoio!$B$4:$AB$4,0)+1),0) | K87: =IFERROR(INDEX(Apoio!$B:$AB,MATCH($C87,Apoio!$B$1:$B$176,0),MATCH('Fluxo de Caixa '!K$5,Apoio!$B$4:$AB$4,0)+1),0) | ... O87: =IFERROR(INDEX(Apoio!$B:$AB,MATCH($C87,Apoio!$B$1:$B$176,0),MATCH('Fluxo de Caixa '!O$5,Apoio!$B$4:$AB$4,0)+1),0) | Q87: =SUM(D87:P87)
C88: SEGUROS DE VEICULOS | D88: =IFERROR(INDEX(Apoio!$B:$AB,MATCH($C88,Apoio!$B$1:$B$176,0),MATCH('Fluxo de Caixa '!D$5,Apoio!$B$4:$AB$4,0)+1),0) | E88: =IFERROR(INDEX(Apoio!$B:$AB,MATCH($C88,Apoio!$B$1:$B$176,0),MATCH('Fluxo de Caixa '!E$5,Apoio!$B$4:$AB$4,0)+1),0) | F88: =IFERROR(INDEX(Apoio!$B:$AB,MATCH($C88,Apoio!$B$1:$B$176,0),MATCH('Fluxo de Caixa '!F$5,Apoio!$B$4:$AB$4,0)+1),0) | G88: =IFERROR(INDEX(Apoio!$B:$AB,MATCH($C88,Apoio!$B$1:$B$176,0),MATCH('Fluxo de Caixa '!G$5,Apoio!$B$4:$AB$4,0)+1),0) | H88: =IFERROR(INDEX(Apoio!$B:$AB,MATCH($C88,Apoio!$B$1:$B$176,0),MATCH('Fluxo de Caixa '!H$5,Apoio!$B$4:$AB$4,0)+1),0) | I88: =IFERROR(INDEX(Apoio!$B:$AB,MATCH($C88,Apoio!$B$1:$B$176,0),MATCH('Fluxo de Caixa '!I$5,Apoio!$B$4:$AB$4,0)+1),0) | J88: =IFERROR(INDEX(Apoio!$B:$AB,MATCH($C88,Apoio!$B$1:$B$176,0),MATCH('Fluxo de Caixa '!J$5,Apoio!$B$4:$AB$4,0)+1),0) | K88: =IFERROR(INDEX(Apoio!$B:$AB,MATCH($C88,Apoio!$B$1:$B$176,0),MATCH('Fluxo de Caixa '!K$5,Apoio!$B$4:$AB$4,0)+1),0) | ... O88: =IFERROR(INDEX(Apoio!$B:$AB,MATCH($C88,Apoio!$B$1:$B$176,0),MATCH('Fluxo de Caixa '!O$5,Apoio!$B$4:$AB$4,0)+1),0) | Q88: =SUM(D88:P88)
C89: PEDAGIOS | D89: =IFERROR(INDEX(Apoio!$B:$AB,MATCH($C89,Apoio!$B$1:$B$176,0),MATCH('Fluxo de Caixa '!D$5,Apoio!$B$4:$AB$4,0)+1),0) | E89: =IFERROR(INDEX(Apoio!$B:$AB,MATCH($C89,Apoio!$B$1:$B$176,0),MATCH('Fluxo de Caixa '!E$5,Apoio!$B$4:$AB$4,0)+1),0) | F89: =IFERROR(INDEX(Apoio!$B:$AB,MATCH($C89,Apoio!$B$1:$B$176,0),MATCH('Fluxo de Caixa '!F$5,Apoio!$B$4:$AB$4,0)+1),0) | G89: =IFERROR(INDEX(Apoio!$B:$AB,MATCH($C89,Apoio!$B$1:$B$176,0),MATCH('Fluxo de Caixa '!G$5,Apoio!$B$4:$AB$4,0)+1),0) | H89: =IFERROR(INDEX(Apoio!$B:$AB,MATCH($C89,Apoio!$B$1:$B$176,0),MATCH('Fluxo de Caixa '!H$5,Apoio!$B$4:$AB$4,0)+1),0) | I89: =IFERROR(INDEX(Apoio!$B:$AB,MATCH($C89,Apoio!$B$1:$B$176,0),MATCH('Fluxo de Caixa '!I$5,Apoio!$B$4:$AB$4,0)+1),0) | J89: =IFERROR(INDEX(Apoio!$B:$AB,MATCH($C89,Apoio!$B$1:$B$176,0),MATCH('Fluxo de Caixa '!J$5,Apoio!$B$4:$AB$4,0)+1),0) | K89: =IFERROR(INDEX(Apoio!$B:$AB,MATCH($C89,Apoio!$B$1:$B$176,0),MATCH('Fluxo de Caixa '!K$5,Apoio!$B$4:$AB$4,0)+1),0) | ... O89: =IFERROR(INDEX(Apoio!$B:$AB,MATCH($C89,Apoio!$B$1:$B$176,0),MATCH('Fluxo de Caixa '!O$5,Apoio!$B$4:$AB$4,0)+1),0) | Q89: =SUM(D89:P89)
C90: DESPACHANTE | D90: =IFERROR(INDEX(Apoio!$B:$AB,MATCH($C90,Apoio!$B$1:$B$176,0),MATCH('Fluxo de Caixa '!D$5,Apoio!$B$4:$AB$4,0)+1),0) | E90: =IFERROR(INDEX(Apoio!$B:$AB,MATCH($C90,Apoio!$B$1:$B$176,0),MATCH('Fluxo de Caixa '!E$5,Apoio!$B$4:$AB$4,0)+1),0) | F90: =IFERROR(INDEX(Apoio!$B:$AB,MATCH($C90,Apoio!$B$1:$B$176,0),MATCH('Fluxo de Caixa '!F$5,Apoio!$B$4:$AB$4,0)+1),0) | G90: =IFERROR(INDEX(Apoio!$B:$AB,MATCH($C90,Apoio!$B$1:$B$176,0),MATCH('Fluxo de Caixa '!G$5,Apoio!$B$4:$AB$4,0)+1),0) | H90: =IFERROR(INDEX(Apoio!$B:$AB,MATCH($C90,Apoio!$B$1:$B$176,0),MATCH('Fluxo de Caixa '!H$5,Apoio!$B$4:$AB$4,0)+1),0) | I90: =IFERROR(INDEX(Apoio!$B:$AB,MATCH($C90,Apoio!$B$1:$B$176,0),MATCH('Fluxo de Caixa '!I$5,Apoio!$B$4:$AB$4,0)+1),0) | J90: =IFERROR(INDEX(Apoio!$B:$AB,MATCH($C90,Apoio!$B$1:$B$176,0),MATCH('Fluxo de Caixa '!J$5,Apoio!$B$4:$AB$4,0)+1),0) | K90: =IFERROR(INDEX(Apoio!$B:$AB,MATCH($C90,Apoio!$B$1:$B$176,0),MATCH('Fluxo de Caixa '!K$5,Apoio!$B$4:$AB$4,0)+1),0) | ... O90: =IFERROR(INDEX(Apoio!$B:$AB,MATCH($C90,Apoio!$B$1:$B$176,0),MATCH('Fluxo de Caixa '!O$5,Apoio!$B$4:$AB$4,0)+1),0) | Q90: =SUM(D90:P90)
C91: CUSTOS E GUIAS DE TRANSFERENCIA VEICULOS | D91: =IFERROR(INDEX(Apoio!$B:$AB,MATCH($C91,Apoio!$B$1:$B$176,0),MATCH('Fluxo de Caixa '!D$5,Apoio!$B$4:$AB$4,0)+1),0) | E91: =IFERROR(INDEX(Apoio!$B:$AB,MATCH($C91,Apoio!$B$1:$B$176,0),MATCH('Fluxo de Caixa '!E$5,Apoio!$B$4:$AB$4,0)+1),0) | F91: =IFERROR(INDEX(Apoio!$B:$AB,MATCH($C91,Apoio!$B$1:$B$176,0),MATCH('Fluxo de Caixa '!F$5,Apoio!$B$4:$AB$4,0)+1),0) | G91: =IFERROR(INDEX(Apoio!$B:$AB,MATCH($C91,Apoio!$B$1:$B$176,0),MATCH('Fluxo de Caixa '!G$5,Apoio!$B$4:$AB$4,0)+1),0) | H91: =IFERROR(INDEX(Apoio!$B:$AB,MATCH($C91,Apoio!$B$1:$B$176,0),MATCH('Fluxo de Caixa '!H$5,Apoio!$B$4:$AB$4,0)+1),0) | I91: =IFERROR(INDEX(Apoio!$B:$AB,MATCH($C91,Apoio!$B$1:$B$176,0),MATCH('Fluxo de Caixa '!I$5,Apoio!$B$4:$AB$4,0)+1),0) | J91: =IFERROR(INDEX(Apoio!$B:$AB,MATCH($C91,Apoio!$B$1:$B$176,0),MATCH('Fluxo de Caixa '!J$5,Apoio!$B$4:$AB$4,0)+1),0) | K91: =IFERROR(INDEX(Apoio!$B:$AB,MATCH($C91,Apoio!$B$1:$B$176,0),MATCH('Fluxo de Caixa '!K$5,Apoio!$B$4:$AB$4,0)+1),0) | ... O91: =IFERROR(INDEX(Apoio!$B:$AB,MATCH($C91,Apoio!$B$1:$B$176,0),MATCH('Fluxo de Caixa '!O$5,Apoio!$B$4:$AB$4,0)+1),0) | Q91: =SUM(D91:P91)
C92: GUINCHO | D92: =IFERROR(INDEX(Apoio!$B:$AB,MATCH($C92,Apoio!$B$1:$B$176,0),MATCH('Fluxo de Caixa '!D$5,Apoio!$B$4:$AB$4,0)+1),0) | E92: =IFERROR(INDEX(Apoio!$B:$AB,MATCH($C92,Apoio!$B$1:$B$176,0),MATCH('Fluxo de Caixa '!E$5,Apoio!$B$4:$AB$4,0)+1),0) | F92: =IFERROR(INDEX(Apoio!$B:$AB,MATCH($C92,Apoio!$B$1:$B$176,0),MATCH('Fluxo de Caixa '!F$5,Apoio!$B$4:$AB$4,0)+1),0) | G92: =IFERROR(INDEX(Apoio!$B:$AB,MATCH($C92,Apoio!$B$1:$B$176,0),MATCH('Fluxo de Caixa '!G$5,Apoio!$B$4:$AB$4,0)+1),0) | H92: =IFERROR(INDEX(Apoio!$B:$AB,MATCH($C92,Apoio!$B$1:$B$176,0),MATCH('Fluxo de Caixa '!H$5,Apoio!$B$4:$AB$4,0)+1),0) | I92: =IFERROR(INDEX(Apoio!$B:$AB,MATCH($C92,Apoio!$B$1:$B$176,0),MATCH('Fluxo de Caixa '!I$5,Apoio!$B$4:$AB$4,0)+1),0) | J92: =IFERROR(INDEX(Apoio!$B:$AB,MATCH($C92,Apoio!$B$1:$B$176,0),MATCH('Fluxo de Caixa '!J$5,Apoio!$B$4:$AB$4,0)+1),0) | K92: =IFERROR(INDEX(Apoio!$B:$AB,MATCH($C92,Apoio!$B$1:$B$176,0),MATCH('Fluxo de Caixa '!K$5,Apoio!$B$4:$AB$4,0)+1),0) | ... O92: =IFERROR(INDEX(Apoio!$B:$AB,MATCH($C92,Apoio!$B$1:$B$176,0),MATCH('Fluxo de Caixa '!O$5,Apoio!$B$4:$AB$4,0)+1),0) | Q92: =SUM(D92:P92)
C93: SERVIÇO LAVA JATO | D93: =IFERROR(INDEX(Apoio!$B:$AB,MATCH($C93,Apoio!$B$1:$B$176,0),MATCH('Fluxo de Caixa '!D$5,Apoio!$B$4:$AB$4,0)+1),0) | E93: =IFERROR(INDEX(Apoio!$B:$AB,MATCH($C93,Apoio!$B$1:$B$176,0),MATCH('Fluxo de Caixa '!E$5,Apoio!$B$4:$AB$4,0)+1),0) | F93: =IFERROR(INDEX(Apoio!$B:$AB,MATCH($C93,Apoio!$B$1:$B$176,0),MATCH('Fluxo de Caixa '!F$5,Apoio!$B$4:$AB$4,0)+1),0) | G93: =IFERROR(INDEX(Apoio!$B:$AB,MATCH($C93,Apoio!$B$1:$B$176,0),MATCH('Fluxo de Caixa '!G$5,Apoio!$B$4:$AB$4,0)+1),0) | H93: =IFERROR(INDEX(Apoio!$B:$AB,MATCH($C93,Apoio!$B$1:$B$176,0),MATCH('Fluxo de Caixa '!H$5,Apoio!$B$4:$AB$4,0)+1),0) | I93: =IFERROR(INDEX(Apoio!$B:$AB,MATCH($C93,Apoio!$B$1:$B$176,0),MATCH('Fluxo de Caixa '!I$5,Apoio!$B$4:$AB$4,0)+1),0) | J93: =IFERROR(INDEX(Apoio!$B:$AB,MATCH($C93,Apoio!$B$1:$B$176,0),MATCH('Fluxo de Caixa '!J$5,Apoio!$B$4:$AB$4,0)+1),0) | K93: =IFERROR(INDEX(Apoio!$B:$AB,MATCH($C93,Apoio!$B$1:$B$176,0),MATCH('Fluxo de Caixa '!K$5,Apoio!$B$4:$AB$4,0)+1),0) | ... O93: =IFERROR(INDEX(Apoio!$B:$AB,MATCH($C93,Apoio!$B$1:$B$176,0),MATCH('Fluxo de Caixa '!O$5,Apoio!$B$4:$AB$4,0)+1),0) | Q93: =SUM(D93:P93)
C95: Gastos com Locações | D95: =SUM(D96:D108) | E95: =SUM(E96:E108) | F95: =SUM(F96:F108) | G95: =SUM(G96:G108) | H95: =SUM(H96:H108) | I95: =SUM(I96:I108) | J95: =SUM(J96:J108) | K95: =SUM(K96:K108) | ... O95: =SUM(O96:O108) | Q95: =SUM(Q96:Q108)
C96: LOCAÇÃO MUNCK / GUINDASTES | D96: =IFERROR(INDEX(Apoio!$B:$AB,MATCH($C96,Apoio!$B$1:$B$176,0),MATCH('Fluxo de Caixa '!D$5,Apoio!$B$4:$AB$4,0)+1),0) | E96: =IFERROR(INDEX(Apoio!$B:$AB,MATCH($C96,Apoio!$B$1:$B$176,0),MATCH('Fluxo de Caixa '!E$5,Apoio!$B$4:$AB$4,0)+1),0) | F96: =IFERROR(INDEX(Apoio!$B:$AB,MATCH($C96,Apoio!$B$1:$B$176,0),MATCH('Fluxo de Caixa '!F$5,Apoio!$B$4:$AB$4,0)+1),0) | G96: =IFERROR(INDEX(Apoio!$B:$AB,MATCH($C96,Apoio!$B$1:$B$176,0),MATCH('Fluxo de Caixa '!G$5,Apoio!$B$4:$AB$4,0)+1),0) | H96: =IFERROR(INDEX(Apoio!$B:$AB,MATCH($C96,Apoio!$B$1:$B$176,0),MATCH('Fluxo de Caixa '!H$5,Apoio!$B$4:$AB$4,0)+1),0) | I96: =IFERROR(INDEX(Apoio!$B:$AB,MATCH($C96,Apoio!$B$1:$B$176,0),MATCH('Fluxo de Caixa '!I$5,Apoio!$B$4:$AB$4,0)+1),0) | J96: =IFERROR(INDEX(Apoio!$B:$AB,MATCH($C96,Apoio!$B$1:$B$176,0),MATCH('Fluxo de Caixa '!J$5,Apoio!$B$4:$AB$4,0)+1),0) | K96: =IFERROR(INDEX(Apoio!$B:$AB,MATCH($C96,Apoio!$B$1:$B$176,0),MATCH('Fluxo de Caixa '!K$5,Apoio!$B$4:$AB$4,0)+1),0) | ... O96: =IFERROR(INDEX(Apoio!$B:$AB,MATCH($C96,Apoio!$B$1:$B$176,0),MATCH('Fluxo de Caixa '!O$5,Apoio!$B$4:$AB$4,0)+1),0) | Q96: =SUM(D96:P96)
C97: LOCAÇÃO COMPRESSORES | D97: =IFERROR(INDEX(Apoio!$B:$AB,MATCH($C97,Apoio!$B$1:$B$176,0),MATCH('Fluxo de Caixa '!D$5,Apoio!$B$4:$AB$4,0)+1),0) | E97: =IFERROR(INDEX(Apoio!$B:$AB,MATCH($C97,Apoio!$B$1:$B$176,0),MATCH('Fluxo de Caixa '!E$5,Apoio!$B$4:$AB$4,0)+1),0) | F97: =IFERROR(INDEX(Apoio!$B:$AB,MATCH($C97,Apoio!$B$1:$B$176,0),MATCH('Fluxo de Caixa '!F$5,Apoio!$B$4:$AB$4,0)+1),0) | G97: =IFERROR(INDEX(Apoio!$B:$AB,MATCH($C97,Apoio!$B$1:$B$176,0),MATCH('Fluxo de Caixa '!G$5,Apoio!$B$4:$AB$4,0)+1),0) | H97: =IFERROR(INDEX(Apoio!$B:$AB,MATCH($C97,Apoio!$B$1:$B$176,0),MATCH('Fluxo de Caixa '!H$5,Apoio!$B$4:$AB$4,0)+1),0) | I97: =IFERROR(INDEX(Apoio!$B:$AB,MATCH($C97,Apoio!$B$1:$B$176,0),MATCH('Fluxo de Caixa '!I$5,Apoio!$B$4:$AB$4,0)+1),0) | J97: =IFERROR(INDEX(Apoio!$B:$AB,MATCH($C97,Apoio!$B$1:$B$176,0),MATCH('Fluxo de Caixa '!J$5,Apoio!$B$4:$AB$4,0)+1),0) | K97: =IFERROR(INDEX(Apoio!$B:$AB,MATCH($C97,Apoio!$B$1:$B$176,0),MATCH('Fluxo de Caixa '!K$5,Apoio!$B$4:$AB$4,0)+1),0) | ... O97: =IFERROR(INDEX(Apoio!$B:$AB,MATCH($C97,Apoio!$B$1:$B$176,0),MATCH('Fluxo de Caixa '!O$5,Apoio!$B$4:$AB$4,0)+1),0) | Q97: =SUM(D97:P97)
C98: LOCAÇÃO GERADOR | D98: =IFERROR(INDEX(Apoio!$B:$AB,MATCH($C98,Apoio!$B$1:$B$176,0),MATCH('Fluxo de Caixa '!D$5,Apoio!$B$4:$AB$4,0)+1),0) | E98: =IFERROR(INDEX(Apoio!$B:$AB,MATCH($C98,Apoio!$B$1:$B$176,0),MATCH('Fluxo de Caixa '!E$5,Apoio!$B$4:$AB$4,0)+1),0) | F98: =IFERROR(INDEX(Apoio!$B:$AB,MATCH($C98,Apoio!$B$1:$B$176,0),MATCH('Fluxo de Caixa '!F$5,Apoio!$B$4:$AB$4,0)+1),0) | G98: =IFERROR(INDEX(Apoio!$B:$AB,MATCH($C98,Apoio!$B$1:$B$176,0),MATCH('Fluxo de Caixa '!G$5,Apoio!$B$4:$AB$4,0)+1),0) | H98: =IFERROR(INDEX(Apoio!$B:$AB,MATCH($C98,Apoio!$B$1:$B$176,0),MATCH('Fluxo de Caixa '!H$5,Apoio!$B$4:$AB$4,0)+1),0) | I98: =IFERROR(INDEX(Apoio!$B:$AB,MATCH($C98,Apoio!$B$1:$B$176,0),MATCH('Fluxo de Caixa '!I$5,Apoio!$B$4:$AB$4,0)+1),0) | J98: =IFERROR(INDEX(Apoio!$B:$AB,MATCH($C98,Apoio!$B$1:$B$176,0),MATCH('Fluxo de Caixa '!J$5,Apoio!$B$4:$AB$4,0)+1),0) | K98: =IFERROR(INDEX(Apoio!$B:$AB,MATCH($C98,Apoio!$B$1:$B$176,0),MATCH('Fluxo de Caixa '!K$5,Apoio!$B$4:$AB$4,0)+1),0) | ... O98: =IFERROR(INDEX(Apoio!$B:$AB,MATCH($C98,Apoio!$B$1:$B$176,0),MATCH('Fluxo de Caixa '!O$5,Apoio!$B$4:$AB$4,0)+1),0) | Q98: =SUM(D98:P98)
C99: LOCAÇÃO EQUIPAMENTOS | D99: =IFERROR(INDEX(Apoio!$B:$AB,MATCH($C99,Apoio!$B$1:$B$176,0),MATCH('Fluxo de Caixa '!D$5,Apoio!$B$4:$AB$4,0)+1),0) | E99: =IFERROR(INDEX(Apoio!$B:$AB,MATCH($C99,Apoio!$B$1:$B$176,0),MATCH('Fluxo de Caixa '!E$5,Apoio!$B$4:$AB$4,0)+1),0) | F99: =IFERROR(INDEX(Apoio!$B:$AB,MATCH($C99,Apoio!$B$1:$B$176,0),MATCH('Fluxo de Caixa '!F$5,Apoio!$B$4:$AB$4,0)+1),0) | G99: =IFERROR(INDEX(Apoio!$B:$AB,MATCH($C99,Apoio!$B$1:$B$176,0),MATCH('Fluxo de Caixa '!G$5,Apoio!$B$4:$AB$4,0)+1),0) | H99: =IFERROR(INDEX(Apoio!$B:$AB,MATCH($C99,Apoio!$B$1:$B$176,0),MATCH('Fluxo de Caixa '!H$5,Apoio!$B$4:$AB$4,0)+1),0) | I99: =IFERROR(INDEX(Apoio!$B:$AB,MATCH($C99,Apoio!$B$1:$B$176,0),MATCH('Fluxo de Caixa '!I$5,Apoio!$B$4:$AB$4,0)+1),0) | J99: =IFERROR(INDEX(Apoio!$B:$AB,MATCH($C99,Apoio!$B$1:$B$176,0),MATCH('Fluxo de Caixa '!J$5,Apoio!$B$4:$AB$4,0)+1),0) | K99: =IFERROR(INDEX(Apoio!$B:$AB,MATCH($C99,Apoio!$B$1:$B$176,0),MATCH('Fluxo de Caixa '!K$5,Apoio!$B$4:$AB$4,0)+1),0) | ... O99: =IFERROR(INDEX(Apoio!$B:$AB,MATCH($C99,Apoio!$B$1:$B$176,0),MATCH('Fluxo de Caixa '!O$5,Apoio!$B$4:$AB$4,0)+1),0) | Q99: =SUM(D99:P99)
C100: LOCAÇÃO EMPILHADEIRA | D100: =IFERROR(INDEX(Apoio!$B:$AB,MATCH($C100,Apoio!$B$1:$B$176,0),MATCH('Fluxo de Caixa '!D$5,Apoio!$B$4:$AB$4,0)+1),0) | E100: =IFERROR(INDEX(Apoio!$B:$AB,MATCH($C100,Apoio!$B$1:$B$176,0),MATCH('Fluxo de Caixa '!E$5,Apoio!$B$4:$AB$4,0)+1),0) | F100: =IFERROR(INDEX(Apoio!$B:$AB,MATCH($C100,Apoio!$B$1:$B$176,0),MATCH('Fluxo de Caixa '!F$5,Apoio!$B$4:$AB$4,0)+1),0) | G100: =IFERROR(INDEX(Apoio!$B:$AB,MATCH($C100,Apoio!$B$1:$B$176,0),MATCH('Fluxo de Caixa '!G$5,Apoio!$B$4:$AB$4,0)+1),0) | H100: =IFERROR(INDEX(Apoio!$B:$AB,MATCH($C100,Apoio!$B$1:$B$176,0),MATCH('Fluxo de Caixa '!H$5,Apoio!$B$4:$AB$4,0)+1),0) | I100: =IFERROR(INDEX(Apoio!$B:$AB,MATCH($C100,Apoio!$B$1:$B$176,0),MATCH('Fluxo de Caixa '!I$5,Apoio!$B$4:$AB$4,0)+1),0) | J100: =IFERROR(INDEX(Apoio!$B:$AB,MATCH($C100,Apoio!$B$1:$B$176,0),MATCH('Fluxo de Caixa '!J$5,Apoio!$B$4:$AB$4,0)+1),0) | K100: =IFERROR(INDEX(Apoio!$B:$AB,MATCH($C100,Apoio!$B$1:$B$176,0),MATCH('Fluxo de Caixa '!K$5,Apoio!$B$4:$AB$4,0)+1),0) | ... O100: =IFERROR(INDEX(Apoio!$B:$AB,MATCH($C100,Apoio!$B$1:$B$176,0),MATCH('Fluxo de Caixa '!O$5,Apoio!$B$4:$AB$4,0)+1),0) | Q100: =SUM(D100:P100)
C101: LOCAÇÃO CONTAINER | D101: =IFERROR(INDEX(Apoio!$B:$AB,MATCH($C101,Apoio!$B$1:$B$176,0),MATCH('Fluxo de Caixa '!D$5,Apoio!$B$4:$AB$4,0)+1),0) | E101: =IFERROR(INDEX(Apoio!$B:$AB,MATCH($C101,Apoio!$B$1:$B$176,0),MATCH('Fluxo de Caixa '!E$5,Apoio!$B$4:$AB$4,0)+1),0) | F101: =IFERROR(INDEX(Apoio!$B:$AB,MATCH($C101,Apoio!$B$1:$B$176,0),MATCH('Fluxo de Caixa '!F$5,Apoio!$B$4:$AB$4,0)+1),0) | G101: =IFERROR(INDEX(Apoio!$B:$AB,MATCH($C101,Apoio!$B$1:$B$176,0),MATCH('Fluxo de Caixa '!G$5,Apoio!$B$4:$AB$4,0)+1),0) | H101: =IFERROR(INDEX(Apoio!$B:$AB,MATCH($C101,Apoio!$B$1:$B$176,0),MATCH('Fluxo de Caixa '!H$5,Apoio!$B$4:$AB$4,0)+1),0) | I101: =IFERROR(INDEX(Apoio!$B:$AB,MATCH($C101,Apoio!$B$1:$B$176,0),MATCH('Fluxo de Caixa '!I$5,Apoio!$B$4:$AB$4,0)+1),0) | J101: =IFERROR(INDEX(Apoio!$B:$AB,MATCH($C101,Apoio!$B$1:$B$176,0),MATCH('Fluxo de Caixa '!J$5,Apoio!$B$4:$AB$4,0)+1),0) | K101: =IFERROR(INDEX(Apoio!$B:$AB,MATCH($C101,Apoio!$B$1:$B$176,0),MATCH('Fluxo de Caixa '!K$5,Apoio!$B$4:$AB$4,0)+1),0) | ... O101: =IFERROR(INDEX(Apoio!$B:$AB,MATCH($C101,Apoio!$B$1:$B$176,0),MATCH('Fluxo de Caixa '!O$5,Apoio!$B$4:$AB$4,0)+1),0) | Q101: =SUM(D101:P101)
C102: LOCAÇÃO ANDAIMES | D102: =IFERROR(INDEX(Apoio!$B:$AB,MATCH($C102,Apoio!$B$1:$B$176,0),MATCH('Fluxo de Caixa '!D$5,Apoio!$B$4:$AB$4,0)+1),0) | E102: =IFERROR(INDEX(Apoio!$B:$AB,MATCH($C102,Apoio!$B$1:$B$176,0),MATCH('Fluxo de Caixa '!E$5,Apoio!$B$4:$AB$4,0)+1),0) | F102: =IFERROR(INDEX(Apoio!$B:$AB,MATCH($C102,Apoio!$B$1:$B$176,0),MATCH('Fluxo de Caixa '!F$5,Apoio!$B$4:$AB$4,0)+1),0) | G102: =IFERROR(INDEX(Apoio!$B:$AB,MATCH($C102,Apoio!$B$1:$B$176,0),MATCH('Fluxo de Caixa '!G$5,Apoio!$B$4:$AB$4,0)+1),0) | H102: =IFERROR(INDEX(Apoio!$B:$AB,MATCH($C102,Apoio!$B$1:$B$176,0),MATCH('Fluxo de Caixa '!H$5,Apoio!$B$4:$AB$4,0)+1),0) | I102: =IFERROR(INDEX(Apoio!$B:$AB,MATCH($C102,Apoio!$B$1:$B$176,0),MATCH('Fluxo de Caixa '!I$5,Apoio!$B$4:$AB$4,0)+1),0) | J102: =IFERROR(INDEX(Apoio!$B:$AB,MATCH($C102,Apoio!$B$1:$B$176,0),MATCH('Fluxo de Caixa '!J$5,Apoio!$B$4:$AB$4,0)+1),0) | K102: =IFERROR(INDEX(Apoio!$B:$AB,MATCH($C102,Apoio!$B$1:$B$176,0),MATCH('Fluxo de Caixa '!K$5,Apoio!$B$4:$AB$4,0)+1),0) | ... O102: =IFERROR(INDEX(Apoio!$B:$AB,MATCH($C102,Apoio!$B$1:$B$176,0),MATCH('Fluxo de Caixa '!O$5,Apoio!$B$4:$AB$4,0)+1),0) | Q102: =SUM(D102:P102)
C103: LOCAÇAO VEICULOS | D103: =IFERROR(INDEX(Apoio!$B:$AB,MATCH($C103,Apoio!$B$1:$B$176,0),MATCH('Fluxo de Caixa '!D$5,Apoio!$B$4:$AB$4,0)+1),0) | E103: =IFERROR(INDEX(Apoio!$B:$AB,MATCH($C103,Apoio!$B$1:$B$176,0),MATCH('Fluxo de Caixa '!E$5,Apoio!$B$4:$AB$4,0)+1),0) | F103: =IFERROR(INDEX(Apoio!$B:$AB,MATCH($C103,Apoio!$B$1:$B$176,0),MATCH('Fluxo de Caixa '!F$5,Apoio!$B$4:$AB$4,0)+1),0) | G103: =IFERROR(INDEX(Apoio!$B:$AB,MATCH($C103,Apoio!$B$1:$B$176,0),MATCH('Fluxo de Caixa '!G$5,Apoio!$B$4:$AB$4,0)+1),0) | H103: =IFERROR(INDEX(Apoio!$B:$AB,MATCH($C103,Apoio!$B$1:$B$176,0),MATCH('Fluxo de Caixa '!H$5,Apoio!$B$4:$AB$4,0)+1),0) | I103: =IFERROR(INDEX(Apoio!$B:$AB,MATCH($C103,Apoio!$B$1:$B$176,0),MATCH('Fluxo de Caixa '!I$5,Apoio!$B$4:$AB$4,0)+1),0) | J103: =IFERROR(INDEX(Apoio!$B:$AB,MATCH($C103,Apoio!$B$1:$B$176,0),MATCH('Fluxo de Caixa '!J$5,Apoio!$B$4:$AB$4,0)+1),0) | K103: =IFERROR(INDEX(Apoio!$B:$AB,MATCH($C103,Apoio!$B$1:$B$176,0),MATCH('Fluxo de Caixa '!K$5,Apoio!$B$4:$AB$4,0)+1),0) | ... O103: =IFERROR(INDEX(Apoio!$B:$AB,MATCH($C103,Apoio!$B$1:$B$176,0),MATCH('Fluxo de Caixa '!O$5,Apoio!$B$4:$AB$4,0)+1),0) | Q103: =SUM(D103:P103)
C104: LOCAÇAO CAÇAMBA P/ RESIDUOS | D104: =IFERROR(INDEX(Apoio!$B:$AB,MATCH($C104,Apoio!$B$1:$B$176,0),MATCH('Fluxo de Caixa '!D$5,Apoio!$B$4:$AB$4,0)+1),0) | E104: =IFERROR(INDEX(Apoio!$B:$AB,MATCH($C104,Apoio!$B$1:$B$176,0),MATCH('Fluxo de Caixa '!E$5,Apoio!$B$4:$AB$4,0)+1),0) | F104: =IFERROR(INDEX(Apoio!$B:$AB,MATCH($C104,Apoio!$B$1:$B$176,0),MATCH('Fluxo de Caixa '!F$5,Apoio!$B$4:$AB$4,0)+1),0) | G104: =IFERROR(INDEX(Apoio!$B:$AB,MATCH($C104,Apoio!$B$1:$B$176,0),MATCH('Fluxo de Caixa '!G$5,Apoio!$B$4:$AB$4,0)+1),0) | H104: =IFERROR(INDEX(Apoio!$B:$AB,MATCH($C104,Apoio!$B$1:$B$176,0),MATCH('Fluxo de Caixa '!H$5,Apoio!$B$4:$AB$4,0)+1),0) | I104: =IFERROR(INDEX(Apoio!$B:$AB,MATCH($C104,Apoio!$B$1:$B$176,0),MATCH('Fluxo de Caixa '!I$5,Apoio!$B$4:$AB$4,0)+1),0) | J104: =IFERROR(INDEX(Apoio!$B:$AB,MATCH($C104,Apoio!$B$1:$B$176,0),MATCH('Fluxo de Caixa '!J$5,Apoio!$B$4:$AB$4,0)+1),0) | K104: =IFERROR(INDEX(Apoio!$B:$AB,MATCH($C104,Apoio!$B$1:$B$176,0),MATCH('Fluxo de Caixa '!K$5,Apoio!$B$4:$AB$4,0)+1),0) | ... O104: =IFERROR(INDEX(Apoio!$B:$AB,MATCH($C104,Apoio!$B$1:$B$176,0),MATCH('Fluxo de Caixa '!O$5,Apoio!$B$4:$AB$4,0)+1),0) | Q104: =SUM(D104:P104)
C105: LOCAÇAO RADIOS DE COMUNICAÇÃO | D105: =IFERROR(INDEX(Apoio!$B:$AB,MATCH($C105,Apoio!$B$1:$B$176,0),MATCH('Fluxo de Caixa '!D$5,Apoio!$B$4:$AB$4,0)+1),0) | E105: =IFERROR(INDEX(Apoio!$B:$AB,MATCH($C105,Apoio!$B$1:$B$176,0),MATCH('Fluxo de Caixa '!E$5,Apoio!$B$4:$AB$4,0)+1),0) | F105: =IFERROR(INDEX(Apoio!$B:$AB,MATCH($C105,Apoio!$B$1:$B$176,0),MATCH('Fluxo de Caixa '!F$5,Apoio!$B$4:$AB$4,0)+1),0) | G105: =IFERROR(INDEX(Apoio!$B:$AB,MATCH($C105,Apoio!$B$1:$B$176,0),MATCH('Fluxo de Caixa '!G$5,Apoio!$B$4:$AB$4,0)+1),0) | H105: =IFERROR(INDEX(Apoio!$B:$AB,MATCH($C105,Apoio!$B$1:$B$176,0),MATCH('Fluxo de Caixa '!H$5,Apoio!$B$4:$AB$4,0)+1),0) | I105: =IFERROR(INDEX(Apoio!$B:$AB,MATCH($C105,Apoio!$B$1:$B$176,0),MATCH('Fluxo de Caixa '!I$5,Apoio!$B$4:$AB$4,0)+1),0) | J105: =IFERROR(INDEX(Apoio!$B:$AB,MATCH($C105,Apoio!$B$1:$B$176,0),MATCH('Fluxo de Caixa '!J$5,Apoio!$B$4:$AB$4,0)+1),0) | K105: =IFERROR(INDEX(Apoio!$B:$AB,MATCH($C105,Apoio!$B$1:$B$176,0),MATCH('Fluxo de Caixa '!K$5,Apoio!$B$4:$AB$4,0)+1),0) | ... O105: =IFERROR(INDEX(Apoio!$B:$AB,MATCH($C105,Apoio!$B$1:$B$176,0),MATCH('Fluxo de Caixa '!O$5,Apoio!$B$4:$AB$4,0)+1),0) | Q105: =SUM(D105:P105)
C106: LOCAÇAO BANHEIRO QUIMICO | D106: =IFERROR(INDEX(Apoio!$B:$AB,MATCH($C106,Apoio!$B$1:$B$176,0),MATCH('Fluxo de Caixa '!D$5,Apoio!$B$4:$AB$4,0)+1),0) | E106: =IFERROR(INDEX(Apoio!$B:$AB,MATCH($C106,Apoio!$B$1:$B$176,0),MATCH('Fluxo de Caixa '!E$5,Apoio!$B$4:$AB$4,0)+1),0) | F106: =IFERROR(INDEX(Apoio!$B:$AB,MATCH($C106,Apoio!$B$1:$B$176,0),MATCH('Fluxo de Caixa '!F$5,Apoio!$B$4:$AB$4,0)+1),0) | G106: =IFERROR(INDEX(Apoio!$B:$AB,MATCH($C106,Apoio!$B$1:$B$176,0),MATCH('Fluxo de Caixa '!G$5,Apoio!$B$4:$AB$4,0)+1),0) | H106: =IFERROR(INDEX(Apoio!$B:$AB,MATCH($C106,Apoio!$B$1:$B$176,0),MATCH('Fluxo de Caixa '!H$5,Apoio!$B$4:$AB$4,0)+1),0) | I106: =IFERROR(INDEX(Apoio!$B:$AB,MATCH($C106,Apoio!$B$1:$B$176,0),MATCH('Fluxo de Caixa '!I$5,Apoio!$B$4:$AB$4,0)+1),0) | J106: =IFERROR(INDEX(Apoio!$B:$AB,MATCH($C106,Apoio!$B$1:$B$176,0),MATCH('Fluxo de Caixa '!J$5,Apoio!$B$4:$AB$4,0)+1),0) | K106: =IFERROR(INDEX(Apoio!$B:$AB,MATCH($C106,Apoio!$B$1:$B$176,0),MATCH('Fluxo de Caixa '!K$5,Apoio!$B$4:$AB$4,0)+1),0) | ... O106: =IFERROR(INDEX(Apoio!$B:$AB,MATCH($C106,Apoio!$B$1:$B$176,0),MATCH('Fluxo de Caixa '!O$5,Apoio!$B$4:$AB$4,0)+1),0) | Q106: =SUM(D106:P106)
C107: LOCAÇAO PLATAFORMA ELEVATORIA | D107: =IFERROR(INDEX(Apoio!$B:$AB,MATCH($C107,Apoio!$B$1:$B$176,0),MATCH('Fluxo de Caixa '!D$5,Apoio!$B$4:$AB$4,0)+1),0) | E107: =IFERROR(INDEX(Apoio!$B:$AB,MATCH($C107,Apoio!$B$1:$B$176,0),MATCH('Fluxo de Caixa '!E$5,Apoio!$B$4:$AB$4,0)+1),0) | F107: =IFERROR(INDEX(Apoio!$B:$AB,MATCH($C107,Apoio!$B$1:$B$176,0),MATCH('Fluxo de Caixa '!F$5,Apoio!$B$4:$AB$4,0)+1),0) | G107: =IFERROR(INDEX(Apoio!$B:$AB,MATCH($C107,Apoio!$B$1:$B$176,0),MATCH('Fluxo de Caixa '!G$5,Apoio!$B$4:$AB$4,0)+1),0) | H107: =IFERROR(INDEX(Apoio!$B:$AB,MATCH($C107,Apoio!$B$1:$B$176,0),MATCH('Fluxo de Caixa '!H$5,Apoio!$B$4:$AB$4,0)+1),0) | I107: =IFERROR(INDEX(Apoio!$B:$AB,MATCH($C107,Apoio!$B$1:$B$176,0),MATCH('Fluxo de Caixa '!I$5,Apoio!$B$4:$AB$4,0)+1),0) | J107: =IFERROR(INDEX(Apoio!$B:$AB,MATCH($C107,Apoio!$B$1:$B$176,0),MATCH('Fluxo de Caixa '!J$5,Apoio!$B$4:$AB$4,0)+1),0) | K107: =IFERROR(INDEX(Apoio!$B:$AB,MATCH($C107,Apoio!$B$1:$B$176,0),MATCH('Fluxo de Caixa '!K$5,Apoio!$B$4:$AB$4,0)+1),0) | ... O107: =IFERROR(INDEX(Apoio!$B:$AB,MATCH($C107,Apoio!$B$1:$B$176,0),MATCH('Fluxo de Caixa '!O$5,Apoio!$B$4:$AB$4,0)+1),0) | Q107: =SUM(D107:P107)
C108: LOCAÇÃO AMBULANCIA / PRIMEIROS SOCORROS | D108: =IFERROR(INDEX(Apoio!$B:$AB,MATCH($C108,Apoio!$B$1:$B$176,0),MATCH('Fluxo de Caixa '!D$5,Apoio!$B$4:$AB$4,0)+1),0) | E108: =IFERROR(INDEX(Apoio!$B:$AB,MATCH($C108,Apoio!$B$1:$B$176,0),MATCH('Fluxo de Caixa '!E$5,Apoio!$B$4:$AB$4,0)+1),0) | F108: =IFERROR(INDEX(Apoio!$B:$AB,MATCH($C108,Apoio!$B$1:$B$176,0),MATCH('Fluxo de Caixa '!F$5,Apoio!$B$4:$AB$4,0)+1),0) | G108: =IFERROR(INDEX(Apoio!$B:$AB,MATCH($C108,Apoio!$B$1:$B$176,0),MATCH('Fluxo de Caixa '!G$5,Apoio!$B$4:$AB$4,0)+1),0) | H108: =IFERROR(INDEX(Apoio!$B:$AB,MATCH($C108,Apoio!$B$1:$B$176,0),MATCH('Fluxo de Caixa '!H$5,Apoio!$B$4:$AB$4,0)+1),0) | I108: =IFERROR(INDEX(Apoio!$B:$AB,MATCH($C108,Apoio!$B$1:$B$176,0),MATCH('Fluxo de Caixa '!I$5,Apoio!$B$4:$AB$4,0)+1),0) | J108: =IFERROR(INDEX(Apoio!$B:$AB,MATCH($C108,Apoio!$B$1:$B$176,0),MATCH('Fluxo de Caixa '!J$5,Apoio!$B$4:$AB$4,0)+1),0) | K108: =IFERROR(INDEX(Apoio!$B:$AB,MATCH($C108,Apoio!$B$1:$B$176,0),MATCH('Fluxo de Caixa '!K$5,Apoio!$B$4:$AB$4,0)+1),0) | ... O108: =IFERROR(INDEX(Apoio!$B:$AB,MATCH($C108,Apoio!$B$1:$B$176,0),MATCH('Fluxo de Caixa '!O$5,Apoio!$B$4:$AB$4,0)+1),0) | Q108: =SUM(D108:P108)
C110: Gastos com Máquinas e Equipamentos | D110: =SUM(D111:D124) | E110: =SUM(E111:E124) | F110: =SUM(F111:F124) | G110: =SUM(G111:G124) | H110: =SUM(H111:H124) | I110: =SUM(I111:I124) | J110: =SUM(J111:J124) | K110: =SUM(K111:K124) | ... O110: =SUM(O111:O124) | Q110: =SUM(Q111:Q124)
C111: MAQUINAS / FERRAMENTAS COMBUSTÃO | D111: =IFERROR(INDEX(Apoio!$B:$AB,MATCH($C111,Apoio!$B$1:$B$176,0),MATCH('Fluxo de Caixa '!D$5,Apoio!$B$4:$AB$4,0)+1),0) | E111: =IFERROR(INDEX(Apoio!$B:$AB,MATCH($C111,Apoio!$B$1:$B$176,0),MATCH('Fluxo de Caixa '!E$5,Apoio!$B$4:$AB$4,0)+1),0) | F111: =IFERROR(INDEX(Apoio!$B:$AB,MATCH($C111,Apoio!$B$1:$B$176,0),MATCH('Fluxo de Caixa '!F$5,Apoio!$B$4:$AB$4,0)+1),0) | G111: =IFERROR(INDEX(Apoio!$B:$AB,MATCH($C111,Apoio!$B$1:$B$176,0),MATCH('Fluxo de Caixa '!G$5,Apoio!$B$4:$AB$4,0)+1),0) | H111: =IFERROR(INDEX(Apoio!$B:$AB,MATCH($C111,Apoio!$B$1:$B$176,0),MATCH('Fluxo de Caixa '!H$5,Apoio!$B$4:$AB$4,0)+1),0) | I111: =IFERROR(INDEX(Apoio!$B:$AB,MATCH($C111,Apoio!$B$1:$B$176,0),MATCH('Fluxo de Caixa '!I$5,Apoio!$B$4:$AB$4,0)+1),0) | J111: =IFERROR(INDEX(Apoio!$B:$AB,MATCH($C111,Apoio!$B$1:$B$176,0),MATCH('Fluxo de Caixa '!J$5,Apoio!$B$4:$AB$4,0)+1),0) | K111: =IFERROR(INDEX(Apoio!$B:$AB,MATCH($C111,Apoio!$B$1:$B$176,0),MATCH('Fluxo de Caixa '!K$5,Apoio!$B$4:$AB$4,0)+1),0) | ... O111: =IFERROR(INDEX(Apoio!$B:$AB,MATCH($C111,Apoio!$B$1:$B$176,0),MATCH('Fluxo de Caixa '!O$5,Apoio!$B$4:$AB$4,0)+1),0) | Q111: =SUM(D111:P111)
C112: MAQUINAS / FERRAMENTAS ELETRICAS | D112: =IFERROR(INDEX(Apoio!$B:$AB,MATCH($C112,Apoio!$B$1:$B$176,0),MATCH('Fluxo de Caixa '!D$5,Apoio!$B$4:$AB$4,0)+1),0) | E112: =IFERROR(INDEX(Apoio!$B:$AB,MATCH($C112,Apoio!$B$1:$B$176,0),MATCH('Fluxo de Caixa '!E$5,Apoio!$B$4:$AB$4,0)+1),0) | F112: =IFERROR(INDEX(Apoio!$B:$AB,MATCH($C112,Apoio!$B$1:$B$176,0),MATCH('Fluxo de Caixa '!F$5,Apoio!$B$4:$AB$4,0)+1),0) | G112: =IFERROR(INDEX(Apoio!$B:$AB,MATCH($C112,Apoio!$B$1:$B$176,0),MATCH('Fluxo de Caixa '!G$5,Apoio!$B$4:$AB$4,0)+1),0) | H112: =IFERROR(INDEX(Apoio!$B:$AB,MATCH($C112,Apoio!$B$1:$B$176,0),MATCH('Fluxo de Caixa '!H$5,Apoio!$B$4:$AB$4,0)+1),0) | I112: =IFERROR(INDEX(Apoio!$B:$AB,MATCH($C112,Apoio!$B$1:$B$176,0),MATCH('Fluxo de Caixa '!I$5,Apoio!$B$4:$AB$4,0)+1),0) | J112: =IFERROR(INDEX(Apoio!$B:$AB,MATCH($C112,Apoio!$B$1:$B$176,0),MATCH('Fluxo de Caixa '!J$5,Apoio!$B$4:$AB$4,0)+1),0) | K112: =IFERROR(INDEX(Apoio!$B:$AB,MATCH($C112,Apoio!$B$1:$B$176,0),MATCH('Fluxo de Caixa '!K$5,Apoio!$B$4:$AB$4,0)+1),0) | ... O112: =IFERROR(INDEX(Apoio!$B:$AB,MATCH($C112,Apoio!$B$1:$B$176,0),MATCH('Fluxo de Caixa '!O$5,Apoio!$B$4:$AB$4,0)+1),0) | Q112: =SUM(D112:P112)
C113: MAQUINAS / FERRAMENTAS PNEUMATICAS | D113: =IFERROR(INDEX(Apoio!$B:$AB,MATCH($C113,Apoio!$B$1:$B$176,0),MATCH('Fluxo de Caixa '!D$5,Apoio!$B$4:$AB$4,0)+1),0) | E113: =IFERROR(INDEX(Apoio!$B:$AB,MATCH($C113,Apoio!$B$1:$B$176,0),MATCH('Fluxo de Caixa '!E$5,Apoio!$B$4:$AB$4,0)+1),0) | F113: =IFERROR(INDEX(Apoio!$B:$AB,MATCH($C113,Apoio!$B$1:$B$176,0),MATCH('Fluxo de Caixa '!F$5,Apoio!$B$4:$AB$4,0)+1),0) | G113: =IFERROR(INDEX(Apoio!$B:$AB,MATCH($C113,Apoio!$B$1:$B$176,0),MATCH('Fluxo de Caixa '!G$5,Apoio!$B$4:$AB$4,0)+1),0) | H113: =IFERROR(INDEX(Apoio!$B:$AB,MATCH($C113,Apoio!$B$1:$B$176,0),MATCH('Fluxo de Caixa '!H$5,Apoio!$B$4:$AB$4,0)+1),0) | I113: =IFERROR(INDEX(Apoio!$B:$AB,MATCH($C113,Apoio!$B$1:$B$176,0),MATCH('Fluxo de Caixa '!I$5,Apoio!$B$4:$AB$4,0)+1),0) | J113: =IFERROR(INDEX(Apoio!$B:$AB,MATCH($C113,Apoio!$B$1:$B$176,0),MATCH('Fluxo de Caixa '!J$5,Apoio!$B$4:$AB$4,0)+1),0) | K113: =IFERROR(INDEX(Apoio!$B:$AB,MATCH($C113,Apoio!$B$1:$B$176,0),MATCH('Fluxo de Caixa '!K$5,Apoio!$B$4:$AB$4,0)+1),0) | ... O113: =IFERROR(INDEX(Apoio!$B:$AB,MATCH($C113,Apoio!$B$1:$B$176,0),MATCH('Fluxo de Caixa '!O$5,Apoio!$B$4:$AB$4,0)+1),0) | Q113: =SUM(D113:P113)
C114: MAQUINAS / EQUIPAMENTOS | D114: =IFERROR(INDEX(Apoio!$B:$AB,MATCH($C114,Apoio!$B$1:$B$176,0),MATCH('Fluxo de Caixa '!D$5,Apoio!$B$4:$AB$4,0)+1),0) | E114: =IFERROR(INDEX(Apoio!$B:$AB,MATCH($C114,Apoio!$B$1:$B$176,0),MATCH('Fluxo de Caixa '!E$5,Apoio!$B$4:$AB$4,0)+1),0) | F114: =IFERROR(INDEX(Apoio!$B:$AB,MATCH($C114,Apoio!$B$1:$B$176,0),MATCH('Fluxo de Caixa '!F$5,Apoio!$B$4:$AB$4,0)+1),0) | G114: =IFERROR(INDEX(Apoio!$B:$AB,MATCH($C114,Apoio!$B$1:$B$176,0),MATCH('Fluxo de Caixa '!G$5,Apoio!$B$4:$AB$4,0)+1),0) | H114: =IFERROR(INDEX(Apoio!$B:$AB,MATCH($C114,Apoio!$B$1:$B$176,0),MATCH('Fluxo de Caixa '!H$5,Apoio!$B$4:$AB$4,0)+1),0) | I114: =IFERROR(INDEX(Apoio!$B:$AB,MATCH($C114,Apoio!$B$1:$B$176,0),MATCH('Fluxo de Caixa '!I$5,Apoio!$B$4:$AB$4,0)+1),0) | J114: =IFERROR(INDEX(Apoio!$B:$AB,MATCH($C114,Apoio!$B$1:$B$176,0),MATCH('Fluxo de Caixa '!J$5,Apoio!$B$4:$AB$4,0)+1),0) | K114: =IFERROR(INDEX(Apoio!$B:$AB,MATCH($C114,Apoio!$B$1:$B$176,0),MATCH('Fluxo de Caixa '!K$5,Apoio!$B$4:$AB$4,0)+1),0) | ... O114: =IFERROR(INDEX(Apoio!$B:$AB,MATCH($C114,Apoio!$B$1:$B$176,0),MATCH('Fluxo de Caixa '!O$5,Apoio!$B$4:$AB$4,0)+1),0) | Q114: =SUM(D114:P114)
C115: MATERIAIS / FERRAMENTAS MANUAIS | D115: =IFERROR(INDEX(Apoio!$B:$AB,MATCH($C115,Apoio!$B$1:$B$176,0),MATCH('Fluxo de Caixa '!D$5,Apoio!$B$4:$AB$4,0)+1),0) | E115: =IFERROR(INDEX(Apoio!$B:$AB,MATCH($C115,Apoio!$B$1:$B$176,0),MATCH('Fluxo de Caixa '!E$5,Apoio!$B$4:$AB$4,0)+1),0) | F115: =IFERROR(INDEX(Apoio!$B:$AB,MATCH($C115,Apoio!$B$1:$B$176,0),MATCH('Fluxo de Caixa '!F$5,Apoio!$B$4:$AB$4,0)+1),0) | G115: =IFERROR(INDEX(Apoio!$B:$AB,MATCH($C115,Apoio!$B$1:$B$176,0),MATCH('Fluxo de Caixa '!G$5,Apoio!$B$4:$AB$4,0)+1),0) | H115: =IFERROR(INDEX(Apoio!$B:$AB,MATCH($C115,Apoio!$B$1:$B$176,0),MATCH('Fluxo de Caixa '!H$5,Apoio!$B$4:$AB$4,0)+1),0) | I115: =IFERROR(INDEX(Apoio!$B:$AB,MATCH($C115,Apoio!$B$1:$B$176,0),MATCH('Fluxo de Caixa '!I$5,Apoio!$B$4:$AB$4,0)+1),0) | J115: =IFERROR(INDEX(Apoio!$B:$AB,MATCH($C115,Apoio!$B$1:$B$176,0),MATCH('Fluxo de Caixa '!J$5,Apoio!$B$4:$AB$4,0)+1),0) | K115: =IFERROR(INDEX(Apoio!$B:$AB,MATCH($C115,Apoio!$B$1:$B$176,0),MATCH('Fluxo de Caixa '!K$5,Apoio!$B$4:$AB$4,0)+1),0) | ... O115: =IFERROR(INDEX(Apoio!$B:$AB,MATCH($C115,Apoio!$B$1:$B$176,0),MATCH('Fluxo de Caixa '!O$5,Apoio!$B$4:$AB$4,0)+1),0) | Q115: =SUM(D115:P115)
C116: MANGUEIRAS / CONEXÕES | D116: =IFERROR(INDEX(Apoio!$B:$AB,MATCH($C116,Apoio!$B$1:$B$176,0),MATCH('Fluxo de Caixa '!D$5,Apoio!$B$4:$AB$4,0)+1),0) | E116: =IFERROR(INDEX(Apoio!$B:$AB,MATCH($C116,Apoio!$B$1:$B$176,0),MATCH('Fluxo de Caixa '!E$5,Apoio!$B$4:$AB$4,0)+1),0) | F116: =IFERROR(INDEX(Apoio!$B:$AB,MATCH($C116,Apoio!$B$1:$B$176,0),MATCH('Fluxo de Caixa '!F$5,Apoio!$B$4:$AB$4,0)+1),0) | G116: =IFERROR(INDEX(Apoio!$B:$AB,MATCH($C116,Apoio!$B$1:$B$176,0),MATCH('Fluxo de Caixa '!G$5,Apoio!$B$4:$AB$4,0)+1),0) | H116: =IFERROR(INDEX(Apoio!$B:$AB,MATCH($C116,Apoio!$B$1:$B$176,0),MATCH('Fluxo de Caixa '!H$5,Apoio!$B$4:$AB$4,0)+1),0) | I116: =IFERROR(INDEX(Apoio!$B:$AB,MATCH($C116,Apoio!$B$1:$B$176,0),MATCH('Fluxo de Caixa '!I$5,Apoio!$B$4:$AB$4,0)+1),0) | J116: =IFERROR(INDEX(Apoio!$B:$AB,MATCH($C116,Apoio!$B$1:$B$176,0),MATCH('Fluxo de Caixa '!J$5,Apoio!$B$4:$AB$4,0)+1),0) | K116: =IFERROR(INDEX(Apoio!$B:$AB,MATCH($C116,Apoio!$B$1:$B$176,0),MATCH('Fluxo de Caixa '!K$5,Apoio!$B$4:$AB$4,0)+1),0) | ... O116: =IFERROR(INDEX(Apoio!$B:$AB,MATCH($C116,Apoio!$B$1:$B$176,0),MATCH('Fluxo de Caixa '!O$5,Apoio!$B$4:$AB$4,0)+1),0) | Q116: =SUM(D116:P116)
C117: MATERIAL ELETRICO | D117: =IFERROR(INDEX(Apoio!$B:$AB,MATCH($C117,Apoio!$B$1:$B$176,0),MATCH('Fluxo de Caixa '!D$5,Apoio!$B$4:$AB$4,0)+1),0) | E117: =IFERROR(INDEX(Apoio!$B:$AB,MATCH($C117,Apoio!$B$1:$B$176,0),MATCH('Fluxo de Caixa '!E$5,Apoio!$B$4:$AB$4,0)+1),0) | F117: =IFERROR(INDEX(Apoio!$B:$AB,MATCH($C117,Apoio!$B$1:$B$176,0),MATCH('Fluxo de Caixa '!F$5,Apoio!$B$4:$AB$4,0)+1),0) | G117: =IFERROR(INDEX(Apoio!$B:$AB,MATCH($C117,Apoio!$B$1:$B$176,0),MATCH('Fluxo de Caixa '!G$5,Apoio!$B$4:$AB$4,0)+1),0) | H117: =IFERROR(INDEX(Apoio!$B:$AB,MATCH($C117,Apoio!$B$1:$B$176,0),MATCH('Fluxo de Caixa '!H$5,Apoio!$B$4:$AB$4,0)+1),0) | I117: =IFERROR(INDEX(Apoio!$B:$AB,MATCH($C117,Apoio!$B$1:$B$176,0),MATCH('Fluxo de Caixa '!I$5,Apoio!$B$4:$AB$4,0)+1),0) | J117: =IFERROR(INDEX(Apoio!$B:$AB,MATCH($C117,Apoio!$B$1:$B$176,0),MATCH('Fluxo de Caixa '!J$5,Apoio!$B$4:$AB$4,0)+1),0) | K117: =IFERROR(INDEX(Apoio!$B:$AB,MATCH($C117,Apoio!$B$1:$B$176,0),MATCH('Fluxo de Caixa '!K$5,Apoio!$B$4:$AB$4,0)+1),0) | ... O117: =IFERROR(INDEX(Apoio!$B:$AB,MATCH($C117,Apoio!$B$1:$B$176,0),MATCH('Fluxo de Caixa '!O$5,Apoio!$B$4:$AB$4,0)+1),0) | Q117: =SUM(D117:P117)
C118: MATERIAIS DE CONSUMO EM OBRAS | D118: =IFERROR(INDEX(Apoio!$B:$AB,MATCH($C118,Apoio!$B$1:$B$176,0),MATCH('Fluxo de Caixa '!D$5,Apoio!$B$4:$AB$4,0)+1),0) | E118: =IFERROR(INDEX(Apoio!$B:$AB,MATCH($C118,Apoio!$B$1:$B$176,0),MATCH('Fluxo de Caixa '!E$5,Apoio!$B$4:$AB$4,0)+1),0) | F118: =IFERROR(INDEX(Apoio!$B:$AB,MATCH($C118,Apoio!$B$1:$B$176,0),MATCH('Fluxo de Caixa '!F$5,Apoio!$B$4:$AB$4,0)+1),0) | G118: =IFERROR(INDEX(Apoio!$B:$AB,MATCH($C118,Apoio!$B$1:$B$176,0),MATCH('Fluxo de Caixa '!G$5,Apoio!$B$4:$AB$4,0)+1),0) | H118: =IFERROR(INDEX(Apoio!$B:$AB,MATCH($C118,Apoio!$B$1:$B$176,0),MATCH('Fluxo de Caixa '!H$5,Apoio!$B$4:$AB$4,0)+1),0) | I118: =IFERROR(INDEX(Apoio!$B:$AB,MATCH($C118,Apoio!$B$1:$B$176,0),MATCH('Fluxo de Caixa '!I$5,Apoio!$B$4:$AB$4,0)+1),0) | J118: =IFERROR(INDEX(Apoio!$B:$AB,MATCH($C118,Apoio!$B$1:$B$176,0),MATCH('Fluxo de Caixa '!J$5,Apoio!$B$4:$AB$4,0)+1),0) | K118: =IFERROR(INDEX(Apoio!$B:$AB,MATCH($C118,Apoio!$B$1:$B$176,0),MATCH('Fluxo de Caixa '!K$5,Apoio!$B$4:$AB$4,0)+1),0) | ... O118: =IFERROR(INDEX(Apoio!$B:$AB,MATCH($C118,Apoio!$B$1:$B$176,0),MATCH('Fluxo de Caixa '!O$5,Apoio!$B$4:$AB$4,0)+1),0) | Q118: =SUM(D118:P118)
C119: MATERIAIS PINCEL / ROLOS / LIXAS | D119: =IFERROR(INDEX(Apoio!$B:$AB,MATCH($C119,Apoio!$B$1:$B$176,0),MATCH('Fluxo de Caixa '!D$5,Apoio!$B$4:$AB$4,0)+1),0) | E119: =IFERROR(INDEX(Apoio!$B:$AB,MATCH($C119,Apoio!$B$1:$B$176,0),MATCH('Fluxo de Caixa '!E$5,Apoio!$B$4:$AB$4,0)+1),0) | F119: =IFERROR(INDEX(Apoio!$B:$AB,MATCH($C119,Apoio!$B$1:$B$176,0),MATCH('Fluxo de Caixa '!F$5,Apoio!$B$4:$AB$4,0)+1),0) | G119: =IFERROR(INDEX(Apoio!$B:$AB,MATCH($C119,Apoio!$B$1:$B$176,0),MATCH('Fluxo de Caixa '!G$5,Apoio!$B$4:$AB$4,0)+1),0) | H119: =IFERROR(INDEX(Apoio!$B:$AB,MATCH($C119,Apoio!$B$1:$B$176,0),MATCH('Fluxo de Caixa '!H$5,Apoio!$B$4:$AB$4,0)+1),0) | I119: =IFERROR(INDEX(Apoio!$B:$AB,MATCH($C119,Apoio!$B$1:$B$176,0),MATCH('Fluxo de Caixa '!I$5,Apoio!$B$4:$AB$4,0)+1),0) | J119: =IFERROR(INDEX(Apoio!$B:$AB,MATCH($C119,Apoio!$B$1:$B$176,0),MATCH('Fluxo de Caixa '!J$5,Apoio!$B$4:$AB$4,0)+1),0) | K119: =IFERROR(INDEX(Apoio!$B:$AB,MATCH($C119,Apoio!$B$1:$B$176,0),MATCH('Fluxo de Caixa '!K$5,Apoio!$B$4:$AB$4,0)+1),0) | ... O119: =IFERROR(INDEX(Apoio!$B:$AB,MATCH($C119,Apoio!$B$1:$B$176,0),MATCH('Fluxo de Caixa '!O$5,Apoio!$B$4:$AB$4,0)+1),0) | Q119: =SUM(D119:P119)
C120: MATERIAS DE ESCRITORIO / PAPELARIA | D120: =IFERROR(INDEX(Apoio!$B:$AB,MATCH($C120,Apoio!$B$1:$B$176,0),MATCH('Fluxo de Caixa '!D$5,Apoio!$B$4:$AB$4,0)+1),0) | E120: =IFERROR(INDEX(Apoio!$B:$AB,MATCH($C120,Apoio!$B$1:$B$176,0),MATCH('Fluxo de Caixa '!E$5,Apoio!$B$4:$AB$4,0)+1),0) | F120: =IFERROR(INDEX(Apoio!$B:$AB,MATCH($C120,Apoio!$B$1:$B$176,0),MATCH('Fluxo de Caixa '!F$5,Apoio!$B$4:$AB$4,0)+1),0) | G120: =IFERROR(INDEX(Apoio!$B:$AB,MATCH($C120,Apoio!$B$1:$B$176,0),MATCH('Fluxo de Caixa '!G$5,Apoio!$B$4:$AB$4,0)+1),0) | H120: =IFERROR(INDEX(Apoio!$B:$AB,MATCH($C120,Apoio!$B$1:$B$176,0),MATCH('Fluxo de Caixa '!H$5,Apoio!$B$4:$AB$4,0)+1),0) | I120: =IFERROR(INDEX(Apoio!$B:$AB,MATCH($C120,Apoio!$B$1:$B$176,0),MATCH('Fluxo de Caixa '!I$5,Apoio!$B$4:$AB$4,0)+1),0) | J120: =IFERROR(INDEX(Apoio!$B:$AB,MATCH($C120,Apoio!$B$1:$B$176,0),MATCH('Fluxo de Caixa '!J$5,Apoio!$B$4:$AB$4,0)+1),0) | K120: =IFERROR(INDEX(Apoio!$B:$AB,MATCH($C120,Apoio!$B$1:$B$176,0),MATCH('Fluxo de Caixa '!K$5,Apoio!$B$4:$AB$4,0)+1),0) | ... O120: =IFERROR(INDEX(Apoio!$B:$AB,MATCH($C120,Apoio!$B$1:$B$176,0),MATCH('Fluxo de Caixa '!O$5,Apoio!$B$4:$AB$4,0)+1),0) | Q120: =SUM(D120:P120)
C121: MATERIAIS DE LIMPEZA / HIGIENE | D121: =IFERROR(INDEX(Apoio!$B:$AB,MATCH($C121,Apoio!$B$1:$B$176,0),MATCH('Fluxo de Caixa '!D$5,Apoio!$B$4:$AB$4,0)+1),0) | E121: =IFERROR(INDEX(Apoio!$B:$AB,MATCH($C121,Apoio!$B$1:$B$176,0),MATCH('Fluxo de Caixa '!E$5,Apoio!$B$4:$AB$4,0)+1),0) | F121: =IFERROR(INDEX(Apoio!$B:$AB,MATCH($C121,Apoio!$B$1:$B$176,0),MATCH('Fluxo de Caixa '!F$5,Apoio!$B$4:$AB$4,0)+1),0) | G121: =IFERROR(INDEX(Apoio!$B:$AB,MATCH($C121,Apoio!$B$1:$B$176,0),MATCH('Fluxo de Caixa '!G$5,Apoio!$B$4:$AB$4,0)+1),0) | H121: =IFERROR(INDEX(Apoio!$B:$AB,MATCH($C121,Apoio!$B$1:$B$176,0),MATCH('Fluxo de Caixa '!H$5,Apoio!$B$4:$AB$4,0)+1),0) | I121: =IFERROR(INDEX(Apoio!$B:$AB,MATCH($C121,Apoio!$B$1:$B$176,0),MATCH('Fluxo de Caixa '!I$5,Apoio!$B$4:$AB$4,0)+1),0) | J121: =IFERROR(INDEX(Apoio!$B:$AB,MATCH($C121,Apoio!$B$1:$B$176,0),MATCH('Fluxo de Caixa '!J$5,Apoio!$B$4:$AB$4,0)+1),0) | K121: =IFERROR(INDEX(Apoio!$B:$AB,MATCH($C121,Apoio!$B$1:$B$176,0),MATCH('Fluxo de Caixa '!K$5,Apoio!$B$4:$AB$4,0)+1),0) | ... O121: =IFERROR(INDEX(Apoio!$B:$AB,MATCH($C121,Apoio!$B$1:$B$176,0),MATCH('Fluxo de Caixa '!O$5,Apoio!$B$4:$AB$4,0)+1),0) | Q121: =SUM(D121:P121)
C122: EQUIPAMENTOS DE AFERIÇÃO | D122: =IFERROR(INDEX(Apoio!$B:$AB,MATCH($C122,Apoio!$B$1:$B$176,0),MATCH('Fluxo de Caixa '!D$5,Apoio!$B$4:$AB$4,0)+1),0) | E122: =IFERROR(INDEX(Apoio!$B:$AB,MATCH($C122,Apoio!$B$1:$B$176,0),MATCH('Fluxo de Caixa '!E$5,Apoio!$B$4:$AB$4,0)+1),0) | F122: =IFERROR(INDEX(Apoio!$B:$AB,MATCH($C122,Apoio!$B$1:$B$176,0),MATCH('Fluxo de Caixa '!F$5,Apoio!$B$4:$AB$4,0)+1),0) | G122: =IFERROR(INDEX(Apoio!$B:$AB,MATCH($C122,Apoio!$B$1:$B$176,0),MATCH('Fluxo de Caixa '!G$5,Apoio!$B$4:$AB$4,0)+1),0) | H122: =IFERROR(INDEX(Apoio!$B:$AB,MATCH($C122,Apoio!$B$1:$B$176,0),MATCH('Fluxo de Caixa '!H$5,Apoio!$B$4:$AB$4,0)+1),0) | I122: =IFERROR(INDEX(Apoio!$B:$AB,MATCH($C122,Apoio!$B$1:$B$176,0),MATCH('Fluxo de Caixa '!I$5,Apoio!$B$4:$AB$4,0)+1),0) | J122: =IFERROR(INDEX(Apoio!$B:$AB,MATCH($C122,Apoio!$B$1:$B$176,0),MATCH('Fluxo de Caixa '!J$5,Apoio!$B$4:$AB$4,0)+1),0) | K122: =IFERROR(INDEX(Apoio!$B:$AB,MATCH($C122,Apoio!$B$1:$B$176,0),MATCH('Fluxo de Caixa '!K$5,Apoio!$B$4:$AB$4,0)+1),0) | ... O122: =IFERROR(INDEX(Apoio!$B:$AB,MATCH($C122,Apoio!$B$1:$B$176,0),MATCH('Fluxo de Caixa '!O$5,Apoio!$B$4:$AB$4,0)+1),0) | Q122: =SUM(D122:P122)
... C124: MANUTENÇÃO/PEÇAS MAQUINAS E EQUIPAMENTOS | D124: =IFERROR(INDEX(Apoio!$B:$AB,MATCH($C124,Apoio!$B$1:$B$176,0),MATCH('Fluxo de Caixa '!D$5,Apoio!$B$4:$AB$4,0)+1),0) | E124: =IFERROR(INDEX(Apoio!$B:$AB,MATCH($C124,Apoio!$B$1:$B$176,0),MATCH('Fluxo de Caixa '!E$5,Apoio!$B$4:$AB$4,0)+1),0) | F124: =IFERROR(INDEX(Apoio!$B:$AB,MATCH($C124,Apoio!$B$1:$B$176,0),MATCH('Fluxo de Caixa '!F$5,Apoio!$B$4:$AB$4,0)+1),0) | G124: =IFERROR(INDEX(Apoio!$B:$AB,MATCH($C124,Apoio!$B$1:$B$176,0),MATCH('Fluxo de Caixa '!G$5,Apoio!$B$4:$AB$4,0)+1),0) | H124: =IFERROR(INDEX(Apoio!$B:$AB,MATCH($C124,Apoio!$B$1:$B$176,0),MATCH('Fluxo de Caixa '!H$5,Apoio!$B$4:$AB$4,0)+1),0) | I124: =IFERROR(INDEX(Apoio!$B:$AB,MATCH($C124,Apoio!$B$1:$B$176,0),MATCH('Fluxo de Caixa '!I$5,Apoio!$B$4:$AB$4,0)+1),0) | J124: =IFERROR(INDEX(Apoio!$B:$AB,MATCH($C124,Apoio!$B$1:$B$176,0),MATCH('Fluxo de Caixa '!J$5,Apoio!$B$4:$AB$4,0)+1),0) | K124: =IFERROR(INDEX(Apoio!$B:$AB,MATCH($C124,Apoio!$B$1:$B$176,0),MATCH('Fluxo de Caixa '!K$5,Apoio!$B$4:$AB$4,0)+1),0) | ... O124: =IFERROR(INDEX(Apoio!$B:$AB,MATCH($C124,Apoio!$B$1:$B$176,0),MATCH('Fluxo de Caixa '!O$5,Apoio!$B$4:$AB$4,0)+1),0) | Q124: =SUM(D124:P124)
...

Sheet Consolidado
A1: Data | B1: Fornecedor | C1: Crédito | D1: Débito | E1: Saldo | F1: Classificação | G1: Ano | H1: C.M. | I1: Mês | J1: Banco | K1: Empresa
A2: 45658 | B2: Saldo Inicial CEF | C2: 435332.04 | E2: 435332.04 | F2: Saldo Inicial CEF | G2: =YEAR(A2) | H2: =MONTH(A2) | I2: =INDEX(mês[],Consolidado!H2,2) | J2: CEF | K2: A IDEAL
A3: 45659 | B3: TRANSFERÊNCIA ENTRE BANCOS CEF X ITAÚ - Transferência entre Bancos (100,00%); | D3: 400000 | E3: 35332.04 | F3: Transferência Emitida | G3: =YEAR(A3) | H3: =MONTH(A3) | I3: =INDEX(mês[],Consolidado!H3,2) | J3: CEF | K3: A IDEAL
A4: 45659 | B4: DEB IOF - JUROS BANCARIOS (100,00%); | D4: 22.79 | E4: 35309.25 | F4: Juros Bancários | G4: =YEAR(A4) | H4: =MONTH(A4) | I4: =INDEX(mês[],Consolidado!H4,2) | J4: CEF | K4: A IDEAL
A5: 45659 | B5: DEB JUROS - JUROS BANCARIOS (100,00%); | D5: 363.04 | E5: 34946.21 | F5: Juros Bancários | G5: =YEAR(A5) | H5: =MONTH(A5) | I5: =INDEX(mês[],Consolidado!H5,2) | J5: CEF | K5: A IDEAL
A6: 45660 | B6: BM 07 Hh - Recebimento de Clientes (100,00%); | C6: 112098.45 | E6: 147044.66 | F6: Recebimento de Clientes | G6: =YEAR(A6) | H6: =MONTH(A6) | I6: =INDEX(mês[],Consolidado!H6,2) | J6: CEF | K6: A IDEAL
A7: 45660 | B7: BM 07 MATERIAIS - Recebimento de Clientes (100,00%); | C7: 70313.58 | E7: 217358.24 | F7: Recebimento de Clientes | G7: =YEAR(A7) | H7: =MONTH(A7) | I7: =INDEX(mês[],Consolidado!H7,2) | J7: CEF | K7: A IDEAL
A8: 45660 | B8: BM 08 MATERIAIS - Recebimento de Clientes (100,00%); | C8: 7781.98 | E8: 225140.22 | F8: Recebimento de Clientes | G8: =YEAR(A8) | H8: =MONTH(A8) | I8: =INDEX(mês[],Consolidado!H8,2) | J8: CEF | K8: A IDEAL
A9: 45660 | B9: RECIBO - Recebimento de Clientes (100,00%); | C9: 63350.67 | E9: 288490.89 | F9: Recebimento de Clientes | G9: =YEAR(A9) | H9: =MONTH(A9) | I9: =INDEX(mês[],Consolidado!H9,2) | J9: CEF | K9: A IDEAL
A10: 45660 | B10: TRANSFERENCIA ENTRE BANCOS CEF X ITAÚ - Transferência entre Bancos (100,00%); | D10: 268576.19 | E10: 19914.7 | F10: Transferência Emitida | G10: =YEAR(A10) | H10: =MONTH(A10) | I10: =INDEX(mês[],Consolidado!H10,2) | J10: CEF | K10: A IDEAL
A11: 45663 | B11: EMPRESTIMO BANCO CAIXA / PEGO PARA PAGAR MERCANTIL - PAGAMENTOS EMPRESTIMOS (100,00%); | D11: 19891.97 | E11: 22.73 | F11: Pagamento de Empréstimos Bancários | G11: =YEAR(A11) | H11: =MONTH(A11) | I11: =INDEX(mês[],Consolidado!H11,2) | J11: CEF | K11: A IDEAL
A12: 45663 | B12: RENDIMENTO APLICAÇÃO - Origens Financeiras (100,00%); | C12: 94.87 | E12: 117.6 | F12: Juros Recebidos | G12: =YEAR(A12) | H12: =MONTH(A12) | I12: =INDEX(mês[],Consolidado!H12,2) | J12: CEF | K12: A IDEAL
A13: 45664 | B13: TRANSFERÊNCIA ENTRE BANCOS ITAÚ X CEF - Transferência entre Bancos (100,00%); | C13: 337744.57 | E13: 337862.17 | F13: Transferência Recebida | G13: =YEAR(A13) | H13: =MONTH(A13) | I13: =INDEX(mês[],Consolidado!H13,2) | J13: CEF | K13: A IDEAL
A14: 45664 | B14: RENDIMENTO APLICAÇÃO - Origens Financeiras (100,00%); | C14: 0.04 | E14: 337862.21 | F14: Juros Recebidos | G14: =YEAR(A14) | H14: =MONTH(A14) | I14: =INDEX(mês[],Consolidado!H14,2) | J14: CEF | K14: A IDEAL
A15: 45664 | B15: FOLHA PGTO REF. 12/2024 - SALARIO (100,00%); | D15: 337862.17 | E15: 0.04 | F15: SALARIO | G15: =YEAR(A15) | H15: =MONTH(A15) | I15: =INDEX(mês[],Consolidado!H15,2) | J15: CEF | K15: A IDEAL
A16: 45666 | B16: TARIFAS BANCÁRIAS - TARIFAS BANCARIAS (100,00%); | D16: 205.8 | E16: -205.76 | F16: TARIFAS BANCARIAS | G16: =YEAR(A16) | H16: =MONTH(A16) | I16: =INDEX(mês[],Consolidado!H16,2) | J16: CEF | K16: A IDEAL
A17: 45667 | B17: VALOR DEPOSITADO PELA MOSAIC - Recebimento de Clientes (100,00%); | C17: 1791.49 | E17: 1585.73 | F17: Recebimento de Clientes | G17: =YEAR(A17) | H17: =MONTH(A17) | I17: =INDEX(mês[],Consolidado!H17,2) | J17: CEF | K17: A IDEAL
A18: 45667 | B18: IMOBILIARIO LOTE PARQUE OESTE - FINANCIAMENTO (100,00%); | D18: 4302.43 | E18: -2716.7 | F18: Financiamentos | G18: =YEAR(A18) | H18: =MONTH(A18) | I18: =INDEX(mês[],Consolidado!H18,2) | J18: CEF | K18: A IDEAL
A19: 45667 | B19: TARIFAS BANCÁRIAS CEF - TARIFAS BANCARIAS (100,00%); | D19: 564.98 | E19: -3281.68 | F19: TARIFAS BANCARIAS | G19: =YEAR(A19) | H19: =MONTH(A19) | I19: =INDEX(mês[],Consolidado!H19,2) | J19: CEF | K19: A IDEAL
A20: 45677 | B20: ADIANTAMENTO 40% - SALARIO (100,00%); | D20: 34885.28 | E20: -38166.96 | F20: SALARIO | G20: =YEAR(A20) | H20: =MONTH(A20) | I20: =INDEX(mês[],Consolidado!H20,2) | J20: CEF | K20: A IDEAL
A21: 45677 | B21: TRANSFERENCIA ENTRE BANCOS ITAÚ X CEF - Transferência entre Bancos (100,00%); | C21: 50000 | E21: 11833.04 | F21: Transferência Recebida | G21: =YEAR(A21) | H21: =MONTH(A21) | I21: =INDEX(mês[],Consolidado!H21,2) | J21: CEF | K21: A IDEAL
A22: 45677 | B22: EMPRESTIMO BANCO CAIXA / CAPITAL DE GIRO R$ 300.000,00 - PAGAMENTOS EMPRESTIMOS (100,00%); | D22: 15804.58 | E22: -3971.54 | F22: Pagamento de Empréstimos Bancários | G22: =YEAR(A22) | H22: =MONTH(A22) | I22: =INDEX(mês[],Consolidado!H22,2) | J22: CEF | K22: A IDEAL
A23: 45678 | B23: TRANSFERÊNCIA ENTRE BANCOS ITÁU X CEF - Transferência entre Bancos (100,00%); | C23: 4000 | E23: 28.46 | F23: Transferência Recebida | G23: =YEAR(A23) | H23: =MONTH(A23) | I23: =INDEX(mês[],Consolidado!H23,2) | J23: CEF | K23: A IDEAL
A24: 45679 | B24: TARIFAS BANCÁRIAS - TARIFAS BANCARIAS (100,00%); | D24: 44.8 | E24: -16.34 | F24: TARIFAS BANCARIAS | G24: =YEAR(A24) | H24: =MONTH(A24) | I24: =INDEX(mês[],Consolidado!H24,2) | J24: CEF | K24: A IDEAL
A25: 45688 | B25: TRANSFERENCIA ENTRE BANCOS ITAÚ X CEF - Transferência entre Bancos (100,00%); | C25: 10000 | E25: 9983.66 | F25: Transferência Recebida | G25: =YEAR(A25) | H25: =MONTH(A25) | I25: =INDEX(mês[],Consolidado!H25,2) | J25: CEF | K25: A IDEAL
A26: 45688 | B26: IMPOSTOS DEBITADOS EM CONTA CAIXA ECONOMICA - PARCELAMENTO (100,00%); | D26: 19946.33 | E26: -9962.67 | F26: Parcelamento de Impostos Exercicio Anterior | G26: =YEAR(A26) | H26: =MONTH(A26) | I26: =INDEX(mês[],Consolidado!H26,2) | J26: CEF | K26: A IDEAL
A27: 45688 | B27: Saldo Final CEF | D27: -9962.67 | E27: -9962.67 | F27: Saldo Final CEF | G27: =YEAR(A27) | H27: =MONTH(A27) | I27: =INDEX(mês[],Consolidado!H27,2) | J27: CEF | K27: A IDEAL
A28: 45691 | B28: BM 08 Hh - Recebimento de Clientes (100,00%); | C28: 83747.86 | E28: 73785.19 | F28: Recebimento de Clientes | G28: =YEAR(A28) | H28: =MONTH(A28) | I28: =INDEX(mês[],Consolidado!H28,2) | J28: CEF | K28: A IDEAL
A29: 45691 | B29: RECIBO LOCAÇÃO - Recebimento de Clientes (100,00%); | C29: 61307.1 | E29: 135092.29 | F29: Recebimento de Clientes | G29: =YEAR(A29) | H29: =MONTH(A29) | I29: =INDEX(mês[],Consolidado!H29,2) | J29: CEF | K29: A IDEAL
A30: 45691 | B30: BM 09 TINTAS - Recebimento de Clientes (100,00%); | C30: 11353.45 | E30: 146445.74 | F30: Recebimento de Clientes | G30: =YEAR(A30) | H30: =MONTH(A30) | I30: =INDEX(mês[],Consolidado!H30,2) | J30: CEF | K30: A IDEAL
A31: 45691 | B31: BM 10 TINTAS - Recebimento de Clientes (100,00%); | C31: 18002.42 | E31: 164448.16 | F31: Recebimento de Clientes | G31: =YEAR(A31) | H31: =MONTH(A31) | I31: =INDEX(mês[],Consolidado!H31,2) | J31: CEF | K31: A IDEAL
A32: 45691 | B32: DEB IOF E DEB JUROS CEF - JUROS BANCARIOS (100,00%); | D32: 289.39 | E32: 164158.77 | F32: Juros Bancários | G32: =YEAR(A32) | H32: =MONTH(A32) | I32: =INDEX(mês[],Consolidado!H32,2) | J32: CEF | K32: A IDEAL
A33: 45692 | B33: TRANSFERÊNCIA ENTRE BANCOS CEF X ITAÚ - Transferência entre Bancos (100,00%); | D33: 164158.77 | E33: 0 | F33: Transferência Emitida | G33: =YEAR(A33) | H33: =MONTH(A33) | I33: =INDEX(mês[],Consolidado!H33,2) | J33: CEF | K33: A IDEAL
A34: 45693 | B34: BM 10 - Recebimento de Clientes (100,00%); | C34: 31444.71 | E34: 31444.71 | F34: Recebimento de Clientes | G34: =YEAR(A34) | H34: =MONTH(A34) | I34: =INDEX(mês[],Consolidado!H34,2) | J34: CEF | K34: A IDEAL
A35: 45693 | B35: TRANSFERENCIA CEF X ITAÚ - Transferência entre Bancos (100,00%); | D35: 31444.71 | E35: 0 | F35: Transferência Emitida | G35: =YEAR(A35) | H35: =MONTH(A35) | I35: =INDEX(mês[],Consolidado!H35,2) | J35: CEF | K35: A IDEAL
A36: 45694 | B36: TRANSFERÊNCIA ENTRE BANCOS ITAÚ X CEF - Transferência entre Bancos (100,00%); | C36: 370205.08 | E36: 370205.08 | F36: Transferência Recebida | G36: =YEAR(A36) | H36: =MONTH(A36) | I36: =INDEX(mês[],Consolidado!H36,2) | J36: CEF | K36: A IDEAL
A37: 45694 | B37: TRANSFERÊNCIA ENTRE BANCOS ITAÚ X CEF - Transferência entre Bancos (100,00%); | C37: 20000 | E37: 390205.08 | F37: Transferência Recebida | G37: =YEAR(A37) | H37: =MONTH(A37) | I37: =INDEX(mês[],Consolidado!H37,2) | J37: CEF | K37: A IDEAL
A38: 45694 | B38: FOLHA PAGAMENTO REF. 01/2025 - SALARIO (100,00%); | D38: 370205.08 | E38: 20000 | F38: SALARIO | G38: =YEAR(A38) | H38: =MONTH(A38) | I38: =INDEX(mês[],Consolidado!H38,2) | J38: CEF | K38: A IDEAL
A39: 45694 | B39: EMPRESTIMO BANCO CAIXA / PEGO PARA PAGAR MERCANTIL - PAGAMENTOS EMPRESTIMOS (100,00%); | D39: 19925.94 | E39: 74.06 | F39: Pagamento de Empréstimos Bancários | G39: =YEAR(A39) | H39: =MONTH(A39) | I39: =INDEX(mês[],Consolidado!H39,2) | J39: CEF | K39: A IDEAL
A40: 45694 | B40: BLOQUEIO JUDICIAL AÇÃO TRABALHISTA - DESPESAS COM PROCESSOS (100,00%); | D40: 82.39 | E40: -8.33 | F40: Devolução de Pagamento Recebido | G40: =YEAR(A40) | H40: =MONTH(A40) | I40: =INDEX(mês[],Consolidado!H40,2) | J40: CEF | K40: A IDEAL
A41: 45698 | B41: DB T CESTA / DEB TARIFA - TARIFAS BANCARIAS (100,00%); | D41: 390.6 | E41: -398.93 | F41: TARIFAS BANCARIAS | G41: =YEAR(A41) | H41: =MONTH(A41) | I41: =INDEX(mês[],Consolidado!H41,2) | J41: CEF | K41: A IDEAL
A42: 45698 | B42: TARIFAS BANCARIAS (SEGURADORA) - TARIFAS BANCARIAS (100,00%); | D42: 375.98 | E42: -774.91 | F42: TARIFAS BANCARIAS | G42: =YEAR(A42) | H42: =MONTH(A42) | I42: =INDEX(mês[],Consolidado!H42,2) | J42: CEF | K42: A IDEAL
A43: 45698 | B43: IMOBILIARIO LOTE PARQUE OESTE - FINANCIAMENTO (100,00%); | D43: 4302.43 | E43: -5077.34 | F43: Financiamentos | G43: =YEAR(A43) | H43: =MONTH(A43) | I43: =INDEX(mês[],Consolidado!H43,2) | J43: CEF | K43: A IDEAL
A44: 45699 | B44: ESTORNO DO PEDIDO 7450 - DESPESAS COM PROCESSOS (100,00%); | C44: 82.39 | E44: -4994.95 | F44: Devolução / Estorno de Pagamento | G44: =YEAR(A44) | H44: =MONTH(A44) | I44: =INDEX(mês[],Consolidado!H44,2) | J44: CEF | K44: A IDEAL
A45: 45705 | B45: BM 09 - Recebimento de Clientes (100,00%); | C45: 912415.31 | E45: 907420.36 | F45: Recebimento de Clientes | G45: =YEAR(A45) | H45: =MONTH(A45) | I45: =INDEX(mês[],Consolidado!H45,2) | J45: CEF | K45: A IDEAL
A46: 45705 | B46: TRANSFERÊNCIA ENTRE BANCOS CEF X SAFRA - Transferência entre Bancos (100,00%); | D46: 103376.65 | E46: 804043.71 | F46: Transferência Emitida | G46: =YEAR(A46) | H46: =MONTH(A46) | I46: =INDEX(mês[],Consolidado!H46,2) | J46: CEF | K46: A IDEAL
A47: 45705 | B47: TRANSFERÊNCIA ENTRE BANCOS CEF X ITAÚ - Transferência entre Bancos (100,00%); | D47: 350000 | E47: 454043.71 | F47: Transferência Emitida | G47: =YEAR(A47) | H47: =MONTH(A47) | I47: =INDEX(mês[],Consolidado!H47,2) | J47: CEF | K47: A IDEAL
A48: 45706 | B48: TRANSFERÊNCIA ENTRE BANCOS CEF X ITAÚ - Transferência entre Bancos (100,00%); | D48: 400000 | E48: 54043.71 | F48: Transferência Emitida | G48: =YEAR(A48) | H48: =MONTH(A48) | I48: =INDEX(mês[],Consolidado!H48,2) | J48: CEF | K48: A IDEAL
A49: 45706 | B49: EMPRESTIMO BANCO CAIXA / CAPITAL DE GIRO R$ 300.000,00 - PAGAMENTOS EMPRESTIMOS (100,00%); | D49: 15804.58 | E49: 38239.13 | F49: Pagamento de Empréstimos Bancários | G49: =YEAR(A49) | H49: =MONTH(A49) | I49: =INDEX(mês[],Consolidado!H49,2) | J49: CEF | K49: A IDEAL
A50: 45708 | B50: TRANSFERÊNCIA ENTRE BANCOS ITAÚ X CEF - Transferência entre Bancos (100,00%); | C50: 14158.03 | E50: 52397.16 | F50: Transferência Recebida | G50: =YEAR(A50) | H50: =MONTH(A50) | I50: =INDEX(mês[],Consolidado!H50,2) | J50: CEF | K50: A IDEAL
A51: 45708 | B51: ADIANTAMENTO 40% - SALARIO (100,00%); | D51: 32397.16 | E51: 20000 | F51: SALARIO | G51: =YEAR(A51) | H51: =MONTH(A51) | I51: =INDEX(mês[],Consolidado!H51,2) | J51: CEF | K51: A IDEAL
A52: 45712 | B52: DEB TARIFA - TARIFAS BANCARIAS (100,00%); | D52: 40.6 | E52: 19959.4 | F52: TARIFAS BANCARIAS | G52: =YEAR(A52) | H52: =MONTH(A52) | I52: =INDEX(mês[],Consolidado!H52,2) | J52: CEF | K52: A IDEAL
A53: 45716 | B53: BM 11 - Recebimento de Clientes (100,00%); | C53: 150167.39 | E53: 170126.79 | F53: Recebimento de Clientes | G53: =YEAR(A53) | H53: =MONTH(A53) | I53: =INDEX(mês[],Consolidado!H53,2) | J53: CEF | K53: A IDEAL
A54: 45716 | B54: TRANSFERÊNCIA ENTRE BANCOS CEF X SAFRA - Transferência entre Bancos (100,00%); | D54: 19106.15 | E54: 151020.64 | F54: Transferência Emitida | G54: =YEAR(A54) | H54: =MONTH(A54) | I54: =INDEX(mês[],Consolidado!H54,2) | J54: CEF | K54: A IDEAL
A55: 45716 | B55: TRANSFERÊNCIA ENTRE BANCOS CEF X ITAÚ - Transferência entre Bancos (100,00%); | D55: 100925.9 | E55: 50094.74 | F55: Transferência Emitida | G55: =YEAR(A55) | H55: =MONTH(A55) | I55: =INDEX(mês[],Consolidado!H55,2) | J55: CEF | K55: A IDEAL
A56: 45716 | B56: 2º PARCELA PLR 2024 VLI - PLR (100,00%); | D56: 27103.73 | E56: 22991.01 | F56: PLR | G56: =YEAR(A56) | H56: =MONTH(A56) | I56: =INDEX(mês[],Consolidado!H56,2) | J56: CEF | K56: A IDEAL
A57: 45716 | B57: IMPOSTOS DEBITADOS EM CONTA CAIXA ECONOMICA - PARCELAMENTO (100,00%); | D57: 20094.74 | E57: 2896.27 | F57: Parcelamento de Impostos Exercicio Anterior | G57: =YEAR(A57) | H57: =MONTH(A57) | I57: =INDEX(mês[],Consolidado!H57,2) | J57: CEF | K57: A IDEAL
A58: 45716 | B58: Saldo Final CEF | D58: 2896.27 | E58: 2896.27 | F58: Saldo Final CEF | G58: =YEAR(A58) | H58: =MONTH(A58) | I58: =INDEX(mês[],Consolidado!H58,2) | J58: CEF | K58: A IDEAL
A59: 45721 | B59: DEB IOF E DEB JUROS BANCO CEF - JUROS BANCARIOS (100,00%); | D59: 212.1 | E59: 2684.17 | F59: Juros Bancários | G59: =YEAR(A59) | H59: =MONTH(A59) | I59: =INDEX(mês[],Consolidado!H59,2) | J59: CEF | K59: A IDEAL
A60: 45722 | B60: TRANSFERÊNCIA ENTRE BANCOS ITAÚ X CEF - Transferência entre Bancos (100,00%); | C60: 370000 | E60: 372684.17 | F60: Transferência Recebida | G60: =YEAR(A60) | H60: =MONTH(A60) | I60: =INDEX(mês[],Consolidado!H60,2) | J60: CEF | K60: A IDEAL
A61: 45722 | B61: DEB TARIFA - TARIFAS BANCARIAS (100,00%); | D61: 35 | E61: 372649.17 | F61: TARIFAS BANCARIAS | G61: =YEAR(A61) | H61: =MONTH(A61) | I61: =INDEX(mês[],Consolidado!H61,2) | J61: CEF | K61: A IDEAL
A62: 45722 | B62: FOLHA PGTO REF. MÊS 02/2025 - SALARIO (100,00%); | D62: 373323.12 | E62: -673.95 | F62: SALARIO | G62: =YEAR(A62) | H62: =MONTH(A62) | I62: =INDEX(mês[],Consolidado!H62,2) | J62: CEF | K62: A IDEAL
A63: 45723 | B63: BM 09 Hh - Recebimento de Clientes (100,00%); | C63: 71183.24 | E63: 70509.29 | F63: Recebimento de Clientes | G63: =YEAR(A63) | H63: =MONTH(A63) | I63: =INDEX(mês[],Consolidado!H63,2) | J63: CEF | K63: A IDEAL
A64: 45723 | B64: BM 11 MATERIAIS - Recebimento de Clientes (100,00%); | C64: 23469.75 | E64: 93979.04 | F64: Recebimento de Clientes | G64: =YEAR(A64) | H64: =MONTH(A64) | I64: =INDEX(mês[],Consolidado!H64,2) | J64: CEF | K64: A IDEAL
A65: 45723 | B65: RECIBO - Recebimento de Clientes (100,00%); | C65: 36970.91 | E65: 130949.95 | F65: Recebimento de Clientes | G65: =YEAR(A65) | H65: =MONTH(A65) | I65: =INDEX(mês[],Consolidado!H65,2) | J65: CEF | K65: A IDEAL
A66: 45726 | B66: BM 12 MATERIAIS - Recebimento de Clientes (100,00%); | C66: 8339.07 | E66: 139289.02 | F66: Recebimento de Clientes | G66: =YEAR(A66) | H66: =MONTH(A66) | I66: =INDEX(mês[],Consolidado!H66,2) | J66: CEF | K66: A IDEAL
A67: 45726 | B67: EMPRESTIMO BANCO CAIXA / PEGO PARA PAGAR MERCANTIL - PAGAMENTOS EMPRESTIMOS (100,00%); | D67: 20408.59 | E67: 118880.43 | F67: Pagamento de Empréstimos Bancários | G67: =YEAR(A67) | H67: =MONTH(A67) | I67: =INDEX(mês[],Consolidado!H67,2) | J67: CEF | K67: A IDEAL
A68: 45726 | B68: TRANSFERÊNCIA ENTRE BANCOS CEF X SAFRA - Transferência entre Bancos (100,00%); | D68: 11720.42 | E68: 107160.01 | F68: Transferência Emitida | G68: =YEAR(A68) | H68: =MONTH(A68) | I68: =INDEX(mês[],Consolidado!H68,2) | J68: CEF | K68: A IDEAL
A69: 45726 | B69: TRANSFERENCIA ENTRE BANCOS CEF X ITAÚ - Transferência entre Bancos (100,00%); | D69: 100000 | E69: 7160.01 | F69: Transferência Emitida | G69: =YEAR(A69) | H69: =MONTH(A69) | I69: =INDEX(mês[],Consolidado!H69,2) | J69: CEF | K69: A IDEAL
A70: 45726 | B70: IMOBILIARIO LOTE PARQUE OESTE - FINANCIAMENTO (100,00%); | D70: 4302.43 | E70: 2857.58 | F70: Financiamentos | G70: =YEAR(A70) | H70: =MONTH(A70) | I70: =INDEX(mês[],Consolidado!H70,2) | J70: CEF | K70: A IDEAL
A71: 45726 | B71: DB T CESTA / SEGURADORA / DEB TARIFA - TARIFAS BANCARIAS (100,00%); | D71: 770.78 | E71: 2086.8 | F71: TARIFAS BANCARIAS | G71: =YEAR(A71) | H71: =MONTH(A71) | I71: =INDEX(mês[],Consolidado!H71,2) | J71: CEF | K71: A IDEAL
A72: 45727 | B72: PROCESSO TRABALHISTA ROBSON SANTIAGO DOS SANTOS - GUIAS TRABALHISTAS E PROCESSO (100,00%); | D72: 63.91 | E72: 2022.89 | F72: Processos Trabalhistas | G72: =YEAR(A72) | H72: =MONTH(A72) | I72: =INDEX(mês[],Consolidado!H72,2) | J72: CEF | K72: A IDEAL
A73: 45727 | B73: TRANSFERÊNCIA ENTRE BANCOS CEF X SAFRA - Transferência entre Bancos (100,00%); | D73: 1032.58 | E73: 990.31 | F73: Transferência Emitida | G73: =YEAR(A73) | H73: =MONTH(A73) | I73: =INDEX(mês[],Consolidado!H73,2) | J73: CEF | K73: A IDEAL
A74: 45727 | B74: SEGURADORA - TARIFAS BANCARIAS (100,00%); | D74: 768.93 | E74: 221.38 | F74: TARIFAS BANCARIAS | G74: =YEAR(A74) | H74: =MONTH(A74) | I74: =INDEX(mês[],Consolidado!H74,2) | J74: CEF | K74: A IDEAL
A75: 45728 | B75: BLOQUEIO JUDICIAL AÇÃO TRABALHISTA ROBSON SANTIAGO - DESPESAS COM PROCESSOS (100,00%); | D75: 221.38 | E75: 1.1118573e-10 | F75: Devolução de Pagamento Recebido | G75: =YEAR(A75) | H75: =MONTH(A75) | I75: =INDEX(mês[],Consolidado!H75,2) | J75: CEF | K75: A IDEAL
A76: 45730 | B76: DESBLOQUEIO JUDICIAL AÇÃO TRABALHISTA ROBSON SANTIAGO - DESPESAS COM PROCESSOS (100,00%); | C76: 221.38 | E76: 221.38 | F76: Devolução / Estorno de Pagamento | G76: =YEAR(A76) | H76: =MONTH(A76) | I76: =INDEX(mês[],Consolidado!H76,2) | J76: CEF | K76: A IDEAL
A77: 45734 | B77: TRANSFERÊNCIA ENTRE BANCOS ITAÚ X CEF - Transferência entre Bancos (100,00%); | C77: 10000 | E77: 10221.38 | F77: Transferência Recebida | G77: =YEAR(A77) | H77: =MONTH(A77) | I77: =INDEX(mês[],Consolidado!H77,2) | J77: CEF | K77: A IDEAL
A78: 45734 | B78: EMPRESTIMO BANCO CAIXA / CAPITAL DE GIRO R$ 300.000,00 - PAGAMENTOS EMPRESTIMOS (100,00%); | D78: 15804.58 | E78: -5583.2 | F78: Pagamento de Empréstimos Bancários | G78: =YEAR(A78) | H78: =MONTH(A78) | I78: =INDEX(mês[],Consolidado!H78,2) | J78: CEF | K78: A IDEAL
A79: 45736 | B79: TRANSFERÊNCIA ENTRE BANCOS ITAÚ X CEF - Transferência entre Bancos (100,00%); | C79: 40000 | E79: 34416.8 | F79: Transferência Recebida | G79: =YEAR(A79) | H79: =MONTH(A79) | I79: =INDEX(mês[],Consolidado!H79,2) | J79: CEF | K79: A IDEAL
A80: 45736 | B80: ADIANTAMENTO 40% - SALARIO (100,00%); | D80: 35917.93 | E80: -1501.13 | F80: SALARIO | G80: =YEAR(A80) | H80: =MONTH(A80) | I80: =INDEX(mês[],Consolidado!H80,2) | J80: CEF | K80: A IDEAL
A81: 45740 | B81: DEB TARIFA - TARIFAS BANCARIAS (100,00%); | D81: 49 | E81: -1550.13 | F81: TARIFAS BANCARIAS | G81: =YEAR(A81) | H81: =MONTH(A81) | I81: =INDEX(mês[],Consolidado!H81,2) | J81: CEF | K81: A IDEAL
A82: 45747 | B82: TRANSFERÊNCIA ENTRE BANCOS SAFRA X CEF - Transferência entre Bancos (100,00%); | C82: 15000 | E82: 13449.87 | F82: Transferência Recebida | G82: =YEAR(A82) | H82: =MONTH(A82) | I82: =INDEX(mês[],Consolidado!H82,2) | J82: CEF | K82: A IDEAL
A83: 45747 | B83: IMPOSTOS DEBITADOS EM CONTA CAIXA ECONOMICA - PARCELAMENTO (100,00%); | D83: 20240.23 | E83: -6790.36 | F83: Parcelamento de Impostos Exercicio Anterior | G83: =YEAR(A83) | H83: =MONTH(A83) | I83: =INDEX(mês[],Consolidado!H83,2) | J83: CEF | K83: A IDEAL
A84: 45747 | B84: Saldo Final CEF | D84: -6790.36 | E84: -6790.36 | F84: Saldo Final CEF | G84: =YEAR(A84) | H84: =MONTH(A84) | I84: =INDEX(mês[],Consolidado!H84,2) | J84: CEF | K84: A IDEAL
A85: 45658 | B85: Saldo Inicial ITAU | C85: 948.89 | E85: 948.89 | F85: Saldo Inicial Itau | G85: =YEAR(A85) | H85: =MONTH(A85) | I85: =INDEX(mês[],Consolidado!H85,2) | J85: ITAU | K85: A IDEAL
A86: 45659 | B86: ADVOGADO GUERRA - TRIBUTÁRIO - HONORARIOS ADVOCATICIOS (100,00%); | D86: 3000 | E86: -2051.11 | F86: HONORÁRIOS ADVOCATÍCIOS | G86: =YEAR(A86) | H86: =MONTH(A86) | I86: =INDEX(mês[],Consolidado!H86,2) | J86: ITAU | K86: A IDEAL
A87: 45659 | B87: TANQUE PRESS/ PISTOLA/ KIT REPARO/ PINO P/ ENGATE - MATERIAIS / FERRAMENTAS MANUAIS (100,00%); | D87: 1156 | E87: -3207.11 | F87: MATERIAIS / FERRAMENTAS MANUAIS | G87: =YEAR(A87) | H87: =MONTH(A87) | I87: =INDEX(mês[],Consolidado!H87,2) | J87: ITAU | K87: A IDEAL
A88: 45659 | B88: CAMISA E CALCA NR10 - UNIFORMES (100,00%); | D88: 3601.17 | E88: -6808.28 | F88: UNIFORMES | G88: =YEAR(A88) | H88: =MONTH(A88) | I88: =INDEX(mês[],Consolidado!H88,2) | J88: ITAU | K88: A IDEAL
A89: 45659 | B89: EPIS - EPIS (100,00%); | D89: 3315 | E89: -10123.28 | F89: EPIS | G89: =YEAR(A89) | H89: =MONTH(A89) | I89: =INDEX(mês[],Consolidado!H89,2) | J89: ITAU | K89: A IDEAL
A90: 45659 | B90: SOCIETY REF. 01.01 A 01.02 - ALUGUEL ALOJAMENTO (100,00%); | D90: 1400 | E90: -11523.28 | F90: ALUGUEL ALOJAMENTO | G90: =YEAR(A90) | H90: =MONTH(A90) | I90: =INDEX(mês[],Consolidado!H90,2) | J90: ITAU | K90: A IDEAL
A91: 45659 | B91: ALUGUEL FUNCIONÁRIOS 01-01 A 01-02-25 - ALUGUEL ALOJAMENTO (100,00%); | D91: 750 | E91: -12273.28 | F91: ALUGUEL ALOJAMENTO | G91: =YEAR(A91) | H91: =MONTH(A91) | I91: =INDEX(mês[],Consolidado!H91,2) | J91: ITAU | K91: A IDEAL
A92: 45659 | B92: SOCIETY - 01.01 A 01.02 - ALUGUEL ALOJAMENTO (100,00%); | D92: 1100 | E92: -13373.28 | F92: ALUGUEL ALOJAMENTO | G92: =YEAR(A92) | H92: =MONTH(A92) | I92: =INDEX(mês[],Consolidado!H92,2) | J92: ITAU | K92: A IDEAL
A93: 45659 | B93: LUCAS 01.01 A 30.01 - ALUGUEL ALOJAMENTO (100,00%); | D93: 600 | E93: -13973.28 | F93: ALUGUEL ALOJAMENTO | G93: =YEAR(A93) | H93: =MONTH(A93) | I93: =INDEX(mês[],Consolidado!H93,2) | J93: ITAU | K93: A IDEAL
A94: 45659 | B94: EPIS - EPIS (100,00%); | D94: 211.35 | E94: -14184.63 | F94: EPIS | G94: =YEAR(A94) | H94: =MONTH(A94) | I94: =INDEX(mês[],Consolidado!H94,2) | J94: ITAU | K94: A IDEAL
A95: 45659 | B95: LOCAÇÃO CONTAINER - LOCAÇÃO CONTAINER (100,00%); | D95: 500 | E95: -14684.63 | F95: LOCAÇÃO CONTAINER | G95: =YEAR(A95) | H95: =MONTH(A95) | I95: =INDEX(mês[],Consolidado!H95,2) | J95: ITAU | K95: A IDEAL
A96: 45659 | B96: EPIS - EPIS (100,00%); | D96: 876.46 | E96: -15561.09 | F96: EPIS | G96: =YEAR(A96) | H96: =MONTH(A96) | I96: =INDEX(mês[],Consolidado!H96,2) | J96: ITAU | K96: A IDEAL
A97: 45659 | B97: EPIS - EPIS (100,00%); | D97: 1529.95 | E97: -17091.04 | F97: EPIS | G97: =YEAR(A97) | H97: =MONTH(A97) | I97: =INDEX(mês[],Consolidado!H97,2) | J97: ITAU | K97: A IDEAL
... A126: 45659 | B126: LOCAÇÃO MUNCK REF. PERÍODO 19/12 A 19/12/24 - LOCAÇÃO MUNCK / GUINDASTES (100,00%); | D126: 2583.36 | E126: -93971.46 | F126: LOCAÇÃO MUNCK / GUINDASTES | G126: =YEAR(A126) | H126: =MONTH(A126) | I126: =INDEX(mês[],Consolidado!H126,2) | J126: ITAU | K126: A IDEAL
A127: 45659 | B127: TRANSFERÊNCIA ENTRE BANCOS CEF X ITAÚ - Transferência entre Bancos (100,00%); | C127: 400000 | E127: 306028.54 | F127: Transferência Recebida | G127: =YEAR(A127) | H127: =MONTH(A127) | I127: =INDEX(mês[],Consolidado!H127,2) | J127: ITAU | K127: A IDEAL
A128: 45659 | B128: BM 04 DEZEMBRO/2024 - Recebimento de Clientes (100,00%); | C128: 128025 | E128: 434053.54 | F128: Recebimento de Clientes | G128: =YEAR(A128) | H128: =MONTH(A128) | I128: =INDEX(mês[],Consolidado!H128,2) | J128: ITAU | K128: A IDEAL
...

Sheet Apresentação GMP
C2: Jan | D2: Fev | E2: Mar | F2: Abr | G2: Mai | H2: Jun | I2: Jul | J2: Ago | K2: Set | L2: Out | M2: Nov | N2: Dez | O2: Acum
B3: Margem Líquida de Caixa 2025 | C3: ='Fluxo de Caixa '!D168 | D3: ='Fluxo de Caixa '!E168 | E3: ='Fluxo de Caixa '!F168 | F3: ='Fluxo de Caixa '!G168 | G3: ='Fluxo de Caixa '!H168 | H3: ='Fluxo de Caixa '!I168 | I3: ='Fluxo de Caixa '!J168 | J3: ='Fluxo de Caixa '!K168 | ... N3: ='Fluxo de Caixa '!O168 | O3: =SUM(C3:N3)
B4: Margem Líquida de Caixa 2023
B5: % Margem Líquida de Caixa 2025 | C5: ='Fluxo de Caixa '!D169 | D5: ='Fluxo de Caixa '!E169 | E5: ='Fluxo de Caixa '!F169 | F5: ='Fluxo de Caixa '!G169 | G5: ='Fluxo de Caixa '!H169 | H5: ='Fluxo de Caixa '!I169 | I5: ='Fluxo de Caixa '!J169 | J5: ='Fluxo de Caixa '!K169 | ... N5: ='Fluxo de Caixa '!O169 | O5: ='Fluxo de Caixa '!Q169
B6: % Margem Líquida de Caixa 2023
B7: Var. Margem Líquida de Caixa | C7: =IFERROR(C3/N4-1,0) | D7: =IFERROR(D3/C3-1,0) | E7: =IFERROR(E3/D3-1,0) | F7: =IFERROR(F3/E3-1,0) | G7: =IFERROR(G3/F3-1,0) | H7: =IFERROR(H3/G3-1,0) | I7: =IFERROR(I3/H3-1,0) | J7: =IFERROR(J3/I3-1,0) | K7: =IFERROR(K3/J3-1,0) | ... N7: =IFERROR(N3/M3-1,0)
C9: Jan | D9: Fev | E9: Mar | F9: Abr | G9: Mai | H9: Jun | I9: Jul | J9: Ago | K9: Set | L9: Out | M9: Nov | N9: Dez | O9: Acum
B10: Recebimentos Operacionais 2025 | C10: ='Fluxo de Caixa '!D20 | D10: ='Fluxo de Caixa '!E20 | E10: ='Fluxo de Caixa '!F20 | F10: ='Fluxo de Caixa '!G20 | G10: ='Fluxo de Caixa '!H20 | H10: ='Fluxo de Caixa '!I20 | I10: ='Fluxo de Caixa '!J20 | J10: ='Fluxo de Caixa '!K20 | ... N10: ='Fluxo de Caixa '!O20 | O10: =SUM(C10:N10)
B11: Recebimentos Operacionais 2023
B12: Var. Rec. Operacionais | C12: =IFERROR(C10/N11-1,0) | D12: =IFERROR(D10/C10-1,0) | E12: =IFERROR(E10/D10-1,0) | F12: =IFERROR(F10/E10-1,0) | G12: =IFERROR(G10/F10-1,0) | H12: =IFERROR(H10/G10-1,0) | I12: =IFERROR(I10/H10-1,0) | J12: =IFERROR(J10/I10-1,0) | K12: =IFERROR(K10/J10-1,0) | ... N12: =IFERROR(N10/M10-1,0)
C14: Jan | D14: Fev | E14: Mar | F14: Abr | G14: Mai | H14: Jun | I14: Jul | J14: Ago | K14: Set | L14: Out | M14: Nov | N14: Dez | O14: Acum
B15: Pagamentos Operacionais 2025 | C15: ='Fluxo de Caixa '!D28 | D15: ='Fluxo de Caixa '!E28 | E15: ='Fluxo de Caixa '!F28 | F15: ='Fluxo de Caixa '!G28 | G15: ='Fluxo de Caixa '!H28 | H15: ='Fluxo de Caixa '!I28 | I15: ='Fluxo de Caixa '!J28 | J15: ='Fluxo de Caixa '!K28 | ... N15: ='Fluxo de Caixa '!O28 | O15: =SUM(C15:N15)
B16: Pagamentos Operacionais 2023
B17: Var. Pgtos. Operacionais | C17: =IFERROR(C15/N16-1,0) | D17: =IFERROR(D15/C15-1,0) | E17: =IFERROR(E15/D15-1,0) | F17: =IFERROR(F15/E15-1,0) | G17: =IFERROR(G15/F15-1,0) | H17: =IFERROR(H15/G15-1,0) | I17: =IFERROR(I15/H15-1,0) | J17: =IFERROR(J15/I15-1,0) | K17: =IFERROR(K15/J15-1,0) | ... N17: =IFERROR(N15/M15-1,0)
B19: Pagamentos Operacionais | C19: Jan | D19: Fev | E19: Mar | F19: Abr | G19: Mai | H19: Jun | I19: Jul | J19: Ago | K19: Set | L19: Out | M19: Nov | N19: Dez | O19: Acum | P19: 80-20 | Q19: %GF
B20: Pgtos Operacionais | C20: ='Fluxo de Caixa '!D28 | D20: ='Fluxo de Caixa '!E28 | E20: ='Fluxo de Caixa '!F28 | F20: ='Fluxo de Caixa '!G28 | G20: ='Fluxo de Caixa '!H28 | H20: ='Fluxo de Caixa '!I28 | I20: ='Fluxo de Caixa '!J28 | J20: ='Fluxo de Caixa '!K28 | ... N20: ='Fluxo de Caixa '!O28 | O20: ='Fluxo de Caixa '!Q28
B21: G. Pessoal | C21: ='Fluxo de Caixa '!D29 | D21: ='Fluxo de Caixa '!E29 | E21: ='Fluxo de Caixa '!F29 | F21: ='Fluxo de Caixa '!G29 | G21: ='Fluxo de Caixa '!H29 | H21: ='Fluxo de Caixa '!I29 | I21: ='Fluxo de Caixa '!J29 | J21: ='Fluxo de Caixa '!K29 | ... N21: ='Fluxo de Caixa '!O29 | O21: ='Fluxo de Caixa '!Q29 | P21: =IFERROR(P20+O21/$O$20,0) | Q21: =IFERROR(O21/$O$20,0)
B22: G. Impostos e Tributos | C22: ='Fluxo de Caixa '!D74 | D22: ='Fluxo de Caixa '!E74 | E22: ='Fluxo de Caixa '!F74 | F22: ='Fluxo de Caixa '!G74 | G22: ='Fluxo de Caixa '!H74 | H22: ='Fluxo de Caixa '!I74 | I22: ='Fluxo de Caixa '!J74 | J22: ='Fluxo de Caixa '!K74 | ... N22: ='Fluxo de Caixa '!O74 | O22: ='Fluxo de Caixa '!Q74 | P22: =IFERROR(P21+O22/$O$20,0) | Q22: =IFERROR(O22/$O$20,0)
B23: G. Locações | C23: ='Fluxo de Caixa '!D95 | D23: ='Fluxo de Caixa '!E95 | E23: ='Fluxo de Caixa '!F95 | F23: ='Fluxo de Caixa '!G95 | G23: ='Fluxo de Caixa '!H95 | H23: ='Fluxo de Caixa '!I95 | I23: ='Fluxo de Caixa '!J95 | J23: ='Fluxo de Caixa '!K95 | ... N23: ='Fluxo de Caixa '!O95 | O23: ='Fluxo de Caixa '!Q95 | P23: =IFERROR(P22+O23/$O$20,0) | Q23: =IFERROR(O23/$O$20,0)
B24: G. Fornecedores | C24: ='Fluxo de Caixa '!D132 | D24: ='Fluxo de Caixa '!E132 | E24: ='Fluxo de Caixa '!F132 | F24: ='Fluxo de Caixa '!G132 | G24: ='Fluxo de Caixa '!H132 | H24: ='Fluxo de Caixa '!I132 | I24: ='Fluxo de Caixa '!J132 | J24: ='Fluxo de Caixa '!K132 | ... N24: ='Fluxo de Caixa '!O132 | O24: ='Fluxo de Caixa '!Q132 | P24: =IFERROR(P23+O24/$O$20,0) | Q24: =IFERROR(O24/$O$20,0)
B25: G. Instalações | C25: ='Fluxo de Caixa '!D55 | D25: ='Fluxo de Caixa '!E55 | E25: ='Fluxo de Caixa '!F55 | F25: ='Fluxo de Caixa '!G55 | G25: ='Fluxo de Caixa '!H55 | H25: ='Fluxo de Caixa '!I55 | I25: ='Fluxo de Caixa '!J55 | J25: ='Fluxo de Caixa '!K55 | ... N25: ='Fluxo de Caixa '!O55 | O25: ='Fluxo de Caixa '!Q55 | P25: =IFERROR(P23+O25/$O$20,0) | Q25: =IFERROR(O25/$O$20,0)
B26: G. Veículos | C26: ='Fluxo de Caixa '!D83 | D26: ='Fluxo de Caixa '!E83 | E26: ='Fluxo de Caixa '!F83 | F26: ='Fluxo de Caixa '!G83 | G26: ='Fluxo de Caixa '!H83 | H26: ='Fluxo de Caixa '!I83 | I26: ='Fluxo de Caixa '!J83 | J26: ='Fluxo de Caixa '!K83 | ... N26: ='Fluxo de Caixa '!O83 | O26: ='Fluxo de Caixa '!Q83 | P26: =IFERROR(P23+O26/$O$20,0) | Q26: =IFERROR(O26/$O$20,0)
B27: G. Administrativos | C27: ='Fluxo de Caixa '!D144 | D27: ='Fluxo de Caixa '!E144 | E27: ='Fluxo de Caixa '!F144 | F27: ='Fluxo de Caixa '!G144 | G27: ='Fluxo de Caixa '!H144 | H27: ='Fluxo de Caixa '!I144 | I27: ='Fluxo de Caixa '!J144 | J27: ='Fluxo de Caixa '!K144 | ... N27: ='Fluxo de Caixa '!O144 | O27: ='Fluxo de Caixa '!Q144 | P27: =IFERROR(P26+O27/$O$20,0) | Q27: =IFERROR(O27/$O$20,0)
B28: G. com Máquinas e Equipamentos | C28: ='Fluxo de Caixa '!D110 | D28: ='Fluxo de Caixa '!E110 | E28: ='Fluxo de Caixa '!F110 | F28: ='Fluxo de Caixa '!G110 | G28: ='Fluxo de Caixa '!H110 | H28: ='Fluxo de Caixa '!I110 | I28: ='Fluxo de Caixa '!J110 | J28: ='Fluxo de Caixa '!K110 | ... N28: ='Fluxo de Caixa '!O110 | O28: ='Fluxo de Caixa '!Q110 | P28: =IFERROR(P27+O28/$O$20,0) | Q28: =IFERROR(O28/$O$20,0)
B29: G. Fretes | C29: ='Fluxo de Caixa '!D126 | D29: ='Fluxo de Caixa '!E126 | E29: ='Fluxo de Caixa '!F126 | F29: ='Fluxo de Caixa '!G126 | G29: ='Fluxo de Caixa '!H126 | H29: ='Fluxo de Caixa '!I126 | I29: ='Fluxo de Caixa '!J126 | J29: ='Fluxo de Caixa '!K126 | ... N29: ='Fluxo de Caixa '!O126 | O29: ='Fluxo de Caixa '!Q126 | P29: =IFERROR(P27+O29/$O$20,0) | Q29: =IFERROR(O29/$O$20,0)
B30: G. Serviços de Terceiros | C30: ='Fluxo de Caixa '!D68 | D30: ='Fluxo de Caixa '!E68 | E30: ='Fluxo de Caixa '!F68 | F30: ='Fluxo de Caixa '!G68 | G30: ='Fluxo de Caixa '!H68 | H30: ='Fluxo de Caixa '!I68 | I30: ='Fluxo de Caixa '!J68 | J30: ='Fluxo de Caixa '!K68 | ... N30: ='Fluxo de Caixa '!O68 | O30: ='Fluxo de Caixa '!Q68 | P30: =IFERROR(P29+O30/$O$20,0) | Q30: =IFERROR(O30/$O$20,0)
B31: G. com Viagens e Hospedagens | C31: ='Fluxo de Caixa '!D140 | D31: ='Fluxo de Caixa '!E140 | E31: ='Fluxo de Caixa '!F140 | F31: ='Fluxo de Caixa '!G140 | G31: ='Fluxo de Caixa '!H140 | H31: ='Fluxo de Caixa '!I140 | I31: ='Fluxo de Caixa '!J140 | J31: ='Fluxo de Caixa '!K140 | ... N31: ='Fluxo de Caixa '!O140 | O31: ='Fluxo de Caixa '!Q140 | P31: =IFERROR(P30+O31/$O$20,0) | Q31: =IFERROR(O31/$O$20,0)
B32: G. Bancários | C32: ='Fluxo de Caixa '!D137 | D32: ='Fluxo de Caixa '!E137 | E32: ='Fluxo de Caixa '!F137 | F32: ='Fluxo de Caixa '!G137 | G32: ='Fluxo de Caixa '!H137 | H32: ='Fluxo de Caixa '!I137 | I32: ='Fluxo de Caixa '!J137 | J32: ='Fluxo de Caixa '!K137 | ... N32: ='Fluxo de Caixa '!O137 | O32: ='Fluxo de Caixa '!Q137 | P32: =IFERROR(P31+O32/$O$20,0) | Q32: =IFERROR(O32/$O$20,0)
B33: Total | C33: =SUM(C21:C32) | D33: =SUM(D21:D32) | E33: =SUM(E21:E32) | F33: =SUM(F21:F32) | G33: =SUM(G21:G32) | H33: =SUM(H21:H32) | I33: =SUM(I21:I32) | J33: =SUM(J21:J32) | ... O33: =SUM(O21:O32)
B34: % Receb. Operacionais | C34: =IFERROR(C33/C$10,0) | D34: =IFERROR(D33/D$10,0) | E34: =IFERROR(E33/E$10,0) | F34: =IFERROR(F33/F$10,0) | G34: =IFERROR(G33/G$10,0) | H34: =IFERROR(H33/H$10,0) | I34: =IFERROR(I33/I$10,0) | J34: =IFERROR(J33/J$10,0) | ... O34: =IFERROR(O33/O$10,0)
B36: Gastos com Pessoal | C36: Jan | D36: Fev | E36: Mar | F36: Abr | G36: Mai | H36: Jun | I36: Jul | J36: Ago | K36: Set | L36: Out | M36: Nov | N36: Dez | O36: Acum | P36: Var. Julho x Junho | Q36: % Recb. Operacionais
B37: ='Fluxo de Caixa '!C30 | C37: ='Fluxo de Caixa '!D30 | D37: ='Fluxo de Caixa '!E30 | E37: ='Fluxo de Caixa '!F30 | F37: ='Fluxo de Caixa '!G30 | G37: ='Fluxo de Caixa '!H30 | H37: ='Fluxo de Caixa '!I30 | I37: ='Fluxo de Caixa '!J30 | ... N37: ='Fluxo de Caixa '!O30 | O37: =SUM(C37:N37) | P37: =IFERROR(I37/H37-1,IF(I37>0,1,0)) | Q37: =IFERROR(O37/$O$10,0) | R37: =I37-H37
B38: ='Fluxo de Caixa '!C34 | C38: ='Fluxo de Caixa '!D34 | D38: ='Fluxo de Caixa '!E34 | E38: ='Fluxo de Caixa '!F34 | F38: ='Fluxo de Caixa '!G34 | G38: ='Fluxo de Caixa '!H34 | H38: ='Fluxo de Caixa '!I34 | I38: ='Fluxo de Caixa '!J34 | ... N38: ='Fluxo de Caixa '!O34 | O38: =SUM(C38:N38) | P38: =IFERROR(I38/H38-1,IF(I38>0,1,0)) | Q38: =IFERROR(O38/$O$10,0) | R38: =I38-H38
B39: ='Fluxo de Caixa '!C37 | C39: ='Fluxo de Caixa '!D37 | D39: ='Fluxo de Caixa '!E37 | E39: ='Fluxo de Caixa '!F37 | F39: ='Fluxo de Caixa '!G37 | G39: ='Fluxo de Caixa '!H37 | H39: ='Fluxo de Caixa '!I37 | I39: ='Fluxo de Caixa '!J37 | ... N39: ='Fluxo de Caixa '!O37 | O39: =SUM(C39:N39) | P39: =IFERROR(I39/H39-1,IF(I39>0,1,0)) | Q39: =IFERROR(O39/$O$10,0) | R39: =I39-H39
B40: ='Fluxo de Caixa '!C45 | C40: ='Fluxo de Caixa '!D45 | D40: ='Fluxo de Caixa '!E45 | E40: ='Fluxo de Caixa '!F45 | F40: ='Fluxo de Caixa '!G45 | G40: ='Fluxo de Caixa '!H45 | H40: ='Fluxo de Caixa '!I45 | I40: ='Fluxo de Caixa '!J45 | ... N40: ='Fluxo de Caixa '!O45 | O40: =SUM(C40:N40) | P40: =IFERROR(I40/H40-1,IF(I40>0,1,0)) | Q40: =IFERROR(O40/$O$10,0) | R40: =I40-H40
B41: ='Fluxo de Caixa '!C36 | C41: ='Fluxo de Caixa '!D36 | D41: ='Fluxo de Caixa '!E36 | E41: ='Fluxo de Caixa '!F36 | F41: ='Fluxo de Caixa '!G36 | G41: ='Fluxo de Caixa '!H36 | H41: ='Fluxo de Caixa '!I36 | I41: ='Fluxo de Caixa '!J36 | ... N41: ='Fluxo de Caixa '!O36 | O41: =SUM(C41:N41) | P41: =IFERROR(I41/H41-1,IF(I41>0,1,0)) | Q41: =IFERROR(O41/$O$10,0) | R41: =I41-H41
B42: ='Fluxo de Caixa '!C43 | C42: ='Fluxo de Caixa '!D43 | D42: ='Fluxo de Caixa '!E43 | E42: ='Fluxo de Caixa '!F43 | F42: ='Fluxo de Caixa '!G43 | G42: ='Fluxo de Caixa '!H43 | H42: ='Fluxo de Caixa '!I43 | I42: ='Fluxo de Caixa '!J43 | ... N42: ='Fluxo de Caixa '!O43 | O42: =SUM(C42:N42) | P42: =IFERROR(I42/H42-1,IF(I42>0,1,0)) | Q42: =IFERROR(O42/$O$10,0) | R42: =I42-H42
B43: ='Fluxo de Caixa '!C44 | C43: ='Fluxo de Caixa '!D44 | D43: ='Fluxo de Caixa '!E44 | E43: ='Fluxo de Caixa '!F44 | F43: ='Fluxo de Caixa '!G44 | G43: ='Fluxo de Caixa '!H44 | H43: ='Fluxo de Caixa '!I44 | I43: ='Fluxo de Caixa '!J44 | ... N43: ='Fluxo de Caixa '!O44 | O43: =SUM(C43:N43) | P43: =IFERROR(I43/H43-1,IF(I43>0,1,0)) | Q43: =IFERROR(O43/$O$10,0) | R43: =I43-H43
B44: FERIAS | C44: ='Fluxo de Caixa '!D32 | D44: ='Fluxo de Caixa '!E32 | E44: ='Fluxo de Caixa '!F32 | F44: ='Fluxo de Caixa '!G32 | G44: ='Fluxo de Caixa '!H32 | H44: ='Fluxo de Caixa '!I32 | I44: ='Fluxo de Caixa '!J32 | J44: ='Fluxo de Caixa '!K32 | ... N44: ='Fluxo de Caixa '!O32 | O44: =SUM(C44:N44) | P44: =IFERROR(I44/H44-1,IF(I44>0,1,0)) | Q44: =IFERROR(O44/$O$10,0) | R44: =I44-H44
B45: ='Fluxo de Caixa '!C39 | C45: ='Fluxo de Caixa '!D39 | D45: ='Fluxo de Caixa '!E39 | E45: ='Fluxo de Caixa '!F39 | F45: ='Fluxo de Caixa '!G39 | G45: ='Fluxo de Caixa '!H39 | H45: ='Fluxo de Caixa '!I39 | I45: ='Fluxo de Caixa '!J39 | ... N45: ='Fluxo de Caixa '!O39 | O45: =SUM(C45:N45) | P45: =IFERROR(I45/H45-1,IF(I45>0,1,0)) | Q45: =IFERROR(O45/$O$10,0) | R45: =I45-H45
B46: EPIS | C46: ='Fluxo de Caixa '!D49 | D46: ='Fluxo de Caixa '!E49 | E46: ='Fluxo de Caixa '!F49 | F46: ='Fluxo de Caixa '!G49 | G46: ='Fluxo de Caixa '!H49 | H46: ='Fluxo de Caixa '!I49 | I46: ='Fluxo de Caixa '!J49 | J46: ='Fluxo de Caixa '!K49 | ... N46: ='Fluxo de Caixa '!O49 | O46: =SUM(C46:N46) | P46: =IFERROR(I46/H46-1,IF(I46>0,1,0)) | Q46: =IFERROR(O46/$O$10,0) | R46: =I46-H46
B47: ='Fluxo de Caixa '!C47 | C47: ='Fluxo de Caixa '!D47 | D47: ='Fluxo de Caixa '!E47 | E47: ='Fluxo de Caixa '!F47 | F47: ='Fluxo de Caixa '!G47 | G47: ='Fluxo de Caixa '!H47 | H47: ='Fluxo de Caixa '!I47 | I47: ='Fluxo de Caixa '!J47 | ... N47: ='Fluxo de Caixa '!O47 | O47: =SUM(C47:N47) | P47: =IFERROR(I47/H47-1,IF(I47>0,1,0)) | Q47: =IFERROR(O47/$O$10,0) | R47: =I47-H47
B48: ='Fluxo de Caixa '!C40 | C48: ='Fluxo de Caixa '!D40 | D48: ='Fluxo de Caixa '!E40 | E48: ='Fluxo de Caixa '!F40 | F48: ='Fluxo de Caixa '!G40 | G48: ='Fluxo de Caixa '!H40 | H48: ='Fluxo de Caixa '!I40 | I48: ='Fluxo de Caixa '!J40 | ... N48: ='Fluxo de Caixa '!O40 | O48: =SUM(C48:N48) | P48: =IFERROR(I48/H48-1,IF(I48>0,1,0)) | Q48: =IFERROR(O48/$O$10,0) | R48: =I48-H48
B49: UNIFORMES | C49: ='Fluxo de Caixa '!D50 | D49: ='Fluxo de Caixa '!E50 | E49: ='Fluxo de Caixa '!F50 | F49: ='Fluxo de Caixa '!G50 | G49: ='Fluxo de Caixa '!H50 | H49: ='Fluxo de Caixa '!I50 | I49: ='Fluxo de Caixa '!J50 | J49: ='Fluxo de Caixa '!K50 | ... N49: ='Fluxo de Caixa '!O50 | O49: =SUM(C49:N49) | P49: =IFERROR(I49/H49-1,IF(I49>0,1,0)) | Q49: =IFERROR(O49/$O$10,0) | R49: =I49-H49
B50: MULTA RESCISORIAS FGTS | C50: ='Fluxo de Caixa '!D33 | D50: ='Fluxo de Caixa '!E33 | E50: ='Fluxo de Caixa '!F33 | F50: ='Fluxo de Caixa '!G33 | G50: ='Fluxo de Caixa '!H33 | H50: ='Fluxo de Caixa '!I33 | I50: ='Fluxo de Caixa '!J33 | J50: ='Fluxo de Caixa '!K33 | ... N50: ='Fluxo de Caixa '!O33 | O50: =SUM(C50:N50) | P50: =IFERROR(I50/H50-1,IF(I50>0,1,0)) | Q50: =IFERROR(O50/$O$10,0) | R50: =I50-H50
B51: EXAMES MÉDICOS | C51: ='Fluxo de Caixa '!D51 | D51: ='Fluxo de Caixa '!E51 | E51: ='Fluxo de Caixa '!F51 | F51: ='Fluxo de Caixa '!G51 | G51: ='Fluxo de Caixa '!H51 | H51: ='Fluxo de Caixa '!I51 | I51: ='Fluxo de Caixa '!J51 | J51: ='Fluxo de Caixa '!K51 | ... N51: ='Fluxo de Caixa '!O51 | O51: =SUM(C51:N51) | P51: =IFERROR(I51/H51-1,IF(I51>0,1,0)) | Q51: =IFERROR(O51/$O$10,0) | R51: =I51-H51
B52: CURSOS / TREINAMENTOS | C52: ='Fluxo de Caixa '!D52 | D52: ='Fluxo de Caixa '!E52 | E52: ='Fluxo de Caixa '!F52 | F52: ='Fluxo de Caixa '!G52 | G52: ='Fluxo de Caixa '!H52 | H52: ='Fluxo de Caixa '!I52 | I52: ='Fluxo de Caixa '!J52 | J52: ='Fluxo de Caixa '!K52 | ... N52: ='Fluxo de Caixa '!O52 | O52: =SUM(C52:N52) | P52: =IFERROR(I52/H52-1,IF(I52>0,1,0)) | Q52: =IFERROR(O52/$O$10,0) | R52: =I52-H52
B53: ='Fluxo de Caixa '!C42 | C53: ='Fluxo de Caixa '!D42 | D53: ='Fluxo de Caixa '!E42 | E53: ='Fluxo de Caixa '!F42 | F53: ='Fluxo de Caixa '!G42 | G53: ='Fluxo de Caixa '!H42 | H53: ='Fluxo de Caixa '!I42 | I53: ='Fluxo de Caixa '!J42 | ... N53: ='Fluxo de Caixa '!O42 | O53: =SUM(C53:N53) | P53: =IFERROR(I53/H53-1,IF(I53>0,1,0)) | Q53: =IFERROR(O53/$O$10,0) | R53: =I53-H53
B54: ='Fluxo de Caixa '!C41 | C54: ='Fluxo de Caixa '!D41 | D54: ='Fluxo de Caixa '!E41 | E54: ='Fluxo de Caixa '!F41 | F54: ='Fluxo de Caixa '!G41 | G54: ='Fluxo de Caixa '!H41 | H54: ='Fluxo de Caixa '!I41 | I54: ='Fluxo de Caixa '!J41 | ... N54: ='Fluxo de Caixa '!O41 | O54: =SUM(C54:N54) | P54: =IFERROR(I54/H54-1,IF(I54>0,1,0)) | Q54: =IFERROR(O54/$O$10,0) | R54: =I54-H54
B55: ='Fluxo de Caixa '!C46 | C55: ='Fluxo de Caixa '!D46 | D55: ='Fluxo de Caixa '!E46 | E55: ='Fluxo de Caixa '!F46 | F55: ='Fluxo de Caixa '!G46 | G55: ='Fluxo de Caixa '!H46 | H55: ='Fluxo de Caixa '!I46 | I55: ='Fluxo de Caixa '!J46 | ... N55: ='Fluxo de Caixa '!O46 | O55: =SUM(C55:N55) | P55: =IFERROR(I55/H55-1,IF(I55>0,1,0)) | Q55: =IFERROR(O55/$O$10,0) | R55: =I55-H55
B56: PROGRAMA DE SEGURANÇA DO TRABALHO | C56: ='Fluxo de Caixa '!D53 | D56: ='Fluxo de Caixa '!E53 | E56: ='Fluxo de Caixa '!F53 | F56: ='Fluxo de Caixa '!G53 | G56: ='Fluxo de Caixa '!H53 | H56: ='Fluxo de Caixa '!I53 | I56: ='Fluxo de Caixa '!J53 | J56: ='Fluxo de Caixa '!K53 | ... N56: ='Fluxo de Caixa '!O53 | O56: =SUM(C56:N56) | P56: =IFERROR(I56/H56-1,IF(I56>0,1,0)) | Q56: =IFERROR(O56/$O$10,0) | R56: =I56-H56
B57: ='Fluxo de Caixa '!C38 | C57: ='Fluxo de Caixa '!D38 | D57: ='Fluxo de Caixa '!E38 | E57: ='Fluxo de Caixa '!F38 | F57: ='Fluxo de Caixa '!G38 | G57: ='Fluxo de Caixa '!H38 | H57: ='Fluxo de Caixa '!I38 | I57: ='Fluxo de Caixa '!J38 | ... N57: ='Fluxo de Caixa '!O38 | O57: =SUM(C57:N57) | P57: =IFERROR(I57/H57-1,IF(I57>0,1,0)) | Q57: =IFERROR(O57/$O$10,0) | R57: =I57-H57
B58: ALIMENTAÇÃO ADM | C58: ='Fluxo de Caixa '!D35 | D58: ='Fluxo de Caixa '!E35 | E58: ='Fluxo de Caixa '!F35 | F58: ='Fluxo de Caixa '!G35 | G58: ='Fluxo de Caixa '!H35 | H58: ='Fluxo de Caixa '!I35 | I58: ='Fluxo de Caixa '!J35 | J58: ='Fluxo de Caixa '!K35 | ... N58: ='Fluxo de Caixa '!O35 | O58: =SUM(C58:N58) | P58: =IFERROR(I58/H58-1,IF(I58>0,1,0)) | Q58: =IFERROR(O58/$O$10,0) | R58: =I58-H58
B59: ='Fluxo de Caixa '!C48 | C59: ='Fluxo de Caixa '!D48 | D59: ='Fluxo de Caixa '!E48 | E59: ='Fluxo de Caixa '!F48 | F59: ='Fluxo de Caixa '!G48 | G59: ='Fluxo de Caixa '!H48 | H59: ='Fluxo de Caixa '!I48 | I59: ='Fluxo de Caixa '!J48 | ... N59: ='Fluxo de Caixa '!O48 | O59: =SUM(C59:N59) | P59: =IFERROR(I59/H59-1,IF(I59>0,1,0)) | Q59: =IFERROR(O59/$O$10,0) | R59: =I59-H59
B60: ='Fluxo de Caixa '!C31 | C60: ='Fluxo de Caixa '!D31 | D60: ='Fluxo de Caixa '!E31 | E60: ='Fluxo de Caixa '!F31 | F60: ='Fluxo de Caixa '!G31 | G60: ='Fluxo de Caixa '!H31 | H60: ='Fluxo de Caixa '!I31 | I60: ='Fluxo de Caixa '!J31 | ... N60: ='Fluxo de Caixa '!O31 | O60: =SUM(C60:N60) | P60: =IFERROR(I60/H60-1,IF(I60>0,1,0)) | Q60: =IFERROR(O60/$O$10,0) | R60: =I60-H60
B61: Total | C61: =SUM(C37:C60) | D61: =SUM(D37:D60) | E61: =SUM(E37:E60) | F61: =SUM(F37:F60) | G61: =SUM(G37:G60) | H61: =SUM(H37:H60) | I61: =SUM(I37:I60) | J61: =SUM(J37:J60) | ... O61: =SUM(O37:O60) | P61: =IFERROR(I61/H61-1,IF(I61>0,1,0))
B62: % Receb. Operacionais | C62: =IFERROR(C61/C$10,0) | D62: =IFERROR(D61/D$10,0) | E62: =IFERROR(E61/E$10,0) | F62: =IFERROR(F61/F$10,0) | G62: =IFERROR(G61/G$10,0) | H62: =IFERROR(H61/H$10,0) | I62: =IFERROR(I61/I$10,0) | J62: =IFERROR(J61/J$10,0) | ... O62: =IFERROR(O61/O$10,0)
B64: Gastos com Fornecedores | C64: Jan | D64: Fev | E64: Mar | F64: Abr | G64: Mai | H64: Jun | I64: Jul | J64: Ago | K64: Set | L64: Out | M64: Nov | N64: Dez | O64: Acum | P64: Var. Julho x Junho | Q64: % Recb. Operacionais
B65: ='Fluxo de Caixa '!C133 | C65: ='Fluxo de Caixa '!D133 | D65: ='Fluxo de Caixa '!E133 | E65: ='Fluxo de Caixa '!F133 | F65: ='Fluxo de Caixa '!G133 | G65: ='Fluxo de Caixa '!H133 | H65: ='Fluxo de Caixa '!I133 | I65: ='Fluxo de Caixa '!J133 | ... N65: ='Fluxo de Caixa '!O133 | O65: ='Fluxo de Caixa '!Q133 | P65: =IFERROR(I65/H65-1,IF(I65>0,1,0)) | Q65: =IFERROR(O65/$O$10,0) | R65: =I65-H65
B66: ABRASIVOS | C66: ='Fluxo de Caixa '!D134 | D66: ='Fluxo de Caixa '!E134 | E66: ='Fluxo de Caixa '!F134 | F66: ='Fluxo de Caixa '!G134 | G66: ='Fluxo de Caixa '!H134 | H66: ='Fluxo de Caixa '!I134 | I66: ='Fluxo de Caixa '!J134 | J66: ='Fluxo de Caixa '!K134 | ... N66: ='Fluxo de Caixa '!O134 | O66: ='Fluxo de Caixa '!Q134 | P66: =IFERROR(I66/H66-1,IF(I66>0,1,0)) | Q66: =IFERROR(O66/$O$10,0) | R66: =I66-H66
B67: ='Fluxo de Caixa '!C135 | C67: ='Fluxo de Caixa '!D135 | D67: ='Fluxo de Caixa '!E135 | E67: ='Fluxo de Caixa '!F135 | F67: ='Fluxo de Caixa '!G135 | G67: ='Fluxo de Caixa '!H135 | H67: ='Fluxo de Caixa '!I135 | I67: ='Fluxo de Caixa '!J135 | ... N67: ='Fluxo de Caixa '!O135 | O67: ='Fluxo de Caixa '!Q135 | P67: =IFERROR(I67/H67-1,IF(I67>0,1,0)) | Q67: =IFERROR(O67/$O$10,0) | R67: =I67-H67
B68: Total | C68: =SUM(C65:C67) | D68: =SUM(D65:D67) | E68: =SUM(E65:E67) | F68: =SUM(F65:F67) | G68: =SUM(G65:G67) | H68: =SUM(H65:H67) | I68: =SUM(I65:I67) | J68: =SUM(J65:J67) | ... O68: =SUM(O65:O67) | P68: =IFERROR(I68/H68-1,IF(I68>0,1,0))
B69: % Receb. Operacionais | C69: =IFERROR(C68/C$10,0) | D69: =IFERROR(D68/D$10,0) | E69: =IFERROR(E68/E$10,0) | F69: =IFERROR(F68/F$10,0) | G69: =IFERROR(G68/G$10,0) | H69: =IFERROR(H68/H$10,0) | I69: =IFERROR(I68/I$10,0) | J69: =IFERROR(J68/J$10,0) | ... O69: =IFERROR(O68/O$10,0)
B71: Gastos com Impostos / Tributos | C71: Jan | D71: Fev | E71: Mar | F71: Abr | G71: Mai | H71: Jun | I71: Jul | J71: Ago | K71: Set | L71: Out | M71: Nov | N71: Dez | O71: Acum | P71: Var. Julho x Junho | Q71: % Recb. Operacionais
B72: ='Fluxo de Caixa '!C76 | C72: ='Fluxo de Caixa '!D76 | D72: ='Fluxo de Caixa '!E76 | E72: ='Fluxo de Caixa '!F76 | F72: ='Fluxo de Caixa '!G76 | G72: ='Fluxo de Caixa '!H76 | H72: ='Fluxo de Caixa '!I76 | I72: ='Fluxo de Caixa '!J76 | ... N72: ='Fluxo de Caixa '!O76 | O72: ='Fluxo de Caixa '!Q76 | P72: =IFERROR(I72/H72-1,IF(I72>0,1,0)) | Q72: =IFERROR(O72/$O$10,0) | R72: =I72-H72
B73: ='Fluxo de Caixa '!C77 | C73: ='Fluxo de Caixa '!D77 | D73: ='Fluxo de Caixa '!E77 | E73: ='Fluxo de Caixa '!F77 | F73: ='Fluxo de Caixa '!G77 | G73: ='Fluxo de Caixa '!H77 | H73: ='Fluxo de Caixa '!I77 | I73: ='Fluxo de Caixa '!J77 | ... N73: ='Fluxo de Caixa '!O77 | O73: ='Fluxo de Caixa '!Q77 | P73: =IFERROR(I73/H73-1,IF(I73>0,1,0)) | Q73: =IFERROR(O73/$O$10,0) | R73: =I73-H73
B74: ='Fluxo de Caixa '!C78 | C74: ='Fluxo de Caixa '!D78 | D74: ='Fluxo de Caixa '!E78 | E74: ='Fluxo de Caixa '!F78 | F74: ='Fluxo de Caixa '!G78 | G74: ='Fluxo de Caixa '!H78 | H74: ='Fluxo de Caixa '!I78 | I74: ='Fluxo de Caixa '!J78 | ... N74: ='Fluxo de Caixa '!O78 | O74: ='Fluxo de Caixa '!Q78 | P74: =IFERROR(I74/H74-1,IF(I74>0,1,0)) | Q74: =IFERROR(O74/$O$10,0) | R74: =I74-H74
B75: ='Fluxo de Caixa '!C75 | C75: ='Fluxo de Caixa '!D75 | D75: ='Fluxo de Caixa '!E75 | E75: ='Fluxo de Caixa '!F75 | F75: ='Fluxo de Caixa '!G75 | G75: ='Fluxo de Caixa '!H75 | H75: ='Fluxo de Caixa '!I75 | I75: ='Fluxo de Caixa '!J75 | ... N75: ='Fluxo de Caixa '!O75 | O75: ='Fluxo de Caixa '!Q75 | P75: =IFERROR(I75/H75-1,IF(I75>0,1,0)) | Q75: =IFERROR(O75/$O$10,0) | R75: =I75-H75
B76: ='Fluxo de Caixa '!C81 | C76: ='Fluxo de Caixa '!D81 | D76: ='Fluxo de Caixa '!E81 | E76: ='Fluxo de Caixa '!F81 | F76: ='Fluxo de Caixa '!G81 | G76: ='Fluxo de Caixa '!H81 | H76: ='Fluxo de Caixa '!I81 | I76: ='Fluxo de Caixa '!J81 | ... N76: ='Fluxo de Caixa '!O81 | O76: ='Fluxo de Caixa '!Q81 | P76: =IFERROR(I76/H76-1,IF(I76>0,1,0)) | Q76: =IFERROR(O76/$O$10,0) | R76: =I76-H76
B77: ='Fluxo de Caixa '!C80 | C77: ='Fluxo de Caixa '!D80 | D77: ='Fluxo de Caixa '!E80 | E77: ='Fluxo de Caixa '!F80 | F77: ='Fluxo de Caixa '!G80 | G77: ='Fluxo de Caixa '!H80 | H77: ='Fluxo de Caixa '!I80 | I77: ='Fluxo de Caixa '!J80 | ... N77: ='Fluxo de Caixa '!O80 | O77: ='Fluxo de Caixa '!Q80 | P77: =IFERROR(I77/H77-1,IF(I77>0,1,0)) | Q77: =IFERROR(O77/$O$10,0) | R77: =I77-H77
B78: ='Fluxo de Caixa '!C79 | C78: ='Fluxo de Caixa '!D79 | D78: ='Fluxo de Caixa '!E79 | E78: ='Fluxo de Caixa '!F79 | F78: ='Fluxo de Caixa '!G79 | G78: ='Fluxo de Caixa '!H79 | H78: ='Fluxo de Caixa '!I79 | I78: ='Fluxo de Caixa '!J79 | ... N78: ='Fluxo de Caixa '!O79 | O78: ='Fluxo de Caixa '!Q79 | P78: =IFERROR(I78/H78-1,IF(I78>0,1,0)) | Q78: =IFERROR(O78/$O$10,0) | R78: =I78-H78
B79: Total | C79: =SUM(C72:C78) | D79: =SUM(D72:D78) | E79: =SUM(E72:E78) | F79: =SUM(F72:F78) | G79: =SUM(G72:G78) | H79: =SUM(H72:H78) | I79: =SUM(I72:I78) | J79: =SUM(J72:J78) | ... O79: =SUM(O72:O78) | P79: =IFERROR(I79/H79-1,IF(I79>0,1,0))
B80: % Receb. Operacionais | C80: =IFERROR(C79/C$10,0) | D80: =IFERROR(D79/D$10,0) | E80: =IFERROR(E79/E$10,0) | F80: =IFERROR(F79/F$10,0) | G80: =IFERROR(G79/G$10,0) | H80: =IFERROR(H79/H$10,0) | I80: =IFERROR(I79/I$10,0) | J80: =IFERROR(J79/J$10,0) | ... O80: =IFERROR(O79/O$10,0)
D81: =D104-D26 | E81: =E104-E26 | F81: =F104-F26 | G81: =G104-G26 | H81: =H104-H26 | I81: =I104-I26 | J81: =J104-J26 | K81: =K104-K26 | ... N81: =N104-N26
B82: Gastos Administrativos | C82: Jan | D82: Fev | E82: Mar | F82: Abr | G82: Mai | H82: Jun | I82: Jul | J82: Ago | K82: Set | L82: Out | M82: Nov | N82: Dez | O82: Acum | P82: Var. Julho x Junho | Q82: % Recb. Operacionais
B83: HONORÁRIOS ADVOCATÍCIOS | C83: ='Fluxo de Caixa '!D147 | D83: ='Fluxo de Caixa '!E147 | E83: ='Fluxo de Caixa '!F147 | F83: ='Fluxo de Caixa '!G147 | G83: ='Fluxo de Caixa '!H147 | H83: ='Fluxo de Caixa '!I147 | I83: ='Fluxo de Caixa '!J147 | J83: ='Fluxo de Caixa '!K147 | ... N83: ='Fluxo de Caixa '!O147 | O83: ='Fluxo de Caixa '!Q147 | P83: =IFERROR(I83/H83-1,IF(I83>0,1,0)) | Q83: =IFERROR(O83/$O$10,0) | R83: =I83-H83
B84: SERVIÇOS DE CONSULTORIA | C84: ='Fluxo de Caixa '!D146 | D84: ='Fluxo de Caixa '!E146 | E84: ='Fluxo de Caixa '!F146 | F84: ='Fluxo de Caixa '!G146 | G84: ='Fluxo de Caixa '!H146 | H84: ='Fluxo de Caixa '!I146 | I84: ='Fluxo de Caixa '!J146 | J84: ='Fluxo de Caixa '!K146 | ... N84: ='Fluxo de Caixa '!O146 | O84: ='Fluxo de Caixa '!Q146 | P84: =IFERROR(I84/H84-1,IF(I84>0,1,0)) | Q84: =IFERROR(O84/$O$10,0) | R84: =I84-H84
B85: ='Fluxo de Caixa '!C145 | C85: ='Fluxo de Caixa '!D145 | D85: ='Fluxo de Caixa '!E145 | E85: ='Fluxo de Caixa '!F145 | F85: ='Fluxo de Caixa '!G145 | G85: ='Fluxo de Caixa '!H145 | H85: ='Fluxo de Caixa '!I145 | I85: ='Fluxo de Caixa '!J145 | ... N85: ='Fluxo de Caixa '!O145 | O85: ='Fluxo de Caixa '!Q145 | P85: =IFERROR(I85/H85-1,IF(I85>0,1,0)) | Q85: =IFERROR(O85/$O$10,0) | R85: =I85-H85
B86: ='Fluxo de Caixa '!C148 | C86: ='Fluxo de Caixa '!D148 | D86: ='Fluxo de Caixa '!E148 | E86: ='Fluxo de Caixa '!F148 | F86: ='Fluxo de Caixa '!G148 | G86: ='Fluxo de Caixa '!H148 | H86: ='Fluxo de Caixa '!I148 | I86: ='Fluxo de Caixa '!J148 | ... N86: ='Fluxo de Caixa '!O148 | O86: ='Fluxo de Caixa '!Q148 | P86: =IFERROR(I86/H86-1,IF(I86>0,1,0)) | Q86: =IFERROR(O86/$O$10,0) | R86: =I86-H86
B87: ='Fluxo de Caixa '!C150 | C87: ='Fluxo de Caixa '!D150 | D87: ='Fluxo de Caixa '!E150 | E87: ='Fluxo de Caixa '!F150 | F87: ='Fluxo de Caixa '!G150 | G87: ='Fluxo de Caixa '!H150 | H87: ='Fluxo de Caixa '!I150 | I87: ='Fluxo de Caixa '!J150 | ... N87: ='Fluxo de Caixa '!O150 | O87: ='Fluxo de Caixa '!Q150 | P87: =IFERROR(I87/H87-1,IF(I87>0,1,0)) | Q87: =IFERROR(O87/$O$10,0) | R87: =I87-H87
B88: SERVIÇO CARTORIO | C88: ='Fluxo de Caixa '!D158 | D88: ='Fluxo de Caixa '!E158 | E88: ='Fluxo de Caixa '!F158 | F88: ='Fluxo de Caixa '!G158 | G88: ='Fluxo de Caixa '!H158 | H88: ='Fluxo de Caixa '!I158 | I88: ='Fluxo de Caixa '!J158 | J88: ='Fluxo de Caixa '!K158 | ... N88: ='Fluxo de Caixa '!O158 | O88: ='Fluxo de Caixa '!Q158 | P88: =IFERROR(I88/H88-1,IF(I88>0,1,0)) | Q88: =IFERROR(O88/$O$10,0) | R88: =I88-H88
B89: SERVIÇO PLOTAGEM / ADESIVO / PLACAS / CRACHAS | C89: ='Fluxo de Caixa '!D162 | D89: ='Fluxo de Caixa '!E162 | E89: ='Fluxo de Caixa '!F162 | F89: ='Fluxo de Caixa '!G162 | G89: ='Fluxo de Caixa '!H162 | H89: ='Fluxo de Caixa '!I162 | I89: ='Fluxo de Caixa '!J162 | J89: ='Fluxo de Caixa '!K162 | ... N89: ='Fluxo de Caixa '!O162 | O89: ='Fluxo de Caixa '!Q162 | P89: =IFERROR(I89/H89-1,IF(I89>0,1,0)) | Q89: =IFERROR(O89/$O$10,0) | R89: =I89-H89
B90: SERVIÇO GOOGLE ADS | C90: ='Fluxo de Caixa '!D153 | D90: ='Fluxo de Caixa '!E153 | E90: ='Fluxo de Caixa '!F153 | F90: ='Fluxo de Caixa '!G153 | G90: ='Fluxo de Caixa '!H153 | H90: ='Fluxo de Caixa '!I153 | I90: ='Fluxo de Caixa '!J153 | J90: ='Fluxo de Caixa '!K153 | ... N90: ='Fluxo de Caixa '!O153 | O90: ='Fluxo de Caixa '!Q153 | P90: =IFERROR(I90/H90-1,IF(I90>0,1,0)) | Q90: =IFERROR(O90/$O$10,0) | R90: =I90-H90
B91: SERVIÇO BRINDES E ACESSORIOS | C91: ='Fluxo de Caixa '!D165 | D91: ='Fluxo de Caixa '!E165 | E91: ='Fluxo de Caixa '!F165 | F91: ='Fluxo de Caixa '!G165 | G91: ='Fluxo de Caixa '!H165 | H91: ='Fluxo de Caixa '!I165 | I91: ='Fluxo de Caixa '!J165 | J91: ='Fluxo de Caixa '!K165 | ... N91: ='Fluxo de Caixa '!O165 | O91: ='Fluxo de Caixa '!Q165 | P91: =IFERROR(I91/H91-1,IF(I91>0,1,0)) | Q91: =IFERROR(O91/$O$10,0) | R91: =I91-H91
B92: SERVIÇO TELEMETRIA / FADIGA | C92: ='Fluxo de Caixa '!D159 | D92: ='Fluxo de Caixa '!E159 | E92: ='Fluxo de Caixa '!F159 | F92: ='Fluxo de Caixa '!G159 | G92: ='Fluxo de Caixa '!H159 | H92: ='Fluxo de Caixa '!I159 | I92: ='Fluxo de Caixa '!J159 | J92: ='Fluxo de Caixa '!K159 | ... N92: ='Fluxo de Caixa '!O159 | O92: ='Fluxo de Caixa '!Q159 | P92: =IFERROR(I92/H92-1,IF(I92>0,1,0)) | Q92: =IFERROR(O92/$O$10,0) | R92: =I92-H92
B93: SERVIÇO CREA ANUIDADE | C93: ='Fluxo de Caixa '!D161 | D93: ='Fluxo de Caixa '!E161 | E93: ='Fluxo de Caixa '!F161 | F93: ='Fluxo de Caixa '!G161 | G93: ='Fluxo de Caixa '!H161 | H93: ='Fluxo de Caixa '!I161 | I93: ='Fluxo de Caixa '!J161 | J93: ='Fluxo de Caixa '!K161 | ... N93: ='Fluxo de Caixa '!O161 | O93: ='Fluxo de Caixa '!Q161 | P93: =IFERROR(I93/H93-1,IF(I93>0,1,0)) | Q93: =IFERROR(O93/$O$10,0) | R93: =I93-H93
B94: ='Fluxo de Caixa '!C149 | C94: ='Fluxo de Caixa '!D149 | D94: ='Fluxo de Caixa '!E149 | E94: ='Fluxo de Caixa '!F149 | F94: ='Fluxo de Caixa '!G149 | G94: ='Fluxo de Caixa '!H149 | H94: ='Fluxo de Caixa '!I149 | I94: ='Fluxo de Caixa '!J149 | ... N94: ='Fluxo de Caixa '!O149 | O94: ='Fluxo de Caixa '!Q149 | P94: =IFERROR(I94/H94-1,IF(I94>0,1,0)) | Q94: =IFERROR(O94/$O$10,0) | R94: =I94-H94
B95: SERVIÇO MOTOBOY / UBER | C95: ='Fluxo de Caixa '!D154 | D95: ='Fluxo de Caixa '!E154 | E95: ='Fluxo de Caixa '!F154 | F95: ='Fluxo de Caixa '!G154 | G95: ='Fluxo de Caixa '!H154 | H95: ='Fluxo de Caixa '!I154 | I95: ='Fluxo de Caixa '!J154 | J95: ='Fluxo de Caixa '!K154 | ... N95: ='Fluxo de Caixa '!O154 | O95: ='Fluxo de Caixa '!Q154 | P95: =IFERROR(I95/H95-1,IF(I95>0,1,0)) | Q95: =IFERROR(O95/$O$10,0) | R95: =I95-H95
B96: SERVIÇO SERASA | C96: ='Fluxo de Caixa '!D152 | D96: ='Fluxo de Caixa '!E152 | E96: ='Fluxo de Caixa '!F152 | F96: ='Fluxo de Caixa '!G152 | G96: ='Fluxo de Caixa '!H152 | H96: ='Fluxo de Caixa '!I152 | I96: ='Fluxo de Caixa '!J152 | J96: ='Fluxo de Caixa '!K152 | ... N96: ='Fluxo de Caixa '!O152 | O96: ='Fluxo de Caixa '!Q152 | P96: =IFERROR(I96/H96-1,IF(I96>0,1,0)) | Q96: =IFERROR(O96/$O$10,0) | R96: =I96-H96
B97: SERVIÇO ALVARAS E LICENCIAMENTO | C97: ='Fluxo de Caixa '!D164 | D97: ='Fluxo de Caixa '!E164 | E97: ='Fluxo de Caixa '!F164 | F97: ='Fluxo de Caixa '!G164 | G97: ='Fluxo de Caixa '!H164 | H97: ='Fluxo de Caixa '!I164 | I97: ='Fluxo de Caixa '!J164 | J97: ='Fluxo de Caixa '!K164 | ... N97: ='Fluxo de Caixa '!O164 | O97: ='Fluxo de Caixa '!Q164 | P97: =IFERROR(I97/H97-1,IF(I97>0,1,0)) | Q97: =IFERROR(O97/$O$10,0) | R97: =I97-H97
B98: SERVIÇO ABRACO ANUIDADE | C98: ='Fluxo de Caixa '!D157 | D98: ='Fluxo de Caixa '!E157 | E98: ='Fluxo de Caixa '!F157 | F98: ='Fluxo de Caixa '!G157 | G98: ='Fluxo de Caixa '!H157 | H98: ='Fluxo de Caixa '!I157 | I98: ='Fluxo de Caixa '!J157 | J98: ='Fluxo de Caixa '!K157 | ... N98: ='Fluxo de Caixa '!O157 | O98: ='Fluxo de Caixa '!Q157 | P98: =IFERROR(I98/H98-1,IF(I98>0,1,0)) | Q98: =IFERROR(O98/$O$10,0) | R98: =I98-H98
B99: SEGURO GARANTIA | C99: ='Fluxo de Caixa '!D160 | D99: ='Fluxo de Caixa '!E160 | E99: ='Fluxo de Caixa '!F160 | F99: ='Fluxo de Caixa '!G160 | G99: ='Fluxo de Caixa '!H160 | H99: ='Fluxo de Caixa '!I160 | I99: ='Fluxo de Caixa '!J160 | J99: ='Fluxo de Caixa '!K160 | ... N99: ='Fluxo de Caixa '!O160 | O99: ='Fluxo de Caixa '!Q160 | P99: =IFERROR(I99/H99-1,IF(I99>0,1,0)) | Q99: =IFERROR(O99/$O$10,0) | R99: =I99-H99
B100: SERVIÇO GRAFICA / IMPRESSAO | C100: ='Fluxo de Caixa '!D155 | D100: ='Fluxo de Caixa '!E155 | E100: ='Fluxo de Caixa '!F155 | F100: ='Fluxo de Caixa '!G155 | G100: ='Fluxo de Caixa '!H155 | H100: ='Fluxo de Caixa '!I155 | I100: ='Fluxo de Caixa '!J155 | J100: ='Fluxo de Caixa '!K155 | ... N100: ='Fluxo de Caixa '!O155 | O100: ='Fluxo de Caixa '!Q155 | P100: =IFERROR(I100/H100-1,IF(I100>0,1,0)) | Q100: =IFERROR(O100/$O$10,0) | R100: =I100-H100
B101: PROJETOS | C101: ='Fluxo de Caixa '!D151 | D101: ='Fluxo de Caixa '!E151 | E101: ='Fluxo de Caixa '!F151 | F101: ='Fluxo de Caixa '!G151 | G101: ='Fluxo de Caixa '!H151 | H101: ='Fluxo de Caixa '!I151 | I101: ='Fluxo de Caixa '!J151 | J101: ='Fluxo de Caixa '!K151 | ... N101: ='Fluxo de Caixa '!O151 | O101: ='Fluxo de Caixa '!Q151 | P101: =IFERROR(I101/H101-1,IF(I101>0,1,0)) | Q101: =IFERROR(O101/$O$10,0) | R101: =I101-H101
B102: SERVIÇO ART | C102: ='Fluxo de Caixa '!D156 | D102: ='Fluxo de Caixa '!E156 | E102: ='Fluxo de Caixa '!F156 | F102: ='Fluxo de Caixa '!G156 | G102: ='Fluxo de Caixa '!H156 | H102: ='Fluxo de Caixa '!I156 | I102: ='Fluxo de Caixa '!J156 | J102: ='Fluxo de Caixa '!K156 | ... N102: ='Fluxo de Caixa '!O156 | O102: ='Fluxo de Caixa '!Q156 | P102: =IFERROR(I102/H102-1,IF(I102>0,1,0)) | Q102: =IFERROR(O102/$O$10,0) | R102: =I102-H102
B103: SERVIÇO E-MAILS | C103: ='Fluxo de Caixa '!D163 | D103: ='Fluxo de Caixa '!E163 | E103: ='Fluxo de Caixa '!F163 | F103: ='Fluxo de Caixa '!G163 | G103: ='Fluxo de Caixa '!H163 | H103: ='Fluxo de Caixa '!I163 | I103: ='Fluxo de Caixa '!J163 | J103: ='Fluxo de Caixa '!K163 | ... N103: ='Fluxo de Caixa '!O163 | O103: ='Fluxo de Caixa '!Q163 | P103: =IFERROR(I103/H103-1,IF(I103>0,1,0)) | Q103: =IFERROR(O103/$O$10,0) | R103: =I103-H103
B104: Total | C104: =SUM(C83:C103) | D104: =SUM(D83:D103) | E104: =SUM(E83:E103) | F104: =SUM(F83:F103) | G104: =SUM(G83:G103) | H104: =SUM(H83:H103) | I104: =SUM(I83:I103) | J104: =SUM(J83:J103) | ... O104: =SUM(O83:O103) | P104: =IFERROR(I104/H104-1,IF(I104>0,1,0))
B105: % Receb. Operacionais | C105: =IFERROR(C104/C$10,0) | D105: =IFERROR(D104/D$10,0) | E105: =IFERROR(E104/E$10,0) | F105: =IFERROR(F104/F$10,0) | G105: =IFERROR(G104/G$10,0) | H105: =IFERROR(H104/H$10,0) | I105: =IFERROR(I104/I$10,0) | J105: =IFERROR(J104/J$10,0) | ... O105: =IFERROR(O104/O$10,0)
B107: Gastos com Instalações | C107: Jan | D107: Fev | E107: Mar | F107: Abr | G107: Mai | H107: Jun | I107: Jul | J107: Ago | K107: Set | L107: Out | M107: Nov | N107: Dez | O107: Acum | P107: Var. Julho x Junho | Q107: % Recb. Operacionais
B108: ='Fluxo de Caixa '!C56 | C108: ='Fluxo de Caixa '!D56 | D108: ='Fluxo de Caixa '!E56 | E108: ='Fluxo de Caixa '!F56 | F108: ='Fluxo de Caixa '!G56 | G108: ='Fluxo de Caixa '!H56 | H108: ='Fluxo de Caixa '!I56 | I108: ='Fluxo de Caixa '!J56 | ... N108: ='Fluxo de Caixa '!O56 | O108: ='Fluxo de Caixa '!Q56 | P108: =IFERROR(I108/H108-1,IF(I108>0,1,0)) | Q108: =IFERROR(O108/$O$10,0) | R108: =I108-H108
...

Sheet Apoio
B1: Ano | C1: (Tudo)
C3: Rótulos de Coluna
C4: Janeiro | E4: Fevereiro | G4: Março | I4: Abril | K4: Maio | M4: Junho | O4: Julho | Q4: Agosto | S4: Setembro | U4: Outubro | W4: Novembro | Y4: Dezembro | AA4: Total Soma de Crédito | AB4: Total Soma de Débito
B5: Rótulos de Linha | C5: Soma de Crédito | D5: Soma de Débito | E5: Soma de Crédito | F5: Soma de Débito | G5: Soma de Crédito | H5: Soma de Débito | I5: Soma de Crédito | J5: Soma de Débito | K5: Soma de Crédito | L5: Soma de Débito | M5: Soma de Crédito | N5: Soma de Débito | O5: Soma de Crédito | P5: Soma de Débito | Q5: Soma de Crédito | R5: Soma de Débito | S5: Soma de Crédito | T5: Soma de Débito | U5: Soma de Crédito | V5: Soma de Débito | W5: Soma de Crédito | X5: Soma de Débito | Y5: Soma de Crédito | Z5: Soma de Débito
A6: =COUNTIF('Fluxo de Caixa '!C:C,B6) | B6: Consórcio | D6: 3006.4 | AB6: 3006.4
A7: =COUNTIF('Fluxo de Caixa '!C:C,B7) | B7: CSLL | F7: 80807.22 | J7: 30730.21 | AB7: 111537.43
A8: =COUNTIF('Fluxo de Caixa '!C:C,B8) | B8: Devolução / Estorno de Pagamento | E8: 164.78 | G8: 6740.48 | I8: 2050 | L8: 2700 | O8: 645.71 | AA8: 9600.97 | AB8: 2700
A9: =COUNTIF('Fluxo de Caixa '!C:C,B9) | B9: Devolução de Pagamento Recebido | F9: 164.78 | H9: 6740.48 | AB9: 6905.26
A10: =COUNTIF('Fluxo de Caixa '!C:C,B10) | B10: IPTU | D10: 3510.85 | F10: 954.17 | H10: 953.93 | J10: 953.93 | L10: 4536.64 | P10: 3704.6 | AB10: 14614.12
A11: =COUNTIF('Fluxo de Caixa '!C:C,B11) | B11: IRPJ | D11: 148466.82 | J11: 38858.12 | AB11: 187324.94
A12: =COUNTIF('Fluxo de Caixa '!C:C,B12) | B12: PIS | D12: 15499.36 | F12: 4219.23 | H12: 6139.58 | J12: 8297.04 | L12: 21787.88 | N12: 10966.3 | P12: 350.43 | AB12: 67259.82
A13: =COUNTIF('Fluxo de Caixa '!C:C,B13) | B13: Pró-Labore | D13: 2520.95 | F13: 3157.96 | H13: 900 | J13: 4113.36 | L13: 1383.33 | N13: 3659.96 | P13: 32731.01 | AB13: 48466.57
A14: =COUNTIF('Fluxo de Caixa '!C:C,B14) | B14: Transferência Emitida | D14: 2579816.4 | F14: 3879579.6 | H14: 1858648.1 | J14: 2017266.3 | L14: 1848736.2 | N14: 1492353.6 | P14: 968426.05 | AB14: 14644826
A15: =COUNTIF('Fluxo de Caixa '!C:C,B15) | B15: Transferência Recebida | C15: 2579816.4 | E15: 3879579.6 | G15: 1858648.1 | I15: 2017266.3 | K15: 3203452.3 | M15: 1492353.6 | O15: 968426.05 | AA15: 15999542
A16: =COUNTIF('Fluxo de Caixa '!C:C,B16) | B16: Saldo Final CEF | D16: -9962.67 | F16: 2896.27 | H16: -6790.36 | J16: 6291.18 | L16: -9341.64 | N16: -8714.28 | P16: 153067.5 | AB16: 127446
A17: =COUNTIF('Fluxo de Caixa '!C:C,B17) | B17: Saldo Inicial CEF | C17: 435332.04 | AA17: 435332.04
A18: =COUNTIF('Fluxo de Caixa '!C:C,B18) | B18: Empréstimo Sócios x Empresa | G18: 35000 | I18: 45000 | K18: 75000 | AA18: 155000
A19: =COUNTIF('Fluxo de Caixa '!C:C,B19) | B19: Pagamento Empréstimo Sócios x Empresa | J19: 80000 | AB19: 80000
A20: =COUNTIF('Fluxo de Caixa '!C:C,B20) | B20: Juros Recebidos | C20: 346.95 | E20: 5.69 | G20: 2.53 | I20: 0.67 | AA20: 355.84
A21: =COUNTIF('Fluxo de Caixa '!C:C,B21) | B21: Saldo Inicial Safra | C21: 102806.82 | AA21: 102806.82
A22: =COUNTIF('Fluxo de Caixa '!C:C,B22) | B22: Saldo Inicial Itau | C22: 562274.75 | AA22: 562274.75
A23: =COUNTIF('Fluxo de Caixa '!C:C,B23) | B23: Saldo Final Safra | D23: 2395.58 | F23: 70052.84 | H23: 2917.84 | J23: 16674.07 | L23: 74054.33 | N23: 256529.57 | P23: 29814.44 | AB23: 452438.67
A24: =COUNTIF('Fluxo de Caixa '!C:C,B24) | B24: Saldo Final Itau | D24: 64565.25 | F24: 153022.37 | H24: -22295.75 | J24: 46816.91 | L24: 20269.86 | N24: 26636.19 | P24: 12909.32 | AB24: 301924.15
A25: =COUNTIF('Fluxo de Caixa '!C:C,B25) | B25: Parcelamento de Impostos Exercicio Anterior | D25: 143237.64 | F25: 71856.49 | H25: 111292.76 | J25: 207684.95 | L25: 165124.25 | N25: 73927.63 | P25: 113849.05 | AB25: 886972.77
A26: =COUNTIF('Fluxo de Caixa '!C:C,B26) | B26: Venda de Imobilizado | M26: 49000 | AA26: 49000
A27: =COUNTIF('Fluxo de Caixa '!C:C,B27) | B27: Outros Recebimentos Não Operacionais | E27: 1295.56 | I27: 251.13 | M27: 2500 | AA27: 4046.69
A28: =COUNTIF('Fluxo de Caixa '!C:C,B28) | B28: Pagamento de Empréstimos Bancários | D28: 35696.55 | F28: 40730.52 | H28: 43077.28 | J28: 42095.09 | L28: 192115.5 | N28: 42150.54 | P28: 99262.79 | AB28: 495128.27
A29: =COUNTIF('Fluxo de Caixa '!C:C,B29) | B29: Construção da Nova Sede | D29: 58161.73 | F29: 81805.24 | H29: 36185.46 | J29: 75533.31 | L29: 181791.31 | N29: 69101.17 | P29: 29206.35 | AB29: 531784.57
A30: =COUNTIF('Fluxo de Caixa '!C:C,B30) | B30: Juros Bancários | D30: 5043.84 | F30: 5246.45 | H30: 3717.89 | J30: 2857.57 | L30: 3530.54 | N30: 2041.45 | P30: 5727.74 | AB30: 28165.48
A31: =COUNTIF('Fluxo de Caixa '!C:C,B31) | B31: Recebimento de Clientes | C31: 1802062.1 | E31: 1687804.9 | G31: 1558821.9 | I31: 2037244.6 | K31: 3108953.3 | M31: 1459018.7 | O31: 1613066.1 | AA31: 13266972
A32: =COUNTIF('Fluxo de Caixa '!C:C,B32) | B32: SALARIO | D32: 498154.44 | F32: 520467.94 | H32: 525625.75 | J32: 526479.56 | L32: 639195.11 | N32: 548773.44 | P32: 558932.38 | AB32: 3817628.6
A33: =COUNTIF('Fluxo de Caixa '!C:C,B33) | B33: TARIFAS BANCARIAS | D33: 2833.92 | F33: 3172.25 | H33: 4054.85 | J33: 1984.97 | L33: 4746.97 | N33: 2445.99 | P33: 3559.35 | AB33: 22798.3
A34: =COUNTIF('Fluxo de Caixa '!C:C,B34) | B34: Financiamentos | D34: 15992.21 | F34: 12276.53 | H34: 12436.17 | J34: 12419.19 | L34: 15877.79 | N34: 12505.27 | P34: 3601.26 | AB34: 85108.42
A35: =COUNTIF('Fluxo de Caixa '!C:C,B35) | B35: PLR | F35: 27103.73 | AB35: 27103.73
A36: =COUNTIF('Fluxo de Caixa '!C:C,B36) | B36: Processos Trabalhistas | D36: 9282.41 | F36: 5757.96 | H36: 4859.55 | J36: 6257.78 | L36: 53194.95 | N36: 143.89 | P36: 5304.9 | AB36: 84801.44
A37: =COUNTIF('Fluxo de Caixa '!C:C,B37) | B37: HONORÁRIOS ADVOCATÍCIOS | D37: 9200 | F37: 16650 | H37: 16737.61 | J37: 6090 | L37: 16332.6 | N37: 6690 | P37: 6690 | AB37: 78390.21
A38: =COUNTIF('Fluxo de Caixa '!C:C,B38) | B38: MATERIAIS / FERRAMENTAS MANUAIS | D38: 2434.54 | F38: 1636.27 | H38: 1862.84 | J38: 2527.4 | L38: 3668.07 | N38: 1326.09 | P38: 5888.51 | AB38: 19343.72
A39: =COUNTIF('Fluxo de Caixa '!C:C,B39) | B39: UNIFORMES | D39: 7976.87 | F39: 14321.2 | H39: 9178.82 | J39: 34004.02 | L39: 51645.32 | N39: 5915.26 | P39: 13427.88 | AB39: 136469.37
A40: =COUNTIF('Fluxo de Caixa '!C:C,B40) | B40: EPIS | D40: 18678.18 | F40: 22034.91 | H40: 39658.26 | J40: 45767.87 | L40: 85904.54 | N40: 31416.45 | P40: 37647.65 | AB40: 281107.86
A41: =COUNTIF('Fluxo de Caixa '!C:C,B41) | B41: ALUGUEL ALOJAMENTO | D41: 39905 | F41: 36248 | H41: 32290 | J41: 33177 | L41: 62874.95 | N41: 36555.34 | P41: 30528.38 | AB41: 271578.67
A42: =COUNTIF('Fluxo de Caixa '!C:C,B42) | B42: 13° SALARIO | D42: 6000 | AB42: 6000
A43: =COUNTIF('Fluxo de Caixa '!C:C,B43) | B43: Entrada por Empréstimos Bancários | I43: 146508.2 | O43: 196800 | AA43: 343308.2
A44: =COUNTIF('Fluxo de Caixa '!C:C,B44) | B44: LOCAÇÃO CONTAINER | D44: 9573.51 | F44: 7203.46 | H44: 6323.46 | J44: 9185.84 | L44: 21641 | N44: 14268.08 | P44: 7217.08 | AB44: 75412.43
A45: =COUNTIF('Fluxo de Caixa '!C:C,B45) | B45: MATERIAIS DE CONSUMO EM OBRAS | D45: 12345.64 | F45: 8768.13 | H45: 9098.86 | J45: 14251.74 | L45: 29154.68 | N45: 10322.32 | P45: 8625.04 | AB45: 92566.41
A46: =COUNTIF('Fluxo de Caixa '!C:C,B46) | B46: HONORÁRIOS CONTÁBEIS | D46: 3774.71 | F46: 5013.35 | H46: 4058.08 | J46: 6415.66 | L46: 27673.87 | N46: 3910 | P46: 3910 | AB46: 54755.67
A47: =COUNTIF('Fluxo de Caixa '!C:C,B47) | B47: FERIAS | D47: 23123.01 | F47: 37845.32 | H47: 31509.33 | J47: 51795.81 | L47: 76822.64 | N47: 46480.39 | P47: 22843.76 | AB47: 290420.26
A48: =COUNTIF('Fluxo de Caixa '!C:C,B48) | B48: MATERIAIS DE LIMPEZA / HIGIENE | D48: 4417.98 | F48: 8655.49 | H48: 1844.06 | J48: 3959.16 | L48: 7525.61 | N48: 4593.45 | P48: 3683.62 | AB48: 34679.37
A49: =COUNTIF('Fluxo de Caixa '!C:C,B49) | B49: MULTA RESCISORIAS FGTS | D49: 32425.59 | F49: 13520.04 | H49: 1775.73 | J49: 19047.61 | L49: 24872.81 | N49: 2724.96 | P49: 22015.96 | AB49: 116382.7
A50: =COUNTIF('Fluxo de Caixa '!C:C,B50) | B50: INTERNET OBRAS | D50: 1748.5 | F50: 1124.34 | H50: 1541.97 | J50: 1389.74 | L50: 4019.96 | N50: 1402.83 | P50: 1427.11 | AB50: 12654.45
A51: =COUNTIF('Fluxo de Caixa '!C:C,B51) | B51: FRETE TRANSPORTADORA | D51: 2413.73 | F51: 3032.02 | H51: 3637.82 | J51: 4749.95 | L51: 2662.44 | N51: 2140.7 | P51: 1508.39 | AB51: 20145.05
A52: =COUNTIF('Fluxo de Caixa '!C:C,B52) | B52: MATERIAIS PINCEL / ROLOS / LIXAS | D52: 3726.98 | AB52: 3726.98
A53: =COUNTIF('Fluxo de Caixa '!C:C,B53) | B53: TINTAS E SOLVENTES | D53: 71561.11 | F53: 46553.93 | H53: 52295.71 | J53: 58772.87 | L53: 159876.79 | N53: 53682.48 | P53: 63122.26 | AB53: 505865.15
A54: =COUNTIF('Fluxo de Caixa '!C:C,B54) | B54: REFEIÇÕES COLABORADORES | D54: 111297.31 | F54: 116255.87 | H54: 115585.2 | J54: 106168.86 | L54: 219996.52 | N54: 104037.94 | P54: 114928.31 | AB54: 888270.01
A55: =COUNTIF('Fluxo de Caixa '!C:C,B55) | B55: LOCAÇÃO MUNCK / GUINDASTES | D55: 4183.36 | F55: 4299.3 | H55: 5438.46 | J55: 3448.37 | L55: 376.62 | N55: 2070.27 | P55: 1250 | AB55: 21066.38
A56: =COUNTIF('Fluxo de Caixa '!C:C,B56) | B56: MAQUINAS / EQUIPAMENTOS | D56: 6612.53 | F56: 2244.28 | J56: 1921.55 | L56: 20000 | N56: 7479.14 | P56: 16924.14 | AB56: 55181.64
A57: =COUNTIF('Fluxo de Caixa '!C:C,B57) | B57: TRANSPORTE DE COLABORADORES | D57: 70918.56 | F57: 75408.96 | H57: 64500.26 | J57: 85011.69 | L57: 189991.91 | N57: 70561.35 | P57: 56397.04 | AB57: 612789.77
A58: =COUNTIF('Fluxo de Caixa '!C:C,B58) | B58: SEGUROS DE VIDA | D58: 11868.73 | F58: 6794.42 | H58: 1707.52 | J58: 11893.65 | L58: 14852.09 | N58: 6758.07 | P58: 1822.34 | AB58: 55696.82
A59: =COUNTIF('Fluxo de Caixa '!C:C,B59) | B59: MULTAS DE TRANSITO | D59: 371.4 | F59: 124.96 | L59: 1540.71 | N59: 104.13 | P59: 1257.23 | AB59: 3398.43
A60: =COUNTIF('Fluxo de Caixa '!C:C,B60) | B60: COMBUSTIVEL EQUIPAMENTOS | D60: 8706.81 | F60: 5285.86 | H60: 4713.79 | J60: 6484.92 | L60: 13547.927 | N60: 6178.79 | P60: 6531.16 | AB60: 51449.257
A61: =COUNTIF('Fluxo de Caixa '!C:C,B61) | B61: LOCAÇÃO COMPRESSORES | D61: 44821.53 | F61: 40100 | H61: 20131.2 | J61: 35034 | L61: 92860.44 | N61: 24600 | P61: 42320 | AB61: 299867.17
A62: =COUNTIF('Fluxo de Caixa '!C:C,B62) | B62: PASSAGENS COLABORADORES | D62: 32624.85 | F62: 30100.95 | H62: 11905.19 | J62: 45877.98 | L62: 62878.55 | N62: 36550.03 | P62: 33595.43 | AB62: 253532.98
A63: =COUNTIF('Fluxo de Caixa '!C:C,B63) | B63: ACERTO RESCISORIOS | D63: 73835.27 | F63: 65029.94 | H63: 6253.57 | J63: 34166.82 | L63: 160006.11 | N63: 31556.35 | P63: 59829.63 | AB63: 430677.69
A64: =COUNTIF('Fluxo de Caixa '!C:C,B64) | B64: ABRASIVOS | D64: 16123.52 | F64: 4000 | J64: 6500 | L64: 26141.05 | N64: 6500 | P64: 10177.66 | AB64: 69442.23
A65: =COUNTIF('Fluxo de Caixa '!C:C,B65) | B65: MANUTENÇÃO/PEÇAS VEICULOS | D65: 14042.15 | F65: 11628.14 | H65: 34322.93 | J65: 18360.76 | L65: 43432.723 | N65: 23220.26 | P65: 17898.43 | AB65: 162905.39
A66: =COUNTIF('Fluxo de Caixa '!C:C,B66) | B66: COMBUSTIVEL VEICULOS | D66: 29500.33 | F66: 32230.36 | H66: 26309.54 | J66: 23870.96 | L66: 77059.636 | N66: 29021.44 | P66: 45889.096 | AB66: 263881.36
A67: =COUNTIF('Fluxo de Caixa '!C:C,B67) | B67: SERVIÇOS DE CONSULTORIA | D67: 3918 | F67: 3918 | H67: 2350.8 | J67: 13400 | L67: 37627.84 | N67: 18149.9 | P67: 7900 | AB67: 87264.54
A68: =COUNTIF('Fluxo de Caixa '!C:C,B68) | B68: SERVIÇO ABRACO ANUIDADE | D68: 1152 | J68: 1152 | P68: 1152 | AB68: 3456
A69: =COUNTIF('Fluxo de Caixa '!C:C,B69) | B69: EXAMES MÉDICOS | D69: 9455.29 | F69: 14338.43 | H69: 16003.59 | J69: 13915.56 | L69: 17043.88 | N69: 6385.52 | P69: 10306.74 | AB69: 87449.01
A70: =COUNTIF('Fluxo de Caixa '!C:C,B70) | B70: LOCAÇÃO EQUIPAMENTOS | D70: 595.15 | L70: 6550 | N70: 600 | AB70: 7745.15
A71: =COUNTIF('Fluxo de Caixa '!C:C,B71) | B71: FGTS FUNCIONARIOS | D71: 62413.11 | F71: 41749.78 | H71: 39773.45 | J71: 43253.77 | L71: 110016.27 | N71: 44725.33 | P71: 2093 | AB71: 344024.71
A72: =COUNTIF('Fluxo de Caixa '!C:C,B72) | B72: SERVIÇO CARTORIO | D72: 289.93 | F72: 50.19 | H72: 16893.65 | J72: 495.57 | L72: 9521 | P72: 496.64 | AB72: 27746.98
A73: =COUNTIF('Fluxo de Caixa '!C:C,B73) | B73: HOTEL COLABORADORES | D73: 3204.76 | F73: 6786.46 | H73: 2847.49 | J73: 8061.43 | L73: 37210.332 | N73: 3423.38 | P73: 7077.2761 | AB73: 68611.128
A74: =COUNTIF('Fluxo de Caixa '!C:C,B74) | B74: SINDICATO | D74: 1452.82 | F74: 1400.79 | H74: 1490.23 | J74: 1501.87 | L74: 6717.64 | N74: 6844.4 | P74: 6884.09 | AB74: 26291.84
A75: =COUNTIF('Fluxo de Caixa '!C:C,B75) | B75: SERVIÇO LIMPEZA ALOJAMENTO/ESCRITORIO | D75: 1892 | F75: 1849.98 | H75: 600 | J75: 1792.41 | L75: 4388 | N75: 800.08 | P75: 2655.4826 | AB75: 13977.953
A76: =COUNTIF('Fluxo de Caixa '!C:C,B76) | B76: MANUTENÇÃO/PEÇAS MAQUINAS E EQUIPAMENTOS | D76: 18342.84 | F76: 12874.7 | H76: 13624.28 | J76: 18557.57 | L76: 32146.64 | N76: 7164.29 | P76: 34869.88 | AB76: 137580.2
A77: =COUNTIF('Fluxo de Caixa '!C:C,B77) | B77: MAQUINAS / FERRAMENTAS PNEUMATICAS | D77: 2363.4 | F77: 591.98 | AB77: 2955.38
A78: =COUNTIF('Fluxo de Caixa '!C:C,B78) | B78: CURSOS / TREINAMENTOS | D78: 2018.3 | F78: 8636.6 | H78: 8405.53 | J78: 9698.49 | L78: 40891.3 | N78: 13858.74 | P78: 8331.12 | AB78: 91840.08
A79: =COUNTIF('Fluxo de Caixa '!C:C,B79) | B79: MATERIAS DE ESCRITORIO / PAPELARIA | D79: 282.66 | F79: 3492.24 | H79: 7531.55 | J79: 1832.84 | L79: 4689.3 | N79: 2464.76 | P79: 3979.34 | AB79: 24272.69
A80: =COUNTIF('Fluxo de Caixa '!C:C,B80) | B80: PROGRAMA DE SEGURANÇA DO TRABALHO | D80: 2083.47 | F80: 1792.54 | H80: 6155.79 | J80: 5479.9 | L80: 5451.95 | N80: 3997.86 | P80: 749.5 | AB80: 25711.01
A81: =COUNTIF('Fluxo de Caixa '!C:C,B81) | B81: PLANO DE SAUDE | D81: 18136.05 | F81: 16582.48 | H81: 11149.82 | J81: 17569.62 | L81: 35269.1 | N81: 24769.2 | P81: 12296.03 | AB81: 135772.3
A82: =COUNTIF('Fluxo de Caixa '!C:C,B82) | B82: INTERNET / TELEFONE ADM | D82: 481.06 | F82: 553.63 | H82: 462.4 | J82: 533.03 | L82: 3343.32 | N82: 1386.15 | P82: 1356.9 | AB82: 8116.49
A83: =COUNTIF('Fluxo de Caixa '!C:C,B83) | B83: ALIMENTAÇÃO ADM | D83: 2410.22 | F83: 2530.34 | H83: 3076.64 | J83: 2753 | L83: 4659.02 | N83: 3526.51 | P83: 2802.4 | AB83: 21758.13
A84: =COUNTIF('Fluxo de Caixa '!C:C,B84) | B84: SISTEMA / SERVIDOR | D84: 5479.65 | F84: 5240.12 | H84: 5614.69 | J84: 5123.12 | L84: 13463.74 | N84: 5614.25 | P84: 4944.1 | AB84: 45479.67
A85: =COUNTIF('Fluxo de Caixa '!C:C,B85) | B85: MATERIAIS DE INFORMATICA / COMPUTADOR | D85: 4031.36 | F85: 3071.04 | H85: 1786.68 | J85: 4565.08 | L85: 6390.71 | N85: 4555.23 | P85: 5168.14 | AB85: 29568.24
A86: =COUNTIF('Fluxo de Caixa '!C:C,B86) | B86: SEGUROS DE VEICULOS | D86: 3988.69 | F86: 4919.24 | H86: 3699.65 | J86: 3592.49 | L86: 9122.64 | N86: 4815.81 | P86: 4930.19 | AB86: 35068.71
A87: =COUNTIF('Fluxo de Caixa '!C:C,B87) | B87: PEDAGIOS | D87: 733.92 | F87: 459.02 | H87: 818.79 | J87: 532.78 | L87: 1101.35 | N87: 1201.41 | P87: 1607.3148 | AB87: 6454.5848
A88: =COUNTIF('Fluxo de Caixa '!C:C,B88) | B88: FRETE MATERIAIS E EQUIPAMENTOS | D88: 14500 | F88: 12693.31 | H88: 10429.69 | J88: 8342 | L88: 42109.19 | N88: 11815.04 | P88: 29936.8 | AB88: 129826.03
A89: =COUNTIF('Fluxo de Caixa '!C:C,B89) | B89: SERVIÇO GOOGLE ADS | D89: 3704 | F89: 2000 | H89: 2000 | J89: 2000 | L89: 5780.68 | N89: 2000 | P89: 1999.9999 | AB89: 19484.68
... A92: =COUNTIF('Fluxo de Caixa '!C:C,B92) | B92: SERVIÇO MOTOBOY / UBER | D92: 818.79 | F92: 530.21 | H92: 1231.33 | J92: 1334.77 | L92: 2665.08 | N92: 1665.52 | P92: 1298.5361 | AB92: 9544.2361
A93: =COUNTIF('Fluxo de Caixa '!C:C,B93) | B93: SERVIÇO CREA ANUIDADE | D93: 8565.81 | F93: 479.57 | J93: 605.29 | L93: 571.18 | N93: 271.47 | P93: 645.97 | AB93: 11139.29
A94: =COUNTIF('Fluxo de Caixa '!C:C,B94) | B94: SERVIÇO PLOTAGEM / ADESIVO / PLACAS / CRACHAS | D94: 728 | F94: 3418 | H94: 2955 | J94: 3458.03 | L94: 2673 | N94: 710 | P94: 4146.53 | AB94: 18088.56
A95: =COUNTIF('Fluxo de Caixa '!C:C,B95) | B95: VALE ALIMENTAÇÃO | D95: 43070.22 | F95: 43292.88 | H95: 46631.3 | J95: 50864.22 | L95: 139549.75 | N95: 58372.56 | P95: 59651.89 | AB95: 441432.82
A96: =COUNTIF('Fluxo de Caixa '!C:C,B96) | B96: BONIFICAÇOES | D96: 7730.01 | F96: 7000 | J96: 18250 | L96: 37500 | N96: 4203.7 | P96: 51316.2 | AB96: 125999.91
A97: =COUNTIF('Fluxo de Caixa '!C:C,B97) | B97: ALUGUEIS ADM | D97: 9000 | F97: 9000 | J97: 9000 | L97: 18000 | N97: 10800 | P97: 2500 | AB97: 58300
A98: =COUNTIF('Fluxo de Caixa '!C:C,B98) | B98: SERVIÇO LAUDO TECNICO | D98: 7921.5 | H98: 5685.2 | J98: 3435.2 | N98: 1605.54 | P98: 3455 | AB98: 22102.44
A99: =COUNTIF('Fluxo de Caixa '!C:C,B99) | B99: AGUA ADM | D99: 177.88 | F99: 375.2 | J99: 178 | L99: 806.11 | N99: 1673.65 | P99: 604.06 | AB99: 3814.9
A100: =COUNTIF('Fluxo de Caixa '!C:C,B100) | B100: ENERGIA ALOJAMENTO | D100: 3816.6 | F100: 3665.79 | H100: 5228.13 | J100: 3784.98 | L100: 10196.59 | N100: 2777.78 | P100: 3799.9 | AB100: 33269.77
A101: =COUNTIF('Fluxo de Caixa '!C:C,B101) | B101: ENERGIA ADM | D101: 6363.59 | F101: 2055.96 | H101: 4987.9 | L101: 4759.92 | N101: 996.5 | P101: 475.22 | AB101: 19639.09
A102: =COUNTIF('Fluxo de Caixa '!C:C,B102) | B102: AGUA ALOJAMENTO | D102: 1816.84 | F102: 1714.57 | H102: 1618.5 | J102: 3784.59 | L102: 6617.69 | N102: 1849.22 | P102: 2014.52 | AB102: 19415.93
A103: =COUNTIF('Fluxo de Caixa '!C:C,B103) | B103: SERVIÇO ALVARAS E LICENCIAMENTO | D103: 1032.93 | H103: 200 | N103: 1100 | P103: 2299.35 | AB103: 4632.28
...

Sheet Naturezas Financeiras
A1: Naturezas Financeiras | D1: Cod. Mês | E1: Mês
A2: 13° SALARIO | D2: 1 | E2: Janeiro
A3: ABRASIVOS | D3: 2 | E3: Fevereiro
A4: ACERTO RESCISORIOS | D4: 3 | E4: Março
A5: AGUA ADM | D5: 4 | E5: Abril
A6: AGUA ALOJAMENTO | D6: 5 | E6: Maio
A7: Ajustes | D7: 6 | E7: Junho
A8: ALUGUEIS ADM | D8: 7 | E8: Julho
A9: ALUGUEL ALOJAMENTO | D9: 8 | E9: Agosto
A10: Aplicações | D10: 9 | E10: Setembro
A11: Aporte de Capital | D11: 10 | E11: Outubro
A12: Aquisição de Maquinas e Equipamentos | D12: 11 | E12: Novembro
A13: ASSISTENCIA MEDICA ADM | D13: 12 | E13: Dezembro
A14: BONIFICAÇOES
A15: COFINS
A16: COMBUSTIVEL EQUIPAMENTOS
A17: COMBUSTIVEL VEICULOS
A18: COMISSÃO
A19: Compra de Ativos
A20: Consórcio
A21: Construção da Nova Sede
A22: CSLL
A23: CURSOS / TREINAMENTOS
A24: CUSTOS E GUIAS DE TRANSFERENCIA VEICULOS
A25: DCTFWEB
... A161: TARIFA PREFEITURA
